Workbook
Name InitialInvestment: Inputs!$B$5
Name PriceEssMonthly: Inputs!$B$8
Name PricePremMonthly: Inputs!$B$9
Name PriceEliteMonthly: Inputs!$B$10
Name PriceEssAnnual: Inputs!$B$11
Name PricePremAnnual: Inputs!$B$12
Name PriceEliteAnnual: Inputs!$B$13
Name AnnualMix: Inputs!$B$16
Name EssentialMix: Inputs!$B$17
Name PremiumMix: Inputs!$B$18
Name EliteMix: Inputs!$B$19
Name GardenSmallMix: Inputs!$B$21
Name GardenMediumMix: Inputs!$B$22
Name GardenLargeMix: Inputs!$B$23
Name MonthlyChurn: Inputs!$B$25
Name AnnualChurn: Inputs!$B$26
Name CAC: Inputs!$B$29
Name ProvPayEss: Inputs!$B$30
Name ProvPayPrem: Inputs!$B$31
Name ProvPayElite: Inputs!$B$32
Name PaymentFee: Inputs!$B$33
Name OpsAI: Inputs!$B$34
Name ProviderDelay: Inputs!$B$37
Name MonthlyFixed: Inputs!$B$38
Name BlendedPriceEssMonthly: Inputs!$B$40
Name BlendedPricePremMonthly: Inputs!$B$41
Name BlendedPriceEliteMonthly: Inputs!$B$42
Name BlendedPriceEssAnnual: Inputs!$B$43
Name BlendedPricePremAnnual: Inputs!$B$44
Name BlendedPriceEliteAnnual: Inputs!$B$45
Name BlendedProvPayEss: Inputs!$B$46
Name BlendedProvPayPrem: Inputs!$B$47
Name BlendedProvPayElite: Inputs!$B$48
Name MktFixed1_3: Inputs!$B$51
Name MktFixed4_6: Inputs!$B$52
Name MktPct7_12: Inputs!$B$53
Name MktPct13_18: Inputs!$B$54
Name MktPct19plus: Inputs!$B$55
Name MktMin7_12: Inputs!$B$56
Name MktMin13_18: Inputs!$B$57
Name MktMin19plus: Inputs!$B$58
Name CashBuffer: Inputs!$B$59
Name InflationRate: Inputs!$B$60
Name ReferralMix: Inputs!$B$61
Name ReferralReward: Inputs!$B$62
Name LaunchMonth: Inputs!$B$63
Name VATRate: Inputs!$B$64
Name VATThreshold: Inputs!$B$65
Name VATAgentMode: Inputs!$B$66
Name SeasonTable: Inputs!$A$74:$B$85
Name AcqSeasonTable: Inputs!$A$74:$C$85
Name ChurnSeasonTable: Inputs!$A$74:$D$85
Name WinterPivotSeasonTable: Inputs!$A$74:$E$85
Name WinterPivotChurnTable: Inputs!$A$74:$F$85
Name MRR_Month12: Model!$Z$16
Name ARR_Month12: Model!$AA$16
Name Cust_Month12: Model!$Y$16
Name Cash_Month12: Model!$AS$16
Name MRR_Month24: Model!$Z$28
Name ARR_Month24: Model!$AA$28

Sheet Headlines
A1: GardensSorted — Financial Headlines (v4 visits + VAT modes)
A2: Calendar VAT quarters | seasonal churn | provider delay | referrals | inflation
A4: KEY METRICS
A5: Y1 ARR | C5: Y2 ARR | E5: Y5 ARR | G5: Cash Y5
A6: =Model!AA16 | C6: =Model!AA28 | E6: =Model!AA64 | G6: =Model!AS64
A8: SNAPSHOT
A9: Metric | B9: Year 1 | C9: Year 2 | D9: Year 5
A10: End customers | B10: =Model!Y16 | C10: =Model!Y28 | D10: =Model!Y64
A11: ARR | B11: =Model!AA16 | C11: =Model!AA28 | D11: =Model!AA64
A12: Gross revenue | B12: =SUM(Model!AE5:AE16) | C12: =SUM(Model!AE17:AE28) | D12: =SUM(Model!AE53:AE64)
A13: Net revenue | B13: =SUM(Model!AH5:AH16) | C13: =SUM(Model!AH17:AH28) | D13: =SUM(Model!AH53:AH64)
A14: VAT paid (calendar Q) | B14: =SUM(Model!AJ5:AJ16) | C14: =SUM(Model!AJ17:AJ28) | D14: =SUM(Model!AJ53:AJ64)
A15: Annual profit | B15: =SUM(Model!AR5:AR16) | C15: =SUM(Model!AR17:AR28) | D15: =SUM(Model!AR53:AR64)
A16: Cash balance | B16: =Model!AS16 | C16: =Model!AS28 | D16: =Model!AS64
A17: Avg logo churn | B17: =AVERAGE(Model!AU6:AU16) | C17: =AVERAGE(Model!AU18:AU28) | D17: =AVERAGE(Model!AU54:AU64)
A18: Platform margin | B18: ='5 Year Summary'!T4 | C18: ='5 Year Summary'!T5 | D18: ='5 Year Summary'!T8
A20: MILESTONES
A21: VAT registration | B21: =IFERROR("Month "&MATCH(TRUE,Model!AG5:Model!AG64,0),"Not in 60 mo")
A22: First profitable month | B22: =IFERROR("Month "&MATCH(1,IF(Model!AR5:AR64>0,1),0),"Not in 60 mo")
A23: Cash payback £17k | B23: =IFERROR("Month "&MATCH(1,IF(Model!AS5:AS64>=InitialInvestment,1),0),"Not in 60 mo")
A24: Provider payment delay | B24: =ProviderDelay&" month(s)"
A25: Fixed platform cost | B25: =MonthlyFixed
A27: MODEL COMPLETENESS
A28: ✓ SaaS cohorts — Essential / Premium / Elite tiers, monthly & annual subs, MRR/ARR
A29: ✓ Visit cadence — 10/20/30 visits per year (provider pay = visits/12 × per-visit rate)
A30: ✓ Garden size mix — customer price & provider pay uplifts for medium (+£10/+£3) and large (+£20/+£6)
A31: ✓ VAT — toggle Principal vs Agent on Inputs B66; see VAT Comparison sheet
A33: ✓ Per-customer ops/AI £5/mo | Marketing phased with cash cap | No salaries (AI ops)
A34: ✓ Sensitivity tabs — churn, mix, CAC, scenarios, winter pivot
A36: NOT MODELLED (by design or later)
A37: • Corporation tax (~19–25%) — add when consistently profitable
A38: • Route density / travel efficiency in clustered postcodes
A39: • Cross-sell to other Sorted brands | Geographic rollout phasing
A40: • HMRC exact deadline (+1 mo 7 days) — model pays in Jan/Apr/Jul/Oct cal months
... A43: WHERE TO GO NEXT
A44: Inputs | B44: All assumptions
A45: 5 Year Summary | B45: Annual P&L
A46: 24 Month Forecast | B46: Monthly detail
A47: Unit Economics | B47: LTV & CAC

Sheet VAT Comparison
A1: VAT — Principal vs Agent
A3: Parallel comparison using Model gross revenue and provider pay. Toggle live model on Inputs B66: 0 = Principal (VAT on gross), 1 = Agent (VAT on margin only).
A4: See docs/vat-principal-vs-agent.md — accountant review required before filing.
A6: Year | B6: Gross revenue | C6: Provider pay | D6: Platform margin | E6: VAT registered (P) | F6: VAT registered (A) | G6: VAT accrued (P) | H6: VAT accrued (A) | I6: Net revenue (P) | J6: Net revenue (A) | K6: Gross profit (P) | L6: Gross profit (A) | M6: GP uplift (A vs P)
A7: Year 1 | B7: =SUM('VAT Dual Calc'!B5:B16) | C7: =SUM('VAT Dual Calc'!C5:C16) | D7: =B7-C7 | E7: ='VAT Dual Calc'!G16 | F7: ='VAT Dual Calc'!H16 | G7: =SUM('VAT Dual Calc'!I5:I16) | H7: =SUM('VAT Dual Calc'!J5:J16) | I7: =SUM('VAT Dual Calc'!K5:K16) | J7: =SUM('VAT Dual Calc'!L5:L16) | K7: =SUM('VAT Dual Calc'!M5:M16) | L7: =SUM('VAT Dual Calc'!N5:N16) | M7: =L7-K7
A8: Year 2 | B8: =SUM('VAT Dual Calc'!B17:B28) | C8: =SUM('VAT Dual Calc'!C17:C28) | D8: =B8-C8 | E8: ='VAT Dual Calc'!G28 | F8: ='VAT Dual Calc'!H28 | G8: =SUM('VAT Dual Calc'!I17:I28) | H8: =SUM('VAT Dual Calc'!J17:J28) | I8: =SUM('VAT Dual Calc'!K17:K28) | J8: =SUM('VAT Dual Calc'!L17:L28) | K8: =SUM('VAT Dual Calc'!M17:M28) | L8: =SUM('VAT Dual Calc'!N17:N28) | M8: =L8-K8
A9: Year 3 | B9: =SUM('VAT Dual Calc'!B29:B40) | C9: =SUM('VAT Dual Calc'!C29:C40) | D9: =B9-C9 | E9: ='VAT Dual Calc'!G40 | F9: ='VAT Dual Calc'!H40 | G9: =SUM('VAT Dual Calc'!I29:I40) | H9: =SUM('VAT Dual Calc'!J29:J40) | I9: =SUM('VAT Dual Calc'!K29:K40) | J9: =SUM('VAT Dual Calc'!L29:L40) | K9: =SUM('VAT Dual Calc'!M29:M40) | L9: =SUM('VAT Dual Calc'!N29:N40) | M9: =L9-K9
A10: Year 4 | B10: =SUM('VAT Dual Calc'!B41:B52) | C10: =SUM('VAT Dual Calc'!C41:C52) | D10: =B10-C10 | E10: ='VAT Dual Calc'!G52 | F10: ='VAT Dual Calc'!H52 | G10: =SUM('VAT Dual Calc'!I41:I52) | H10: =SUM('VAT Dual Calc'!J41:J52) | I10: =SUM('VAT Dual Calc'!K41:K52) | J10: =SUM('VAT Dual Calc'!L41:L52) | K10: =SUM('VAT Dual Calc'!M41:M52) | L10: =SUM('VAT Dual Calc'!N41:N52) | M10: =L10-K10
A11: Year 5 | B11: =SUM('VAT Dual Calc'!B53:B64) | C11: =SUM('VAT Dual Calc'!C53:C64) | D11: =B11-C11 | E11: ='VAT Dual Calc'!G64 | F11: ='VAT Dual Calc'!H64 | G11: =SUM('VAT Dual Calc'!I53:I64) | H11: =SUM('VAT Dual Calc'!J53:J64) | I11: =SUM('VAT Dual Calc'!K53:K64) | J11: =SUM('VAT Dual Calc'!L53:L64) | K11: =SUM('VAT Dual Calc'!M53:M64) | L11: =SUM('VAT Dual Calc'!N53:N64) | M11: =L11-K11
A14: First VAT registration month (Principal) | B14: =IFERROR(MATCH(TRUE,'VAT Dual Calc'!G5:G64,0)+4,"Not in 60 mo")
A15: First VAT registration month (Agent) | B15: =IFERROR(MATCH(TRUE,'VAT Dual Calc'!H5:H64,0)+4,"Not in 60 mo")
A17: Current model mode | B17: =IF(VATAgentMode=1,"Agent (margin VAT)","Principal (gross VAT)")

Sheet Assumptions
A1: Assumptions & Methodology v4 (10/20/30 visits per year + VAT modes)
A2: Edit yellow cells on the Inputs sheet — all tabs update automatically.
A4: Parameter | B4: Live Value | C4: Notes
A5: Initial investment | B5: =InitialInvestment | C5: Total startup capital
A6: Essential Monthly | B6: =PriceEssMonthly | C6: 10 visits/yr — 3-month minimum
A7: Premium Monthly | B7: =PricePremMonthly | C7: 20 visits/yr — 3-month minimum
A8: Elite Monthly | B8: =PriceEliteMonthly | C8: 30 visits/yr + patio refresh — 3-month minimum
A9: Essential Annual | B9: =PriceEssAnnual | C9: 12-month commitment
A10: Premium Annual | B10: =PricePremAnnual | C10: 12-month commitment
A11: Elite Annual | B11: =PriceEliteAnnual | C11: 12-month commitment
A12: Annual plan mix | B12: =AnnualMix | C12: Industry B2C: 15–25%
A13: Essential tier mix | B13: =EssentialMix | C13: Share of new customers
A14: Premium tier mix | B14: =PremiumMix | C14: Share of new customers
A15: Elite tier mix | B15: =EliteMix | C15: Share of new customers
A16: Small garden mix | B16: =GardenSmallMix | C16: Customer & provider blend
A17: Medium garden mix | B17: =GardenMediumMix | C17: +£10/mo customer, +£3/visit provider
A18: Large garden mix | B18: =GardenLargeMix | C18: +£20/mo customer, +£6/visit provider
A19: Monthly churn (post min term) | B19: =MonthlyChurn | C19: Home services B2C: 4–7%/mo
A20: Annual churn (at renewal) | B20: =AnnualChurn | C20: B2C annual: 15–25%
A21: CAC | B21: =CAC | C21: Paid acquisition
A22: Provider pay — Essential (small) | B22: =ProvPayEss | C22: 10 visits/yr × £15/visit ÷ 12
A23: Provider pay — Premium (small) | B23: =ProvPayPrem | C23: 20 visits/yr × £15/visit ÷ 12
A24: Provider pay — Elite (small) | B24: =ProvPayElite | C24: 30 visits/yr × £15/visit ÷ 12
A25: Blended provider pay — Essential | B25: =BlendedProvPayEss | C25: Garden-size weighted
A26: Blended provider pay — Premium | B26: =BlendedProvPayPrem | C26: Garden-size weighted
A27: Blended provider pay — Elite | B27: =BlendedProvPayElite | C27: Garden-size weighted
A28: Payment fees | B28: =PaymentFee | C28: Stripe processing
A29: Ops + AI per customer | B29: =OpsAI | C29: Per active subscriber/month
A30: VAT agent mode | B30: =VATAgentMode | C30: 0=Principal (VAT on gross), 1=Agent (VAT on margin)

Sheet Inputs
A1: Sorted — SaaS Forecast v4 (10/20/30 visits per year + VAT principal/agent)
A2: All forecast sheets recalculate automatically when you change inputs below.
A3: Parameter | B3: Value | C3: Notes
A4: INITIAL INVESTMENT
A5: Initial investment (£) | B5: 17000 | C5: Total startup capital available
A7: SUBSCRIPTION PRICING
A8: Essential Monthly (£/mo, small) | B8: 29.95 | C8: 10 visits/yr — medium +£10, large +£20
A9: Premium Monthly (£/mo, small) | B9: 54.95 | C9: 20 visits/yr — medium +£10, large +£20
A10: Elite Monthly (£/mo, small) | B10: 89.95 | C10: 30 visits/yr + patio refresh — medium +£10, large +£20
A11: Essential Annual (£/yr, small) | B11: 299.95 | C11: medium +£100, large +£200
A12: Premium Annual (£/yr, small) | B12: 549.95 | C12: medium +£100, large +£200
A13: Elite Annual (£/yr, small) | B13: 899.95 | C13: medium +£100, large +£200
A15: PLAN MIX
A16: Annual plan mix (%) | B16: 0.2 | C16: Industry B2C benchmark: 15–25%
A17: Essential tier mix (%) | B17: 0.55 | C17: Share of new customers within billing type
A18: Premium tier mix (%) | B18: 0.32 | C18: Share of new customers within billing type
A19: Elite tier mix (%) | B19: 0.13 | C19: Share of new customers within billing type
A20: GARDEN SIZE MIX
A21: Small garden mix (%) | B21: 0.5 | C21: Up to 75 m²
A22: Medium garden mix (%) | B22: 0.35 | C22: 75–150 m² (+£10/mo customer, +£3/visit provider)
A23: Large garden mix (%) | B23: 0.15 | C23: 150+ m² (+£20/mo customer, +£6/visit provider)
A24: CHURN (edit for sensitivity)
A25: Monthly plan churn — post min term (%/mo) | B25: 0.055 | C25: Home services B2C: 4–7%. Applied after month 3.
A26: Annual plan churn — at renewal (%/yr) | B26: 0.2 | C26: B2C annual renewal: 15–25%
A28: UNIT ECONOMICS
A29: Customer Acquisition Cost — CAC (£) | B29: 70 | C29: Paid acquisition per customer
A30: Provider pay — Essential (£/mo, small garden) | B30: 12.5 | C30: 10 visits/yr × £15/visit ÷ 12
A31: Provider pay — Premium (£/mo, small garden) | B31: 25 | C31: 20 visits/yr × £15/visit ÷ 12
A32: Provider pay — Elite (£/mo, small garden) | B32: 37.5 | C32: 30 visits/yr × £15/visit ÷ 12
A33: Payment processing fee (%) | B33: 0.03 | C33: Stripe/card fees
A34: Ops + AI cost per customer (£/mo) | B34: 5 | C34: Support, hosting, AI per active sub
A35: CASH TIMING
A36: CASH TIMING | B36: 1 | C36: Providers invoiced ~30 days after service — cash float benefit
A37: Provider payment delay (months) | B37: 1 | C37: Hosting, AI base, tools — excludes per-customer ops
A38: Monthly fixed platform cost (£) | B38: 250 | C38: Jan/Apr/Jul/Oct for preceding calendar quarter (UK)
A39: BLENDED PRICING & PROVIDER PAY (calculated)
A40: Blended Essential monthly (£/mo) | B40: =$B$8*$B$21+($B$8+10)*$B$22+($B$8+20)*$B$23
A41: Blended Premium monthly (£/mo) | B41: =$B$9*$B$21+($B$9+10)*$B$22+($B$9+20)*$B$23
A42: Blended Elite monthly (£/mo) | B42: =$B$10*$B$21+($B$10+10)*$B$22+($B$10+20)*$B$23
A43: Blended Essential annual (£/yr) | B43: =$B$11*$B$21+($B$11+100)*$B$22+($B$11+200)*$B$23
A44: Blended Premium annual (£/yr) | B44: =$B$12*$B$21+($B$12+100)*$B$22+($B$12+200)*$B$23
A45: Blended Elite annual (£/yr) | B45: =$B$13*$B$21+($B$13+100)*$B$22+($B$13+200)*$B$23
A46: Blended provider pay — Essential (£/mo) | B46: =(10/12)*($B$21*15+$B$22*18+$B$23*21)
A47: Blended provider pay — Premium (£/mo) | B47: =(20/12)*($B$21*15+$B$22*18+$B$23*21)
A48: Blended provider pay — Elite (£/mo) | B48: =(30/12)*($B$21*15+$B$22*18+$B$23*21)
A49: MARKETING SPEND
A50: Months 1–3 fixed spend (£/mo) | B50: 1500 | C50: Soft launch phase
A51: Months 1–3 fixed spend (£/mo) | B51: 1500 | C51: Soft launch phase
A52: Months 4–6 fixed spend (£/mo) | B52: 2500 | C52: Ramp phase — capped by cash buffer from month 4
A53: Months 7–12 — % of prior month revenue | B53: 0.12 | C53: Scales with revenue
A54: Months 13–18 — % of prior month revenue | B54: 0.1
A55: Months 19+ — % of prior month revenue | B55: 0.08 | C55: Floor spend
A56: Min marketing months 7–12 (£/mo) | B56: 3000 | C56: Floor spend
A57: Min marketing months 13–18 (£/mo) | B57: 4000 | C57: Floor spend
A58: Min marketing months 19+ (£/mo) | B58: 5000 | C58: Floor spend
A59: Cash buffer retained (£) | B59: 2000 | C59: Min cash kept before marketing cap
A60: Annual price increase / inflation (%) | B60: 0.025 | C60: Applied each model year to all subs
A61: Referral mix (% of new customers) | B61: 0.15 | C61: 10–20% industry benchmark
A62: Referral reward (£ per referral) | B62: 15 | C62: One-off — no marketing cost
A63: Launch calendar month (1=Jan … 12=Dec) | B63: 3 | C63: March = pre-season launch
A64: VAT rate (%) | B64: 0.2 | C64: Standard rate once registered
A65: VAT registration threshold (£) | B65: 90000 | C65: Rolling 12-month gross turnover
A66: VAT basis — Agent mode (1=Agent, 0=Principal) | B66: 0 | C66: 0 = VAT on full customer revenue (principal). 1 = VAT on platform margin only (agent).
... A70: Launch calendar month (1=Jan … 12=Dec) | B70: 3 | C70: March = pre-season launch
A72: SEASONALITY (calendar month)
A73: Month | B73: Acq mult | C73: Notes | D73: Churn mult | E73: Pivot acq | F73: Pivot churn
A74: 1 | B74: 0.56 | C74: Low | pivot acq ×1.29, churn ×0.79 | D74: 1.37 | E74: 0.72 | F74: 1.08
A75: 2 | B75: 0.66 | C75: Pre-season | pivot acq ×1.24, churn ×0.82 | D75: 1.28 | E75: 0.82 | F75: 1.05
A76: 3 | B76: 0.87 | C76: Spring | churn ×1.04 | D76: 1.04 | E76: 0.87 | F76: 1.04
A77: 4 | B77: 1.07 | C77: Ramp | churn ×0.85 | D77: 0.85 | E77: 1.07 | F77: 0.85
A78: 5 | B78: 1.17 | C78: Peak | churn ×0.76 | D78: 0.76 | E78: 1.17 | F78: 0.76
A79: 6 | B79: 1.22 | C79: Peak | churn ×0.71 | D79: 0.71 | E79: 1.22 | F79: 0.71
A80: 7 | B80: 1.22 | C80: Peak | churn ×0.71 | D80: 0.71 | E80: 1.22 | F80: 0.71
A81: 8 | B81: 1.17 | C81: Peak | churn ×0.76 | D81: 0.76 | E81: 1.17 | F81: 0.76
A82: 9 | B82: 1.02 | C82: Shoulder | churn ×0.90 | D82: 0.9 | E82: 1.02 | F82: 0.9
A83: 10 | B83: 0.82 | C83: Wind-down | pivot acq ×1.22, churn ×0.94 | D83: 1.04 | E83: 1 | F83: 0.98
A84: 11 | B84: 0.61 | C84: Low | pivot acq ×1.72, churn ×0.77 | D84: 1.23 | E84: 1.05 | F84: 0.95
A85: 12 | B85: 0.56 | C85: Low | pivot acq ×1.39, churn ×0.79 | D85: 1.37 | E85: 0.78 | F85: 1.08
A86: WINTER PIVOT SEASONALITY (property care — gutter, leaf, patio)
A87: Used by Sens - Winter Pivot scenario. Oct–Nov boosted for leaf/gutter; winter churn reduced (customers stay on year-round plan).
A88: Start on Headlines tab.
A89: Edit yellow cells — all tabs recalculate.
A90: Seasonality affects paid acquisition by calendar month.
A91: VAT applies once rolling 12-mo gross exceeds threshold.

Sheet 5 Year Summary
A1: 5-Year Summary
A3: Year | B3: Cust | C3: MRR | D3: ARR | E3: Paid | F3: Referrals | G3: Gross | H3: Net | I3: VAcc | J3: VPay | K3: VBal | L3: Prov | M3: Fees | N3: Ops | O3: Fixed | P3: Ref£ | Q3: Mkt | R3: Profit | S3: Cash | T3: Margin | U3: Prov# | V3: MRRGr | W3: Churn | X3: CumPft
A4: Year 1 | B4: =Model!Y16 | C4: =Model!Z16 | D4: =Model!AA16 | E4: =SUM(Model!H5:H16) | F4: =SUM(Model!I5:I16) | G4: =SUM(Model!AE5:AE16) | H4: =SUM(Model!AH5:AH16) | I4: =SUM(Model!AI5:AI16) | J4: =SUM(Model!AJ5:AJ16) | K4: =Model!AK16 | L4: =SUM(Model!AL5:AL16) | M4: =SUM(Model!AM5:AM16) | N4: =SUM(Model!AN5:AN16) | O4: =SUM(Model!AO5:AO16) | P4: =SUM(Model!AP5:AP16) | Q4: =SUM(Model!AQ5:AQ16) | R4: =SUM(Model!AR5:AR16) | S4: =Model!AS16 | T4: =IF(G4>0,(H4-L4-M4-N4-O4)/G4,0) | U4: =ROUNDUP(B4/140,0) | V4: — | W4: =AVERAGE(Model!AU6:AU16) | X4: =SUM($R$4:R4)
A5: Year 2 | B5: =Model!Y28 | C5: =Model!Z28 | D5: =Model!AA28 | E5: =SUM(Model!H17:H28) | F5: =SUM(Model!I17:I28) | G5: =SUM(Model!AE17:AE28) | H5: =SUM(Model!AH17:AH28) | I5: =SUM(Model!AI17:AI28) | J5: =SUM(Model!AJ17:AJ28) | K5: =Model!AK28 | L5: =SUM(Model!AL17:AL28) | M5: =SUM(Model!AM17:AM28) | N5: =SUM(Model!AN17:AN28) | O5: =SUM(Model!AO17:AO28) | P5: =SUM(Model!AP17:AP28) | Q5: =SUM(Model!AQ17:AQ28) | R5: =SUM(Model!AR17:AR28) | S5: =Model!AS28 | T5: =IF(G5>0,(H5-L5-M5-N5-O5)/G5,0) | U5: =ROUNDUP(B5/140,0) | V5: =(C5-C4)/C4 | W5: =AVERAGE(Model!AU18:AU28) | X5: =SUM($R$4:R5)
A6: Year 3 | B6: =Model!Y40 | C6: =Model!Z40 | D6: =Model!AA40 | E6: =SUM(Model!H29:H40) | F6: =SUM(Model!I29:I40) | G6: =SUM(Model!AE29:AE40) | H6: =SUM(Model!AH29:AH40) | I6: =SUM(Model!AI29:AI40) | J6: =SUM(Model!AJ29:AJ40) | K6: =Model!AK40 | L6: =SUM(Model!AL29:AL40) | M6: =SUM(Model!AM29:AM40) | N6: =SUM(Model!AN29:AN40) | O6: =SUM(Model!AO29:AO40) | P6: =SUM(Model!AP29:AP40) | Q6: =SUM(Model!AQ29:AQ40) | R6: =SUM(Model!AR29:AR40) | S6: =Model!AS40 | T6: =IF(G6>0,(H6-L6-M6-N6-O6)/G6,0) | U6: =ROUNDUP(B6/140,0) | V6: =(C6-C5)/C5 | W6: =AVERAGE(Model!AU30:AU40) | X6: =SUM($R$4:R6)
A7: Year 4 | B7: =Model!Y52 | C7: =Model!Z52 | D7: =Model!AA52 | E7: =SUM(Model!H41:H52) | F7: =SUM(Model!I41:I52) | G7: =SUM(Model!AE41:AE52) | H7: =SUM(Model!AH41:AH52) | I7: =SUM(Model!AI41:AI52) | J7: =SUM(Model!AJ41:AJ52) | K7: =Model!AK52 | L7: =SUM(Model!AL41:AL52) | M7: =SUM(Model!AM41:AM52) | N7: =SUM(Model!AN41:AN52) | O7: =SUM(Model!AO41:AO52) | P7: =SUM(Model!AP41:AP52) | Q7: =SUM(Model!AQ41:AQ52) | R7: =SUM(Model!AR41:AR52) | S7: =Model!AS52 | T7: =IF(G7>0,(H7-L7-M7-N7-O7)/G7,0) | U7: =ROUNDUP(B7/140,0) | V7: =(C7-C6)/C6 | W7: =AVERAGE(Model!AU42:AU52) | X7: =SUM($R$4:R7)
A8: Year 5 | B8: =Model!Y64 | C8: =Model!Z64 | D8: =Model!AA64 | E8: =SUM(Model!H53:H64) | F8: =SUM(Model!I53:I64) | G8: =SUM(Model!AE53:AE64) | H8: =SUM(Model!AH53:AH64) | I8: =SUM(Model!AI53:AI64) | J8: =SUM(Model!AJ53:AJ64) | K8: =Model!AK64 | L8: =SUM(Model!AL53:AL64) | M8: =SUM(Model!AM53:AM64) | N8: =SUM(Model!AN53:AN64) | O8: =SUM(Model!AO53:AO64) | P8: =SUM(Model!AP53:AP64) | Q8: =SUM(Model!AQ53:AQ64) | R8: =SUM(Model!AR53:AR64) | S8: =Model!AS64 | T8: =IF(G8>0,(H8-L8-M8-N8-O8)/G8,0) | U8: =ROUNDUP(B8/140,0) | V8: =(C8-C7)/C7 | W8: =AVERAGE(Model!AU54:AU64) | X8: =SUM($R$4:R8)
A10: VAT registration | B10: =IFERROR("Month "&MATCH(TRUE,Model!AG5:Model!AG64,0),"Not in 60 mo")
A11: VAT payments | B11: Calendar: Jan=Q4 prior yr, Apr=Q1, Jul=Q2, Oct=Q3

Sheet 24 Month Forecast
A1: 24-Month Forecast
A3: Month | B3: CalMo | C3: Paid | D3: Referral | E3: Total | F3: Cust | G3: EffChurn | H3: MRR | I3: ARR | J3: Gross | K3: Net | L3: VAcc | M3: VPay | N3: VBal | O3: Prov | P3: Fees | Q3: Ops | R3: Fixed | S3: Ref£ | T3: Mkt | U3: Pft | V3: Cash | W3: Churn
A4: Month 1 | B4: =Model!B5 | C4: =Model!H5 | D4: =Model!I5 | E4: =Model!J5 | F4: =Model!Y5 | G4: =Model!F5 | H4: =Model!Z5 | I4: =Model!AA5 | J4: =Model!AE5 | K4: =Model!AH5 | L4: =Model!AI5 | M4: =Model!AJ5 | N4: =Model!AK5 | O4: =Model!AL5 | P4: =Model!AM5 | Q4: =Model!AN5 | R4: =Model!AO5 | ... V4: =Model!AS5 | W4: =Model!AU5
A5: Month 2 | B5: =Model!B6 | C5: =Model!H6 | D5: =Model!I6 | E5: =Model!J6 | F5: =Model!Y6 | G5: =Model!F6 | H5: =Model!Z6 | I5: =Model!AA6 | J5: =Model!AE6 | K5: =Model!AH6 | L5: =Model!AI6 | M5: =Model!AJ6 | N5: =Model!AK6 | O5: =Model!AL6 | P5: =Model!AM6 | Q5: =Model!AN6 | R5: =Model!AO6 | ... V5: =Model!AS6 | W5: =Model!AU6
A6: Month 3 | B6: =Model!B7 | C6: =Model!H7 | D6: =Model!I7 | E6: =Model!J7 | F6: =Model!Y7 | G6: =Model!F7 | H6: =Model!Z7 | I6: =Model!AA7 | J6: =Model!AE7 | K6: =Model!AH7 | L6: =Model!AI7 | M6: =Model!AJ7 | N6: =Model!AK7 | O6: =Model!AL7 | P6: =Model!AM7 | Q6: =Model!AN7 | R6: =Model!AO7 | ... V6: =Model!AS7 | W6: =Model!AU7
A7: Month 4 | B7: =Model!B8 | C7: =Model!H8 | D7: =Model!I8 | E7: =Model!J8 | F7: =Model!Y8 | G7: =Model!F8 | H7: =Model!Z8 | I7: =Model!AA8 | J7: =Model!AE8 | K7: =Model!AH8 | L7: =Model!AI8 | M7: =Model!AJ8 | N7: =Model!AK8 | O7: =Model!AL8 | P7: =Model!AM8 | Q7: =Model!AN8 | R7: =Model!AO8 | ... V7: =Model!AS8 | W7: =Model!AU8
A8: Month 5 | B8: =Model!B9 | C8: =Model!H9 | D8: =Model!I9 | E8: =Model!J9 | F8: =Model!Y9 | G8: =Model!F9 | H8: =Model!Z9 | I8: =Model!AA9 | J8: =Model!AE9 | K8: =Model!AH9 | L8: =Model!AI9 | M8: =Model!AJ9 | N8: =Model!AK9 | O8: =Model!AL9 | P8: =Model!AM9 | Q8: =Model!AN9 | R8: =Model!AO9 | ... V8: =Model!AS9 | W8: =Model!AU9
A9: Month 6 | B9: =Model!B10 | C9: =Model!H10 | D9: =Model!I10 | E9: =Model!J10 | F9: =Model!Y10 | G9: =Model!F10 | H9: =Model!Z10 | I9: =Model!AA10 | J9: =Model!AE10 | K9: =Model!AH10 | L9: =Model!AI10 | M9: =Model!AJ10 | N9: =Model!AK10 | O9: =Model!AL10 | P9: =Model!AM10 | Q9: =Model!AN10 | R9: =Model!AO10 | ... V9: =Model!AS10 | W9: =Model!AU10
A10: Month 7 | B10: =Model!B11 | C10: =Model!H11 | D10: =Model!I11 | E10: =Model!J11 | F10: =Model!Y11 | G10: =Model!F11 | H10: =Model!Z11 | I10: =Model!AA11 | J10: =Model!AE11 | K10: =Model!AH11 | L10: =Model!AI11 | M10: =Model!AJ11 | N10: =Model!AK11 | O10: =Model!AL11 | P10: =Model!AM11 | Q10: =Model!AN11 | R10: =Model!AO11 | ... V10: =Model!AS11 | W10: =Model!AU11
A11: Month 8 | B11: =Model!B12 | C11: =Model!H12 | D11: =Model!I12 | E11: =Model!J12 | F11: =Model!Y12 | G11: =Model!F12 | H11: =Model!Z12 | I11: =Model!AA12 | J11: =Model!AE12 | K11: =Model!AH12 | L11: =Model!AI12 | M11: =Model!AJ12 | N11: =Model!AK12 | O11: =Model!AL12 | P11: =Model!AM12 | Q11: =Model!AN12 | R11: =Model!AO12 | ... V11: =Model!AS12 | W11: =Model!AU12
A12: Month 9 | B12: =Model!B13 | C12: =Model!H13 | D12: =Model!I13 | E12: =Model!J13 | F12: =Model!Y13 | G12: =Model!F13 | H12: =Model!Z13 | I12: =Model!AA13 | J12: =Model!AE13 | K12: =Model!AH13 | L12: =Model!AI13 | M12: =Model!AJ13 | N12: =Model!AK13 | O12: =Model!AL13 | P12: =Model!AM13 | Q12: =Model!AN13 | R12: =Model!AO13 | ... V12: =Model!AS13 | W12: =Model!AU13
A13: Month 10 | B13: =Model!B14 | C13: =Model!H14 | D13: =Model!I14 | E13: =Model!J14 | F13: =Model!Y14 | G13: =Model!F14 | H13: =Model!Z14 | I13: =Model!AA14 | J13: =Model!AE14 | K13: =Model!AH14 | L13: =Model!AI14 | M13: =Model!AJ14 | N13: =Model!AK14 | O13: =Model!AL14 | P13: =Model!AM14 | Q13: =Model!AN14 | R13: =Model!AO14 | ... V13: =Model!AS14 | W13: =Model!AU14
A14: Month 11 | B14: =Model!B15 | C14: =Model!H15 | D14: =Model!I15 | E14: =Model!J15 | F14: =Model!Y15 | G14: =Model!F15 | H14: =Model!Z15 | I14: =Model!AA15 | J14: =Model!AE15 | K14: =Model!AH15 | L14: =Model!AI15 | M14: =Model!AJ15 | N14: =Model!AK15 | O14: =Model!AL15 | P14: =Model!AM15 | Q14: =Model!AN15 | R14: =Model!AO15 | ... V14: =Model!AS15 | W14: =Model!AU15
A15: Month 12 | B15: =Model!B16 | C15: =Model!H16 | D15: =Model!I16 | E15: =Model!J16 | F15: =Model!Y16 | G15: =Model!F16 | H15: =Model!Z16 | I15: =Model!AA16 | J15: =Model!AE16 | K15: =Model!AH16 | L15: =Model!AI16 | M15: =Model!AJ16 | N15: =Model!AK16 | O15: =Model!AL16 | P15: =Model!AM16 | Q15: =Model!AN16 | R15: =Model!AO16 | ... V15: =Model!AS16 | W15: =Model!AU16
... A27: Month 24 | B27: =Model!B28 | C27: =Model!H28 | D27: =Model!I28 | E27: =Model!J28 | F27: =Model!Y28 | G27: =Model!F28 | H27: =Model!Z28 | I27: =Model!AA28 | J27: =Model!AE28 | K27: =Model!AH28 | L27: =Model!AI28 | M27: =Model!AJ28 | N27: =Model!AK28 | O27: =Model!AL28 | P27: =Model!AM28 | Q27: =Model!AN28 | R27: =Model!AO28 | ... V27: =Model!AS28 | W27: =Model!AU28

Sheet Unit Economics
A1: Unit Economics v4 (10/20/30 visits + garden-size blended)
A3: Metric | B3: Value | C3: Unit
A4: Blended ARPU (MRR per customer) | B4: =EssentialMix*(1-AnnualMix)*BlendedPriceEssMonthly+PremiumMix*(1-AnnualMix)*BlendedPricePremMonthly+EliteMix*(1-AnnualMix)*BlendedPriceEliteMonthly+EssentialMix*AnnualMix*BlendedPriceEssAnnual/12+PremiumMix*AnnualMix*BlendedPricePremAnnual/12+EliteMix*AnnualMix*BlendedPriceEliteAnnual/12 | C4: £/mo
A5: Monthly plan ARPU | B5: =EssentialMix*BlendedPriceEssMonthly+PremiumMix*BlendedPricePremMonthly+EliteMix*BlendedPriceEliteMonthly | C5: £/mo
A6: Annual plan ARPU (normalised) | B6: =EssentialMix*BlendedPriceEssAnnual/12+PremiumMix*BlendedPricePremAnnual/12+EliteMix*BlendedPriceEliteAnnual/12 | C6: £/mo
A8: Provider cost per customer (blended tier + garden size) | B8: =EssentialMix*BlendedProvPayEss+PremiumMix*BlendedProvPayPrem+EliteMix*BlendedProvPayElite | C8: £/mo
A9: Payment fees per customer | B9: =B4*PaymentFee | C9: £/mo
A10: Ops + AI per customer | B10: =OpsAI | C10: £/mo
A12: Gross margin per customer (pre-marketing) | B12: =B4-B8-B4*PaymentFee-OpsAI | C12: £/mo
A13: CAC | B13: =CAC | C13: £
A14: Months to recover CAC | B14: =B13/B12 | C14: months
A16: Customer lifetime — monthly plan (post min term) | B16: =1/MonthlyChurn | C16: months
A17: Expected annual renewals — annual plan | B17: =1/AnnualChurn | C17: renewals
A18: LTV — monthly plan (simplified) | B18: =B5*(1-PaymentFee)*ProvPayEss/PriceEssMonthly*(1/MonthlyChurn)*EssentialMix/(EssentialMix+PremiumMix+EliteMix) | C18: £
A19: LTV — annual plan (simplified) | B19: =B6*12*(1-PaymentFee)*(1/AnnualChurn) | C19: £
A20: LTV:CAC — monthly plan | B20: =B18/CAC | C20: x
A21: LTV:CAC — blended | B21: =B4*(1-PaymentFee)*((1-AnnualMix)/MonthlyChurn+AnnualMix*12/AnnualChurn)/CAC | C21: x
A22: Inflated ARPU (Year 2 prices) | B22: =B4*(1+InflationRate) | C22: £/mo
A23: Effective CAC (paid customers only) | B23: =CAC | C23: £
A24: Blended CAC (incl. referrals) | B24: =CAC*(1-ReferralMix) | C24: £/customer
A25: Monthly fixed platform cost | B25: =MonthlyFixed | C25: £/mo

Sheet Sens - Scenarios
A1: Scenario Comparison — Conservative / Base / Aggressive (v4)
A2: Edit yellow cells in Conservative & Aggressive columns. Base uses live Inputs (£70 CAC). Marketing spend: Inputs rows 31–39.
A4: Parameter | B4: Conservative | C4: Base (live Inputs) | D4: Aggressive
A5: Monthly churn (post min term) | B5: 0.07 | C5: =MonthlyChurn | D5: 0.04
A6: Annual churn (at renewal) | B6: 0.25 | C6: =AnnualChurn | D6: 0.15
A7: Annual plan mix | B7: 0.15 | C7: =AnnualMix | D7: 0.3
A8: CAC (£) | B8: 110 | C8: =CAC | D8: 40
A11: OUTPUT METRICS
A12: Metric | B12: Conservative | C12: Base | D12: Aggressive
A13: End Year 1 — Customers | B13: ='Scenario Engine'!Y$16 | C13: ='Scenario Engine'!BU$16 | D13: ='Scenario Engine'!DQ$16
A14: End Year 1 — MRR (£) | B14: ='Scenario Engine'!Z$16 | C14: ='Scenario Engine'!BV$16 | D14: ='Scenario Engine'!DR$16
A15: End Year 1 — ARR (£) | B15: ='Scenario Engine'!AA$16 | C15: ='Scenario Engine'!BW$16 | D15: ='Scenario Engine'!DS$16
A16: End Year 1 — Cash Balance (£) | B16: ='Scenario Engine'!AS$16 | C16: ='Scenario Engine'!CO$16 | D16: ='Scenario Engine'!EK$16
A17: Year 1 — Gross Revenue (£) | B17: =SUM('Scenario Engine'!AE$5:'Scenario Engine'!AE$16) | C17: =SUM('Scenario Engine'!CA$5:'Scenario Engine'!CA$16) | D17: =SUM('Scenario Engine'!DW$5:'Scenario Engine'!DW$16)
A18: Year 1 — Net Revenue (£) | B18: =SUM('Scenario Engine'!AH$5:'Scenario Engine'!AH$16) | C18: =SUM('Scenario Engine'!CD$5:'Scenario Engine'!CD$16) | D18: =SUM('Scenario Engine'!DZ$5:'Scenario Engine'!DZ$16)
A19: Year 1 — Profit (£) | B19: =SUM('Scenario Engine'!AR$5:'Scenario Engine'!AR$16) | C19: =SUM('Scenario Engine'!CN$5:'Scenario Engine'!CN$16) | D19: =SUM('Scenario Engine'!EJ$5:'Scenario Engine'!EJ$16)
A20: End Year 2 — Customers | B20: ='Scenario Engine'!Y$28 | C20: ='Scenario Engine'!BU$28 | D20: ='Scenario Engine'!DQ$28
A21: End Year 2 — MRR (£) | B21: ='Scenario Engine'!Z$28 | C21: ='Scenario Engine'!BV$28 | D21: ='Scenario Engine'!DR$28
A22: End Year 2 — ARR (£) | B22: ='Scenario Engine'!AA$28 | C22: ='Scenario Engine'!BW$28 | D22: ='Scenario Engine'!DS$28
A23: End Year 2 — Cash Balance (£) | B23: ='Scenario Engine'!AS$28 | C23: ='Scenario Engine'!CO$28 | D23: ='Scenario Engine'!EK$28
A24: Year 2 — Gross Revenue (£) | B24: =SUM('Scenario Engine'!AE$17:'Scenario Engine'!AE$28) | C24: =SUM('Scenario Engine'!CA$17:'Scenario Engine'!CA$28) | D24: =SUM('Scenario Engine'!DW$17:'Scenario Engine'!DW$28)
A25: End Year 5 — Customers | B25: ='Scenario Engine'!Y$64 | C25: ='Scenario Engine'!BU$64 | D25: ='Scenario Engine'!DQ$64
A26: End Year 5 — MRR (£) | B26: ='Scenario Engine'!Z$64 | C26: ='Scenario Engine'!BV$64 | D26: ='Scenario Engine'!DR$64
A27: End Year 5 — ARR (£) | B27: ='Scenario Engine'!AA$64 | C27: ='Scenario Engine'!BW$64 | D27: ='Scenario Engine'!DS$64
A28: End Year 5 — Cash Balance (£) | B28: ='Scenario Engine'!AS$64 | C28: ='Scenario Engine'!CO$64 | D28: ='Scenario Engine'!EK$64

Sheet Sens - Churn
A1: Churn Sensitivity — v3 Elite full model
A2: Edit churn in column A (yellow). Live model outputs in section below for comparison.
A4: Current Monthly Churn (Inputs) | B4: =MonthlyChurn
A5: Live Y1 MRR | B5: =Model!Z16
A6: Live Y2 MRR | B6: =Model!Z28
A7: Live Y2 ARR | B7: =Model!AA28
A8: Live Y5 ARR | B8: =Model!AA64
A9: Live Y5 Cash | B9: =Model!AS64
A12: Monthly Churn | B12: Y1 MRR | C12: Y1 Cust | D12: Y2 MRR | E12: Y2 ARR | F12: Y2 Cash | G12: Y5 ARR
A13: 0.03 | B13: ='Scenario Engine'!FN$16 | C13: ='Scenario Engine'!FM$16 | D13: ='Scenario Engine'!FN$28 | E13: ='Scenario Engine'!FO$28 | F13: ='Scenario Engine'!FQ$28 | G13: ='Scenario Engine'!EY$64
A14: 0.035 | B14: ='Scenario Engine'!HJ$16 | C14: ='Scenario Engine'!HI$16 | D14: ='Scenario Engine'!HJ$28 | E14: ='Scenario Engine'!HK$28 | F14: ='Scenario Engine'!HI$28 | G14: ='Scenario Engine'!GQ$64
A15: 0.04 | B15: ='Scenario Engine'!JF$16 | C15: ='Scenario Engine'!JE$16 | D15: ='Scenario Engine'!JF$28 | E15: ='Scenario Engine'!JG$28 | F15: ='Scenario Engine'!JA$28 | G15: ='Scenario Engine'!II$64
A16: 0.045 | B16: ='Scenario Engine'!LB$16 | C16: ='Scenario Engine'!LA$16 | D16: ='Scenario Engine'!LB$28 | E16: ='Scenario Engine'!LC$28 | F16: ='Scenario Engine'!KS$28 | G16: ='Scenario Engine'!KA$64
A17: 0.05 | B17: ='Scenario Engine'!MX$16 | C17: ='Scenario Engine'!MW$16 | D17: ='Scenario Engine'!MX$28 | E17: ='Scenario Engine'!MY$28 | F17: ='Scenario Engine'!MK$28 | G17: ='Scenario Engine'!LS$64
A18: 0.055 | B18: ='Scenario Engine'!OT$16 | C18: ='Scenario Engine'!OS$16 | D18: ='Scenario Engine'!OT$28 | E18: ='Scenario Engine'!OU$28 | F18: ='Scenario Engine'!OC$28 | G18: ='Scenario Engine'!NK$64
A19: 0.06 | B19: ='Scenario Engine'!QP$16 | C19: ='Scenario Engine'!QO$16 | D19: ='Scenario Engine'!QP$28 | E19: ='Scenario Engine'!QQ$28 | F19: ='Scenario Engine'!PU$28 | G19: ='Scenario Engine'!PC$64
A20: 0.065 | B20: ='Scenario Engine'!SL$16 | C20: ='Scenario Engine'!SK$16 | D20: ='Scenario Engine'!SL$28 | E20: ='Scenario Engine'!SM$28 | F20: ='Scenario Engine'!RM$28 | G20: ='Scenario Engine'!QU$64
A21: 0.07 | B21: ='Scenario Engine'!UH$16 | C21: ='Scenario Engine'!UG$16 | D21: ='Scenario Engine'!UH$28 | E21: ='Scenario Engine'!UI$28 | F21: ='Scenario Engine'!TE$28 | G21: ='Scenario Engine'!SM$64
A22: 0.07 | B22: ='Scenario Engine'!KZ$16 | C22: ='Scenario Engine'!KY$16 | D22: ='Scenario Engine'!KZ$28 | E22: ='Scenario Engine'!LA$28 | F22: ='Scenario Engine'!LK$28 | G22: ='Scenario Engine'!LA$64

Sheet Sens - Annual Mix
A1: Annual Plan Mix Sensitivity — v3 Elite engine
A2: Edit mix % in column A (yellow).
A4: Current (Inputs) | B4: =AnnualMix
A7: Annual Mix | B7: Y1 MRR | C7: Blended ARPU | D7: Y2 MRR | E7: Y2 ARR | F7: Y5 ARR | G7: Y5 Cash
A9: 0.1 | B9: ='Scenario Engine'!WD$16 | C9: =IF('Scenario Engine'!WC$16>0,'Scenario Engine'!WD$16/'Scenario Engine'!WC$16,0) | D9: ='Scenario Engine'!WD$28 | E9: ='Scenario Engine'!WE$28 | F9: ='Scenario Engine'!UE$64 | G9: ='Scenario Engine'!UW$64
A10: 0.15 | B10: ='Scenario Engine'!XZ$16 | C10: =IF('Scenario Engine'!XY$16>0,'Scenario Engine'!XZ$16/'Scenario Engine'!XY$16,0) | D10: ='Scenario Engine'!XZ$28 | E10: ='Scenario Engine'!YA$28 | F10: ='Scenario Engine'!VW$64 | G10: ='Scenario Engine'!WO$64
A11: 0.2 | B11: ='Scenario Engine'!ZV$16 | C11: =IF('Scenario Engine'!ZU$16>0,'Scenario Engine'!ZV$16/'Scenario Engine'!ZU$16,0) | D11: ='Scenario Engine'!ZV$28 | E11: ='Scenario Engine'!ZW$28 | F11: ='Scenario Engine'!XO$64 | G11: ='Scenario Engine'!YG$64
A12: 0.25 | B12: ='Scenario Engine'!ABR$16 | C12: =IF('Scenario Engine'!ABQ$16>0,'Scenario Engine'!ABR$16/'Scenario Engine'!ABQ$16,0) | D12: ='Scenario Engine'!ABR$28 | E12: ='Scenario Engine'!ABS$28 | F12: ='Scenario Engine'!ZG$64 | G12: ='Scenario Engine'!ZY$64
A13: 0.3 | B13: ='Scenario Engine'!ADN$16 | C13: =IF('Scenario Engine'!ADM$16>0,'Scenario Engine'!ADN$16/'Scenario Engine'!ADM$16,0) | D13: ='Scenario Engine'!ADN$28 | E13: ='Scenario Engine'!ADO$28 | F13: ='Scenario Engine'!AAY$64 | G13: ='Scenario Engine'!ABQ$64
A14: 0.35 | B14: ='Scenario Engine'!AFJ$16 | C14: =IF('Scenario Engine'!AFI$16>0,'Scenario Engine'!AFJ$16/'Scenario Engine'!AFI$16,0) | D14: ='Scenario Engine'!AFJ$28 | E14: ='Scenario Engine'!AFK$28 | F14: ='Scenario Engine'!ACQ$64 | G14: ='Scenario Engine'!ADI$64
A15: 0.4 | B15: ='Scenario Engine'!AHF$16 | C15: =IF('Scenario Engine'!AHE$16>0,'Scenario Engine'!AHF$16/'Scenario Engine'!AHE$16,0) | D15: ='Scenario Engine'!AHF$28 | E15: ='Scenario Engine'!AHG$28 | F15: ='Scenario Engine'!AEI$64 | G15: ='Scenario Engine'!AFA$64

Sheet Sens - CAC & Marketing
A1: CAC Sensitivity — v3 Elite full model engine
A2: Edit CAC in column A (yellow). Sweep spans optimistic (£40) to conservative (£120).
A4: Current (Inputs) | B4: =CAC
A7: CAC (£) | B7: Y1 New Cust | C7: Y1 End Cust | D7: Y1 MRR | E7: Y2 MRR | F7: Y2 Cash | G7: Y5 Cash
A9: 40 | B9: =SUM('Scenario Engine'!AIJ$5:'Scenario Engine'!AIJ$16) | C9: ='Scenario Engine'!AJA$16 | D9: ='Scenario Engine'!AJB$16 | E9: ='Scenario Engine'!AJB$28 | F9: ='Scenario Engine'!AJU$28 | G9: ='Scenario Engine'!AJU$64
A10: 50 | B10: =SUM('Scenario Engine'!AKF$5:'Scenario Engine'!AKF$16) | C10: ='Scenario Engine'!AKW$16 | D10: ='Scenario Engine'!AKX$16 | E10: ='Scenario Engine'!AKX$28 | F10: ='Scenario Engine'!ALQ$28 | G10: ='Scenario Engine'!ALQ$64
A11: 60 | B11: =SUM('Scenario Engine'!AMB$5:'Scenario Engine'!AMB$16) | C11: ='Scenario Engine'!AMS$16 | D11: ='Scenario Engine'!AMT$16 | E11: ='Scenario Engine'!AMT$28 | F11: ='Scenario Engine'!ANM$28 | G11: ='Scenario Engine'!ANM$64
A12: 70 | B12: =SUM('Scenario Engine'!ANX$5:'Scenario Engine'!ANX$16) | C12: ='Scenario Engine'!AOO$16 | D12: ='Scenario Engine'!AOP$16 | E12: ='Scenario Engine'!AOP$28 | F12: ='Scenario Engine'!API$28 | G12: ='Scenario Engine'!API$64
A13: 80 | B13: =SUM('Scenario Engine'!APT$5:'Scenario Engine'!APT$16) | C13: ='Scenario Engine'!AQK$16 | D13: ='Scenario Engine'!AQL$16 | E13: ='Scenario Engine'!AQL$28 | F13: ='Scenario Engine'!ARE$28 | G13: ='Scenario Engine'!ARE$64
A14: 100 | B14: =SUM('Scenario Engine'!ARP$5:'Scenario Engine'!ARP$16) | C14: ='Scenario Engine'!ASG$16 | D14: ='Scenario Engine'!ASH$16 | E14: ='Scenario Engine'!ASH$28 | F14: ='Scenario Engine'!ATA$28 | G14: ='Scenario Engine'!ATA$64
A15: 120 | B15: =SUM('Scenario Engine'!ATL$5:'Scenario Engine'!ATL$16) | C15: ='Scenario Engine'!AUC$16 | D15: ='Scenario Engine'!AUD$16 | E15: ='Scenario Engine'!AUD$28 | F15: ='Scenario Engine'!AUW$28 | G15: ='Scenario Engine'!AUW$64

Sheet Sens - Winter Pivot
A1: Winter Pivot — Property Care Scenario (v3 Elite)
A2: Compares base garden seasonality vs year-round property care. Edit yellow cells. Pivot seasonality: Inputs cols E & F.
A4: SCENARIO ASSUMPTIONS
A5: Positioning | B5: Year-round property care subscription (mowing pauses Dec–Feb; gutter, leaf & patio included on Premium)
A6: Essential tier mix | B6: 0.65
A7: Premium price uplift (£/mo) | B7: 10
A8: Same as base | B8: CAC, churn rates, marketing & pricing otherwise from Inputs
A11: SEASONALITY COMPARISON (calendar month)
A12: Month | B12: Base acq | C12: Pivot acq | D12: Δ acq | E12: Base churn× | F12: Pivot churn× | G12: Δ churn
A13: Jan | B13: =Inputs!B74 | C13: =Inputs!E74 | D13: =C13-B13 | E13: =Inputs!D74 | F13: =Inputs!F74 | G13: =F13-E13
A14: Feb | B14: =Inputs!B75 | C14: =Inputs!E75 | D14: =C14-B14 | E14: =Inputs!D75 | F14: =Inputs!F75 | G14: =F14-E14
A15: Mar | B15: =Inputs!B76 | C15: =Inputs!E76 | D15: =C15-B15 | E15: =Inputs!D76 | F15: =Inputs!F76 | G15: =F15-E15
A16: Apr | B16: =Inputs!B77 | C16: =Inputs!E77 | D16: =C16-B16 | E16: =Inputs!D77 | F16: =Inputs!F77 | G16: =F16-E16
A17: May | B17: =Inputs!B78 | C17: =Inputs!E78 | D17: =C17-B17 | E17: =Inputs!D78 | F17: =Inputs!F78 | G17: =F17-E17
A18: Jun | B18: =Inputs!B79 | C18: =Inputs!E79 | D18: =C18-B18 | E18: =Inputs!D79 | F18: =Inputs!F79 | G18: =F18-E18
A19: Jul | B19: =Inputs!B80 | C19: =Inputs!E80 | D19: =C19-B19 | E19: =Inputs!D80 | F19: =Inputs!F80 | G19: =F19-E19
A20: Aug | B20: =Inputs!B81 | C20: =Inputs!E81 | D20: =C20-B20 | E20: =Inputs!D81 | F20: =Inputs!F81 | G20: =F20-E20
A21: Sep | B21: =Inputs!B82 | C21: =Inputs!E82 | D21: =C21-B21 | E21: =Inputs!D82 | F21: =Inputs!F82 | G21: =F21-E21
A22: Oct | B22: =Inputs!B83 | C22: =Inputs!E83 | D22: =C22-B22 | E22: =Inputs!D83 | F22: =Inputs!F83 | G22: =F22-E22
A23: Nov | B23: =Inputs!B84 | C23: =Inputs!E84 | D23: =C23-B23 | E23: =Inputs!D84 | F23: =Inputs!F84 | G23: =F23-E23
A24: Dec | B24: =Inputs!B85 | C24: =Inputs!E85 | D24: =C24-B24 | E24: =Inputs!D85 | F24: =Inputs!F85 | G24: =F24-E24
A27: OUTPUT COMPARISON — Base vs Winter Pivot (full model engine)
A28: Base = standard seasonality (Inputs cols B & D). Winter Pivot = cols E & F + Premium property care bundle.
A30: Metric | B30: Base | C30: Winter Pivot | D30: Delta
A31: End Year 1 — Customers | B31: ='Scenario Engine'!BU$16 | C31: ='Scenario Engine'!AVY$16 | D31: =C31-B31
A32: End Year 1 — MRR (£) | B32: ='Scenario Engine'!BV$16 | C32: ='Scenario Engine'!AVZ$16 | D32: =C32-B32
A33: End Year 1 — ARR (£) | B33: ='Scenario Engine'!BW$16 | C33: ='Scenario Engine'!AWA$16 | D33: =C33-B33
A34: End Year 1 — Cash (£) | B34: ='Scenario Engine'!CO$16 | C34: ='Scenario Engine'!AWS$16 | D34: =C34-B34
A35: Year 1 — Gross Revenue (£) | B35: =SUM('Scenario Engine'!CA$5:'Scenario Engine'!CA$16) | C35: =SUM('Scenario Engine'!AWE$5:'Scenario Engine'!AWE$16) | D35: =C35-B35
A36: Year 1 — Profit (£) | B36: =SUM('Scenario Engine'!CN$5:'Scenario Engine'!CN$16) | C36: =SUM('Scenario Engine'!AWR$5:'Scenario Engine'!AWR$16) | D36: =C36-B36
A37: End Year 2 — Customers | B37: ='Scenario Engine'!BU$28 | C37: ='Scenario Engine'!AVY$28 | D37: =C37-B37
A38: End Year 2 — MRR (£) | B38: ='Scenario Engine'!BV$28 | C38: ='Scenario Engine'!AVZ$28 | D38: =C38-B38
A39: End Year 2 — Cash (£) | B39: ='Scenario Engine'!CO$28 | C39: ='Scenario Engine'!AWS$28 | D39: =C39-B39
A40: End Year 5 — Customers | B40: ='Scenario Engine'!BU$64 | C40: ='Scenario Engine'!AVY$64 | D40: =C40-B40
A41: End Year 5 — MRR (£) | B41: ='Scenario Engine'!BV$64 | C41: ='Scenario Engine'!AVZ$64 | D41: =C41-B41
A42: End Year 5 — Cash (£) | B42: ='Scenario Engine'!CO$64 | C42: ='Scenario Engine'!AWS$64 | D42: =C42-B42

Sheet Model
A1: 60-Month Model v4 — 10/20/30 visits per year + VAT principal/agent toggle
A4: Mo | B4: Cal | C4: CY | D4: Acq | E4: Infl | F4: ECh | G4: Mkt | H4: Paid | I4: Ref | J4: Tot | K4: NMo | L4: NAn | M4: NEsM | N4: NPrM | O4: NElM | P4: NEsA | Q4: NPrA | R4: NElA | S4: AEsM | T4: APrM | U4: AElM | V4: AEsA | W4: APrA | X4: AElA | Y4: Cust | Z4: MRR | AA4: ARR | AB4: Mo$ | AC4: NwAn | AD4: Ren | AE4: Gross | AF4: R12 | AG4: VAT | AH4: Net | AI4: VAcc | AJ4: VPay | AK4: VBal | AL4: Prov | AM4: Fee | AN4: Ops | AO4: Fix | AP4: Ref$ | AQ4: Mkt | AR4: Pft | AS4: Cash | AT4: ARPU | AU4: Chrn
A5: 1 | B5: =MOD(A5-1+LaunchMonth-1,12)+1 | C5: =INT((A5-1+LaunchMonth-1)/12)+1 | D5: =VLOOKUP(B5,SeasonTable,2,FALSE) | E5: =(1+InflationRate)^INT((A5-1)/12) | F5: =MonthlyChurn*VLOOKUP(B5,ChurnSeasonTable,4,FALSE) | G5: =MktFixed1_3 | H5: =IF(G5>0,MAX(1,ROUND(G5/CAC*D5,0)),0) | I5: =IF(H5>0,ROUND(H5*ReferralMix/(1-ReferralMix),0),0) | J5: =H5+I5 | K5: =ROUND(J5*(1-AnnualMix),0) | L5: =J5-K5 | M5: =ROUND(K5*EssentialMix,0) | N5: =ROUND(K5*PremiumMix,0) | O5: =K5-M5-N5 | P5: =ROUND(L5*EssentialMix,0) | Q5: =ROUND(L5*PremiumMix,0) | R5: =L5-P5-Q5 | S5: =M5 | T5: =N5 | U5: =O5 | V5: =P5 | W5: =Q5 | X5: =R5 | Y5: =S5+T5+U5+V5+W5+X5 | Z5: =S5*BlendedPriceEssMonthly*E5+T5*BlendedPricePremMonthly*E5+U5*BlendedPriceEliteMonthly*E5+V5*BlendedPriceEssAnnual*E5/12+W5*BlendedPricePremAnnual*E5/12+X5*BlendedPriceEliteAnnual*E5/12 | AA5: =Z5*12 | AB5: =S5*BlendedPriceEssMonthly*E5+T5*BlendedPricePremMonthly*E5+U5*BlendedPriceEliteMonthly*E5 | AC5: =P5*BlendedPriceEssAnnual*E5+Q5*BlendedPricePremAnnual*E5+R5*BlendedPriceEliteAnnual*E5 | AD5: =0+0+0 | AE5: =AB5+AC5+AD5 | AF5: =SUM(AE$5:AE5) | AG5: =IF(VATAgentMode,SUM($AE$5:$AE5)-SUM($AL$5:$AL5)>=VATThreshold,SUM($AE$5:$AE5)>=VATThreshold) | AH5: =IF(AG5,IF(VATAgentMode,AE5-((AE5-AL5)-(AE5-AL5)/(1+VATRate)),AE5/(1+VATRate)),AE5) | AI5: =AE5-AH5 | AJ5: =IF(AG5=0,0,IF(B5=1,SUMPRODUCT(--(($C$5:$C5=$C5-1)*($B$5:$B5>=10)*($B$5:$B5<=12)),$AI$5:$AI5),IF(B5=4,SUMPRODUCT(--(($C$5:$C5=$C5)*($B$5:$B5>=1)*($B$5:$B5<=3)),$AI$5:$AI5),IF(B5=7,SUMPRODUCT(--(($C$5:$C5=$C5)*($B$5:$B5>=4)*($B$5:$B5<=6)),$AI$5:$AI5),IF(B5=10,SUMPRODUCT(--(($C$5:$C5=$C5)*($B$5:$B5>=7)*($B$5:$B5<=9)),$AI$5:$AI5),0))))) | AK5: =AI5-AJ5 | AL5: =IF(ProviderDelay>=1,0,S5*BlendedProvPayEss+T5*BlendedProvPayPrem+U5*BlendedProvPayElite+V5*BlendedProvPayEss+W5*BlendedProvPayPrem+X5*BlendedProvPayElite) | AM5: =AE5*PaymentFee | AN5: =Y5*OpsAI | AO5: =MonthlyFixed | AP5: =I5*ReferralReward | AQ5: =G5 | AR5: =AH5-AL5-AM5-AN5-AO5-AP5-AQ5 | AS5: =InitialInvestment+AE5-(AL5+AM5+AN5+AO5+AP5+AQ5+AJ5) | AT5: =IF(Y5>0,Z5/Y5,0) | AU5: 0
A6: 2 | B6: =MOD(A6-1+LaunchMonth-1,12)+1 | C6: =INT((A6-1+LaunchMonth-1)/12)+1 | D6: =VLOOKUP(B6,SeasonTable,2,FALSE) | E6: =(1+InflationRate)^INT((A6-1)/12) | F6: =MonthlyChurn*VLOOKUP(B6,ChurnSeasonTable,4,FALSE) | G6: =MktFixed1_3 | H6: =IF(G6>0,MAX(1,ROUND(G6/CAC*D6,0)),0) | I6: =IF(H6>0,ROUND(H6*ReferralMix/(1-ReferralMix),0),0) | J6: =H6+I6 | K6: =ROUND(J6*(1-AnnualMix),0) | L6: =J6-K6 | M6: =ROUND(K6*EssentialMix,0) | N6: =ROUND(K6*PremiumMix,0) | O6: =K6-M6-N6 | P6: =ROUND(L6*EssentialMix,0) | Q6: =ROUND(L6*PremiumMix,0) | R6: =L6-P6-Q6 | S6: =M6+M5 | T6: =N6+N5 | U6: =O6+O5 | V6: =SUM(P$5:P6) | W6: =SUM(Q$5:Q6) | X6: =SUM(R$5:R6) | Y6: =S6+T6+U6+V6+W6+X6 | Z6: =S6*BlendedPriceEssMonthly*E6+T6*BlendedPricePremMonthly*E6+U6*BlendedPriceEliteMonthly*E6+V6*BlendedPriceEssAnnual*E6/12+W6*BlendedPricePremAnnual*E6/12+X6*BlendedPriceEliteAnnual*E6/12 | AA6: =Z6*12 | AB6: =S6*BlendedPriceEssMonthly*E6+T6*BlendedPricePremMonthly*E6+U6*BlendedPriceEliteMonthly*E6 | AC6: =P6*BlendedPriceEssAnnual*E6+Q6*BlendedPricePremAnnual*E6+R6*BlendedPriceEliteAnnual*E6 | AD6: =0+0+0 | AE6: =AB6+AC6+AD6 | AF6: =SUM(AE$5:AE6) | AG6: =OR(AG5,IF(VATAgentMode,SUM($AE$5:$AE6)-SUM($AL$5:$AL6)>=VATThreshold,SUM($AE$5:$AE6)>=VATThreshold)) | AH6: =IF(AG6,IF(VATAgentMode,AE6-((AE6-AL6)-(AE6-AL6)/(1+VATRate)),AE6/(1+VATRate)),AE6) | AI6: =AE6-AH6 | AJ6: =IF(AG6=0,0,IF(B6=1,SUMPRODUCT(--(($C$5:$C6=$C6-1)*($B$5:$B6>=10)*($B$5:$B6<=12)),$AI$5:$AI6),IF(B6=4,SUMPRODUCT(--(($C$5:$C6=$C6)*($B$5:$B6>=1)*($B$5:$B6<=3)),$AI$5:$AI6),IF(B6=7,SUMPRODUCT(--(($C$5:$C6=$C6)*($B$5:$B6>=4)*($B$5:$B6<=6)),$AI$5:$AI6),IF(B6=10,SUMPRODUCT(--(($C$5:$C6=$C6)*($B$5:$B6>=7)*($B$5:$B6<=9)),$AI$5:$AI6),0))))) | AK6: =AK5+AI6-AJ6 | AL6: =IF(ProviderDelay>=1,S5*BlendedProvPayEss+T5*BlendedProvPayPrem+U5*BlendedProvPayElite+V5*BlendedProvPayEss+W5*BlendedProvPayPrem+X5*BlendedProvPayElite,S6*BlendedProvPayEss+T6*BlendedProvPayPrem+U6*BlendedProvPayElite+V6*BlendedProvPayEss+W6*BlendedProvPayPrem+X6*BlendedProvPayElite) | AM6: =AE6*PaymentFee | AN6: =Y6*OpsAI | AO6: =MonthlyFixed | AP6: =I6*ReferralReward | AQ6: =G6 | AR6: =AH6-AL6-AM6-AN6-AO6-AP6-AQ6 | AS6: =AS5+AE6-(AL6+AM6+AN6+AO6+AP6+AQ6+AJ6) | AT6: =IF(Y6>0,Z6/Y6,0) | AU6: =IF(Y5>0,MAX(0,(Y5+J6-Y6)/Y5),0)
A7: 3 | B7: =MOD(A7-1+LaunchMonth-1,12)+1 | C7: =INT((A7-1+LaunchMonth-1)/12)+1 | D7: =VLOOKUP(B7,SeasonTable,2,FALSE) | E7: =(1+InflationRate)^INT((A7-1)/12) | F7: =MonthlyChurn*VLOOKUP(B7,ChurnSeasonTable,4,FALSE) | G7: =MktFixed1_3 | H7: =IF(G7>0,MAX(1,ROUND(G7/CAC*D7,0)),0) | I7: =IF(H7>0,ROUND(H7*ReferralMix/(1-ReferralMix),0),0) | J7: =H7+I7 | K7: =ROUND(J7*(1-AnnualMix),0) | L7: =J7-K7 | M7: =ROUND(K7*EssentialMix,0) | N7: =ROUND(K7*PremiumMix,0) | O7: =K7-M7-N7 | P7: =ROUND(L7*EssentialMix,0) | Q7: =ROUND(L7*PremiumMix,0) | R7: =L7-P7-Q7 | S7: =M7+M6+M5 | T7: =N7+N6+N5 | U7: =O7+O6+O5 | V7: =SUM(P$5:P7) | W7: =SUM(Q$5:Q7) | X7: =SUM(R$5:R7) | Y7: =S7+T7+U7+V7+W7+X7 | Z7: =S7*BlendedPriceEssMonthly*E7+T7*BlendedPricePremMonthly*E7+U7*BlendedPriceEliteMonthly*E7+V7*BlendedPriceEssAnnual*E7/12+W7*BlendedPricePremAnnual*E7/12+X7*BlendedPriceEliteAnnual*E7/12 | AA7: =Z7*12 | AB7: =S7*BlendedPriceEssMonthly*E7+T7*BlendedPricePremMonthly*E7+U7*BlendedPriceEliteMonthly*E7 | AC7: =P7*BlendedPriceEssAnnual*E7+Q7*BlendedPricePremAnnual*E7+R7*BlendedPriceEliteAnnual*E7 | AD7: =0+0+0 | AE7: =AB7+AC7+AD7 | AF7: =SUM(AE$5:AE7) | AG7: =OR(AG6,IF(VATAgentMode,SUM($AE$5:$AE7)-SUM($AL$5:$AL7)>=VATThreshold,SUM($AE$5:$AE7)>=VATThreshold)) | AH7: =IF(AG7,IF(VATAgentMode,AE7-((AE7-AL7)-(AE7-AL7)/(1+VATRate)),AE7/(1+VATRate)),AE7) | AI7: =AE7-AH7 | AJ7: =IF(AG7=0,0,IF(B7=1,SUMPRODUCT(--(($C$5:$C7=$C7-1)*($B$5:$B7>=10)*($B$5:$B7<=12)),$AI$5:$AI7),IF(B7=4,SUMPRODUCT(--(($C$5:$C7=$C7)*($B$5:$B7>=1)*($B$5:$B7<=3)),$AI$5:$AI7),IF(B7=7,SUMPRODUCT(--(($C$5:$C7=$C7)*($B$5:$B7>=4)*($B$5:$B7<=6)),$AI$5:$AI7),IF(B7=10,SUMPRODUCT(--(($C$5:$C7=$C7)*($B$5:$B7>=7)*($B$5:$B7<=9)),$AI$5:$AI7),0))))) | AK7: =AK6+AI7-AJ7 | AL7: =IF(ProviderDelay>=1,S6*BlendedProvPayEss+T6*BlendedProvPayPrem+U6*BlendedProvPayElite+V6*BlendedProvPayEss+W6*BlendedProvPayPrem+X6*BlendedProvPayElite,S7*BlendedProvPayEss+T7*BlendedProvPayPrem+U7*BlendedProvPayElite+V7*BlendedProvPayEss+W7*BlendedProvPayPrem+X7*BlendedProvPayElite) | AM7: =AE7*PaymentFee | AN7: =Y7*OpsAI | AO7: =MonthlyFixed | AP7: =I7*ReferralReward | AQ7: =G7 | AR7: =AH7-AL7-AM7-AN7-AO7-AP7-AQ7 | AS7: =AS6+AE7-(AL7+AM7+AN7+AO7+AP7+AQ7+AJ7) | AT7: =IF(Y7>0,Z7/Y7,0) | AU7: =IF(Y6>0,MAX(0,(Y6+J7-Y7)/Y6),0)
A8: 4 | B8: =MOD(A8-1+LaunchMonth-1,12)+1 | C8: =INT((A8-1+LaunchMonth-1)/12)+1 | D8: =VLOOKUP(B8,SeasonTable,2,FALSE) | E8: =(1+InflationRate)^INT((A8-1)/12) | F8: =MonthlyChurn*VLOOKUP(B8,ChurnSeasonTable,4,FALSE) | G8: =MIN(MktFixed4_6,MAX(0,AS7-CashBuffer)) | H8: =IF(G8>0,MAX(1,ROUND(G8/CAC*D8,0)),0) | I8: =IF(H8>0,ROUND(H8*ReferralMix/(1-ReferralMix),0),0) | J8: =H8+I8 | K8: =ROUND(J8*(1-AnnualMix),0) | L8: =J8-K8 | M8: =ROUND(K8*EssentialMix,0) | N8: =ROUND(K8*PremiumMix,0) | O8: =K8-M8-N8 | P8: =ROUND(L8*EssentialMix,0) | Q8: =ROUND(L8*PremiumMix,0) | R8: =L8-P8-Q8 | S8: =M8+M7+M6+MAX(0,S7-M7-M6)*(1-F8) | T8: =N8+N7+N6+MAX(0,T7-N7-N6)*(1-F8) | U8: =O8+O7+O6+MAX(0,U7-O7-O6)*(1-F8) | V8: =SUM(P$5:P8) | W8: =SUM(Q$5:Q8) | X8: =SUM(R$5:R8) | Y8: =S8+T8+U8+V8+W8+X8 | Z8: =S8*BlendedPriceEssMonthly*E8+T8*BlendedPricePremMonthly*E8+U8*BlendedPriceEliteMonthly*E8+V8*BlendedPriceEssAnnual*E8/12+W8*BlendedPricePremAnnual*E8/12+X8*BlendedPriceEliteAnnual*E8/12 | AA8: =Z8*12 | AB8: =S8*BlendedPriceEssMonthly*E8+T8*BlendedPricePremMonthly*E8+U8*BlendedPriceEliteMonthly*E8 | AC8: =P8*BlendedPriceEssAnnual*E8+Q8*BlendedPricePremAnnual*E8+R8*BlendedPriceEliteAnnual*E8 | AD8: =0+0+0 | AE8: =AB8+AC8+AD8 | AF8: =SUM(AE$5:AE8) | AG8: =OR(AG7,IF(VATAgentMode,SUM($AE$5:$AE8)-SUM($AL$5:$AL8)>=VATThreshold,SUM($AE$5:$AE8)>=VATThreshold)) | AH8: =IF(AG8,IF(VATAgentMode,AE8-((AE8-AL8)-(AE8-AL8)/(1+VATRate)),AE8/(1+VATRate)),AE8) | AI8: =AE8-AH8 | AJ8: =IF(AG8=0,0,IF(B8=1,SUMPRODUCT(--(($C$5:$C8=$C8-1)*($B$5:$B8>=10)*($B$5:$B8<=12)),$AI$5:$AI8),IF(B8=4,SUMPRODUCT(--(($C$5:$C8=$C8)*($B$5:$B8>=1)*($B$5:$B8<=3)),$AI$5:$AI8),IF(B8=7,SUMPRODUCT(--(($C$5:$C8=$C8)*($B$5:$B8>=4)*($B$5:$B8<=6)),$AI$5:$AI8),IF(B8=10,SUMPRODUCT(--(($C$5:$C8=$C8)*($B$5:$B8>=7)*($B$5:$B8<=9)),$AI$5:$AI8),0))))) | AK8: =AK7+AI8-AJ8 | AL8: =IF(ProviderDelay>=1,S7*BlendedProvPayEss+T7*BlendedProvPayPrem+U7*BlendedProvPayElite+V7*BlendedProvPayEss+W7*BlendedProvPayPrem+X7*BlendedProvPayElite,S8*BlendedProvPayEss+T8*BlendedProvPayPrem+U8*BlendedProvPayElite+V8*BlendedProvPayEss+W8*BlendedProvPayPrem+X8*BlendedProvPayElite) | AM8: =AE8*PaymentFee | AN8: =Y8*OpsAI | AO8: =MonthlyFixed | AP8: =I8*ReferralReward | AQ8: =G8 | AR8: =AH8-AL8-AM8-AN8-AO8-AP8-AQ8 | AS8: =AS7+AE8-(AL8+AM8+AN8+AO8+AP8+AQ8+AJ8) | AT8: =IF(Y8>0,Z8/Y8,0) | AU8: =IF(Y7>0,MAX(0,(Y7+J8-Y8)/Y7),0)
A9: 5 | B9: =MOD(A9-1+LaunchMonth-1,12)+1 | C9: =INT((A9-1+LaunchMonth-1)/12)+1 | D9: =VLOOKUP(B9,SeasonTable,2,FALSE) | E9: =(1+InflationRate)^INT((A9-1)/12) | F9: =MonthlyChurn*VLOOKUP(B9,ChurnSeasonTable,4,FALSE) | G9: =MIN(MktFixed4_6,MAX(0,AS8-CashBuffer)) | H9: =IF(G9>0,MAX(1,ROUND(G9/CAC*D9,0)),0) | I9: =IF(H9>0,ROUND(H9*ReferralMix/(1-ReferralMix),0),0) | J9: =H9+I9 | K9: =ROUND(J9*(1-AnnualMix),0) | L9: =J9-K9 | M9: =ROUND(K9*EssentialMix,0) | N9: =ROUND(K9*PremiumMix,0) | O9: =K9-M9-N9 | P9: =ROUND(L9*EssentialMix,0) | Q9: =ROUND(L9*PremiumMix,0) | R9: =L9-P9-Q9 | S9: =M9+M8+M7+MAX(0,S8-M8-M7)*(1-F9) | T9: =N9+N8+N7+MAX(0,T8-N8-N7)*(1-F9) | U9: =O9+O8+O7+MAX(0,U8-O8-O7)*(1-F9) | V9: =SUM(P$5:P9) | W9: =SUM(Q$5:Q9) | X9: =SUM(R$5:R9) | Y9: =S9+T9+U9+V9+W9+X9 | Z9: =S9*BlendedPriceEssMonthly*E9+T9*BlendedPricePremMonthly*E9+U9*BlendedPriceEliteMonthly*E9+V9*BlendedPriceEssAnnual*E9/12+W9*BlendedPricePremAnnual*E9/12+X9*BlendedPriceEliteAnnual*E9/12 | AA9: =Z9*12 | AB9: =S9*BlendedPriceEssMonthly*E9+T9*BlendedPricePremMonthly*E9+U9*BlendedPriceEliteMonthly*E9 | AC9: =P9*BlendedPriceEssAnnual*E9+Q9*BlendedPricePremAnnual*E9+R9*BlendedPriceEliteAnnual*E9 | AD9: =0+0+0 | AE9: =AB9+AC9+AD9 | AF9: =SUM(AE$5:AE9) | AG9: =OR(AG8,IF(VATAgentMode,SUM($AE$5:$AE9)-SUM($AL$5:$AL9)>=VATThreshold,SUM($AE$5:$AE9)>=VATThreshold)) | AH9: =IF(AG9,IF(VATAgentMode,AE9-((AE9-AL9)-(AE9-AL9)/(1+VATRate)),AE9/(1+VATRate)),AE9) | AI9: =AE9-AH9 | AJ9: =IF(AG9=0,0,IF(B9=1,SUMPRODUCT(--(($C$5:$C9=$C9-1)*($B$5:$B9>=10)*($B$5:$B9<=12)),$AI$5:$AI9),IF(B9=4,SUMPRODUCT(--(($C$5:$C9=$C9)*($B$5:$B9>=1)*($B$5:$B9<=3)),$AI$5:$AI9),IF(B9=7,SUMPRODUCT(--(($C$5:$C9=$C9)*($B$5:$B9>=4)*($B$5:$B9<=6)),$AI$5:$AI9),IF(B9=10,SUMPRODUCT(--(($C$5:$C9=$C9)*($B$5:$B9>=7)*($B$5:$B9<=9)),$AI$5:$AI9),0))))) | AK9: =AK8+AI9-AJ9 | AL9: =IF(ProviderDelay>=1,S8*BlendedProvPayEss+T8*BlendedProvPayPrem+U8*BlendedProvPayElite+V8*BlendedProvPayEss+W8*BlendedProvPayPrem+X8*BlendedProvPayElite,S9*BlendedProvPayEss+T9*BlendedProvPayPrem+U9*BlendedProvPayElite+V9*BlendedProvPayEss+W9*BlendedProvPayPrem+X9*BlendedProvPayElite) | AM9: =AE9*PaymentFee | AN9: =Y9*OpsAI | AO9: =MonthlyFixed | AP9: =I9*ReferralReward | AQ9: =G9 | AR9: =AH9-AL9-AM9-AN9-AO9-AP9-AQ9 | AS9: =AS8+AE9-(AL9+AM9+AN9+AO9+AP9+AQ9+AJ9) | AT9: =IF(Y9>0,Z9/Y9,0) | AU9: =IF(Y8>0,MAX(0,(Y8+J9-Y9)/Y8),0)
A10: 6 | B10: =MOD(A10-1+LaunchMonth-1,12)+1 | C10: =INT((A10-1+LaunchMonth-1)/12)+1 | D10: =VLOOKUP(B10,SeasonTable,2,FALSE) | E10: =(1+InflationRate)^INT((A10-1)/12) | F10: =MonthlyChurn*VLOOKUP(B10,ChurnSeasonTable,4,FALSE) | G10: =MIN(MktFixed4_6,MAX(0,AS9-CashBuffer)) | H10: =IF(G10>0,MAX(1,ROUND(G10/CAC*D10,0)),0) | I10: =IF(H10>0,ROUND(H10*ReferralMix/(1-ReferralMix),0),0) | J10: =H10+I10 | K10: =ROUND(J10*(1-AnnualMix),0) | L10: =J10-K10 | M10: =ROUND(K10*EssentialMix,0) | N10: =ROUND(K10*PremiumMix,0) | O10: =K10-M10-N10 | P10: =ROUND(L10*EssentialMix,0) | Q10: =ROUND(L10*PremiumMix,0) | R10: =L10-P10-Q10 | S10: =M10+M9+M8+MAX(0,S9-M9-M8)*(1-F10) | T10: =N10+N9+N8+MAX(0,T9-N9-N8)*(1-F10) | U10: =O10+O9+O8+MAX(0,U9-O9-O8)*(1-F10) | V10: =SUM(P$5:P10) | W10: =SUM(Q$5:Q10) | X10: =SUM(R$5:R10) | Y10: =S10+T10+U10+V10+W10+X10 | Z10: =S10*BlendedPriceEssMonthly*E10+T10*BlendedPricePremMonthly*E10+U10*BlendedPriceEliteMonthly*E10+V10*BlendedPriceEssAnnual*E10/12+W10*BlendedPricePremAnnual*E10/12+X10*BlendedPriceEliteAnnual*E10/12 | AA10: =Z10*12 | AB10: =S10*BlendedPriceEssMonthly*E10+T10*BlendedPricePremMonthly*E10+U10*BlendedPriceEliteMonthly*E10 | AC10: =P10*BlendedPriceEssAnnual*E10+Q10*BlendedPricePremAnnual*E10+R10*BlendedPriceEliteAnnual*E10 | AD10: =0+0+0 | AE10: =AB10+AC10+AD10 | AF10: =SUM(AE$5:AE10) | AG10: =OR(AG9,IF(VATAgentMode,SUM($AE$5:$AE10)-SUM($AL$5:$AL10)>=VATThreshold,SUM($AE$5:$AE10)>=VATThreshold)) | AH10: =IF(AG10,IF(VATAgentMode,AE10-((AE10-AL10)-(AE10-AL10)/(1+VATRate)),AE10/(1+VATRate)),AE10) | AI10: =AE10-AH10 | AJ10: =IF(AG10=0,0,IF(B10=1,SUMPRODUCT(--(($C$5:$C10=$C10-1)*($B$5:$B10>=10)*($B$5:$B10<=12)),$AI$5:$AI10),IF(B10=4,SUMPRODUCT(--(($C$5:$C10=$C10)*($B$5:$B10>=1)*($B$5:$B10<=3)),$AI$5:$AI10),IF(B10=7,SUMPRODUCT(--(($C$5:$C10=$C10)*($B$5:$B10>=4)*($B$5:$B10<=6)),$AI$5:$AI10),IF(B10=10,SUMPRODUCT(--(($C$5:$C10=$C10)*($B$5:$B10>=7)*($B$5:$B10<=9)),$AI$5:$AI10),0))))) | AK10: =AK9+AI10-AJ10 | AL10: =IF(ProviderDelay>=1,S9*BlendedProvPayEss+T9*BlendedProvPayPrem+U9*BlendedProvPayElite+V9*BlendedProvPayEss+W9*BlendedProvPayPrem+X9*BlendedProvPayElite,S10*BlendedProvPayEss+T10*BlendedProvPayPrem+U10*BlendedProvPayElite+V10*BlendedProvPayEss+W10*BlendedProvPayPrem+X10*BlendedProvPayElite) | AM10: =AE10*PaymentFee | AN10: =Y10*OpsAI | AO10: =MonthlyFixed | AP10: =I10*ReferralReward | AQ10: =G10 | AR10: =AH10-AL10-AM10-AN10-AO10-AP10-AQ10 | AS10: =AS9+AE10-(AL10+AM10+AN10+AO10+AP10+AQ10+AJ10) | AT10: =IF(Y10>0,Z10/Y10,0) | AU10: =IF(Y9>0,MAX(0,(Y9+J10-Y10)/Y9),0)
A11: 7 | B11: =MOD(A11-1+LaunchMonth-1,12)+1 | C11: =INT((A11-1+LaunchMonth-1)/12)+1 | D11: =VLOOKUP(B11,SeasonTable,2,FALSE) | E11: =(1+InflationRate)^INT((A11-1)/12) | F11: =MonthlyChurn*VLOOKUP(B11,ChurnSeasonTable,4,FALSE) | G11: =MIN(MAX(MktMin7_12,AE10*MktPct7_12),MAX(0,AS10-CashBuffer)) | H11: =IF(G11>0,MAX(1,ROUND(G11/CAC*D11,0)),0) | I11: =IF(H11>0,ROUND(H11*ReferralMix/(1-ReferralMix),0),0) | J11: =H11+I11 | K11: =ROUND(J11*(1-AnnualMix),0) | L11: =J11-K11 | M11: =ROUND(K11*EssentialMix,0) | N11: =ROUND(K11*PremiumMix,0) | O11: =K11-M11-N11 | P11: =ROUND(L11*EssentialMix,0) | Q11: =ROUND(L11*PremiumMix,0) | R11: =L11-P11-Q11 | S11: =M11+M10+M9+MAX(0,S10-M10-M9)*(1-F11) | T11: =N11+N10+N9+MAX(0,T10-N10-N9)*(1-F11) | U11: =O11+O10+O9+MAX(0,U10-O10-O9)*(1-F11) | V11: =SUM(P$5:P11) | W11: =SUM(Q$5:Q11) | X11: =SUM(R$5:R11) | Y11: =S11+T11+U11+V11+W11+X11 | Z11: =S11*BlendedPriceEssMonthly*E11+T11*BlendedPricePremMonthly*E11+U11*BlendedPriceEliteMonthly*E11+V11*BlendedPriceEssAnnual*E11/12+W11*BlendedPricePremAnnual*E11/12+X11*BlendedPriceEliteAnnual*E11/12 | AA11: =Z11*12 | AB11: =S11*BlendedPriceEssMonthly*E11+T11*BlendedPricePremMonthly*E11+U11*BlendedPriceEliteMonthly*E11 | AC11: =P11*BlendedPriceEssAnnual*E11+Q11*BlendedPricePremAnnual*E11+R11*BlendedPriceEliteAnnual*E11 | AD11: =0+0+0 | AE11: =AB11+AC11+AD11 | AF11: =SUM(AE$5:AE11) | AG11: =OR(AG10,IF(VATAgentMode,SUM($AE$5:$AE11)-SUM($AL$5:$AL11)>=VATThreshold,SUM($AE$5:$AE11)>=VATThreshold)) | AH11: =IF(AG11,IF(VATAgentMode,AE11-((AE11-AL11)-(AE11-AL11)/(1+VATRate)),AE11/(1+VATRate)),AE11) | AI11: =AE11-AH11 | AJ11: =IF(AG11=0,0,IF(B11=1,SUMPRODUCT(--(($C$5:$C11=$C11-1)*($B$5:$B11>=10)*($B$5:$B11<=12)),$AI$5:$AI11),IF(B11=4,SUMPRODUCT(--(($C$5:$C11=$C11)*($B$5:$B11>=1)*($B$5:$B11<=3)),$AI$5:$AI11),IF(B11=7,SUMPRODUCT(--(($C$5:$C11=$C11)*($B$5:$B11>=4)*($B$5:$B11<=6)),$AI$5:$AI11),IF(B11=10,SUMPRODUCT(--(($C$5:$C11=$C11)*($B$5:$B11>=7)*($B$5:$B11<=9)),$AI$5:$AI11),0))))) | AK11: =AK10+AI11-AJ11 | AL11: =IF(ProviderDelay>=1,S10*BlendedProvPayEss+T10*BlendedProvPayPrem+U10*BlendedProvPayElite+V10*BlendedProvPayEss+W10*BlendedProvPayPrem+X10*BlendedProvPayElite,S11*BlendedProvPayEss+T11*BlendedProvPayPrem+U11*BlendedProvPayElite+V11*BlendedProvPayEss+W11*BlendedProvPayPrem+X11*BlendedProvPayElite) | AM11: =AE11*PaymentFee | AN11: =Y11*OpsAI | AO11: =MonthlyFixed | AP11: =I11*ReferralReward | AQ11: =G11 | AR11: =AH11-AL11-AM11-AN11-AO11-AP11-AQ11 | AS11: =AS10+AE11-(AL11+AM11+AN11+AO11+AP11+AQ11+AJ11) | AT11: =IF(Y11>0,Z11/Y11,0) | AU11: =IF(Y10>0,MAX(0,(Y10+J11-Y11)/Y10),0)
A12: 8 | B12: =MOD(A12-1+LaunchMonth-1,12)+1 | C12: =INT((A12-1+LaunchMonth-1)/12)+1 | D12: =VLOOKUP(B12,SeasonTable,2,FALSE) | E12: =(1+InflationRate)^INT((A12-1)/12) | F12: =MonthlyChurn*VLOOKUP(B12,ChurnSeasonTable,4,FALSE) | G12: =MIN(MAX(MktMin7_12,AE11*MktPct7_12),MAX(0,AS11-CashBuffer)) | H12: =IF(G12>0,MAX(1,ROUND(G12/CAC*D12,0)),0) | I12: =IF(H12>0,ROUND(H12*ReferralMix/(1-ReferralMix),0),0) | J12: =H12+I12 | K12: =ROUND(J12*(1-AnnualMix),0) | L12: =J12-K12 | M12: =ROUND(K12*EssentialMix,0) | N12: =ROUND(K12*PremiumMix,0) | O12: =K12-M12-N12 | P12: =ROUND(L12*EssentialMix,0) | Q12: =ROUND(L12*PremiumMix,0) | R12: =L12-P12-Q12 | S12: =M12+M11+M10+MAX(0,S11-M11-M10)*(1-F12) | T12: =N12+N11+N10+MAX(0,T11-N11-N10)*(1-F12) | U12: =O12+O11+O10+MAX(0,U11-O11-O10)*(1-F12) | V12: =SUM(P$5:P12) | W12: =SUM(Q$5:Q12) | X12: =SUM(R$5:R12) | Y12: =S12+T12+U12+V12+W12+X12 | Z12: =S12*BlendedPriceEssMonthly*E12+T12*BlendedPricePremMonthly*E12+U12*BlendedPriceEliteMonthly*E12+V12*BlendedPriceEssAnnual*E12/12+W12*BlendedPricePremAnnual*E12/12+X12*BlendedPriceEliteAnnual*E12/12 | AA12: =Z12*12 | AB12: =S12*BlendedPriceEssMonthly*E12+T12*BlendedPricePremMonthly*E12+U12*BlendedPriceEliteMonthly*E12 | AC12: =P12*BlendedPriceEssAnnual*E12+Q12*BlendedPricePremAnnual*E12+R12*BlendedPriceEliteAnnual*E12 | AD12: =0+0+0 | AE12: =AB12+AC12+AD12 | AF12: =SUM(AE$5:AE12) | AG12: =OR(AG11,IF(VATAgentMode,SUM($AE$5:$AE12)-SUM($AL$5:$AL12)>=VATThreshold,SUM($AE$5:$AE12)>=VATThreshold)) | AH12: =IF(AG12,IF(VATAgentMode,AE12-((AE12-AL12)-(AE12-AL12)/(1+VATRate)),AE12/(1+VATRate)),AE12) | AI12: =AE12-AH12 | AJ12: =IF(AG12=0,0,IF(B12=1,SUMPRODUCT(--(($C$5:$C12=$C12-1)*($B$5:$B12>=10)*($B$5:$B12<=12)),$AI$5:$AI12),IF(B12=4,SUMPRODUCT(--(($C$5:$C12=$C12)*($B$5:$B12>=1)*($B$5:$B12<=3)),$AI$5:$AI12),IF(B12=7,SUMPRODUCT(--(($C$5:$C12=$C12)*($B$5:$B12>=4)*($B$5:$B12<=6)),$AI$5:$AI12),IF(B12=10,SUMPRODUCT(--(($C$5:$C12=$C12)*($B$5:$B12>=7)*($B$5:$B12<=9)),$AI$5:$AI12),0))))) | AK12: =AK11+AI12-AJ12 | AL12: =IF(ProviderDelay>=1,S11*BlendedProvPayEss+T11*BlendedProvPayPrem+U11*BlendedProvPayElite+V11*BlendedProvPayEss+W11*BlendedProvPayPrem+X11*BlendedProvPayElite,S12*BlendedProvPayEss+T12*BlendedProvPayPrem+U12*BlendedProvPayElite+V12*BlendedProvPayEss+W12*BlendedProvPayPrem+X12*BlendedProvPayElite) | AM12: =AE12*PaymentFee | AN12: =Y12*OpsAI | AO12: =MonthlyFixed | AP12: =I12*ReferralReward | AQ12: =G12 | AR12: =AH12-AL12-AM12-AN12-AO12-AP12-AQ12 | AS12: =AS11+AE12-(AL12+AM12+AN12+AO12+AP12+AQ12+AJ12) | AT12: =IF(Y12>0,Z12/Y12,0) | AU12: =IF(Y11>0,MAX(0,(Y11+J12-Y12)/Y11),0)
A13: 9 | B13: =MOD(A13-1+LaunchMonth-1,12)+1 | C13: =INT((A13-1+LaunchMonth-1)/12)+1 | D13: =VLOOKUP(B13,SeasonTable,2,FALSE) | E13: =(1+InflationRate)^INT((A13-1)/12) | F13: =MonthlyChurn*VLOOKUP(B13,ChurnSeasonTable,4,FALSE) | G13: =MIN(MAX(MktMin7_12,AE12*MktPct7_12),MAX(0,AS12-CashBuffer)) | H13: =IF(G13>0,MAX(1,ROUND(G13/CAC*D13,0)),0) | I13: =IF(H13>0,ROUND(H13*ReferralMix/(1-ReferralMix),0),0) | J13: =H13+I13 | K13: =ROUND(J13*(1-AnnualMix),0) | L13: =J13-K13 | M13: =ROUND(K13*EssentialMix,0) | N13: =ROUND(K13*PremiumMix,0) | O13: =K13-M13-N13 | P13: =ROUND(L13*EssentialMix,0) | Q13: =ROUND(L13*PremiumMix,0) | R13: =L13-P13-Q13 | S13: =M13+M12+M11+MAX(0,S12-M12-M11)*(1-F13) | T13: =N13+N12+N11+MAX(0,T12-N12-N11)*(1-F13) | U13: =O13+O12+O11+MAX(0,U12-O12-O11)*(1-F13) | V13: =SUM(P$5:P13) | W13: =SUM(Q$5:Q13) | X13: =SUM(R$5:R13) | Y13: =S13+T13+U13+V13+W13+X13 | Z13: =S13*BlendedPriceEssMonthly*E13+T13*BlendedPricePremMonthly*E13+U13*BlendedPriceEliteMonthly*E13+V13*BlendedPriceEssAnnual*E13/12+W13*BlendedPricePremAnnual*E13/12+X13*BlendedPriceEliteAnnual*E13/12 | AA13: =Z13*12 | AB13: =S13*BlendedPriceEssMonthly*E13+T13*BlendedPricePremMonthly*E13+U13*BlendedPriceEliteMonthly*E13 | AC13: =P13*BlendedPriceEssAnnual*E13+Q13*BlendedPricePremAnnual*E13+R13*BlendedPriceEliteAnnual*E13 | AD13: =0+0+0 | AE13: =AB13+AC13+AD13 | AF13: =SUM(AE$5:AE13) | AG13: =OR(AG12,IF(VATAgentMode,SUM($AE$5:$AE13)-SUM($AL$5:$AL13)>=VATThreshold,SUM($AE$5:$AE13)>=VATThreshold)) | AH13: =IF(AG13,IF(VATAgentMode,AE13-((AE13-AL13)-(AE13-AL13)/(1+VATRate)),AE13/(1+VATRate)),AE13) | AI13: =AE13-AH13 | AJ13: =IF(AG13=0,0,IF(B13=1,SUMPRODUCT(--(($C$5:$C13=$C13-1)*($B$5:$B13>=10)*($B$5:$B13<=12)),$AI$5:$AI13),IF(B13=4,SUMPRODUCT(--(($C$5:$C13=$C13)*($B$5:$B13>=1)*($B$5:$B13<=3)),$AI$5:$AI13),IF(B13=7,SUMPRODUCT(--(($C$5:$C13=$C13)*($B$5:$B13>=4)*($B$5:$B13<=6)),$AI$5:$AI13),IF(B13=10,SUMPRODUCT(--(($C$5:$C13=$C13)*($B$5:$B13>=7)*($B$5:$B13<=9)),$AI$5:$AI13),0))))) | AK13: =AK12+AI13-AJ13 | AL13: =IF(ProviderDelay>=1,S12*BlendedProvPayEss+T12*BlendedProvPayPrem+U12*BlendedProvPayElite+V12*BlendedProvPayEss+W12*BlendedProvPayPrem+X12*BlendedProvPayElite,S13*BlendedProvPayEss+T13*BlendedProvPayPrem+U13*BlendedProvPayElite+V13*BlendedProvPayEss+W13*BlendedProvPayPrem+X13*BlendedProvPayElite) | AM13: =AE13*PaymentFee | AN13: =Y13*OpsAI | AO13: =MonthlyFixed | AP13: =I13*ReferralReward | AQ13: =G13 | AR13: =AH13-AL13-AM13-AN13-AO13-AP13-AQ13 | AS13: =AS12+AE13-(AL13+AM13+AN13+AO13+AP13+AQ13+AJ13) | AT13: =IF(Y13>0,Z13/Y13,0) | AU13: =IF(Y12>0,MAX(0,(Y12+J13-Y13)/Y12),0)
A14: 10 | B14: =MOD(A14-1+LaunchMonth-1,12)+1 | C14: =INT((A14-1+LaunchMonth-1)/12)+1 | D14: =VLOOKUP(B14,SeasonTable,2,FALSE) | E14: =(1+InflationRate)^INT((A14-1)/12) | F14: =MonthlyChurn*VLOOKUP(B14,ChurnSeasonTable,4,FALSE) | G14: =MIN(MAX(MktMin7_12,AE13*MktPct7_12),MAX(0,AS13-CashBuffer)) | H14: =IF(G14>0,MAX(1,ROUND(G14/CAC*D14,0)),0) | I14: =IF(H14>0,ROUND(H14*ReferralMix/(1-ReferralMix),0),0) | J14: =H14+I14 | K14: =ROUND(J14*(1-AnnualMix),0) | L14: =J14-K14 | M14: =ROUND(K14*EssentialMix,0) | N14: =ROUND(K14*PremiumMix,0) | O14: =K14-M14-N14 | P14: =ROUND(L14*EssentialMix,0) | Q14: =ROUND(L14*PremiumMix,0) | R14: =L14-P14-Q14 | S14: =M14+M13+M12+MAX(0,S13-M13-M12)*(1-F14) | T14: =N14+N13+N12+MAX(0,T13-N13-N12)*(1-F14) | U14: =O14+O13+O12+MAX(0,U13-O13-O12)*(1-F14) | V14: =SUM(P$5:P14) | W14: =SUM(Q$5:Q14) | X14: =SUM(R$5:R14) | Y14: =S14+T14+U14+V14+W14+X14 | Z14: =S14*BlendedPriceEssMonthly*E14+T14*BlendedPricePremMonthly*E14+U14*BlendedPriceEliteMonthly*E14+V14*BlendedPriceEssAnnual*E14/12+W14*BlendedPricePremAnnual*E14/12+X14*BlendedPriceEliteAnnual*E14/12 | AA14: =Z14*12 | AB14: =S14*BlendedPriceEssMonthly*E14+T14*BlendedPricePremMonthly*E14+U14*BlendedPriceEliteMonthly*E14 | AC14: =P14*BlendedPriceEssAnnual*E14+Q14*BlendedPricePremAnnual*E14+R14*BlendedPriceEliteAnnual*E14 | AD14: =0+0+0 | AE14: =AB14+AC14+AD14 | AF14: =SUM(AE$5:AE14) | AG14: =OR(AG13,IF(VATAgentMode,SUM($AE$5:$AE14)-SUM($AL$5:$AL14)>=VATThreshold,SUM($AE$5:$AE14)>=VATThreshold)) | AH14: =IF(AG14,IF(VATAgentMode,AE14-((AE14-AL14)-(AE14-AL14)/(1+VATRate)),AE14/(1+VATRate)),AE14) | AI14: =AE14-AH14 | AJ14: =IF(AG14=0,0,IF(B14=1,SUMPRODUCT(--(($C$5:$C14=$C14-1)*($B$5:$B14>=10)*($B$5:$B14<=12)),$AI$5:$AI14),IF(B14=4,SUMPRODUCT(--(($C$5:$C14=$C14)*($B$5:$B14>=1)*($B$5:$B14<=3)),$AI$5:$AI14),IF(B14=7,SUMPRODUCT(--(($C$5:$C14=$C14)*($B$5:$B14>=4)*($B$5:$B14<=6)),$AI$5:$AI14),IF(B14=10,SUMPRODUCT(--(($C$5:$C14=$C14)*($B$5:$B14>=7)*($B$5:$B14<=9)),$AI$5:$AI14),0))))) | AK14: =AK13+AI14-AJ14 | AL14: =IF(ProviderDelay>=1,S13*BlendedProvPayEss+T13*BlendedProvPayPrem+U13*BlendedProvPayElite+V13*BlendedProvPayEss+W13*BlendedProvPayPrem+X13*BlendedProvPayElite,S14*BlendedProvPayEss+T14*BlendedProvPayPrem+U14*BlendedProvPayElite+V14*BlendedProvPayEss+W14*BlendedProvPayPrem+X14*BlendedProvPayElite) | AM14: =AE14*PaymentFee | AN14: =Y14*OpsAI | AO14: =MonthlyFixed | AP14: =I14*ReferralReward | AQ14: =G14 | AR14: =AH14-AL14-AM14-AN14-AO14-AP14-AQ14 | AS14: =AS13+AE14-(AL14+AM14+AN14+AO14+AP14+AQ14+AJ14) | AT14: =IF(Y14>0,Z14/Y14,0) | AU14: =IF(Y13>0,MAX(0,(Y13+J14-Y14)/Y13),0)
A15: 11 | B15: =MOD(A15-1+LaunchMonth-1,12)+1 | C15: =INT((A15-1+LaunchMonth-1)/12)+1 | D15: =VLOOKUP(B15,SeasonTable,2,FALSE) | E15: =(1+InflationRate)^INT((A15-1)/12) | F15: =MonthlyChurn*VLOOKUP(B15,ChurnSeasonTable,4,FALSE) | G15: =MIN(MAX(MktMin7_12,AE14*MktPct7_12),MAX(0,AS14-CashBuffer)) | H15: =IF(G15>0,MAX(1,ROUND(G15/CAC*D15,0)),0) | I15: =IF(H15>0,ROUND(H15*ReferralMix/(1-ReferralMix),0),0) | J15: =H15+I15 | K15: =ROUND(J15*(1-AnnualMix),0) | L15: =J15-K15 | M15: =ROUND(K15*EssentialMix,0) | N15: =ROUND(K15*PremiumMix,0) | O15: =K15-M15-N15 | P15: =ROUND(L15*EssentialMix,0) | Q15: =ROUND(L15*PremiumMix,0) | R15: =L15-P15-Q15 | S15: =M15+M14+M13+MAX(0,S14-M14-M13)*(1-F15) | T15: =N15+N14+N13+MAX(0,T14-N14-N13)*(1-F15) | U15: =O15+O14+O13+MAX(0,U14-O14-O13)*(1-F15) | V15: =SUM(P$5:P15) | W15: =SUM(Q$5:Q15) | X15: =SUM(R$5:R15) | Y15: =S15+T15+U15+V15+W15+X15 | Z15: =S15*BlendedPriceEssMonthly*E15+T15*BlendedPricePremMonthly*E15+U15*BlendedPriceEliteMonthly*E15+V15*BlendedPriceEssAnnual*E15/12+W15*BlendedPricePremAnnual*E15/12+X15*BlendedPriceEliteAnnual*E15/12 | AA15: =Z15*12 | AB15: =S15*BlendedPriceEssMonthly*E15+T15*BlendedPricePremMonthly*E15+U15*BlendedPriceEliteMonthly*E15 | AC15: =P15*BlendedPriceEssAnnual*E15+Q15*BlendedPricePremAnnual*E15+R15*BlendedPriceEliteAnnual*E15 | AD15: =0+0+0 | AE15: =AB15+AC15+AD15 | AF15: =SUM(AE$5:AE15) | AG15: =OR(AG14,IF(VATAgentMode,SUM($AE$5:$AE15)-SUM($AL$5:$AL15)>=VATThreshold,SUM($AE$5:$AE15)>=VATThreshold)) | AH15: =IF(AG15,IF(VATAgentMode,AE15-((AE15-AL15)-(AE15-AL15)/(1+VATRate)),AE15/(1+VATRate)),AE15) | AI15: =AE15-AH15 | AJ15: =IF(AG15=0,0,IF(B15=1,SUMPRODUCT(--(($C$5:$C15=$C15-1)*($B$5:$B15>=10)*($B$5:$B15<=12)),$AI$5:$AI15),IF(B15=4,SUMPRODUCT(--(($C$5:$C15=$C15)*($B$5:$B15>=1)*($B$5:$B15<=3)),$AI$5:$AI15),IF(B15=7,SUMPRODUCT(--(($C$5:$C15=$C15)*($B$5:$B15>=4)*($B$5:$B15<=6)),$AI$5:$AI15),IF(B15=10,SUMPRODUCT(--(($C$5:$C15=$C15)*($B$5:$B15>=7)*($B$5:$B15<=9)),$AI$5:$AI15),0))))) | AK15: =AK14+AI15-AJ15 | AL15: =IF(ProviderDelay>=1,S14*BlendedProvPayEss+T14*BlendedProvPayPrem+U14*BlendedProvPayElite+V14*BlendedProvPayEss+W14*BlendedProvPayPrem+X14*BlendedProvPayElite,S15*BlendedProvPayEss+T15*BlendedProvPayPrem+U15*BlendedProvPayElite+V15*BlendedProvPayEss+W15*BlendedProvPayPrem+X15*BlendedProvPayElite) | AM15: =AE15*PaymentFee | AN15: =Y15*OpsAI | AO15: =MonthlyFixed | AP15: =I15*ReferralReward | AQ15: =G15 | AR15: =AH15-AL15-AM15-AN15-AO15-AP15-AQ15 | AS15: =AS14+AE15-(AL15+AM15+AN15+AO15+AP15+AQ15+AJ15) | AT15: =IF(Y15>0,Z15/Y15,0) | AU15: =IF(Y14>0,MAX(0,(Y14+J15-Y15)/Y14),0)
A16: 12 | B16: =MOD(A16-1+LaunchMonth-1,12)+1 | C16: =INT((A16-1+LaunchMonth-1)/12)+1 | D16: =VLOOKUP(B16,SeasonTable,2,FALSE) | E16: =(1+InflationRate)^INT((A16-1)/12) | F16: =MonthlyChurn*VLOOKUP(B16,ChurnSeasonTable,4,FALSE) | G16: =MIN(MAX(MktMin7_12,AE15*MktPct7_12),MAX(0,AS15-CashBuffer)) | H16: =IF(G16>0,MAX(1,ROUND(G16/CAC*D16,0)),0) | I16: =IF(H16>0,ROUND(H16*ReferralMix/(1-ReferralMix),0),0) | J16: =H16+I16 | K16: =ROUND(J16*(1-AnnualMix),0) | L16: =J16-K16 | M16: =ROUND(K16*EssentialMix,0) | N16: =ROUND(K16*PremiumMix,0) | O16: =K16-M16-N16 | P16: =ROUND(L16*EssentialMix,0) | Q16: =ROUND(L16*PremiumMix,0) | R16: =L16-P16-Q16 | S16: =M16+M15+M14+MAX(0,S15-M15-M14)*(1-F16) | T16: =N16+N15+N14+MAX(0,T15-N15-N14)*(1-F16) | U16: =O16+O15+O14+MAX(0,U15-O15-O14)*(1-F16) | V16: =SUM(P$5:P16) | W16: =SUM(Q$5:Q16) | X16: =SUM(R$5:R16) | Y16: =S16+T16+U16+V16+W16+X16 | Z16: =S16*BlendedPriceEssMonthly*E16+T16*BlendedPricePremMonthly*E16+U16*BlendedPriceEliteMonthly*E16+V16*BlendedPriceEssAnnual*E16/12+W16*BlendedPricePremAnnual*E16/12+X16*BlendedPriceEliteAnnual*E16/12 | AA16: =Z16*12 | AB16: =S16*BlendedPriceEssMonthly*E16+T16*BlendedPricePremMonthly*E16+U16*BlendedPriceEliteMonthly*E16 | AC16: =P16*BlendedPriceEssAnnual*E16+Q16*BlendedPricePremAnnual*E16+R16*BlendedPriceEliteAnnual*E16 | AD16: =0+0+0 | AE16: =AB16+AC16+AD16 | AF16: =SUM(AE5:AE16) | AG16: =OR(AG15,IF(VATAgentMode,SUM($AE5:$AE16)-SUM($AL5:$AL16)>=VATThreshold,SUM($AE5:$AE16)>=VATThreshold)) | AH16: =IF(AG16,IF(VATAgentMode,AE16-((AE16-AL16)-(AE16-AL16)/(1+VATRate)),AE16/(1+VATRate)),AE16) | AI16: =AE16-AH16 | AJ16: =IF(AG16=0,0,IF(B16=1,SUMPRODUCT(--(($C$5:$C16=$C16-1)*($B$5:$B16>=10)*($B$5:$B16<=12)),$AI$5:$AI16),IF(B16=4,SUMPRODUCT(--(($C$5:$C16=$C16)*($B$5:$B16>=1)*($B$5:$B16<=3)),$AI$5:$AI16),IF(B16=7,SUMPRODUCT(--(($C$5:$C16=$C16)*($B$5:$B16>=4)*($B$5:$B16<=6)),$AI$5:$AI16),IF(B16=10,SUMPRODUCT(--(($C$5:$C16=$C16)*($B$5:$B16>=7)*($B$5:$B16<=9)),$AI$5:$AI16),0))))) | AK16: =AK15+AI16-AJ16 | AL16: =IF(ProviderDelay>=1,S15*BlendedProvPayEss+T15*BlendedProvPayPrem+U15*BlendedProvPayElite+V15*BlendedProvPayEss+W15*BlendedProvPayPrem+X15*BlendedProvPayElite,S16*BlendedProvPayEss+T16*BlendedProvPayPrem+U16*BlendedProvPayElite+V16*BlendedProvPayEss+W16*BlendedProvPayPrem+X16*BlendedProvPayElite) | AM16: =AE16*PaymentFee | AN16: =Y16*OpsAI | AO16: =MonthlyFixed | AP16: =I16*ReferralReward | AQ16: =G16 | AR16: =AH16-AL16-AM16-AN16-AO16-AP16-AQ16 | AS16: =AS15+AE16-(AL16+AM16+AN16+AO16+AP16+AQ16+AJ16) | AT16: =IF(Y16>0,Z16/Y16,0) | AU16: =IF(Y15>0,MAX(0,(Y15+J16-Y16)/Y15),0)
A17: 13 | B17: =MOD(A17-1+LaunchMonth-1,12)+1 | C17: =INT((A17-1+LaunchMonth-1)/12)+1 | D17: =VLOOKUP(B17,SeasonTable,2,FALSE) | E17: =(1+InflationRate)^INT((A17-1)/12) | F17: =MonthlyChurn*VLOOKUP(B17,ChurnSeasonTable,4,FALSE) | G17: =MIN(MAX(MktMin13_18,AE16*MktPct13_18),MAX(0,AS16-CashBuffer)) | H17: =IF(G17>0,MAX(1,ROUND(G17/CAC*D17,0)),0) | I17: =IF(H17>0,ROUND(H17*ReferralMix/(1-ReferralMix),0),0) | J17: =H17+I17 | K17: =ROUND(J17*(1-AnnualMix),0) | L17: =J17-K17 | M17: =ROUND(K17*EssentialMix,0) | N17: =ROUND(K17*PremiumMix,0) | O17: =K17-M17-N17 | P17: =ROUND(L17*EssentialMix,0) | Q17: =ROUND(L17*PremiumMix,0) | R17: =L17-P17-Q17 | S17: =M17+M16+M15+MAX(0,S16-M16-M15)*(1-F17) | T17: =N17+N16+N15+MAX(0,T16-N16-N15)*(1-F17) | U17: =O17+O16+O15+MAX(0,U16-O16-O15)*(1-F17) | V17: =V16+P17-P5*(AnnualChurn*VLOOKUP(B17,ChurnSeasonTable,4,FALSE))*POWER(1-(AnnualChurn*VLOOKUP(B17,ChurnSeasonTable,4,FALSE)),0) | W17: =W16+Q17-Q5*(AnnualChurn*VLOOKUP(B17,ChurnSeasonTable,4,FALSE))*POWER(1-(AnnualChurn*VLOOKUP(B17,ChurnSeasonTable,4,FALSE)),0) | X17: =X16+R17-R5*(AnnualChurn*VLOOKUP(B17,ChurnSeasonTable,4,FALSE))*POWER(1-(AnnualChurn*VLOOKUP(B17,ChurnSeasonTable,4,FALSE)),0) | Y17: =S17+T17+U17+V17+W17+X17 | Z17: =S17*BlendedPriceEssMonthly*E17+T17*BlendedPricePremMonthly*E17+U17*BlendedPriceEliteMonthly*E17+V17*BlendedPriceEssAnnual*E17/12+W17*BlendedPricePremAnnual*E17/12+X17*BlendedPriceEliteAnnual*E17/12 | AA17: =Z17*12 | AB17: =S17*BlendedPriceEssMonthly*E17+T17*BlendedPricePremMonthly*E17+U17*BlendedPriceEliteMonthly*E17 | AC17: =P17*BlendedPriceEssAnnual*E17+Q17*BlendedPricePremAnnual*E17+R17*BlendedPriceEliteAnnual*E17 | AD17: =P5*POWER(1-(AnnualChurn*VLOOKUP(B17,ChurnSeasonTable,4,FALSE)),1)*BlendedPriceEssAnnual*E17+Q5*POWER(1-(AnnualChurn*VLOOKUP(B17,ChurnSeasonTable,4,FALSE)),1)*BlendedPricePremAnnual*E17+R5*POWER(1-(AnnualChurn*VLOOKUP(B17,ChurnSeasonTable,4,FALSE)),1)*BlendedPriceEliteAnnual*E17 | AE17: =AB17+AC17+AD17 | AF17: =SUM(AE6:AE17) | AG17: =OR(AG16,IF(VATAgentMode,SUM($AE6:$AE17)-SUM($AL6:$AL17)>=VATThreshold,SUM($AE6:$AE17)>=VATThreshold)) | AH17: =IF(AG17,IF(VATAgentMode,AE17-((AE17-AL17)-(AE17-AL17)/(1+VATRate)),AE17/(1+VATRate)),AE17) | AI17: =AE17-AH17 | AJ17: =IF(AG17=0,0,IF(B17=1,SUMPRODUCT(--(($C$5:$C17=$C17-1)*($B$5:$B17>=10)*($B$5:$B17<=12)),$AI$5:$AI17),IF(B17=4,SUMPRODUCT(--(($C$5:$C17=$C17)*($B$5:$B17>=1)*($B$5:$B17<=3)),$AI$5:$AI17),IF(B17=7,SUMPRODUCT(--(($C$5:$C17=$C17)*($B$5:$B17>=4)*($B$5:$B17<=6)),$AI$5:$AI17),IF(B17=10,SUMPRODUCT(--(($C$5:$C17=$C17)*($B$5:$B17>=7)*($B$5:$B17<=9)),$AI$5:$AI17),0))))) | AK17: =AK16+AI17-AJ17 | AL17: =IF(ProviderDelay>=1,S16*BlendedProvPayEss+T16*BlendedProvPayPrem+U16*BlendedProvPayElite+V16*BlendedProvPayEss+W16*BlendedProvPayPrem+X16*BlendedProvPayElite,S17*BlendedProvPayEss+T17*BlendedProvPayPrem+U17*BlendedProvPayElite+V17*BlendedProvPayEss+W17*BlendedProvPayPrem+X17*BlendedProvPayElite) | AM17: =AE17*PaymentFee | AN17: =Y17*OpsAI | AO17: =MonthlyFixed | AP17: =I17*ReferralReward | AQ17: =G17 | AR17: =AH17-AL17-AM17-AN17-AO17-AP17-AQ17 | AS17: =AS16+AE17-(AL17+AM17+AN17+AO17+AP17+AQ17+AJ17) | AT17: =IF(Y17>0,Z17/Y17,0) | AU17: =IF(Y16>0,MAX(0,(Y16+J17-Y17)/Y16),0)
A18: 14 | B18: =MOD(A18-1+LaunchMonth-1,12)+1 | C18: =INT((A18-1+LaunchMonth-1)/12)+1 | D18: =VLOOKUP(B18,SeasonTable,2,FALSE) | E18: =(1+InflationRate)^INT((A18-1)/12) | F18: =MonthlyChurn*VLOOKUP(B18,ChurnSeasonTable,4,FALSE) | G18: =MIN(MAX(MktMin13_18,AE17*MktPct13_18),MAX(0,AS17-CashBuffer)) | H18: =IF(G18>0,MAX(1,ROUND(G18/CAC*D18,0)),0) | I18: =IF(H18>0,ROUND(H18*ReferralMix/(1-ReferralMix),0),0) | J18: =H18+I18 | K18: =ROUND(J18*(1-AnnualMix),0) | L18: =J18-K18 | M18: =ROUND(K18*EssentialMix,0) | N18: =ROUND(K18*PremiumMix,0) | O18: =K18-M18-N18 | P18: =ROUND(L18*EssentialMix,0) | Q18: =ROUND(L18*PremiumMix,0) | R18: =L18-P18-Q18 | S18: =M18+M17+M16+MAX(0,S17-M17-M16)*(1-F18) | T18: =N18+N17+N16+MAX(0,T17-N17-N16)*(1-F18) | U18: =O18+O17+O16+MAX(0,U17-O17-O16)*(1-F18) | V18: =V17+P18-P6*(AnnualChurn*VLOOKUP(B18,ChurnSeasonTable,4,FALSE))*POWER(1-(AnnualChurn*VLOOKUP(B18,ChurnSeasonTable,4,FALSE)),0) | W18: =W17+Q18-Q6*(AnnualChurn*VLOOKUP(B18,ChurnSeasonTable,4,FALSE))*POWER(1-(AnnualChurn*VLOOKUP(B18,ChurnSeasonTable,4,FALSE)),0) | X18: =X17+R18-R6*(AnnualChurn*VLOOKUP(B18,ChurnSeasonTable,4,FALSE))*POWER(1-(AnnualChurn*VLOOKUP(B18,ChurnSeasonTable,4,FALSE)),0) | Y18: =S18+T18+U18+V18+W18+X18 | Z18: =S18*BlendedPriceEssMonthly*E18+T18*BlendedPricePremMonthly*E18+U18*BlendedPriceEliteMonthly*E18+V18*BlendedPriceEssAnnual*E18/12+W18*BlendedPricePremAnnual*E18/12+X18*BlendedPriceEliteAnnual*E18/12 | AA18: =Z18*12 | AB18: =S18*BlendedPriceEssMonthly*E18+T18*BlendedPricePremMonthly*E18+U18*BlendedPriceEliteMonthly*E18 | AC18: =P18*BlendedPriceEssAnnual*E18+Q18*BlendedPricePremAnnual*E18+R18*BlendedPriceEliteAnnual*E18 | AD18: =P6*POWER(1-(AnnualChurn*VLOOKUP(B18,ChurnSeasonTable,4,FALSE)),1)*BlendedPriceEssAnnual*E18+Q6*POWER(1-(AnnualChurn*VLOOKUP(B18,ChurnSeasonTable,4,FALSE)),1)*BlendedPricePremAnnual*E18+R6*POWER(1-(AnnualChurn*VLOOKUP(B18,ChurnSeasonTable,4,FALSE)),1)*BlendedPriceEliteAnnual*E18 | AE18: =AB18+AC18+AD18 | AF18: =SUM(AE7:AE18) | AG18: =OR(AG17,IF(VATAgentMode,SUM($AE7:$AE18)-SUM($AL7:$AL18)>=VATThreshold,SUM($AE7:$AE18)>=VATThreshold)) | AH18: =IF(AG18,IF(VATAgentMode,AE18-((AE18-AL18)-(AE18-AL18)/(1+VATRate)),AE18/(1+VATRate)),AE18) | AI18: =AE18-AH18 | AJ18: =IF(AG18=0,0,IF(B18=1,SUMPRODUCT(--(($C$5:$C18=$C18-1)*($B$5:$B18>=10)*($B$5:$B18<=12)),$AI$5:$AI18),IF(B18=4,SUMPRODUCT(--(($C$5:$C18=$C18)*($B$5:$B18>=1)*($B$5:$B18<=3)),$AI$5:$AI18),IF(B18=7,SUMPRODUCT(--(($C$5:$C18=$C18)*($B$5:$B18>=4)*($B$5:$B18<=6)),$AI$5:$AI18),IF(B18=10,SUMPRODUCT(--(($C$5:$C18=$C18)*($B$5:$B18>=7)*($B$5:$B18<=9)),$AI$5:$AI18),0))))) | AK18: =AK17+AI18-AJ18 | AL18: =IF(ProviderDelay>=1,S17*BlendedProvPayEss+T17*BlendedProvPayPrem+U17*BlendedProvPayElite+V17*BlendedProvPayEss+W17*BlendedProvPayPrem+X17*BlendedProvPayElite,S18*BlendedProvPayEss+T18*BlendedProvPayPrem+U18*BlendedProvPayElite+V18*BlendedProvPayEss+W18*BlendedProvPayPrem+X18*BlendedProvPayElite) | AM18: =AE18*PaymentFee | AN18: =Y18*OpsAI | AO18: =MonthlyFixed | AP18: =I18*ReferralReward | AQ18: =G18 | AR18: =AH18-AL18-AM18-AN18-AO18-AP18-AQ18 | AS18: =AS17+AE18-(AL18+AM18+AN18+AO18+AP18+AQ18+AJ18) | AT18: =IF(Y18>0,Z18/Y18,0) | AU18: =IF(Y17>0,MAX(0,(Y17+J18-Y18)/Y17),0)
A19: 15 | B19: =MOD(A19-1+LaunchMonth-1,12)+1 | C19: =INT((A19-1+LaunchMonth-1)/12)+1 | D19: =VLOOKUP(B19,SeasonTable,2,FALSE) | E19: =(1+InflationRate)^INT((A19-1)/12) | F19: =MonthlyChurn*VLOOKUP(B19,ChurnSeasonTable,4,FALSE) | G19: =MIN(MAX(MktMin13_18,AE18*MktPct13_18),MAX(0,AS18-CashBuffer)) | H19: =IF(G19>0,MAX(1,ROUND(G19/CAC*D19,0)),0) | I19: =IF(H19>0,ROUND(H19*ReferralMix/(1-ReferralMix),0),0) | J19: =H19+I19 | K19: =ROUND(J19*(1-AnnualMix),0) | L19: =J19-K19 | M19: =ROUND(K19*EssentialMix,0) | N19: =ROUND(K19*PremiumMix,0) | O19: =K19-M19-N19 | P19: =ROUND(L19*EssentialMix,0) | Q19: =ROUND(L19*PremiumMix,0) | R19: =L19-P19-Q19 | S19: =M19+M18+M17+MAX(0,S18-M18-M17)*(1-F19) | T19: =N19+N18+N17+MAX(0,T18-N18-N17)*(1-F19) | U19: =O19+O18+O17+MAX(0,U18-O18-O17)*(1-F19) | V19: =V18+P19-P7*(AnnualChurn*VLOOKUP(B19,ChurnSeasonTable,4,FALSE))*POWER(1-(AnnualChurn*VLOOKUP(B19,ChurnSeasonTable,4,FALSE)),0) | W19: =W18+Q19-Q7*(AnnualChurn*VLOOKUP(B19,ChurnSeasonTable,4,FALSE))*POWER(1-(AnnualChurn*VLOOKUP(B19,ChurnSeasonTable,4,FALSE)),0) | X19: =X18+R19-R7*(AnnualChurn*VLOOKUP(B19,ChurnSeasonTable,4,FALSE))*POWER(1-(AnnualChurn*VLOOKUP(B19,ChurnSeasonTable,4,FALSE)),0) | Y19: =S19+T19+U19+V19+W19+X19 | Z19: =S19*BlendedPriceEssMonthly*E19+T19*BlendedPricePremMonthly*E19+U19*BlendedPriceEliteMonthly*E19+V19*BlendedPriceEssAnnual*E19/12+W19*BlendedPricePremAnnual*E19/12+X19*BlendedPriceEliteAnnual*E19/12 | AA19: =Z19*12 | AB19: =S19*BlendedPriceEssMonthly*E19+T19*BlendedPricePremMonthly*E19+U19*BlendedPriceEliteMonthly*E19 | AC19: =P19*BlendedPriceEssAnnual*E19+Q19*BlendedPricePremAnnual*E19+R19*BlendedPriceEliteAnnual*E19 | AD19: =P7*POWER(1-(AnnualChurn*VLOOKUP(B19,ChurnSeasonTable,4,FALSE)),1)*BlendedPriceEssAnnual*E19+Q7*POWER(1-(AnnualChurn*VLOOKUP(B19,ChurnSeasonTable,4,FALSE)),1)*BlendedPricePremAnnual*E19+R7*POWER(1-(AnnualChurn*VLOOKUP(B19,ChurnSeasonTable,4,FALSE)),1)*BlendedPriceEliteAnnual*E19 | AE19: =AB19+AC19+AD19 | AF19: =SUM(AE8:AE19) | AG19: =OR(AG18,IF(VATAgentMode,SUM($AE8:$AE19)-SUM($AL8:$AL19)>=VATThreshold,SUM($AE8:$AE19)>=VATThreshold)) | AH19: =IF(AG19,IF(VATAgentMode,AE19-((AE19-AL19)-(AE19-AL19)/(1+VATRate)),AE19/(1+VATRate)),AE19) | AI19: =AE19-AH19 | AJ19: =IF(AG19=0,0,IF(B19=1,SUMPRODUCT(--(($C$5:$C19=$C19-1)*($B$5:$B19>=10)*($B$5:$B19<=12)),$AI$5:$AI19),IF(B19=4,SUMPRODUCT(--(($C$5:$C19=$C19)*($B$5:$B19>=1)*($B$5:$B19<=3)),$AI$5:$AI19),IF(B19=7,SUMPRODUCT(--(($C$5:$C19=$C19)*($B$5:$B19>=4)*($B$5:$B19<=6)),$AI$5:$AI19),IF(B19=10,SUMPRODUCT(--(($C$5:$C19=$C19)*($B$5:$B19>=7)*($B$5:$B19<=9)),$AI$5:$AI19),0))))) | AK19: =AK18+AI19-AJ19 | AL19: =IF(ProviderDelay>=1,S18*BlendedProvPayEss+T18*BlendedProvPayPrem+U18*BlendedProvPayElite+V18*BlendedProvPayEss+W18*BlendedProvPayPrem+X18*BlendedProvPayElite,S19*BlendedProvPayEss+T19*BlendedProvPayPrem+U19*BlendedProvPayElite+V19*BlendedProvPayEss+W19*BlendedProvPayPrem+X19*BlendedProvPayElite) | AM19: =AE19*PaymentFee | AN19: =Y19*OpsAI | AO19: =MonthlyFixed | AP19: =I19*ReferralReward | AQ19: =G19 | AR19: =AH19-AL19-AM19-AN19-AO19-AP19-AQ19 | AS19: =AS18+AE19-(AL19+AM19+AN19+AO19+AP19+AQ19+AJ19) | AT19: =IF(Y19>0,Z19/Y19,0) | AU19: =IF(Y18>0,MAX(0,(Y18+J19-Y19)/Y18),0)
A20: 16 | B20: =MOD(A20-1+LaunchMonth-1,12)+1 | C20: =INT((A20-1+LaunchMonth-1)/12)+1 | D20: =VLOOKUP(B20,SeasonTable,2,FALSE) | E20: =(1+InflationRate)^INT((A20-1)/12) | F20: =MonthlyChurn*VLOOKUP(B20,ChurnSeasonTable,4,FALSE) | G20: =MIN(MAX(MktMin13_18,AE19*MktPct13_18),MAX(0,AS19-CashBuffer)) | H20: =IF(G20>0,MAX(1,ROUND(G20/CAC*D20,0)),0) | I20: =IF(H20>0,ROUND(H20*ReferralMix/(1-ReferralMix),0),0) | J20: =H20+I20 | K20: =ROUND(J20*(1-AnnualMix),0) | L20: =J20-K20 | M20: =ROUND(K20*EssentialMix,0) | N20: =ROUND(K20*PremiumMix,0) | O20: =K20-M20-N20 | P20: =ROUND(L20*EssentialMix,0) | Q20: =ROUND(L20*PremiumMix,0) | R20: =L20-P20-Q20 | S20: =M20+M19+M18+MAX(0,S19-M19-M18)*(1-F20) | T20: =N20+N19+N18+MAX(0,T19-N19-N18)*(1-F20) | U20: =O20+O19+O18+MAX(0,U19-O19-O18)*(1-F20) | V20: =V19+P20-P8*(AnnualChurn*VLOOKUP(B20,ChurnSeasonTable,4,FALSE))*POWER(1-(AnnualChurn*VLOOKUP(B20,ChurnSeasonTable,4,FALSE)),0) | W20: =W19+Q20-Q8*(AnnualChurn*VLOOKUP(B20,ChurnSeasonTable,4,FALSE))*POWER(1-(AnnualChurn*VLOOKUP(B20,ChurnSeasonTable,4,FALSE)),0) | X20: =X19+R20-R8*(AnnualChurn*VLOOKUP(B20,ChurnSeasonTable,4,FALSE))*POWER(1-(AnnualChurn*VLOOKUP(B20,ChurnSeasonTable,4,FALSE)),0) | Y20: =S20+T20+U20+V20+W20+X20 | Z20: =S20*BlendedPriceEssMonthly*E20+T20*BlendedPricePremMonthly*E20+U20*BlendedPriceEliteMonthly*E20+V20*BlendedPriceEssAnnual*E20/12+W20*BlendedPricePremAnnual*E20/12+X20*BlendedPriceEliteAnnual*E20/12 | AA20: =Z20*12 | AB20: =S20*BlendedPriceEssMonthly*E20+T20*BlendedPricePremMonthly*E20+U20*BlendedPriceEliteMonthly*E20 | AC20: =P20*BlendedPriceEssAnnual*E20+Q20*BlendedPricePremAnnual*E20+R20*BlendedPriceEliteAnnual*E20 | AD20: =P8*POWER(1-(AnnualChurn*VLOOKUP(B20,ChurnSeasonTable,4,FALSE)),1)*BlendedPriceEssAnnual*E20+Q8*POWER(1-(AnnualChurn*VLOOKUP(B20,ChurnSeasonTable,4,FALSE)),1)*BlendedPricePremAnnual*E20+R8*POWER(1-(AnnualChurn*VLOOKUP(B20,ChurnSeasonTable,4,FALSE)),1)*BlendedPriceEliteAnnual*E20 | AE20: =AB20+AC20+AD20 | AF20: =SUM(AE9:AE20) | AG20: =OR(AG19,IF(VATAgentMode,SUM($AE9:$AE20)-SUM($AL9:$AL20)>=VATThreshold,SUM($AE9:$AE20)>=VATThreshold)) | AH20: =IF(AG20,IF(VATAgentMode,AE20-((AE20-AL20)-(AE20-AL20)/(1+VATRate)),AE20/(1+VATRate)),AE20) | AI20: =AE20-AH20 | AJ20: =IF(AG20=0,0,IF(B20=1,SUMPRODUCT(--(($C$5:$C20=$C20-1)*($B$5:$B20>=10)*($B$5:$B20<=12)),$AI$5:$AI20),IF(B20=4,SUMPRODUCT(--(($C$5:$C20=$C20)*($B$5:$B20>=1)*($B$5:$B20<=3)),$AI$5:$AI20),IF(B20=7,SUMPRODUCT(--(($C$5:$C20=$C20)*($B$5:$B20>=4)*($B$5:$B20<=6)),$AI$5:$AI20),IF(B20=10,SUMPRODUCT(--(($C$5:$C20=$C20)*($B$5:$B20>=7)*($B$5:$B20<=9)),$AI$5:$AI20),0))))) | AK20: =AK19+AI20-AJ20 | AL20: =IF(ProviderDelay>=1,S19*BlendedProvPayEss+T19*BlendedProvPayPrem+U19*BlendedProvPayElite+V19*BlendedProvPayEss+W19*BlendedProvPayPrem+X19*BlendedProvPayElite,S20*BlendedProvPayEss+T20*BlendedProvPayPrem+U20*BlendedProvPayElite+V20*BlendedProvPayEss+W20*BlendedProvPayPrem+X20*BlendedProvPayElite) | AM20: =AE20*PaymentFee | AN20: =Y20*OpsAI | AO20: =MonthlyFixed | AP20: =I20*ReferralReward | AQ20: =G20 | AR20: =AH20-AL20-AM20-AN20-AO20-AP20-AQ20 | AS20: =AS19+AE20-(AL20+AM20+AN20+AO20+AP20+AQ20+AJ20) | AT20: =IF(Y20>0,Z20/Y20,0) | AU20: =IF(Y19>0,MAX(0,(Y19+J20-Y20)/Y19),0)
A21: 17 | B21: =MOD(A21-1+LaunchMonth-1,12)+1 | C21: =INT((A21-1+LaunchMonth-1)/12)+1 | D21: =VLOOKUP(B21,SeasonTable,2,FALSE) | E21: =(1+InflationRate)^INT((A21-1)/12) | F21: =MonthlyChurn*VLOOKUP(B21,ChurnSeasonTable,4,FALSE) | G21: =MIN(MAX(MktMin13_18,AE20*MktPct13_18),MAX(0,AS20-CashBuffer)) | H21: =IF(G21>0,MAX(1,ROUND(G21/CAC*D21,0)),0) | I21: =IF(H21>0,ROUND(H21*ReferralMix/(1-ReferralMix),0),0) | J21: =H21+I21 | K21: =ROUND(J21*(1-AnnualMix),0) | L21: =J21-K21 | M21: =ROUND(K21*EssentialMix,0) | N21: =ROUND(K21*PremiumMix,0) | O21: =K21-M21-N21 | P21: =ROUND(L21*EssentialMix,0) | Q21: =ROUND(L21*PremiumMix,0) | R21: =L21-P21-Q21 | S21: =M21+M20+M19+MAX(0,S20-M20-M19)*(1-F21) | T21: =N21+N20+N19+MAX(0,T20-N20-N19)*(1-F21) | U21: =O21+O20+O19+MAX(0,U20-O20-O19)*(1-F21) | V21: =V20+P21-P9*(AnnualChurn*VLOOKUP(B21,ChurnSeasonTable,4,FALSE))*POWER(1-(AnnualChurn*VLOOKUP(B21,ChurnSeasonTable,4,FALSE)),0) | W21: =W20+Q21-Q9*(AnnualChurn*VLOOKUP(B21,ChurnSeasonTable,4,FALSE))*POWER(1-(AnnualChurn*VLOOKUP(B21,ChurnSeasonTable,4,FALSE)),0) | X21: =X20+R21-R9*(AnnualChurn*VLOOKUP(B21,ChurnSeasonTable,4,FALSE))*POWER(1-(AnnualChurn*VLOOKUP(B21,ChurnSeasonTable,4,FALSE)),0) | Y21: =S21+T21+U21+V21+W21+X21 | Z21: =S21*BlendedPriceEssMonthly*E21+T21*BlendedPricePremMonthly*E21+U21*BlendedPriceEliteMonthly*E21+V21*BlendedPriceEssAnnual*E21/12+W21*BlendedPricePremAnnual*E21/12+X21*BlendedPriceEliteAnnual*E21/12 | AA21: =Z21*12 | AB21: =S21*BlendedPriceEssMonthly*E21+T21*BlendedPricePremMonthly*E21+U21*BlendedPriceEliteMonthly*E21 | AC21: =P21*BlendedPriceEssAnnual*E21+Q21*BlendedPricePremAnnual*E21+R21*BlendedPriceEliteAnnual*E21 | AD21: =P9*POWER(1-(AnnualChurn*VLOOKUP(B21,ChurnSeasonTable,4,FALSE)),1)*BlendedPriceEssAnnual*E21+Q9*POWER(1-(AnnualChurn*VLOOKUP(B21,ChurnSeasonTable,4,FALSE)),1)*BlendedPricePremAnnual*E21+R9*POWER(1-(AnnualChurn*VLOOKUP(B21,ChurnSeasonTable,4,FALSE)),1)*BlendedPriceEliteAnnual*E21 | AE21: =AB21+AC21+AD21 | AF21: =SUM(AE10:AE21) | AG21: =OR(AG20,IF(VATAgentMode,SUM($AE10:$AE21)-SUM($AL10:$AL21)>=VATThreshold,SUM($AE10:$AE21)>=VATThreshold)) | AH21: =IF(AG21,IF(VATAgentMode,AE21-((AE21-AL21)-(AE21-AL21)/(1+VATRate)),AE21/(1+VATRate)),AE21) | AI21: =AE21-AH21 | AJ21: =IF(AG21=0,0,IF(B21=1,SUMPRODUCT(--(($C$5:$C21=$C21-1)*($B$5:$B21>=10)*($B$5:$B21<=12)),$AI$5:$AI21),IF(B21=4,SUMPRODUCT(--(($C$5:$C21=$C21)*($B$5:$B21>=1)*($B$5:$B21<=3)),$AI$5:$AI21),IF(B21=7,SUMPRODUCT(--(($C$5:$C21=$C21)*($B$5:$B21>=4)*($B$5:$B21<=6)),$AI$5:$AI21),IF(B21=10,SUMPRODUCT(--(($C$5:$C21=$C21)*($B$5:$B21>=7)*($B$5:$B21<=9)),$AI$5:$AI21),0))))) | AK21: =AK20+AI21-AJ21 | AL21: =IF(ProviderDelay>=1,S20*BlendedProvPayEss+T20*BlendedProvPayPrem+U20*BlendedProvPayElite+V20*BlendedProvPayEss+W20*BlendedProvPayPrem+X20*BlendedProvPayElite,S21*BlendedProvPayEss+T21*BlendedProvPayPrem+U21*BlendedProvPayElite+V21*BlendedProvPayEss+W21*BlendedProvPayPrem+X21*BlendedProvPayElite) | AM21: =AE21*PaymentFee | AN21: =Y21*OpsAI | AO21: =MonthlyFixed | AP21: =I21*ReferralReward | AQ21: =G21 | AR21: =AH21-AL21-AM21-AN21-AO21-AP21-AQ21 | AS21: =AS20+AE21-(AL21+AM21+AN21+AO21+AP21+AQ21+AJ21) | AT21: =IF(Y21>0,Z21/Y21,0) | AU21: =IF(Y20>0,MAX(0,(Y20+J21-Y21)/Y20),0)
A22: 18 | B22: =MOD(A22-1+LaunchMonth-1,12)+1 | C22: =INT((A22-1+LaunchMonth-1)/12)+1 | D22: =VLOOKUP(B22,SeasonTable,2,FALSE) | E22: =(1+InflationRate)^INT((A22-1)/12) | F22: =MonthlyChurn*VLOOKUP(B22,ChurnSeasonTable,4,FALSE) | G22: =MIN(MAX(MktMin13_18,AE21*MktPct13_18),MAX(0,AS21-CashBuffer)) | H22: =IF(G22>0,MAX(1,ROUND(G22/CAC*D22,0)),0) | I22: =IF(H22>0,ROUND(H22*ReferralMix/(1-ReferralMix),0),0) | J22: =H22+I22 | K22: =ROUND(J22*(1-AnnualMix),0) | L22: =J22-K22 | M22: =ROUND(K22*EssentialMix,0) | N22: =ROUND(K22*PremiumMix,0) | O22: =K22-M22-N22 | P22: =ROUND(L22*EssentialMix,0) | Q22: =ROUND(L22*PremiumMix,0) | R22: =L22-P22-Q22 | S22: =M22+M21+M20+MAX(0,S21-M21-M20)*(1-F22) | T22: =N22+N21+N20+MAX(0,T21-N21-N20)*(1-F22) | U22: =O22+O21+O20+MAX(0,U21-O21-O20)*(1-F22) | V22: =V21+P22-P10*(AnnualChurn*VLOOKUP(B22,ChurnSeasonTable,4,FALSE))*POWER(1-(AnnualChurn*VLOOKUP(B22,ChurnSeasonTable,4,FALSE)),0) | W22: =W21+Q22-Q10*(AnnualChurn*VLOOKUP(B22,ChurnSeasonTable,4,FALSE))*POWER(1-(AnnualChurn*VLOOKUP(B22,ChurnSeasonTable,4,FALSE)),0) | X22: =X21+R22-R10*(AnnualChurn*VLOOKUP(B22,ChurnSeasonTable,4,FALSE))*POWER(1-(AnnualChurn*VLOOKUP(B22,ChurnSeasonTable,4,FALSE)),0) | Y22: =S22+T22+U22+V22+W22+X22 | Z22: =S22*BlendedPriceEssMonthly*E22+T22*BlendedPricePremMonthly*E22+U22*BlendedPriceEliteMonthly*E22+V22*BlendedPriceEssAnnual*E22/12+W22*BlendedPricePremAnnual*E22/12+X22*BlendedPriceEliteAnnual*E22/12 | AA22: =Z22*12 | AB22: =S22*BlendedPriceEssMonthly*E22+T22*BlendedPricePremMonthly*E22+U22*BlendedPriceEliteMonthly*E22 | AC22: =P22*BlendedPriceEssAnnual*E22+Q22*BlendedPricePremAnnual*E22+R22*BlendedPriceEliteAnnual*E22 | AD22: =P10*POWER(1-(AnnualChurn*VLOOKUP(B22,ChurnSeasonTable,4,FALSE)),1)*BlendedPriceEssAnnual*E22+Q10*POWER(1-(AnnualChurn*VLOOKUP(B22,ChurnSeasonTable,4,FALSE)),1)*BlendedPricePremAnnual*E22+R10*POWER(1-(AnnualChurn*VLOOKUP(B22,ChurnSeasonTable,4,FALSE)),1)*BlendedPriceEliteAnnual*E22 | AE22: =AB22+AC22+AD22 | AF22: =SUM(AE11:AE22) | AG22: =OR(AG21,IF(VATAgentMode,SUM($AE11:$AE22)-SUM($AL11:$AL22)>=VATThreshold,SUM($AE11:$AE22)>=VATThreshold)) | AH22: =IF(AG22,IF(VATAgentMode,AE22-((AE22-AL22)-(AE22-AL22)/(1+VATRate)),AE22/(1+VATRate)),AE22) | AI22: =AE22-AH22 | AJ22: =IF(AG22=0,0,IF(B22=1,SUMPRODUCT(--(($C$5:$C22=$C22-1)*($B$5:$B22>=10)*($B$5:$B22<=12)),$AI$5:$AI22),IF(B22=4,SUMPRODUCT(--(($C$5:$C22=$C22)*($B$5:$B22>=1)*($B$5:$B22<=3)),$AI$5:$AI22),IF(B22=7,SUMPRODUCT(--(($C$5:$C22=$C22)*($B$5:$B22>=4)*($B$5:$B22<=6)),$AI$5:$AI22),IF(B22=10,SUMPRODUCT(--(($C$5:$C22=$C22)*($B$5:$B22>=7)*($B$5:$B22<=9)),$AI$5:$AI22),0))))) | AK22: =AK21+AI22-AJ22 | AL22: =IF(ProviderDelay>=1,S21*BlendedProvPayEss+T21*BlendedProvPayPrem+U21*BlendedProvPayElite+V21*BlendedProvPayEss+W21*BlendedProvPayPrem+X21*BlendedProvPayElite,S22*BlendedProvPayEss+T22*BlendedProvPayPrem+U22*BlendedProvPayElite+V22*BlendedProvPayEss+W22*BlendedProvPayPrem+X22*BlendedProvPayElite) | AM22: =AE22*PaymentFee | AN22: =Y22*OpsAI | AO22: =MonthlyFixed | AP22: =I22*ReferralReward | AQ22: =G22 | AR22: =AH22-AL22-AM22-AN22-AO22-AP22-AQ22 | AS22: =AS21+AE22-(AL22+AM22+AN22+AO22+AP22+AQ22+AJ22) | AT22: =IF(Y22>0,Z22/Y22,0) | AU22: =IF(Y21>0,MAX(0,(Y21+J22-Y22)/Y21),0)
A23: 19 | B23: =MOD(A23-1+LaunchMonth-1,12)+1 | C23: =INT((A23-1+LaunchMonth-1)/12)+1 | D23: =VLOOKUP(B23,SeasonTable,2,FALSE) | E23: =(1+InflationRate)^INT((A23-1)/12) | F23: =MonthlyChurn*VLOOKUP(B23,ChurnSeasonTable,4,FALSE) | G23: =MIN(MAX(MktMin19plus,AE22*MktPct19plus),MAX(0,AS22-CashBuffer)) | H23: =IF(G23>0,MAX(1,ROUND(G23/CAC*D23,0)),0) | I23: =IF(H23>0,ROUND(H23*ReferralMix/(1-ReferralMix),0),0) | J23: =H23+I23 | K23: =ROUND(J23*(1-AnnualMix),0) | L23: =J23-K23 | M23: =ROUND(K23*EssentialMix,0) | N23: =ROUND(K23*PremiumMix,0) | O23: =K23-M23-N23 | P23: =ROUND(L23*EssentialMix,0) | Q23: =ROUND(L23*PremiumMix,0) | R23: =L23-P23-Q23 | S23: =M23+M22+M21+MAX(0,S22-M22-M21)*(1-F23) | T23: =N23+N22+N21+MAX(0,T22-N22-N21)*(1-F23) | U23: =O23+O22+O21+MAX(0,U22-O22-O21)*(1-F23) | V23: =V22+P23-P11*(AnnualChurn*VLOOKUP(B23,ChurnSeasonTable,4,FALSE))*POWER(1-(AnnualChurn*VLOOKUP(B23,ChurnSeasonTable,4,FALSE)),0) | W23: =W22+Q23-Q11*(AnnualChurn*VLOOKUP(B23,ChurnSeasonTable,4,FALSE))*POWER(1-(AnnualChurn*VLOOKUP(B23,ChurnSeasonTable,4,FALSE)),0) | X23: =X22+R23-R11*(AnnualChurn*VLOOKUP(B23,ChurnSeasonTable,4,FALSE))*POWER(1-(AnnualChurn*VLOOKUP(B23,ChurnSeasonTable,4,FALSE)),0) | Y23: =S23+T23+U23+V23+W23+X23 | Z23: =S23*BlendedPriceEssMonthly*E23+T23*BlendedPricePremMonthly*E23+U23*BlendedPriceEliteMonthly*E23+V23*BlendedPriceEssAnnual*E23/12+W23*BlendedPricePremAnnual*E23/12+X23*BlendedPriceEliteAnnual*E23/12 | AA23: =Z23*12 | AB23: =S23*BlendedPriceEssMonthly*E23+T23*BlendedPricePremMonthly*E23+U23*BlendedPriceEliteMonthly*E23 | AC23: =P23*BlendedPriceEssAnnual*E23+Q23*BlendedPricePremAnnual*E23+R23*BlendedPriceEliteAnnual*E23 | AD23: =P11*POWER(1-(AnnualChurn*VLOOKUP(B23,ChurnSeasonTable,4,FALSE)),1)*BlendedPriceEssAnnual*E23+Q11*POWER(1-(AnnualChurn*VLOOKUP(B23,ChurnSeasonTable,4,FALSE)),1)*BlendedPricePremAnnual*E23+R11*POWER(1-(AnnualChurn*VLOOKUP(B23,ChurnSeasonTable,4,FALSE)),1)*BlendedPriceEliteAnnual*E23 | AE23: =AB23+AC23+AD23 | AF23: =SUM(AE12:AE23) | AG23: =OR(AG22,IF(VATAgentMode,SUM($AE12:$AE23)-SUM($AL12:$AL23)>=VATThreshold,SUM($AE12:$AE23)>=VATThreshold)) | AH23: =IF(AG23,IF(VATAgentMode,AE23-((AE23-AL23)-(AE23-AL23)/(1+VATRate)),AE23/(1+VATRate)),AE23) | AI23: =AE23-AH23 | AJ23: =IF(AG23=0,0,IF(B23=1,SUMPRODUCT(--(($C$5:$C23=$C23-1)*($B$5:$B23>=10)*($B$5:$B23<=12)),$AI$5:$AI23),IF(B23=4,SUMPRODUCT(--(($C$5:$C23=$C23)*($B$5:$B23>=1)*($B$5:$B23<=3)),$AI$5:$AI23),IF(B23=7,SUMPRODUCT(--(($C$5:$C23=$C23)*($B$5:$B23>=4)*($B$5:$B23<=6)),$AI$5:$AI23),IF(B23=10,SUMPRODUCT(--(($C$5:$C23=$C23)*($B$5:$B23>=7)*($B$5:$B23<=9)),$AI$5:$AI23),0))))) | AK23: =AK22+AI23-AJ23 | AL23: =IF(ProviderDelay>=1,S22*BlendedProvPayEss+T22*BlendedProvPayPrem+U22*BlendedProvPayElite+V22*BlendedProvPayEss+W22*BlendedProvPayPrem+X22*BlendedProvPayElite,S23*BlendedProvPayEss+T23*BlendedProvPayPrem+U23*BlendedProvPayElite+V23*BlendedProvPayEss+W23*BlendedProvPayPrem+X23*BlendedProvPayElite) | AM23: =AE23*PaymentFee | AN23: =Y23*OpsAI | AO23: =MonthlyFixed | AP23: =I23*ReferralReward | AQ23: =G23 | AR23: =AH23-AL23-AM23-AN23-AO23-AP23-AQ23 | AS23: =AS22+AE23-(AL23+AM23+AN23+AO23+AP23+AQ23+AJ23) | AT23: =IF(Y23>0,Z23/Y23,0) | AU23: =IF(Y22>0,MAX(0,(Y22+J23-Y23)/Y22),0)
A24: 20 | B24: =MOD(A24-1+LaunchMonth-1,12)+1 | C24: =INT((A24-1+LaunchMonth-1)/12)+1 | D24: =VLOOKUP(B24,SeasonTable,2,FALSE) | E24: =(1+InflationRate)^INT((A24-1)/12) | F24: =MonthlyChurn*VLOOKUP(B24,ChurnSeasonTable,4,FALSE) | G24: =MIN(MAX(MktMin19plus,AE23*MktPct19plus),MAX(0,AS23-CashBuffer)) | H24: =IF(G24>0,MAX(1,ROUND(G24/CAC*D24,0)),0) | I24: =IF(H24>0,ROUND(H24*ReferralMix/(1-ReferralMix),0),0) | J24: =H24+I24 | K24: =ROUND(J24*(1-AnnualMix),0) | L24: =J24-K24 | M24: =ROUND(K24*EssentialMix,0) | N24: =ROUND(K24*PremiumMix,0) | O24: =K24-M24-N24 | P24: =ROUND(L24*EssentialMix,0) | Q24: =ROUND(L24*PremiumMix,0) | R24: =L24-P24-Q24 | S24: =M24+M23+M22+MAX(0,S23-M23-M22)*(1-F24) | T24: =N24+N23+N22+MAX(0,T23-N23-N22)*(1-F24) | U24: =O24+O23+O22+MAX(0,U23-O23-O22)*(1-F24) | V24: =V23+P24-P12*(AnnualChurn*VLOOKUP(B24,ChurnSeasonTable,4,FALSE))*POWER(1-(AnnualChurn*VLOOKUP(B24,ChurnSeasonTable,4,FALSE)),0) | W24: =W23+Q24-Q12*(AnnualChurn*VLOOKUP(B24,ChurnSeasonTable,4,FALSE))*POWER(1-(AnnualChurn*VLOOKUP(B24,ChurnSeasonTable,4,FALSE)),0) | X24: =X23+R24-R12*(AnnualChurn*VLOOKUP(B24,ChurnSeasonTable,4,FALSE))*POWER(1-(AnnualChurn*VLOOKUP(B24,ChurnSeasonTable,4,FALSE)),0) | Y24: =S24+T24+U24+V24+W24+X24 | Z24: =S24*BlendedPriceEssMonthly*E24+T24*BlendedPricePremMonthly*E24+U24*BlendedPriceEliteMonthly*E24+V24*BlendedPriceEssAnnual*E24/12+W24*BlendedPricePremAnnual*E24/12+X24*BlendedPriceEliteAnnual*E24/12 | AA24: =Z24*12 | AB24: =S24*BlendedPriceEssMonthly*E24+T24*BlendedPricePremMonthly*E24+U24*BlendedPriceEliteMonthly*E24 | AC24: =P24*BlendedPriceEssAnnual*E24+Q24*BlendedPricePremAnnual*E24+R24*BlendedPriceEliteAnnual*E24 | AD24: =P12*POWER(1-(AnnualChurn*VLOOKUP(B24,ChurnSeasonTable,4,FALSE)),1)*BlendedPriceEssAnnual*E24+Q12*POWER(1-(AnnualChurn*VLOOKUP(B24,ChurnSeasonTable,4,FALSE)),1)*BlendedPricePremAnnual*E24+R12*POWER(1-(AnnualChurn*VLOOKUP(B24,ChurnSeasonTable,4,FALSE)),1)*BlendedPriceEliteAnnual*E24 | AE24: =AB24+AC24+AD24 | AF24: =SUM(AE13:AE24) | AG24: =OR(AG23,IF(VATAgentMode,SUM($AE13:$AE24)-SUM($AL13:$AL24)>=VATThreshold,SUM($AE13:$AE24)>=VATThreshold)) | AH24: =IF(AG24,IF(VATAgentMode,AE24-((AE24-AL24)-(AE24-AL24)/(1+VATRate)),AE24/(1+VATRate)),AE24) | AI24: =AE24-AH24 | AJ24: =IF(AG24=0,0,IF(B24=1,SUMPRODUCT(--(($C$5:$C24=$C24-1)*($B$5:$B24>=10)*($B$5:$B24<=12)),$AI$5:$AI24),IF(B24=4,SUMPRODUCT(--(($C$5:$C24=$C24)*($B$5:$B24>=1)*($B$5:$B24<=3)),$AI$5:$AI24),IF(B24=7,SUMPRODUCT(--(($C$5:$C24=$C24)*($B$5:$B24>=4)*($B$5:$B24<=6)),$AI$5:$AI24),IF(B24=10,SUMPRODUCT(--(($C$5:$C24=$C24)*($B$5:$B24>=7)*($B$5:$B24<=9)),$AI$5:$AI24),0))))) | AK24: =AK23+AI24-AJ24 | AL24: =IF(ProviderDelay>=1,S23*BlendedProvPayEss+T23*BlendedProvPayPrem+U23*BlendedProvPayElite+V23*BlendedProvPayEss+W23*BlendedProvPayPrem+X23*BlendedProvPayElite,S24*BlendedProvPayEss+T24*BlendedProvPayPrem+U24*BlendedProvPayElite+V24*BlendedProvPayEss+W24*BlendedProvPayPrem+X24*BlendedProvPayElite) | AM24: =AE24*PaymentFee | AN24: =Y24*OpsAI | AO24: =MonthlyFixed | AP24: =I24*ReferralReward | AQ24: =G24 | AR24: =AH24-AL24-AM24-AN24-AO24-AP24-AQ24 | AS24: =AS23+AE24-(AL24+AM24+AN24+AO24+AP24+AQ24+AJ24) | AT24: =IF(Y24>0,Z24/Y24,0) | AU24: =IF(Y23>0,MAX(0,(Y23+J24-Y24)/Y23),0)
A25: 21 | B25: =MOD(A25-1+LaunchMonth-1,12)+1 | C25: =INT((A25-1+LaunchMonth-1)/12)+1 | D25: =VLOOKUP(B25,SeasonTable,2,FALSE) | E25: =(1+InflationRate)^INT((A25-1)/12) | F25: =MonthlyChurn*VLOOKUP(B25,ChurnSeasonTable,4,FALSE) | G25: =MIN(MAX(MktMin19plus,AE24*MktPct19plus),MAX(0,AS24-CashBuffer)) | H25: =IF(G25>0,MAX(1,ROUND(G25/CAC*D25,0)),0) | I25: =IF(H25>0,ROUND(H25*ReferralMix/(1-ReferralMix),0),0) | J25: =H25+I25 | K25: =ROUND(J25*(1-AnnualMix),0) | L25: =J25-K25 | M25: =ROUND(K25*EssentialMix,0) | N25: =ROUND(K25*PremiumMix,0) | O25: =K25-M25-N25 | P25: =ROUND(L25*EssentialMix,0) | Q25: =ROUND(L25*PremiumMix,0) | R25: =L25-P25-Q25 | S25: =M25+M24+M23+MAX(0,S24-M24-M23)*(1-F25) | T25: =N25+N24+N23+MAX(0,T24-N24-N23)*(1-F25) | U25: =O25+O24+O23+MAX(0,U24-O24-O23)*(1-F25) | V25: =V24+P25-P13*(AnnualChurn*VLOOKUP(B25,ChurnSeasonTable,4,FALSE))*POWER(1-(AnnualChurn*VLOOKUP(B25,ChurnSeasonTable,4,FALSE)),0) | W25: =W24+Q25-Q13*(AnnualChurn*VLOOKUP(B25,ChurnSeasonTable,4,FALSE))*POWER(1-(AnnualChurn*VLOOKUP(B25,ChurnSeasonTable,4,FALSE)),0) | X25: =X24+R25-R13*(AnnualChurn*VLOOKUP(B25,ChurnSeasonTable,4,FALSE))*POWER(1-(AnnualChurn*VLOOKUP(B25,ChurnSeasonTable,4,FALSE)),0) | Y25: =S25+T25+U25+V25+W25+X25 | Z25: =S25*BlendedPriceEssMonthly*E25+T25*BlendedPricePremMonthly*E25+U25*BlendedPriceEliteMonthly*E25+V25*BlendedPriceEssAnnual*E25/12+W25*BlendedPricePremAnnual*E25/12+X25*BlendedPriceEliteAnnual*E25/12 | AA25: =Z25*12 | AB25: =S25*BlendedPriceEssMonthly*E25+T25*BlendedPricePremMonthly*E25+U25*BlendedPriceEliteMonthly*E25 | AC25: =P25*BlendedPriceEssAnnual*E25+Q25*BlendedPricePremAnnual*E25+R25*BlendedPriceEliteAnnual*E25 | AD25: =P13*POWER(1-(AnnualChurn*VLOOKUP(B25,ChurnSeasonTable,4,FALSE)),1)*BlendedPriceEssAnnual*E25+Q13*POWER(1-(AnnualChurn*VLOOKUP(B25,ChurnSeasonTable,4,FALSE)),1)*BlendedPricePremAnnual*E25+R13*POWER(1-(AnnualChurn*VLOOKUP(B25,ChurnSeasonTable,4,FALSE)),1)*BlendedPriceEliteAnnual*E25 | AE25: =AB25+AC25+AD25 | AF25: =SUM(AE14:AE25) | AG25: =OR(AG24,IF(VATAgentMode,SUM($AE14:$AE25)-SUM($AL14:$AL25)>=VATThreshold,SUM($AE14:$AE25)>=VATThreshold)) | AH25: =IF(AG25,IF(VATAgentMode,AE25-((AE25-AL25)-(AE25-AL25)/(1+VATRate)),AE25/(1+VATRate)),AE25) | AI25: =AE25-AH25 | AJ25: =IF(AG25=0,0,IF(B25=1,SUMPRODUCT(--(($C$5:$C25=$C25-1)*($B$5:$B25>=10)*($B$5:$B25<=12)),$AI$5:$AI25),IF(B25=4,SUMPRODUCT(--(($C$5:$C25=$C25)*($B$5:$B25>=1)*($B$5:$B25<=3)),$AI$5:$AI25),IF(B25=7,SUMPRODUCT(--(($C$5:$C25=$C25)*($B$5:$B25>=4)*($B$5:$B25<=6)),$AI$5:$AI25),IF(B25=10,SUMPRODUCT(--(($C$5:$C25=$C25)*($B$5:$B25>=7)*($B$5:$B25<=9)),$AI$5:$AI25),0))))) | AK25: =AK24+AI25-AJ25 | AL25: =IF(ProviderDelay>=1,S24*BlendedProvPayEss+T24*BlendedProvPayPrem+U24*BlendedProvPayElite+V24*BlendedProvPayEss+W24*BlendedProvPayPrem+X24*BlendedProvPayElite,S25*BlendedProvPayEss+T25*BlendedProvPayPrem+U25*BlendedProvPayElite+V25*BlendedProvPayEss+W25*BlendedProvPayPrem+X25*BlendedProvPayElite) | AM25: =AE25*PaymentFee | AN25: =Y25*OpsAI | AO25: =MonthlyFixed | AP25: =I25*ReferralReward | AQ25: =G25 | AR25: =AH25-AL25-AM25-AN25-AO25-AP25-AQ25 | AS25: =AS24+AE25-(AL25+AM25+AN25+AO25+AP25+AQ25+AJ25) | AT25: =IF(Y25>0,Z25/Y25,0) | AU25: =IF(Y24>0,MAX(0,(Y24+J25-Y25)/Y24),0)
A26: 22 | B26: =MOD(A26-1+LaunchMonth-1,12)+1 | C26: =INT((A26-1+LaunchMonth-1)/12)+1 | D26: =VLOOKUP(B26,SeasonTable,2,FALSE) | E26: =(1+InflationRate)^INT((A26-1)/12) | F26: =MonthlyChurn*VLOOKUP(B26,ChurnSeasonTable,4,FALSE) | G26: =MIN(MAX(MktMin19plus,AE25*MktPct19plus),MAX(0,AS25-CashBuffer)) | H26: =IF(G26>0,MAX(1,ROUND(G26/CAC*D26,0)),0) | I26: =IF(H26>0,ROUND(H26*ReferralMix/(1-ReferralMix),0),0) | J26: =H26+I26 | K26: =ROUND(J26*(1-AnnualMix),0) | L26: =J26-K26 | M26: =ROUND(K26*EssentialMix,0) | N26: =ROUND(K26*PremiumMix,0) | O26: =K26-M26-N26 | P26: =ROUND(L26*EssentialMix,0) | Q26: =ROUND(L26*PremiumMix,0) | R26: =L26-P26-Q26 | S26: =M26+M25+M24+MAX(0,S25-M25-M24)*(1-F26) | T26: =N26+N25+N24+MAX(0,T25-N25-N24)*(1-F26) | U26: =O26+O25+O24+MAX(0,U25-O25-O24)*(1-F26) | V26: =V25+P26-P14*(AnnualChurn*VLOOKUP(B26,ChurnSeasonTable,4,FALSE))*POWER(1-(AnnualChurn*VLOOKUP(B26,ChurnSeasonTable,4,FALSE)),0) | W26: =W25+Q26-Q14*(AnnualChurn*VLOOKUP(B26,ChurnSeasonTable,4,FALSE))*POWER(1-(AnnualChurn*VLOOKUP(B26,ChurnSeasonTable,4,FALSE)),0) | X26: =X25+R26-R14*(AnnualChurn*VLOOKUP(B26,ChurnSeasonTable,4,FALSE))*POWER(1-(AnnualChurn*VLOOKUP(B26,ChurnSeasonTable,4,FALSE)),0) | Y26: =S26+T26+U26+V26+W26+X26 | Z26: =S26*BlendedPriceEssMonthly*E26+T26*BlendedPricePremMonthly*E26+U26*BlendedPriceEliteMonthly*E26+V26*BlendedPriceEssAnnual*E26/12+W26*BlendedPricePremAnnual*E26/12+X26*BlendedPriceEliteAnnual*E26/12 | AA26: =Z26*12 | AB26: =S26*BlendedPriceEssMonthly*E26+T26*BlendedPricePremMonthly*E26+U26*BlendedPriceEliteMonthly*E26 | AC26: =P26*BlendedPriceEssAnnual*E26+Q26*BlendedPricePremAnnual*E26+R26*BlendedPriceEliteAnnual*E26 | AD26: =P14*POWER(1-(AnnualChurn*VLOOKUP(B26,ChurnSeasonTable,4,FALSE)),1)*BlendedPriceEssAnnual*E26+Q14*POWER(1-(AnnualChurn*VLOOKUP(B26,ChurnSeasonTable,4,FALSE)),1)*BlendedPricePremAnnual*E26+R14*POWER(1-(AnnualChurn*VLOOKUP(B26,ChurnSeasonTable,4,FALSE)),1)*BlendedPriceEliteAnnual*E26 | AE26: =AB26+AC26+AD26 | AF26: =SUM(AE15:AE26) | AG26: =OR(AG25,IF(VATAgentMode,SUM($AE15:$AE26)-SUM($AL15:$AL26)>=VATThreshold,SUM($AE15:$AE26)>=VATThreshold)) | AH26: =IF(AG26,IF(VATAgentMode,AE26-((AE26-AL26)-(AE26-AL26)/(1+VATRate)),AE26/(1+VATRate)),AE26) | AI26: =AE26-AH26 | AJ26: =IF(AG26=0,0,IF(B26=1,SUMPRODUCT(--(($C$5:$C26=$C26-1)*($B$5:$B26>=10)*($B$5:$B26<=12)),$AI$5:$AI26),IF(B26=4,SUMPRODUCT(--(($C$5:$C26=$C26)*($B$5:$B26>=1)*($B$5:$B26<=3)),$AI$5:$AI26),IF(B26=7,SUMPRODUCT(--(($C$5:$C26=$C26)*($B$5:$B26>=4)*($B$5:$B26<=6)),$AI$5:$AI26),IF(B26=10,SUMPRODUCT(--(($C$5:$C26=$C26)*($B$5:$B26>=7)*($B$5:$B26<=9)),$AI$5:$AI26),0))))) | AK26: =AK25+AI26-AJ26 | AL26: =IF(ProviderDelay>=1,S25*BlendedProvPayEss+T25*BlendedProvPayPrem+U25*BlendedProvPayElite+V25*BlendedProvPayEss+W25*BlendedProvPayPrem+X25*BlendedProvPayElite,S26*BlendedProvPayEss+T26*BlendedProvPayPrem+U26*BlendedProvPayElite+V26*BlendedProvPayEss+W26*BlendedProvPayPrem+X26*BlendedProvPayElite) | AM26: =AE26*PaymentFee | AN26: =Y26*OpsAI | AO26: =MonthlyFixed | AP26: =I26*ReferralReward | AQ26: =G26 | AR26: =AH26-AL26-AM26-AN26-AO26-AP26-AQ26 | AS26: =AS25+AE26-(AL26+AM26+AN26+AO26+AP26+AQ26+AJ26) | AT26: =IF(Y26>0,Z26/Y26,0) | AU26: =IF(Y25>0,MAX(0,(Y25+J26-Y26)/Y25),0)
A27: 23 | B27: =MOD(A27-1+LaunchMonth-1,12)+1 | C27: =INT((A27-1+LaunchMonth-1)/12)+1 | D27: =VLOOKUP(B27,SeasonTable,2,FALSE) | E27: =(1+InflationRate)^INT((A27-1)/12) | F27: =MonthlyChurn*VLOOKUP(B27,ChurnSeasonTable,4,FALSE) | G27: =MIN(MAX(MktMin19plus,AE26*MktPct19plus),MAX(0,AS26-CashBuffer)) | H27: =IF(G27>0,MAX(1,ROUND(G27/CAC*D27,0)),0) | I27: =IF(H27>0,ROUND(H27*ReferralMix/(1-ReferralMix),0),0) | J27: =H27+I27 | K27: =ROUND(J27*(1-AnnualMix),0) | L27: =J27-K27 | M27: =ROUND(K27*EssentialMix,0) | N27: =ROUND(K27*PremiumMix,0) | O27: =K27-M27-N27 | P27: =ROUND(L27*EssentialMix,0) | Q27: =ROUND(L27*PremiumMix,0) | R27: =L27-P27-Q27 | S27: =M27+M26+M25+MAX(0,S26-M26-M25)*(1-F27) | T27: =N27+N26+N25+MAX(0,T26-N26-N25)*(1-F27) | U27: =O27+O26+O25+MAX(0,U26-O26-O25)*(1-F27) | V27: =V26+P27-P15*(AnnualChurn*VLOOKUP(B27,ChurnSeasonTable,4,FALSE))*POWER(1-(AnnualChurn*VLOOKUP(B27,ChurnSeasonTable,4,FALSE)),0) | W27: =W26+Q27-Q15*(AnnualChurn*VLOOKUP(B27,ChurnSeasonTable,4,FALSE))*POWER(1-(AnnualChurn*VLOOKUP(B27,ChurnSeasonTable,4,FALSE)),0) | X27: =X26+R27-R15*(AnnualChurn*VLOOKUP(B27,ChurnSeasonTable,4,FALSE))*POWER(1-(AnnualChurn*VLOOKUP(B27,ChurnSeasonTable,4,FALSE)),0) | Y27: =S27+T27+U27+V27+W27+X27 | Z27: =S27*BlendedPriceEssMonthly*E27+T27*BlendedPricePremMonthly*E27+U27*BlendedPriceEliteMonthly*E27+V27*BlendedPriceEssAnnual*E27/12+W27*BlendedPricePremAnnual*E27/12+X27*BlendedPriceEliteAnnual*E27/12 | AA27: =Z27*12 | AB27: =S27*BlendedPriceEssMonthly*E27+T27*BlendedPricePremMonthly*E27+U27*BlendedPriceEliteMonthly*E27 | AC27: =P27*BlendedPriceEssAnnual*E27+Q27*BlendedPricePremAnnual*E27+R27*BlendedPriceEliteAnnual*E27 | AD27: =P15*POWER(1-(AnnualChurn*VLOOKUP(B27,ChurnSeasonTable,4,FALSE)),1)*BlendedPriceEssAnnual*E27+Q15*POWER(1-(AnnualChurn*VLOOKUP(B27,ChurnSeasonTable,4,FALSE)),1)*BlendedPricePremAnnual*E27+R15*POWER(1-(AnnualChurn*VLOOKUP(B27,ChurnSeasonTable,4,FALSE)),1)*BlendedPriceEliteAnnual*E27 | AE27: =AB27+AC27+AD27 | AF27: =SUM(AE16:AE27) | AG27: =OR(AG26,IF(VATAgentMode,SUM($AE16:$AE27)-SUM($AL16:$AL27)>=VATThreshold,SUM($AE16:$AE27)>=VATThreshold)) | AH27: =IF(AG27,IF(VATAgentMode,AE27-((AE27-AL27)-(AE27-AL27)/(1+VATRate)),AE27/(1+VATRate)),AE27) | AI27: =AE27-AH27 | AJ27: =IF(AG27=0,0,IF(B27=1,SUMPRODUCT(--(($C$5:$C27=$C27-1)*($B$5:$B27>=10)*($B$5:$B27<=12)),$AI$5:$AI27),IF(B27=4,SUMPRODUCT(--(($C$5:$C27=$C27)*($B$5:$B27>=1)*($B$5:$B27<=3)),$AI$5:$AI27),IF(B27=7,SUMPRODUCT(--(($C$5:$C27=$C27)*($B$5:$B27>=4)*($B$5:$B27<=6)),$AI$5:$AI27),IF(B27=10,SUMPRODUCT(--(($C$5:$C27=$C27)*($B$5:$B27>=7)*($B$5:$B27<=9)),$AI$5:$AI27),0))))) | AK27: =AK26+AI27-AJ27 | AL27: =IF(ProviderDelay>=1,S26*BlendedProvPayEss+T26*BlendedProvPayPrem+U26*BlendedProvPayElite+V26*BlendedProvPayEss+W26*BlendedProvPayPrem+X26*BlendedProvPayElite,S27*BlendedProvPayEss+T27*BlendedProvPayPrem+U27*BlendedProvPayElite+V27*BlendedProvPayEss+W27*BlendedProvPayPrem+X27*BlendedProvPayElite) | AM27: =AE27*PaymentFee | AN27: =Y27*OpsAI | AO27: =MonthlyFixed | AP27: =I27*ReferralReward | AQ27: =G27 | AR27: =AH27-AL27-AM27-AN27-AO27-AP27-AQ27 | AS27: =AS26+AE27-(AL27+AM27+AN27+AO27+AP27+AQ27+AJ27) | AT27: =IF(Y27>0,Z27/Y27,0) | AU27: =IF(Y26>0,MAX(0,(Y26+J27-Y27)/Y26),0)
A28: 24 | B28: =MOD(A28-1+LaunchMonth-1,12)+1 | C28: =INT((A28-1+LaunchMonth-1)/12)+1 | D28: =VLOOKUP(B28,SeasonTable,2,FALSE) | E28: =(1+InflationRate)^INT((A28-1)/12) | F28: =MonthlyChurn*VLOOKUP(B28,ChurnSeasonTable,4,FALSE) | G28: =MIN(MAX(MktMin19plus,AE27*MktPct19plus),MAX(0,AS27-CashBuffer)) | H28: =IF(G28>0,MAX(1,ROUND(G28/CAC*D28,0)),0) | I28: =IF(H28>0,ROUND(H28*ReferralMix/(1-ReferralMix),0),0) | J28: =H28+I28 | K28: =ROUND(J28*(1-AnnualMix),0) | L28: =J28-K28 | M28: =ROUND(K28*EssentialMix,0) | N28: =ROUND(K28*PremiumMix,0) | O28: =K28-M28-N28 | P28: =ROUND(L28*EssentialMix,0) | Q28: =ROUND(L28*PremiumMix,0) | R28: =L28-P28-Q28 | S28: =M28+M27+M26+MAX(0,S27-M27-M26)*(1-F28) | T28: =N28+N27+N26+MAX(0,T27-N27-N26)*(1-F28) | U28: =O28+O27+O26+MAX(0,U27-O27-O26)*(1-F28) | V28: =V27+P28-P16*(AnnualChurn*VLOOKUP(B28,ChurnSeasonTable,4,FALSE))*POWER(1-(AnnualChurn*VLOOKUP(B28,ChurnSeasonTable,4,FALSE)),0) | W28: =W27+Q28-Q16*(AnnualChurn*VLOOKUP(B28,ChurnSeasonTable,4,FALSE))*POWER(1-(AnnualChurn*VLOOKUP(B28,ChurnSeasonTable,4,FALSE)),0) | X28: =X27+R28-R16*(AnnualChurn*VLOOKUP(B28,ChurnSeasonTable,4,FALSE))*POWER(1-(AnnualChurn*VLOOKUP(B28,ChurnSeasonTable,4,FALSE)),0) | Y28: =S28+T28+U28+V28+W28+X28 | Z28: =S28*BlendedPriceEssMonthly*E28+T28*BlendedPricePremMonthly*E28+U28*BlendedPriceEliteMonthly*E28+V28*BlendedPriceEssAnnual*E28/12+W28*BlendedPricePremAnnual*E28/12+X28*BlendedPriceEliteAnnual*E28/12 | AA28: =Z28*12 | AB28: =S28*BlendedPriceEssMonthly*E28+T28*BlendedPricePremMonthly*E28+U28*BlendedPriceEliteMonthly*E28 | AC28: =P28*BlendedPriceEssAnnual*E28+Q28*BlendedPricePremAnnual*E28+R28*BlendedPriceEliteAnnual*E28 | AD28: =P16*POWER(1-(AnnualChurn*VLOOKUP(B28,ChurnSeasonTable,4,FALSE)),1)*BlendedPriceEssAnnual*E28+Q16*POWER(1-(AnnualChurn*VLOOKUP(B28,ChurnSeasonTable,4,FALSE)),1)*BlendedPricePremAnnual*E28+R16*POWER(1-(AnnualChurn*VLOOKUP(B28,ChurnSeasonTable,4,FALSE)),1)*BlendedPriceEliteAnnual*E28 | AE28: =AB28+AC28+AD28 | AF28: =SUM(AE17:AE28) | AG28: =OR(AG27,IF(VATAgentMode,SUM($AE17:$AE28)-SUM($AL17:$AL28)>=VATThreshold,SUM($AE17:$AE28)>=VATThreshold)) | AH28: =IF(AG28,IF(VATAgentMode,AE28-((AE28-AL28)-(AE28-AL28)/(1+VATRate)),AE28/(1+VATRate)),AE28) | AI28: =AE28-AH28 | AJ28: =IF(AG28=0,0,IF(B28=1,SUMPRODUCT(--(($C$5:$C28=$C28-1)*($B$5:$B28>=10)*($B$5:$B28<=12)),$AI$5:$AI28),IF(B28=4,SUMPRODUCT(--(($C$5:$C28=$C28)*($B$5:$B28>=1)*($B$5:$B28<=3)),$AI$5:$AI28),IF(B28=7,SUMPRODUCT(--(($C$5:$C28=$C28)*($B$5:$B28>=4)*($B$5:$B28<=6)),$AI$5:$AI28),IF(B28=10,SUMPRODUCT(--(($C$5:$C28=$C28)*($B$5:$B28>=7)*($B$5:$B28<=9)),$AI$5:$AI28),0))))) | AK28: =AK27+AI28-AJ28 | AL28: =IF(ProviderDelay>=1,S27*BlendedProvPayEss+T27*BlendedProvPayPrem+U27*BlendedProvPayElite+V27*BlendedProvPayEss+W27*BlendedProvPayPrem+X27*BlendedProvPayElite,S28*BlendedProvPayEss+T28*BlendedProvPayPrem+U28*BlendedProvPayElite+V28*BlendedProvPayEss+W28*BlendedProvPayPrem+X28*BlendedProvPayElite) | AM28: =AE28*PaymentFee | AN28: =Y28*OpsAI | AO28: =MonthlyFixed | AP28: =I28*ReferralReward | AQ28: =G28 | AR28: =AH28-AL28-AM28-AN28-AO28-AP28-AQ28 | AS28: =AS27+AE28-(AL28+AM28+AN28+AO28+AP28+AQ28+AJ28) | AT28: =IF(Y28>0,Z28/Y28,0) | AU28: =IF(Y27>0,MAX(0,(Y27+J28-Y28)/Y27),0)
A29: 25 | B29: =MOD(A29-1+LaunchMonth-1,12)+1 | C29: =INT((A29-1+LaunchMonth-1)/12)+1 | D29: =VLOOKUP(B29,SeasonTable,2,FALSE) | E29: =(1+InflationRate)^INT((A29-1)/12) | F29: =MonthlyChurn*VLOOKUP(B29,ChurnSeasonTable,4,FALSE) | G29: =MIN(MAX(MktMin19plus,AE28*MktPct19plus),MAX(0,AS28-CashBuffer)) | H29: =IF(G29>0,MAX(1,ROUND(G29/CAC*D29,0)),0) | I29: =IF(H29>0,ROUND(H29*ReferralMix/(1-ReferralMix),0),0) | J29: =H29+I29 | K29: =ROUND(J29*(1-AnnualMix),0) | L29: =J29-K29 | M29: =ROUND(K29*EssentialMix,0) | N29: =ROUND(K29*PremiumMix,0) | O29: =K29-M29-N29 | P29: =ROUND(L29*EssentialMix,0) | Q29: =ROUND(L29*PremiumMix,0) | R29: =L29-P29-Q29 | S29: =M29+M28+M27+MAX(0,S28-M28-M27)*(1-F29) | T29: =N29+N28+N27+MAX(0,T28-N28-N27)*(1-F29) | U29: =O29+O28+O27+MAX(0,U28-O28-O27)*(1-F29) | V29: =V28+P29-P17*(AnnualChurn*VLOOKUP(B29,ChurnSeasonTable,4,FALSE))*POWER(1-(AnnualChurn*VLOOKUP(B29,ChurnSeasonTable,4,FALSE)),0)+P5*(AnnualChurn*VLOOKUP(B29,ChurnSeasonTable,4,FALSE))*POWER(1-(AnnualChurn*VLOOKUP(B29,ChurnSeasonTable,4,FALSE)),1) | W29: =W28+Q29-Q17*(AnnualChurn*VLOOKUP(B29,ChurnSeasonTable,4,FALSE))*POWER(1-(AnnualChurn*VLOOKUP(B29,ChurnSeasonTable,4,FALSE)),0)+Q5*(AnnualChurn*VLOOKUP(B29,ChurnSeasonTable,4,FALSE))*POWER(1-(AnnualChurn*VLOOKUP(B29,ChurnSeasonTable,4,FALSE)),1) | X29: =X28+R29-R17*(AnnualChurn*VLOOKUP(B29,ChurnSeasonTable,4,FALSE))*POWER(1-(AnnualChurn*VLOOKUP(B29,ChurnSeasonTable,4,FALSE)),0)+R5*(AnnualChurn*VLOOKUP(B29,ChurnSeasonTable,4,FALSE))*POWER(1-(AnnualChurn*VLOOKUP(B29,ChurnSeasonTable,4,FALSE)),1) | Y29: =S29+T29+U29+V29+W29+X29 | Z29: =S29*BlendedPriceEssMonthly*E29+T29*BlendedPricePremMonthly*E29+U29*BlendedPriceEliteMonthly*E29+V29*BlendedPriceEssAnnual*E29/12+W29*BlendedPricePremAnnual*E29/12+X29*BlendedPriceEliteAnnual*E29/12 | AA29: =Z29*12 | AB29: =S29*BlendedPriceEssMonthly*E29+T29*BlendedPricePremMonthly*E29+U29*BlendedPriceEliteMonthly*E29 | AC29: =P29*BlendedPriceEssAnnual*E29+Q29*BlendedPricePremAnnual*E29+R29*BlendedPriceEliteAnnual*E29 | AD29: =P17*POWER(1-(AnnualChurn*VLOOKUP(B29,ChurnSeasonTable,4,FALSE)),1)*BlendedPriceEssAnnual*E29+P5*POWER(1-(AnnualChurn*VLOOKUP(B29,ChurnSeasonTable,4,FALSE)),2)*BlendedPriceEssAnnual*E29+Q17*POWER(1-(AnnualChurn*VLOOKUP(B29,ChurnSeasonTable,4,FALSE)),1)*BlendedPricePremAnnual*E29+Q5*POWER(1-(AnnualChurn*VLOOKUP(B29,ChurnSeasonTable,4,FALSE)),2)*BlendedPricePremAnnual*E29+R17*POWER(1-(AnnualChurn*VLOOKUP(B29,ChurnSeasonTable,4,FALSE)),1)*BlendedPriceEliteAnnual*E29+R5*POWER(1-(AnnualChurn*VLOOKUP(B29,ChurnSeasonTable,4,FALSE)),2)*BlendedPriceEliteAnnual*E29 | AE29: =AB29+AC29+AD29 | AF29: =SUM(AE18:AE29) | AG29: =OR(AG28,IF(VATAgentMode,SUM($AE18:$AE29)-SUM($AL18:$AL29)>=VATThreshold,SUM($AE18:$AE29)>=VATThreshold)) | AH29: =IF(AG29,IF(VATAgentMode,AE29-((AE29-AL29)-(AE29-AL29)/(1+VATRate)),AE29/(1+VATRate)),AE29) | AI29: =AE29-AH29 | AJ29: =IF(AG29=0,0,IF(B29=1,SUMPRODUCT(--(($C$5:$C29=$C29-1)*($B$5:$B29>=10)*($B$5:$B29<=12)),$AI$5:$AI29),IF(B29=4,SUMPRODUCT(--(($C$5:$C29=$C29)*($B$5:$B29>=1)*($B$5:$B29<=3)),$AI$5:$AI29),IF(B29=7,SUMPRODUCT(--(($C$5:$C29=$C29)*($B$5:$B29>=4)*($B$5:$B29<=6)),$AI$5:$AI29),IF(B29=10,SUMPRODUCT(--(($C$5:$C29=$C29)*($B$5:$B29>=7)*($B$5:$B29<=9)),$AI$5:$AI29),0))))) | AK29: =AK28+AI29-AJ29 | AL29: =IF(ProviderDelay>=1,S28*BlendedProvPayEss+T28*BlendedProvPayPrem+U28*BlendedProvPayElite+V28*BlendedProvPayEss+W28*BlendedProvPayPrem+X28*BlendedProvPayElite,S29*BlendedProvPayEss+T29*BlendedProvPayPrem+U29*BlendedProvPayElite+V29*BlendedProvPayEss+W29*BlendedProvPayPrem+X29*BlendedProvPayElite) | AM29: =AE29*PaymentFee | AN29: =Y29*OpsAI | AO29: =MonthlyFixed | AP29: =I29*ReferralReward | AQ29: =G29 | AR29: =AH29-AL29-AM29-AN29-AO29-AP29-AQ29 | AS29: =AS28+AE29-(AL29+AM29+AN29+AO29+AP29+AQ29+AJ29) | AT29: =IF(Y29>0,Z29/Y29,0) | AU29: =IF(Y28>0,MAX(0,(Y28+J29-Y29)/Y28),0)
A30: 26 | B30: =MOD(A30-1+LaunchMonth-1,12)+1 | C30: =INT((A30-1+LaunchMonth-1)/12)+1 | D30: =VLOOKUP(B30,SeasonTable,2,FALSE) | E30: =(1+InflationRate)^INT((A30-1)/12) | F30: =MonthlyChurn*VLOOKUP(B30,ChurnSeasonTable,4,FALSE) | G30: =MIN(MAX(MktMin19plus,AE29*MktPct19plus),MAX(0,AS29-CashBuffer)) | H30: =IF(G30>0,MAX(1,ROUND(G30/CAC*D30,0)),0) | I30: =IF(H30>0,ROUND(H30*ReferralMix/(1-ReferralMix),0),0) | J30: =H30+I30 | K30: =ROUND(J30*(1-AnnualMix),0) | L30: =J30-K30 | M30: =ROUND(K30*EssentialMix,0) | N30: =ROUND(K30*PremiumMix,0) | O30: =K30-M30-N30 | P30: =ROUND(L30*EssentialMix,0) | Q30: =ROUND(L30*PremiumMix,0) | R30: =L30-P30-Q30 | S30: =M30+M29+M28+MAX(0,S29-M29-M28)*(1-F30) | T30: =N30+N29+N28+MAX(0,T29-N29-N28)*(1-F30) | U30: =O30+O29+O28+MAX(0,U29-O29-O28)*(1-F30) | V30: =V29+P30-P18*(AnnualChurn*VLOOKUP(B30,ChurnSeasonTable,4,FALSE))*POWER(1-(AnnualChurn*VLOOKUP(B30,ChurnSeasonTable,4,FALSE)),0)+P6*(AnnualChurn*VLOOKUP(B30,ChurnSeasonTable,4,FALSE))*POWER(1-(AnnualChurn*VLOOKUP(B30,ChurnSeasonTable,4,FALSE)),1) | W30: =W29+Q30-Q18*(AnnualChurn*VLOOKUP(B30,ChurnSeasonTable,4,FALSE))*POWER(1-(AnnualChurn*VLOOKUP(B30,ChurnSeasonTable,4,FALSE)),0)+Q6*(AnnualChurn*VLOOKUP(B30,ChurnSeasonTable,4,FALSE))*POWER(1-(AnnualChurn*VLOOKUP(B30,ChurnSeasonTable,4,FALSE)),1) | X30: =X29+R30-R18*(AnnualChurn*VLOOKUP(B30,ChurnSeasonTable,4,FALSE))*POWER(1-(AnnualChurn*VLOOKUP(B30,ChurnSeasonTable,4,FALSE)),0)+R6*(AnnualChurn*VLOOKUP(B30,ChurnSeasonTable,4,FALSE))*POWER(1-(AnnualChurn*VLOOKUP(B30,ChurnSeasonTable,4,FALSE)),1) | Y30: =S30+T30+U30+V30+W30+X30 | Z30: =S30*BlendedPriceEssMonthly*E30+T30*BlendedPricePremMonthly*E30+U30*BlendedPriceEliteMonthly*E30+V30*BlendedPriceEssAnnual*E30/12+W30*BlendedPricePremAnnual*E30/12+X30*BlendedPriceEliteAnnual*E30/12 | AA30: =Z30*12 | AB30: =S30*BlendedPriceEssMonthly*E30+T30*BlendedPricePremMonthly*E30+U30*BlendedPriceEliteMonthly*E30 | AC30: =P30*BlendedPriceEssAnnual*E30+Q30*BlendedPricePremAnnual*E30+R30*BlendedPriceEliteAnnual*E30 | AD30: =P18*POWER(1-(AnnualChurn*VLOOKUP(B30,ChurnSeasonTable,4,FALSE)),1)*BlendedPriceEssAnnual*E30+P6*POWER(1-(AnnualChurn*VLOOKUP(B30,ChurnSeasonTable,4,FALSE)),2)*BlendedPriceEssAnnual*E30+Q18*POWER(1-(AnnualChurn*VLOOKUP(B30,ChurnSeasonTable,4,FALSE)),1)*BlendedPricePremAnnual*E30+Q6*POWER(1-(AnnualChurn*VLOOKUP(B30,ChurnSeasonTable,4,FALSE)),2)*BlendedPricePremAnnual*E30+R18*POWER(1-(AnnualChurn*VLOOKUP(B30,ChurnSeasonTable,4,FALSE)),1)*BlendedPriceEliteAnnual*E30+R6*POWER(1-(AnnualChurn*VLOOKUP(B30,ChurnSeasonTable,4,FALSE)),2)*BlendedPriceEliteAnnual*E30 | AE30: =AB30+AC30+AD30 | AF30: =SUM(AE19:AE30) | AG30: =OR(AG29,IF(VATAgentMode,SUM($AE19:$AE30)-SUM($AL19:$AL30)>=VATThreshold,SUM($AE19:$AE30)>=VATThreshold)) | AH30: =IF(AG30,IF(VATAgentMode,AE30-((AE30-AL30)-(AE30-AL30)/(1+VATRate)),AE30/(1+VATRate)),AE30) | AI30: =AE30-AH30 | AJ30: =IF(AG30=0,0,IF(B30=1,SUMPRODUCT(--(($C$5:$C30=$C30-1)*($B$5:$B30>=10)*($B$5:$B30<=12)),$AI$5:$AI30),IF(B30=4,SUMPRODUCT(--(($C$5:$C30=$C30)*($B$5:$B30>=1)*($B$5:$B30<=3)),$AI$5:$AI30),IF(B30=7,SUMPRODUCT(--(($C$5:$C30=$C30)*($B$5:$B30>=4)*($B$5:$B30<=6)),$AI$5:$AI30),IF(B30=10,SUMPRODUCT(--(($C$5:$C30=$C30)*($B$5:$B30>=7)*($B$5:$B30<=9)),$AI$5:$AI30),0))))) | AK30: =AK29+AI30-AJ30 | AL30: =IF(ProviderDelay>=1,S29*BlendedProvPayEss+T29*BlendedProvPayPrem+U29*BlendedProvPayElite+V29*BlendedProvPayEss+W29*BlendedProvPayPrem+X29*BlendedProvPayElite,S30*BlendedProvPayEss+T30*BlendedProvPayPrem+U30*BlendedProvPayElite+V30*BlendedProvPayEss+W30*BlendedProvPayPrem+X30*BlendedProvPayElite) | AM30: =AE30*PaymentFee | AN30: =Y30*OpsAI | AO30: =MonthlyFixed | AP30: =I30*ReferralReward | AQ30: =G30 | AR30: =AH30-AL30-AM30-AN30-AO30-AP30-AQ30 | AS30: =AS29+AE30-(AL30+AM30+AN30+AO30+AP30+AQ30+AJ30) | AT30: =IF(Y30>0,Z30/Y30,0) | AU30: =IF(Y29>0,MAX(0,(Y29+J30-Y30)/Y29),0)
A31: 27 | B31: =MOD(A31-1+LaunchMonth-1,12)+1 | C31: =INT((A31-1+LaunchMonth-1)/12)+1 | D31: =VLOOKUP(B31,SeasonTable,2,FALSE) | E31: =(1+InflationRate)^INT((A31-1)/12) | F31: =MonthlyChurn*VLOOKUP(B31,ChurnSeasonTable,4,FALSE) | G31: =MIN(MAX(MktMin19plus,AE30*MktPct19plus),MAX(0,AS30-CashBuffer)) | H31: =IF(G31>0,MAX(1,ROUND(G31/CAC*D31,0)),0) | I31: =IF(H31>0,ROUND(H31*ReferralMix/(1-ReferralMix),0),0) | J31: =H31+I31 | K31: =ROUND(J31*(1-AnnualMix),0) | L31: =J31-K31 | M31: =ROUND(K31*EssentialMix,0) | N31: =ROUND(K31*PremiumMix,0) | O31: =K31-M31-N31 | P31: =ROUND(L31*EssentialMix,0) | Q31: =ROUND(L31*PremiumMix,0) | R31: =L31-P31-Q31 | S31: =M31+M30+M29+MAX(0,S30-M30-M29)*(1-F31) | T31: =N31+N30+N29+MAX(0,T30-N30-N29)*(1-F31) | U31: =O31+O30+O29+MAX(0,U30-O30-O29)*(1-F31) | V31: =V30+P31-P19*(AnnualChurn*VLOOKUP(B31,ChurnSeasonTable,4,FALSE))*POWER(1-(AnnualChurn*VLOOKUP(B31,ChurnSeasonTable,4,FALSE)),0)+P7*(AnnualChurn*VLOOKUP(B31,ChurnSeasonTable,4,FALSE))*POWER(1-(AnnualChurn*VLOOKUP(B31,ChurnSeasonTable,4,FALSE)),1) | W31: =W30+Q31-Q19*(AnnualChurn*VLOOKUP(B31,ChurnSeasonTable,4,FALSE))*POWER(1-(AnnualChurn*VLOOKUP(B31,ChurnSeasonTable,4,FALSE)),0)+Q7*(AnnualChurn*VLOOKUP(B31,ChurnSeasonTable,4,FALSE))*POWER(1-(AnnualChurn*VLOOKUP(B31,ChurnSeasonTable,4,FALSE)),1) | X31: =X30+R31-R19*(AnnualChurn*VLOOKUP(B31,ChurnSeasonTable,4,FALSE))*POWER(1-(AnnualChurn*VLOOKUP(B31,ChurnSeasonTable,4,FALSE)),0)+R7*(AnnualChurn*VLOOKUP(B31,ChurnSeasonTable,4,FALSE))*POWER(1-(AnnualChurn*VLOOKUP(B31,ChurnSeasonTable,4,FALSE)),1) | Y31: =S31+T31+U31+V31+W31+X31 | Z31: =S31*BlendedPriceEssMonthly*E31+T31*BlendedPricePremMonthly*E31+U31*BlendedPriceEliteMonthly*E31+V31*BlendedPriceEssAnnual*E31/12+W31*BlendedPricePremAnnual*E31/12+X31*BlendedPriceEliteAnnual*E31/12 | AA31: =Z31*12 | AB31: =S31*BlendedPriceEssMonthly*E31+T31*BlendedPricePremMonthly*E31+U31*BlendedPriceEliteMonthly*E31 | AC31: =P31*BlendedPriceEssAnnual*E31+Q31*BlendedPricePremAnnual*E31+R31*BlendedPriceEliteAnnual*E31 | AD31: =P19*POWER(1-(AnnualChurn*VLOOKUP(B31,ChurnSeasonTable,4,FALSE)),1)*BlendedPriceEssAnnual*E31+P7*POWER(1-(AnnualChurn*VLOOKUP(B31,ChurnSeasonTable,4,FALSE)),2)*BlendedPriceEssAnnual*E31+Q19*POWER(1-(AnnualChurn*VLOOKUP(B31,ChurnSeasonTable,4,FALSE)),1)*BlendedPricePremAnnual*E31+Q7*POWER(1-(AnnualChurn*VLOOKUP(B31,ChurnSeasonTable,4,FALSE)),2)*BlendedPricePremAnnual*E31+R19*POWER(1-(AnnualChurn*VLOOKUP(B31,ChurnSeasonTable,4,FALSE)),1)*BlendedPriceEliteAnnual*E31+R7*POWER(1-(AnnualChurn*VLOOKUP(B31,ChurnSeasonTable,4,FALSE)),2)*BlendedPriceEliteAnnual*E31 | AE31: =AB31+AC31+AD31 | AF31: =SUM(AE20:AE31) | AG31: =OR(AG30,IF(VATAgentMode,SUM($AE20:$AE31)-SUM($AL20:$AL31)>=VATThreshold,SUM($AE20:$AE31)>=VATThreshold)) | AH31: =IF(AG31,IF(VATAgentMode,AE31-((AE31-AL31)-(AE31-AL31)/(1+VATRate)),AE31/(1+VATRate)),AE31) | AI31: =AE31-AH31 | AJ31: =IF(AG31=0,0,IF(B31=1,SUMPRODUCT(--(($C$5:$C31=$C31-1)*($B$5:$B31>=10)*($B$5:$B31<=12)),$AI$5:$AI31),IF(B31=4,SUMPRODUCT(--(($C$5:$C31=$C31)*($B$5:$B31>=1)*($B$5:$B31<=3)),$AI$5:$AI31),IF(B31=7,SUMPRODUCT(--(($C$5:$C31=$C31)*($B$5:$B31>=4)*($B$5:$B31<=6)),$AI$5:$AI31),IF(B31=10,SUMPRODUCT(--(($C$5:$C31=$C31)*($B$5:$B31>=7)*($B$5:$B31<=9)),$AI$5:$AI31),0))))) | AK31: =AK30+AI31-AJ31 | AL31: =IF(ProviderDelay>=1,S30*BlendedProvPayEss+T30*BlendedProvPayPrem+U30*BlendedProvPayElite+V30*BlendedProvPayEss+W30*BlendedProvPayPrem+X30*BlendedProvPayElite,S31*BlendedProvPayEss+T31*BlendedProvPayPrem+U31*BlendedProvPayElite+V31*BlendedProvPayEss+W31*BlendedProvPayPrem+X31*BlendedProvPayElite) | AM31: =AE31*PaymentFee | AN31: =Y31*OpsAI | AO31: =MonthlyFixed | AP31: =I31*ReferralReward | AQ31: =G31 | AR31: =AH31-AL31-AM31-AN31-AO31-AP31-AQ31 | AS31: =AS30+AE31-(AL31+AM31+AN31+AO31+AP31+AQ31+AJ31) | AT31: =IF(Y31>0,Z31/Y31,0) | AU31: =IF(Y30>0,MAX(0,(Y30+J31-Y31)/Y30),0)
A32: 28 | B32: =MOD(A32-1+LaunchMonth-1,12)+1 | C32: =INT((A32-1+LaunchMonth-1)/12)+1 | D32: =VLOOKUP(B32,SeasonTable,2,FALSE) | E32: =(1+InflationRate)^INT((A32-1)/12) | F32: =MonthlyChurn*VLOOKUP(B32,ChurnSeasonTable,4,FALSE) | G32: =MIN(MAX(MktMin19plus,AE31*MktPct19plus),MAX(0,AS31-CashBuffer)) | H32: =IF(G32>0,MAX(1,ROUND(G32/CAC*D32,0)),0) | I32: =IF(H32>0,ROUND(H32*ReferralMix/(1-ReferralMix),0),0) | J32: =H32+I32 | K32: =ROUND(J32*(1-AnnualMix),0) | L32: =J32-K32 | M32: =ROUND(K32*EssentialMix,0) | N32: =ROUND(K32*PremiumMix,0) | O32: =K32-M32-N32 | P32: =ROUND(L32*EssentialMix,0) | Q32: =ROUND(L32*PremiumMix,0) | R32: =L32-P32-Q32 | S32: =M32+M31+M30+MAX(0,S31-M31-M30)*(1-F32) | T32: =N32+N31+N30+MAX(0,T31-N31-N30)*(1-F32) | U32: =O32+O31+O30+MAX(0,U31-O31-O30)*(1-F32) | V32: =V31+P32-P20*(AnnualChurn*VLOOKUP(B32,ChurnSeasonTable,4,FALSE))*POWER(1-(AnnualChurn*VLOOKUP(B32,ChurnSeasonTable,4,FALSE)),0)+P8*(AnnualChurn*VLOOKUP(B32,ChurnSeasonTable,4,FALSE))*POWER(1-(AnnualChurn*VLOOKUP(B32,ChurnSeasonTable,4,FALSE)),1) | W32: =W31+Q32-Q20*(AnnualChurn*VLOOKUP(B32,ChurnSeasonTable,4,FALSE))*POWER(1-(AnnualChurn*VLOOKUP(B32,ChurnSeasonTable,4,FALSE)),0)+Q8*(AnnualChurn*VLOOKUP(B32,ChurnSeasonTable,4,FALSE))*POWER(1-(AnnualChurn*VLOOKUP(B32,ChurnSeasonTable,4,FALSE)),1) | X32: =X31+R32-R20*(AnnualChurn*VLOOKUP(B32,ChurnSeasonTable,4,FALSE))*POWER(1-(AnnualChurn*VLOOKUP(B32,ChurnSeasonTable,4,FALSE)),0)+R8*(AnnualChurn*VLOOKUP(B32,ChurnSeasonTable,4,FALSE))*POWER(1-(AnnualChurn*VLOOKUP(B32,ChurnSeasonTable,4,FALSE)),1) | Y32: =S32+T32+U32+V32+W32+X32 | Z32: =S32*BlendedPriceEssMonthly*E32+T32*BlendedPricePremMonthly*E32+U32*BlendedPriceEliteMonthly*E32+V32*BlendedPriceEssAnnual*E32/12+W32*BlendedPricePremAnnual*E32/12+X32*BlendedPriceEliteAnnual*E32/12 | AA32: =Z32*12 | AB32: =S32*BlendedPriceEssMonthly*E32+T32*BlendedPricePremMonthly*E32+U32*BlendedPriceEliteMonthly*E32 | AC32: =P32*BlendedPriceEssAnnual*E32+Q32*BlendedPricePremAnnual*E32+R32*BlendedPriceEliteAnnual*E32 | AD32: =P20*POWER(1-(AnnualChurn*VLOOKUP(B32,ChurnSeasonTable,4,FALSE)),1)*BlendedPriceEssAnnual*E32+P8*POWER(1-(AnnualChurn*VLOOKUP(B32,ChurnSeasonTable,4,FALSE)),2)*BlendedPriceEssAnnual*E32+Q20*POWER(1-(AnnualChurn*VLOOKUP(B32,ChurnSeasonTable,4,FALSE)),1)*BlendedPricePremAnnual*E32+Q8*POWER(1-(AnnualChurn*VLOOKUP(B32,ChurnSeasonTable,4,FALSE)),2)*BlendedPricePremAnnual*E32+R20*POWER(1-(AnnualChurn*VLOOKUP(B32,ChurnSeasonTable,4,FALSE)),1)*BlendedPriceEliteAnnual*E32+R8*POWER(1-(AnnualChurn*VLOOKUP(B32,ChurnSeasonTable,4,FALSE)),2)*BlendedPriceEliteAnnual*E32 | AE32: =AB32+AC32+AD32 | AF32: =SUM(AE21:AE32) | AG32: =OR(AG31,IF(VATAgentMode,SUM($AE21:$AE32)-SUM($AL21:$AL32)>=VATThreshold,SUM($AE21:$AE32)>=VATThreshold)) | AH32: =IF(AG32,IF(VATAgentMode,AE32-((AE32-AL32)-(AE32-AL32)/(1+VATRate)),AE32/(1+VATRate)),AE32) | AI32: =AE32-AH32 | AJ32: =IF(AG32=0,0,IF(B32=1,SUMPRODUCT(--(($C$5:$C32=$C32-1)*($B$5:$B32>=10)*($B$5:$B32<=12)),$AI$5:$AI32),IF(B32=4,SUMPRODUCT(--(($C$5:$C32=$C32)*($B$5:$B32>=1)*($B$5:$B32<=3)),$AI$5:$AI32),IF(B32=7,SUMPRODUCT(--(($C$5:$C32=$C32)*($B$5:$B32>=4)*($B$5:$B32<=6)),$AI$5:$AI32),IF(B32=10,SUMPRODUCT(--(($C$5:$C32=$C32)*($B$5:$B32>=7)*($B$5:$B32<=9)),$AI$5:$AI32),0))))) | AK32: =AK31+AI32-AJ32 | AL32: =IF(ProviderDelay>=1,S31*BlendedProvPayEss+T31*BlendedProvPayPrem+U31*BlendedProvPayElite+V31*BlendedProvPayEss+W31*BlendedProvPayPrem+X31*BlendedProvPayElite,S32*BlendedProvPayEss+T32*BlendedProvPayPrem+U32*BlendedProvPayElite+V32*BlendedProvPayEss+W32*BlendedProvPayPrem+X32*BlendedProvPayElite) | AM32: =AE32*PaymentFee | AN32: =Y32*OpsAI | AO32: =MonthlyFixed | AP32: =I32*ReferralReward | AQ32: =G32 | AR32: =AH32-AL32-AM32-AN32-AO32-AP32-AQ32 | AS32: =AS31+AE32-(AL32+AM32+AN32+AO32+AP32+AQ32+AJ32) | AT32: =IF(Y32>0,Z32/Y32,0) | AU32: =IF(Y31>0,MAX(0,(Y31+J32-Y32)/Y31),0)
A33: 29 | B33: =MOD(A33-1+LaunchMonth-1,12)+1 | C33: =INT((A33-1+LaunchMonth-1)/12)+1 | D33: =VLOOKUP(B33,SeasonTable,2,FALSE) | E33: =(1+InflationRate)^INT((A33-1)/12) | F33: =MonthlyChurn*VLOOKUP(B33,ChurnSeasonTable,4,FALSE) | G33: =MIN(MAX(MktMin19plus,AE32*MktPct19plus),MAX(0,AS32-CashBuffer)) | H33: =IF(G33>0,MAX(1,ROUND(G33/CAC*D33,0)),0) | I33: =IF(H33>0,ROUND(H33*ReferralMix/(1-ReferralMix),0),0) | J33: =H33+I33 | K33: =ROUND(J33*(1-AnnualMix),0) | L33: =J33-K33 | M33: =ROUND(K33*EssentialMix,0) | N33: =ROUND(K33*PremiumMix,0) | O33: =K33-M33-N33 | P33: =ROUND(L33*EssentialMix,0) | Q33: =ROUND(L33*PremiumMix,0) | R33: =L33-P33-Q33 | S33: =M33+M32+M31+MAX(0,S32-M32-M31)*(1-F33) | T33: =N33+N32+N31+MAX(0,T32-N32-N31)*(1-F33) | U33: =O33+O32+O31+MAX(0,U32-O32-O31)*(1-F33) | V33: =V32+P33-P21*(AnnualChurn*VLOOKUP(B33,ChurnSeasonTable,4,FALSE))*POWER(1-(AnnualChurn*VLOOKUP(B33,ChurnSeasonTable,4,FALSE)),0)+P9*(AnnualChurn*VLOOKUP(B33,ChurnSeasonTable,4,FALSE))*POWER(1-(AnnualChurn*VLOOKUP(B33,ChurnSeasonTable,4,FALSE)),1) | W33: =W32+Q33-Q21*(AnnualChurn*VLOOKUP(B33,ChurnSeasonTable,4,FALSE))*POWER(1-(AnnualChurn*VLOOKUP(B33,ChurnSeasonTable,4,FALSE)),0)+Q9*(AnnualChurn*VLOOKUP(B33,ChurnSeasonTable,4,FALSE))*POWER(1-(AnnualChurn*VLOOKUP(B33,ChurnSeasonTable,4,FALSE)),1) | X33: =X32+R33-R21*(AnnualChurn*VLOOKUP(B33,ChurnSeasonTable,4,FALSE))*POWER(1-(AnnualChurn*VLOOKUP(B33,ChurnSeasonTable,4,FALSE)),0)+R9*(AnnualChurn*VLOOKUP(B33,ChurnSeasonTable,4,FALSE))*POWER(1-(AnnualChurn*VLOOKUP(B33,ChurnSeasonTable,4,FALSE)),1) | Y33: =S33+T33+U33+V33+W33+X33 | Z33: =S33*BlendedPriceEssMonthly*E33+T33*BlendedPricePremMonthly*E33+U33*BlendedPriceEliteMonthly*E33+V33*BlendedPriceEssAnnual*E33/12+W33*BlendedPricePremAnnual*E33/12+X33*BlendedPriceEliteAnnual*E33/12 | AA33: =Z33*12 | AB33: =S33*BlendedPriceEssMonthly*E33+T33*BlendedPricePremMonthly*E33+U33*BlendedPriceEliteMonthly*E33 | AC33: =P33*BlendedPriceEssAnnual*E33+Q33*BlendedPricePremAnnual*E33+R33*BlendedPriceEliteAnnual*E33 | AD33: =P21*POWER(1-(AnnualChurn*VLOOKUP(B33,ChurnSeasonTable,4,FALSE)),1)*BlendedPriceEssAnnual*E33+P9*POWER(1-(AnnualChurn*VLOOKUP(B33,ChurnSeasonTable,4,FALSE)),2)*BlendedPriceEssAnnual*E33+Q21*POWER(1-(AnnualChurn*VLOOKUP(B33,ChurnSeasonTable,4,FALSE)),1)*BlendedPricePremAnnual*E33+Q9*POWER(1-(AnnualChurn*VLOOKUP(B33,ChurnSeasonTable,4,FALSE)),2)*BlendedPricePremAnnual*E33+R21*POWER(1-(AnnualChurn*VLOOKUP(B33,ChurnSeasonTable,4,FALSE)),1)*BlendedPriceEliteAnnual*E33+R9*POWER(1-(AnnualChurn*VLOOKUP(B33,ChurnSeasonTable,4,FALSE)),2)*BlendedPriceEliteAnnual*E33 | AE33: =AB33+AC33+AD33 | AF33: =SUM(AE22:AE33) | AG33: =OR(AG32,IF(VATAgentMode,SUM($AE22:$AE33)-SUM($AL22:$AL33)>=VATThreshold,SUM($AE22:$AE33)>=VATThreshold)) | AH33: =IF(AG33,IF(VATAgentMode,AE33-((AE33-AL33)-(AE33-AL33)/(1+VATRate)),AE33/(1+VATRate)),AE33) | AI33: =AE33-AH33 | AJ33: =IF(AG33=0,0,IF(B33=1,SUMPRODUCT(--(($C$5:$C33=$C33-1)*($B$5:$B33>=10)*($B$5:$B33<=12)),$AI$5:$AI33),IF(B33=4,SUMPRODUCT(--(($C$5:$C33=$C33)*($B$5:$B33>=1)*($B$5:$B33<=3)),$AI$5:$AI33),IF(B33=7,SUMPRODUCT(--(($C$5:$C33=$C33)*($B$5:$B33>=4)*($B$5:$B33<=6)),$AI$5:$AI33),IF(B33=10,SUMPRODUCT(--(($C$5:$C33=$C33)*($B$5:$B33>=7)*($B$5:$B33<=9)),$AI$5:$AI33),0))))) | AK33: =AK32+AI33-AJ33 | AL33: =IF(ProviderDelay>=1,S32*BlendedProvPayEss+T32*BlendedProvPayPrem+U32*BlendedProvPayElite+V32*BlendedProvPayEss+W32*BlendedProvPayPrem+X32*BlendedProvPayElite,S33*BlendedProvPayEss+T33*BlendedProvPayPrem+U33*BlendedProvPayElite+V33*BlendedProvPayEss+W33*BlendedProvPayPrem+X33*BlendedProvPayElite) | AM33: =AE33*PaymentFee | AN33: =Y33*OpsAI | AO33: =MonthlyFixed | AP33: =I33*ReferralReward | AQ33: =G33 | AR33: =AH33-AL33-AM33-AN33-AO33-AP33-AQ33 | AS33: =AS32+AE33-(AL33+AM33+AN33+AO33+AP33+AQ33+AJ33) | AT33: =IF(Y33>0,Z33/Y33,0) | AU33: =IF(Y32>0,MAX(0,(Y32+J33-Y33)/Y32),0)
A34: 30 | B34: =MOD(A34-1+LaunchMonth-1,12)+1 | C34: =INT((A34-1+LaunchMonth-1)/12)+1 | D34: =VLOOKUP(B34,SeasonTable,2,FALSE) | E34: =(1+InflationRate)^INT((A34-1)/12) | F34: =MonthlyChurn*VLOOKUP(B34,ChurnSeasonTable,4,FALSE) | G34: =MIN(MAX(MktMin19plus,AE33*MktPct19plus),MAX(0,AS33-CashBuffer)) | H34: =IF(G34>0,MAX(1,ROUND(G34/CAC*D34,0)),0) | I34: =IF(H34>0,ROUND(H34*ReferralMix/(1-ReferralMix),0),0) | J34: =H34+I34 | K34: =ROUND(J34*(1-AnnualMix),0) | L34: =J34-K34 | M34: =ROUND(K34*EssentialMix,0) | N34: =ROUND(K34*PremiumMix,0) | O34: =K34-M34-N34 | P34: =ROUND(L34*EssentialMix,0) | Q34: =ROUND(L34*PremiumMix,0) | R34: =L34-P34-Q34 | S34: =M34+M33+M32+MAX(0,S33-M33-M32)*(1-F34) | T34: =N34+N33+N32+MAX(0,T33-N33-N32)*(1-F34) | U34: =O34+O33+O32+MAX(0,U33-O33-O32)*(1-F34) | V34: =V33+P34-P22*(AnnualChurn*VLOOKUP(B34,ChurnSeasonTable,4,FALSE))*POWER(1-(AnnualChurn*VLOOKUP(B34,ChurnSeasonTable,4,FALSE)),0)+P10*(AnnualChurn*VLOOKUP(B34,ChurnSeasonTable,4,FALSE))*POWER(1-(AnnualChurn*VLOOKUP(B34,ChurnSeasonTable,4,FALSE)),1) | W34: =W33+Q34-Q22*(AnnualChurn*VLOOKUP(B34,ChurnSeasonTable,4,FALSE))*POWER(1-(AnnualChurn*VLOOKUP(B34,ChurnSeasonTable,4,FALSE)),0)+Q10*(AnnualChurn*VLOOKUP(B34,ChurnSeasonTable,4,FALSE))*POWER(1-(AnnualChurn*VLOOKUP(B34,ChurnSeasonTable,4,FALSE)),1) | X34: =X33+R34-R22*(AnnualChurn*VLOOKUP(B34,ChurnSeasonTable,4,FALSE))*POWER(1-(AnnualChurn*VLOOKUP(B34,ChurnSeasonTable,4,FALSE)),0)+R10*(AnnualChurn*VLOOKUP(B34,ChurnSeasonTable,4,FALSE))*POWER(1-(AnnualChurn*VLOOKUP(B34,ChurnSeasonTable,4,FALSE)),1) | Y34: =S34+T34+U34+V34+W34+X34 | Z34: =S34*BlendedPriceEssMonthly*E34+T34*BlendedPricePremMonthly*E34+U34*BlendedPriceEliteMonthly*E34+V34*BlendedPriceEssAnnual*E34/12+W34*BlendedPricePremAnnual*E34/12+X34*BlendedPriceEliteAnnual*E34/12 | AA34: =Z34*12 | AB34: =S34*BlendedPriceEssMonthly*E34+T34*BlendedPricePremMonthly*E34+U34*BlendedPriceEliteMonthly*E34 | AC34: =P34*BlendedPriceEssAnnual*E34+Q34*BlendedPricePremAnnual*E34+R34*BlendedPriceEliteAnnual*E34 | AD34: =P22*POWER(1-(AnnualChurn*VLOOKUP(B34,ChurnSeasonTable,4,FALSE)),1)*BlendedPriceEssAnnual*E34+P10*POWER(1-(AnnualChurn*VLOOKUP(B34,ChurnSeasonTable,4,FALSE)),2)*BlendedPriceEssAnnual*E34+Q22*POWER(1-(AnnualChurn*VLOOKUP(B34,ChurnSeasonTable,4,FALSE)),1)*BlendedPricePremAnnual*E34+Q10*POWER(1-(AnnualChurn*VLOOKUP(B34,ChurnSeasonTable,4,FALSE)),2)*BlendedPricePremAnnual*E34+R22*POWER(1-(AnnualChurn*VLOOKUP(B34,ChurnSeasonTable,4,FALSE)),1)*BlendedPriceEliteAnnual*E34+R10*POWER(1-(AnnualChurn*VLOOKUP(B34,ChurnSeasonTable,4,FALSE)),2)*BlendedPriceEliteAnnual*E34 | AE34: =AB34+AC34+AD34 | AF34: =SUM(AE23:AE34) | AG34: =OR(AG33,IF(VATAgentMode,SUM($AE23:$AE34)-SUM($AL23:$AL34)>=VATThreshold,SUM($AE23:$AE34)>=VATThreshold)) | AH34: =IF(AG34,IF(VATAgentMode,AE34-((AE34-AL34)-(AE34-AL34)/(1+VATRate)),AE34/(1+VATRate)),AE34) | AI34: =AE34-AH34 | AJ34: =IF(AG34=0,0,IF(B34=1,SUMPRODUCT(--(($C$5:$C34=$C34-1)*($B$5:$B34>=10)*($B$5:$B34<=12)),$AI$5:$AI34),IF(B34=4,SUMPRODUCT(--(($C$5:$C34=$C34)*($B$5:$B34>=1)*($B$5:$B34<=3)),$AI$5:$AI34),IF(B34=7,SUMPRODUCT(--(($C$5:$C34=$C34)*($B$5:$B34>=4)*($B$5:$B34<=6)),$AI$5:$AI34),IF(B34=10,SUMPRODUCT(--(($C$5:$C34=$C34)*($B$5:$B34>=7)*($B$5:$B34<=9)),$AI$5:$AI34),0))))) | AK34: =AK33+AI34-AJ34 | AL34: =IF(ProviderDelay>=1,S33*BlendedProvPayEss+T33*BlendedProvPayPrem+U33*BlendedProvPayElite+V33*BlendedProvPayEss+W33*BlendedProvPayPrem+X33*BlendedProvPayElite,S34*BlendedProvPayEss+T34*BlendedProvPayPrem+U34*BlendedProvPayElite+V34*BlendedProvPayEss+W34*BlendedProvPayPrem+X34*BlendedProvPayElite) | AM34: =AE34*PaymentFee | AN34: =Y34*OpsAI | AO34: =MonthlyFixed | AP34: =I34*ReferralReward | AQ34: =G34 | AR34: =AH34-AL34-AM34-AN34-AO34-AP34-AQ34 | AS34: =AS33+AE34-(AL34+AM34+AN34+AO34+AP34+AQ34+AJ34) | AT34: =IF(Y34>0,Z34/Y34,0) | AU34: =IF(Y33>0,MAX(0,(Y33+J34-Y34)/Y33),0)
A35: 31 | B35: =MOD(A35-1+LaunchMonth-1,12)+1 | C35: =INT((A35-1+LaunchMonth-1)/12)+1 | D35: =VLOOKUP(B35,SeasonTable,2,FALSE) | E35: =(1+InflationRate)^INT((A35-1)/12) | F35: =MonthlyChurn*VLOOKUP(B35,ChurnSeasonTable,4,FALSE) | G35: =MIN(MAX(MktMin19plus,AE34*MktPct19plus),MAX(0,AS34-CashBuffer)) | H35: =IF(G35>0,MAX(1,ROUND(G35/CAC*D35,0)),0) | I35: =IF(H35>0,ROUND(H35*ReferralMix/(1-ReferralMix),0),0) | J35: =H35+I35 | K35: =ROUND(J35*(1-AnnualMix),0) | L35: =J35-K35 | M35: =ROUND(K35*EssentialMix,0) | N35: =ROUND(K35*PremiumMix,0) | O35: =K35-M35-N35 | P35: =ROUND(L35*EssentialMix,0) | Q35: =ROUND(L35*PremiumMix,0) | R35: =L35-P35-Q35 | S35: =M35+M34+M33+MAX(0,S34-M34-M33)*(1-F35) | T35: =N35+N34+N33+MAX(0,T34-N34-N33)*(1-F35) | U35: =O35+O34+O33+MAX(0,U34-O34-O33)*(1-F35) | V35: =V34+P35-P23*(AnnualChurn*VLOOKUP(B35,ChurnSeasonTable,4,FALSE))*POWER(1-(AnnualChurn*VLOOKUP(B35,ChurnSeasonTable,4,FALSE)),0)+P11*(AnnualChurn*VLOOKUP(B35,ChurnSeasonTable,4,FALSE))*POWER(1-(AnnualChurn*VLOOKUP(B35,ChurnSeasonTable,4,FALSE)),1) | W35: =W34+Q35-Q23*(AnnualChurn*VLOOKUP(B35,ChurnSeasonTable,4,FALSE))*POWER(1-(AnnualChurn*VLOOKUP(B35,ChurnSeasonTable,4,FALSE)),0)+Q11*(AnnualChurn*VLOOKUP(B35,ChurnSeasonTable,4,FALSE))*POWER(1-(AnnualChurn*VLOOKUP(B35,ChurnSeasonTable,4,FALSE)),1) | X35: =X34+R35-R23*(AnnualChurn*VLOOKUP(B35,ChurnSeasonTable,4,FALSE))*POWER(1-(AnnualChurn*VLOOKUP(B35,ChurnSeasonTable,4,FALSE)),0)+R11*(AnnualChurn*VLOOKUP(B35,ChurnSeasonTable,4,FALSE))*POWER(1-(AnnualChurn*VLOOKUP(B35,ChurnSeasonTable,4,FALSE)),1) | Y35: =S35+T35+U35+V35+W35+X35 | Z35: =S35*BlendedPriceEssMonthly*E35+T35*BlendedPricePremMonthly*E35+U35*BlendedPriceEliteMonthly*E35+V35*BlendedPriceEssAnnual*E35/12+W35*BlendedPricePremAnnual*E35/12+X35*BlendedPriceEliteAnnual*E35/12 | AA35: =Z35*12 | AB35: =S35*BlendedPriceEssMonthly*E35+T35*BlendedPricePremMonthly*E35+U35*BlendedPriceEliteMonthly*E35 | AC35: =P35*BlendedPriceEssAnnual*E35+Q35*BlendedPricePremAnnual*E35+R35*BlendedPriceEliteAnnual*E35 | AD35: =P23*POWER(1-(AnnualChurn*VLOOKUP(B35,ChurnSeasonTable,4,FALSE)),1)*BlendedPriceEssAnnual*E35+P11*POWER(1-(AnnualChurn*VLOOKUP(B35,ChurnSeasonTable,4,FALSE)),2)*BlendedPriceEssAnnual*E35+Q23*POWER(1-(AnnualChurn*VLOOKUP(B35,ChurnSeasonTable,4,FALSE)),1)*BlendedPricePremAnnual*E35+Q11*POWER(1-(AnnualChurn*VLOOKUP(B35,ChurnSeasonTable,4,FALSE)),2)*BlendedPricePremAnnual*E35+R23*POWER(1-(AnnualChurn*VLOOKUP(B35,ChurnSeasonTable,4,FALSE)),1)*BlendedPriceEliteAnnual*E35+R11*POWER(1-(AnnualChurn*VLOOKUP(B35,ChurnSeasonTable,4,FALSE)),2)*BlendedPriceEliteAnnual*E35 | AE35: =AB35+AC35+AD35 | AF35: =SUM(AE24:AE35) | AG35: =OR(AG34,IF(VATAgentMode,SUM($AE24:$AE35)-SUM($AL24:$AL35)>=VATThreshold,SUM($AE24:$AE35)>=VATThreshold)) | AH35: =IF(AG35,IF(VATAgentMode,AE35-((AE35-AL35)-(AE35-AL35)/(1+VATRate)),AE35/(1+VATRate)),AE35) | AI35: =AE35-AH35 | AJ35: =IF(AG35=0,0,IF(B35=1,SUMPRODUCT(--(($C$5:$C35=$C35-1)*($B$5:$B35>=10)*($B$5:$B35<=12)),$AI$5:$AI35),IF(B35=4,SUMPRODUCT(--(($C$5:$C35=$C35)*($B$5:$B35>=1)*($B$5:$B35<=3)),$AI$5:$AI35),IF(B35=7,SUMPRODUCT(--(($C$5:$C35=$C35)*($B$5:$B35>=4)*($B$5:$B35<=6)),$AI$5:$AI35),IF(B35=10,SUMPRODUCT(--(($C$5:$C35=$C35)*($B$5:$B35>=7)*($B$5:$B35<=9)),$AI$5:$AI35),0))))) | AK35: =AK34+AI35-AJ35 | AL35: =IF(ProviderDelay>=1,S34*BlendedProvPayEss+T34*BlendedProvPayPrem+U34*BlendedProvPayElite+V34*BlendedProvPayEss+W34*BlendedProvPayPrem+X34*BlendedProvPayElite,S35*BlendedProvPayEss+T35*BlendedProvPayPrem+U35*BlendedProvPayElite+V35*BlendedProvPayEss+W35*BlendedProvPayPrem+X35*BlendedProvPayElite) | AM35: =AE35*PaymentFee | AN35: =Y35*OpsAI | AO35: =MonthlyFixed | AP35: =I35*ReferralReward | AQ35: =G35 | AR35: =AH35-AL35-AM35-AN35-AO35-AP35-AQ35 | AS35: =AS34+AE35-(AL35+AM35+AN35+AO35+AP35+AQ35+AJ35) | AT35: =IF(Y35>0,Z35/Y35,0) | AU35: =IF(Y34>0,MAX(0,(Y34+J35-Y35)/Y34),0)
A36: 32 | B36: =MOD(A36-1+LaunchMonth-1,12)+1 | C36: =INT((A36-1+LaunchMonth-1)/12)+1 | D36: =VLOOKUP(B36,SeasonTable,2,FALSE) | E36: =(1+InflationRate)^INT((A36-1)/12) | F36: =MonthlyChurn*VLOOKUP(B36,ChurnSeasonTable,4,FALSE) | G36: =MIN(MAX(MktMin19plus,AE35*MktPct19plus),MAX(0,AS35-CashBuffer)) | H36: =IF(G36>0,MAX(1,ROUND(G36/CAC*D36,0)),0) | I36: =IF(H36>0,ROUND(H36*ReferralMix/(1-ReferralMix),0),0) | J36: =H36+I36 | K36: =ROUND(J36*(1-AnnualMix),0) | L36: =J36-K36 | M36: =ROUND(K36*EssentialMix,0) | N36: =ROUND(K36*PremiumMix,0) | O36: =K36-M36-N36 | P36: =ROUND(L36*EssentialMix,0) | Q36: =ROUND(L36*PremiumMix,0) | R36: =L36-P36-Q36 | S36: =M36+M35+M34+MAX(0,S35-M35-M34)*(1-F36) | T36: =N36+N35+N34+MAX(0,T35-N35-N34)*(1-F36) | U36: =O36+O35+O34+MAX(0,U35-O35-O34)*(1-F36) | V36: =V35+P36-P24*(AnnualChurn*VLOOKUP(B36,ChurnSeasonTable,4,FALSE))*POWER(1-(AnnualChurn*VLOOKUP(B36,ChurnSeasonTable,4,FALSE)),0)+P12*(AnnualChurn*VLOOKUP(B36,ChurnSeasonTable,4,FALSE))*POWER(1-(AnnualChurn*VLOOKUP(B36,ChurnSeasonTable,4,FALSE)),1) | W36: =W35+Q36-Q24*(AnnualChurn*VLOOKUP(B36,ChurnSeasonTable,4,FALSE))*POWER(1-(AnnualChurn*VLOOKUP(B36,ChurnSeasonTable,4,FALSE)),0)+Q12*(AnnualChurn*VLOOKUP(B36,ChurnSeasonTable,4,FALSE))*POWER(1-(AnnualChurn*VLOOKUP(B36,ChurnSeasonTable,4,FALSE)),1) | X36: =X35+R36-R24*(AnnualChurn*VLOOKUP(B36,ChurnSeasonTable,4,FALSE))*POWER(1-(AnnualChurn*VLOOKUP(B36,ChurnSeasonTable,4,FALSE)),0)+R12*(AnnualChurn*VLOOKUP(B36,ChurnSeasonTable,4,FALSE))*POWER(1-(AnnualChurn*VLOOKUP(B36,ChurnSeasonTable,4,FALSE)),1) | Y36: =S36+T36+U36+V36+W36+X36 | Z36: =S36*BlendedPriceEssMonthly*E36+T36*BlendedPricePremMonthly*E36+U36*BlendedPriceEliteMonthly*E36+V36*BlendedPriceEssAnnual*E36/12+W36*BlendedPricePremAnnual*E36/12+X36*BlendedPriceEliteAnnual*E36/12 | AA36: =Z36*12 | AB36: =S36*BlendedPriceEssMonthly*E36+T36*BlendedPricePremMonthly*E36+U36*BlendedPriceEliteMonthly*E36 | AC36: =P36*BlendedPriceEssAnnual*E36+Q36*BlendedPricePremAnnual*E36+R36*BlendedPriceEliteAnnual*E36 | AD36: =P24*POWER(1-(AnnualChurn*VLOOKUP(B36,ChurnSeasonTable,4,FALSE)),1)*BlendedPriceEssAnnual*E36+P12*POWER(1-(AnnualChurn*VLOOKUP(B36,ChurnSeasonTable,4,FALSE)),2)*BlendedPriceEssAnnual*E36+Q24*POWER(1-(AnnualChurn*VLOOKUP(B36,ChurnSeasonTable,4,FALSE)),1)*BlendedPricePremAnnual*E36+Q12*POWER(1-(AnnualChurn*VLOOKUP(B36,ChurnSeasonTable,4,FALSE)),2)*BlendedPricePremAnnual*E36+R24*POWER(1-(AnnualChurn*VLOOKUP(B36,ChurnSeasonTable,4,FALSE)),1)*BlendedPriceEliteAnnual*E36+R12*POWER(1-(AnnualChurn*VLOOKUP(B36,ChurnSeasonTable,4,FALSE)),2)*BlendedPriceEliteAnnual*E36 | AE36: =AB36+AC36+AD36 | AF36: =SUM(AE25:AE36) | AG36: =OR(AG35,IF(VATAgentMode,SUM($AE25:$AE36)-SUM($AL25:$AL36)>=VATThreshold,SUM($AE25:$AE36)>=VATThreshold)) | AH36: =IF(AG36,IF(VATAgentMode,AE36-((AE36-AL36)-(AE36-AL36)/(1+VATRate)),AE36/(1+VATRate)),AE36) | AI36: =AE36-AH36 | AJ36: =IF(AG36=0,0,IF(B36=1,SUMPRODUCT(--(($C$5:$C36=$C36-1)*($B$5:$B36>=10)*($B$5:$B36<=12)),$AI$5:$AI36),IF(B36=4,SUMPRODUCT(--(($C$5:$C36=$C36)*($B$5:$B36>=1)*($B$5:$B36<=3)),$AI$5:$AI36),IF(B36=7,SUMPRODUCT(--(($C$5:$C36=$C36)*($B$5:$B36>=4)*($B$5:$B36<=6)),$AI$5:$AI36),IF(B36=10,SUMPRODUCT(--(($C$5:$C36=$C36)*($B$5:$B36>=7)*($B$5:$B36<=9)),$AI$5:$AI36),0))))) | AK36: =AK35+AI36-AJ36 | AL36: =IF(ProviderDelay>=1,S35*BlendedProvPayEss+T35*BlendedProvPayPrem+U35*BlendedProvPayElite+V35*BlendedProvPayEss+W35*BlendedProvPayPrem+X35*BlendedProvPayElite,S36*BlendedProvPayEss+T36*BlendedProvPayPrem+U36*BlendedProvPayElite+V36*BlendedProvPayEss+W36*BlendedProvPayPrem+X36*BlendedProvPayElite) | AM36: =AE36*PaymentFee | AN36: =Y36*OpsAI | AO36: =MonthlyFixed | AP36: =I36*ReferralReward | AQ36: =G36 | AR36: =AH36-AL36-AM36-AN36-AO36-AP36-AQ36 | AS36: =AS35+AE36-(AL36+AM36+AN36+AO36+AP36+AQ36+AJ36) | AT36: =IF(Y36>0,Z36/Y36,0) | AU36: =IF(Y35>0,MAX(0,(Y35+J36-Y36)/Y35),0)
A37: 33 | B37: =MOD(A37-1+LaunchMonth-1,12)+1 | C37: =INT((A37-1+LaunchMonth-1)/12)+1 | D37: =VLOOKUP(B37,SeasonTable,2,FALSE) | E37: =(1+InflationRate)^INT((A37-1)/12) | F37: =MonthlyChurn*VLOOKUP(B37,ChurnSeasonTable,4,FALSE) | G37: =MIN(MAX(MktMin19plus,AE36*MktPct19plus),MAX(0,AS36-CashBuffer)) | H37: =IF(G37>0,MAX(1,ROUND(G37/CAC*D37,0)),0) | I37: =IF(H37>0,ROUND(H37*ReferralMix/(1-ReferralMix),0),0) | J37: =H37+I37 | K37: =ROUND(J37*(1-AnnualMix),0) | L37: =J37-K37 | M37: =ROUND(K37*EssentialMix,0) | N37: =ROUND(K37*PremiumMix,0) | O37: =K37-M37-N37 | P37: =ROUND(L37*EssentialMix,0) | Q37: =ROUND(L37*PremiumMix,0) | R37: =L37-P37-Q37 | S37: =M37+M36+M35+MAX(0,S36-M36-M35)*(1-F37) | T37: =N37+N36+N35+MAX(0,T36-N36-N35)*(1-F37) | U37: =O37+O36+O35+MAX(0,U36-O36-O35)*(1-F37) | V37: =V36+P37-P25*(AnnualChurn*VLOOKUP(B37,ChurnSeasonTable,4,FALSE))*POWER(1-(AnnualChurn*VLOOKUP(B37,ChurnSeasonTable,4,FALSE)),0)+P13*(AnnualChurn*VLOOKUP(B37,ChurnSeasonTable,4,FALSE))*POWER(1-(AnnualChurn*VLOOKUP(B37,ChurnSeasonTable,4,FALSE)),1) | W37: =W36+Q37-Q25*(AnnualChurn*VLOOKUP(B37,ChurnSeasonTable,4,FALSE))*POWER(1-(AnnualChurn*VLOOKUP(B37,ChurnSeasonTable,4,FALSE)),0)+Q13*(AnnualChurn*VLOOKUP(B37,ChurnSeasonTable,4,FALSE))*POWER(1-(AnnualChurn*VLOOKUP(B37,ChurnSeasonTable,4,FALSE)),1) | X37: =X36+R37-R25*(AnnualChurn*VLOOKUP(B37,ChurnSeasonTable,4,FALSE))*POWER(1-(AnnualChurn*VLOOKUP(B37,ChurnSeasonTable,4,FALSE)),0)+R13*(AnnualChurn*VLOOKUP(B37,ChurnSeasonTable,4,FALSE))*POWER(1-(AnnualChurn*VLOOKUP(B37,ChurnSeasonTable,4,FALSE)),1) | Y37: =S37+T37+U37+V37+W37+X37 | Z37: =S37*BlendedPriceEssMonthly*E37+T37*BlendedPricePremMonthly*E37+U37*BlendedPriceEliteMonthly*E37+V37*BlendedPriceEssAnnual*E37/12+W37*BlendedPricePremAnnual*E37/12+X37*BlendedPriceEliteAnnual*E37/12 | AA37: =Z37*12 | AB37: =S37*BlendedPriceEssMonthly*E37+T37*BlendedPricePremMonthly*E37+U37*BlendedPriceEliteMonthly*E37 | AC37: =P37*BlendedPriceEssAnnual*E37+Q37*BlendedPricePremAnnual*E37+R37*BlendedPriceEliteAnnual*E37 | AD37: =P25*POWER(1-(AnnualChurn*VLOOKUP(B37,ChurnSeasonTable,4,FALSE)),1)*BlendedPriceEssAnnual*E37+P13*POWER(1-(AnnualChurn*VLOOKUP(B37,ChurnSeasonTable,4,FALSE)),2)*BlendedPriceEssAnnual*E37+Q25*POWER(1-(AnnualChurn*VLOOKUP(B37,ChurnSeasonTable,4,FALSE)),1)*BlendedPricePremAnnual*E37+Q13*POWER(1-(AnnualChurn*VLOOKUP(B37,ChurnSeasonTable,4,FALSE)),2)*BlendedPricePremAnnual*E37+R25*POWER(1-(AnnualChurn*VLOOKUP(B37,ChurnSeasonTable,4,FALSE)),1)*BlendedPriceEliteAnnual*E37+R13*POWER(1-(AnnualChurn*VLOOKUP(B37,ChurnSeasonTable,4,FALSE)),2)*BlendedPriceEliteAnnual*E37 | AE37: =AB37+AC37+AD37 | AF37: =SUM(AE26:AE37) | AG37: =OR(AG36,IF(VATAgentMode,SUM($AE26:$AE37)-SUM($AL26:$AL37)>=VATThreshold,SUM($AE26:$AE37)>=VATThreshold)) | AH37: =IF(AG37,IF(VATAgentMode,AE37-((AE37-AL37)-(AE37-AL37)/(1+VATRate)),AE37/(1+VATRate)),AE37) | AI37: =AE37-AH37 | AJ37: =IF(AG37=0,0,IF(B37=1,SUMPRODUCT(--(($C$5:$C37=$C37-1)*($B$5:$B37>=10)*($B$5:$B37<=12)),$AI$5:$AI37),IF(B37=4,SUMPRODUCT(--(($C$5:$C37=$C37)*($B$5:$B37>=1)*($B$5:$B37<=3)),$AI$5:$AI37),IF(B37=7,SUMPRODUCT(--(($C$5:$C37=$C37)*($B$5:$B37>=4)*($B$5:$B37<=6)),$AI$5:$AI37),IF(B37=10,SUMPRODUCT(--(($C$5:$C37=$C37)*($B$5:$B37>=7)*($B$5:$B37<=9)),$AI$5:$AI37),0))))) | AK37: =AK36+AI37-AJ37 | AL37: =IF(ProviderDelay>=1,S36*BlendedProvPayEss+T36*BlendedProvPayPrem+U36*BlendedProvPayElite+V36*BlendedProvPayEss+W36*BlendedProvPayPrem+X36*BlendedProvPayElite,S37*BlendedProvPayEss+T37*BlendedProvPayPrem+U37*BlendedProvPayElite+V37*BlendedProvPayEss+W37*BlendedProvPayPrem+X37*BlendedProvPayElite) | AM37: =AE37*PaymentFee | AN37: =Y37*OpsAI | AO37: =MonthlyFixed | AP37: =I37*ReferralReward | AQ37: =G37 | AR37: =AH37-AL37-AM37-AN37-AO37-AP37-AQ37 | AS37: =AS36+AE37-(AL37+AM37+AN37+AO37+AP37+AQ37+AJ37) | AT37: =IF(Y37>0,Z37/Y37,0) | AU37: =IF(Y36>0,MAX(0,(Y36+J37-Y37)/Y36),0)
A38: 34 | B38: =MOD(A38-1+LaunchMonth-1,12)+1 | C38: =INT((A38-1+LaunchMonth-1)/12)+1 | D38: =VLOOKUP(B38,SeasonTable,2,FALSE) | E38: =(1+InflationRate)^INT((A38-1)/12) | F38: =MonthlyChurn*VLOOKUP(B38,ChurnSeasonTable,4,FALSE) | G38: =MIN(MAX(MktMin19plus,AE37*MktPct19plus),MAX(0,AS37-CashBuffer)) | H38: =IF(G38>0,MAX(1,ROUND(G38/CAC*D38,0)),0) | I38: =IF(H38>0,ROUND(H38*ReferralMix/(1-ReferralMix),0),0) | J38: =H38+I38 | K38: =ROUND(J38*(1-AnnualMix),0) | L38: =J38-K38 | M38: =ROUND(K38*EssentialMix,0) | N38: =ROUND(K38*PremiumMix,0) | O38: =K38-M38-N38 | P38: =ROUND(L38*EssentialMix,0) | Q38: =ROUND(L38*PremiumMix,0) | R38: =L38-P38-Q38 | S38: =M38+M37+M36+MAX(0,S37-M37-M36)*(1-F38) | T38: =N38+N37+N36+MAX(0,T37-N37-N36)*(1-F38) | U38: =O38+O37+O36+MAX(0,U37-O37-O36)*(1-F38) | V38: =V37+P38-P26*(AnnualChurn*VLOOKUP(B38,ChurnSeasonTable,4,FALSE))*POWER(1-(AnnualChurn*VLOOKUP(B38,ChurnSeasonTable,4,FALSE)),0)+P14*(AnnualChurn*VLOOKUP(B38,ChurnSeasonTable,4,FALSE))*POWER(1-(AnnualChurn*VLOOKUP(B38,ChurnSeasonTable,4,FALSE)),1) | W38: =W37+Q38-Q26*(AnnualChurn*VLOOKUP(B38,ChurnSeasonTable,4,FALSE))*POWER(1-(AnnualChurn*VLOOKUP(B38,ChurnSeasonTable,4,FALSE)),0)+Q14*(AnnualChurn*VLOOKUP(B38,ChurnSeasonTable,4,FALSE))*POWER(1-(AnnualChurn*VLOOKUP(B38,ChurnSeasonTable,4,FALSE)),1) | X38: =X37+R38-R26*(AnnualChurn*VLOOKUP(B38,ChurnSeasonTable,4,FALSE))*POWER(1-(AnnualChurn*VLOOKUP(B38,ChurnSeasonTable,4,FALSE)),0)+R14*(AnnualChurn*VLOOKUP(B38,ChurnSeasonTable,4,FALSE))*POWER(1-(AnnualChurn*VLOOKUP(B38,ChurnSeasonTable,4,FALSE)),1) | Y38: =S38+T38+U38+V38+W38+X38 | Z38: =S38*BlendedPriceEssMonthly*E38+T38*BlendedPricePremMonthly*E38+U38*BlendedPriceEliteMonthly*E38+V38*BlendedPriceEssAnnual*E38/12+W38*BlendedPricePremAnnual*E38/12+X38*BlendedPriceEliteAnnual*E38/12 | AA38: =Z38*12 | AB38: =S38*BlendedPriceEssMonthly*E38+T38*BlendedPricePremMonthly*E38+U38*BlendedPriceEliteMonthly*E38 | AC38: =P38*BlendedPriceEssAnnual*E38+Q38*BlendedPricePremAnnual*E38+R38*BlendedPriceEliteAnnual*E38 | AD38: =P26*POWER(1-(AnnualChurn*VLOOKUP(B38,ChurnSeasonTable,4,FALSE)),1)*BlendedPriceEssAnnual*E38+P14*POWER(1-(AnnualChurn*VLOOKUP(B38,ChurnSeasonTable,4,FALSE)),2)*BlendedPriceEssAnnual*E38+Q26*POWER(1-(AnnualChurn*VLOOKUP(B38,ChurnSeasonTable,4,FALSE)),1)*BlendedPricePremAnnual*E38+Q14*POWER(1-(AnnualChurn*VLOOKUP(B38,ChurnSeasonTable,4,FALSE)),2)*BlendedPricePremAnnual*E38+R26*POWER(1-(AnnualChurn*VLOOKUP(B38,ChurnSeasonTable,4,FALSE)),1)*BlendedPriceEliteAnnual*E38+R14*POWER(1-(AnnualChurn*VLOOKUP(B38,ChurnSeasonTable,4,FALSE)),2)*BlendedPriceEliteAnnual*E38 | AE38: =AB38+AC38+AD38 | AF38: =SUM(AE27:AE38) | AG38: =OR(AG37,IF(VATAgentMode,SUM($AE27:$AE38)-SUM($AL27:$AL38)>=VATThreshold,SUM($AE27:$AE38)>=VATThreshold)) | AH38: =IF(AG38,IF(VATAgentMode,AE38-((AE38-AL38)-(AE38-AL38)/(1+VATRate)),AE38/(1+VATRate)),AE38) | AI38: =AE38-AH38 | AJ38: =IF(AG38=0,0,IF(B38=1,SUMPRODUCT(--(($C$5:$C38=$C38-1)*($B$5:$B38>=10)*($B$5:$B38<=12)),$AI$5:$AI38),IF(B38=4,SUMPRODUCT(--(($C$5:$C38=$C38)*($B$5:$B38>=1)*($B$5:$B38<=3)),$AI$5:$AI38),IF(B38=7,SUMPRODUCT(--(($C$5:$C38=$C38)*($B$5:$B38>=4)*($B$5:$B38<=6)),$AI$5:$AI38),IF(B38=10,SUMPRODUCT(--(($C$5:$C38=$C38)*($B$5:$B38>=7)*($B$5:$B38<=9)),$AI$5:$AI38),0))))) | AK38: =AK37+AI38-AJ38 | AL38: =IF(ProviderDelay>=1,S37*BlendedProvPayEss+T37*BlendedProvPayPrem+U37*BlendedProvPayElite+V37*BlendedProvPayEss+W37*BlendedProvPayPrem+X37*BlendedProvPayElite,S38*BlendedProvPayEss+T38*BlendedProvPayPrem+U38*BlendedProvPayElite+V38*BlendedProvPayEss+W38*BlendedProvPayPrem+X38*BlendedProvPayElite) | AM38: =AE38*PaymentFee | AN38: =Y38*OpsAI | AO38: =MonthlyFixed | AP38: =I38*ReferralReward | AQ38: =G38 | AR38: =AH38-AL38-AM38-AN38-AO38-AP38-AQ38 | AS38: =AS37+AE38-(AL38+AM38+AN38+AO38+AP38+AQ38+AJ38) | AT38: =IF(Y38>0,Z38/Y38,0) | AU38: =IF(Y37>0,MAX(0,(Y37+J38-Y38)/Y37),0)
A39: 35 | B39: =MOD(A39-1+LaunchMonth-1,12)+1 | C39: =INT((A39-1+LaunchMonth-1)/12)+1 | D39: =VLOOKUP(B39,SeasonTable,2,FALSE) | E39: =(1+InflationRate)^INT((A39-1)/12) | F39: =MonthlyChurn*VLOOKUP(B39,ChurnSeasonTable,4,FALSE) | G39: =MIN(MAX(MktMin19plus,AE38*MktPct19plus),MAX(0,AS38-CashBuffer)) | H39: =IF(G39>0,MAX(1,ROUND(G39/CAC*D39,0)),0) | I39: =IF(H39>0,ROUND(H39*ReferralMix/(1-ReferralMix),0),0) | J39: =H39+I39 | K39: =ROUND(J39*(1-AnnualMix),0) | L39: =J39-K39 | M39: =ROUND(K39*EssentialMix,0) | N39: =ROUND(K39*PremiumMix,0) | O39: =K39-M39-N39 | P39: =ROUND(L39*EssentialMix,0) | Q39: =ROUND(L39*PremiumMix,0) | R39: =L39-P39-Q39 | S39: =M39+M38+M37+MAX(0,S38-M38-M37)*(1-F39) | T39: =N39+N38+N37+MAX(0,T38-N38-N37)*(1-F39) | U39: =O39+O38+O37+MAX(0,U38-O38-O37)*(1-F39) | V39: =V38+P39-P27*(AnnualChurn*VLOOKUP(B39,ChurnSeasonTable,4,FALSE))*POWER(1-(AnnualChurn*VLOOKUP(B39,ChurnSeasonTable,4,FALSE)),0)+P15*(AnnualChurn*VLOOKUP(B39,ChurnSeasonTable,4,FALSE))*POWER(1-(AnnualChurn*VLOOKUP(B39,ChurnSeasonTable,4,FALSE)),1) | W39: =W38+Q39-Q27*(AnnualChurn*VLOOKUP(B39,ChurnSeasonTable,4,FALSE))*POWER(1-(AnnualChurn*VLOOKUP(B39,ChurnSeasonTable,4,FALSE)),0)+Q15*(AnnualChurn*VLOOKUP(B39,ChurnSeasonTable,4,FALSE))*POWER(1-(AnnualChurn*VLOOKUP(B39,ChurnSeasonTable,4,FALSE)),1) | X39: =X38+R39-R27*(AnnualChurn*VLOOKUP(B39,ChurnSeasonTable,4,FALSE))*POWER(1-(AnnualChurn*VLOOKUP(B39,ChurnSeasonTable,4,FALSE)),0)+R15*(AnnualChurn*VLOOKUP(B39,ChurnSeasonTable,4,FALSE))*POWER(1-(AnnualChurn*VLOOKUP(B39,ChurnSeasonTable,4,FALSE)),1) | Y39: =S39+T39+U39+V39+W39+X39 | Z39: =S39*BlendedPriceEssMonthly*E39+T39*BlendedPricePremMonthly*E39+U39*BlendedPriceEliteMonthly*E39+V39*BlendedPriceEssAnnual*E39/12+W39*BlendedPricePremAnnual*E39/12+X39*BlendedPriceEliteAnnual*E39/12 | AA39: =Z39*12 | AB39: =S39*BlendedPriceEssMonthly*E39+T39*BlendedPricePremMonthly*E39+U39*BlendedPriceEliteMonthly*E39 | AC39: =P39*BlendedPriceEssAnnual*E39+Q39*BlendedPricePremAnnual*E39+R39*BlendedPriceEliteAnnual*E39 | AD39: =P27*POWER(1-(AnnualChurn*VLOOKUP(B39,ChurnSeasonTable,4,FALSE)),1)*BlendedPriceEssAnnual*E39+P15*POWER(1-(AnnualChurn*VLOOKUP(B39,ChurnSeasonTable,4,FALSE)),2)*BlendedPriceEssAnnual*E39+Q27*POWER(1-(AnnualChurn*VLOOKUP(B39,ChurnSeasonTable,4,FALSE)),1)*BlendedPricePremAnnual*E39+Q15*POWER(1-(AnnualChurn*VLOOKUP(B39,ChurnSeasonTable,4,FALSE)),2)*BlendedPricePremAnnual*E39+R27*POWER(1-(AnnualChurn*VLOOKUP(B39,ChurnSeasonTable,4,FALSE)),1)*BlendedPriceEliteAnnual*E39+R15*POWER(1-(AnnualChurn*VLOOKUP(B39,ChurnSeasonTable,4,FALSE)),2)*BlendedPriceEliteAnnual*E39 | AE39: =AB39+AC39+AD39 | AF39: =SUM(AE28:AE39) | AG39: =OR(AG38,IF(VATAgentMode,SUM($AE28:$AE39)-SUM($AL28:$AL39)>=VATThreshold,SUM($AE28:$AE39)>=VATThreshold)) | AH39: =IF(AG39,IF(VATAgentMode,AE39-((AE39-AL39)-(AE39-AL39)/(1+VATRate)),AE39/(1+VATRate)),AE39) | AI39: =AE39-AH39 | AJ39: =IF(AG39=0,0,IF(B39=1,SUMPRODUCT(--(($C$5:$C39=$C39-1)*($B$5:$B39>=10)*($B$5:$B39<=12)),$AI$5:$AI39),IF(B39=4,SUMPRODUCT(--(($C$5:$C39=$C39)*($B$5:$B39>=1)*($B$5:$B39<=3)),$AI$5:$AI39),IF(B39=7,SUMPRODUCT(--(($C$5:$C39=$C39)*($B$5:$B39>=4)*($B$5:$B39<=6)),$AI$5:$AI39),IF(B39=10,SUMPRODUCT(--(($C$5:$C39=$C39)*($B$5:$B39>=7)*($B$5:$B39<=9)),$AI$5:$AI39),0))))) | AK39: =AK38+AI39-AJ39 | AL39: =IF(ProviderDelay>=1,S38*BlendedProvPayEss+T38*BlendedProvPayPrem+U38*BlendedProvPayElite+V38*BlendedProvPayEss+W38*BlendedProvPayPrem+X38*BlendedProvPayElite,S39*BlendedProvPayEss+T39*BlendedProvPayPrem+U39*BlendedProvPayElite+V39*BlendedProvPayEss+W39*BlendedProvPayPrem+X39*BlendedProvPayElite) | AM39: =AE39*PaymentFee | AN39: =Y39*OpsAI | AO39: =MonthlyFixed | AP39: =I39*ReferralReward | AQ39: =G39 | AR39: =AH39-AL39-AM39-AN39-AO39-AP39-AQ39 | AS39: =AS38+AE39-(AL39+AM39+AN39+AO39+AP39+AQ39+AJ39) | AT39: =IF(Y39>0,Z39/Y39,0) | AU39: =IF(Y38>0,MAX(0,(Y38+J39-Y39)/Y38),0)
A40: 36 | B40: =MOD(A40-1+LaunchMonth-1,12)+1 | C40: =INT((A40-1+LaunchMonth-1)/12)+1 | D40: =VLOOKUP(B40,SeasonTable,2,FALSE) | E40: =(1+InflationRate)^INT((A40-1)/12) | F40: =MonthlyChurn*VLOOKUP(B40,ChurnSeasonTable,4,FALSE) | G40: =MIN(MAX(MktMin19plus,AE39*MktPct19plus),MAX(0,AS39-CashBuffer)) | H40: =IF(G40>0,MAX(1,ROUND(G40/CAC*D40,0)),0) | I40: =IF(H40>0,ROUND(H40*ReferralMix/(1-ReferralMix),0),0) | J40: =H40+I40 | K40: =ROUND(J40*(1-AnnualMix),0) | L40: =J40-K40 | M40: =ROUND(K40*EssentialMix,0) | N40: =ROUND(K40*PremiumMix,0) | O40: =K40-M40-N40 | P40: =ROUND(L40*EssentialMix,0) | Q40: =ROUND(L40*PremiumMix,0) | R40: =L40-P40-Q40 | S40: =M40+M39+M38+MAX(0,S39-M39-M38)*(1-F40) | T40: =N40+N39+N38+MAX(0,T39-N39-N38)*(1-F40) | U40: =O40+O39+O38+MAX(0,U39-O39-O38)*(1-F40) | V40: =V39+P40-P28*(AnnualChurn*VLOOKUP(B40,ChurnSeasonTable,4,FALSE))*POWER(1-(AnnualChurn*VLOOKUP(B40,ChurnSeasonTable,4,FALSE)),0)+P16*(AnnualChurn*VLOOKUP(B40,ChurnSeasonTable,4,FALSE))*POWER(1-(AnnualChurn*VLOOKUP(B40,ChurnSeasonTable,4,FALSE)),1) | W40: =W39+Q40-Q28*(AnnualChurn*VLOOKUP(B40,ChurnSeasonTable,4,FALSE))*POWER(1-(AnnualChurn*VLOOKUP(B40,ChurnSeasonTable,4,FALSE)),0)+Q16*(AnnualChurn*VLOOKUP(B40,ChurnSeasonTable,4,FALSE))*POWER(1-(AnnualChurn*VLOOKUP(B40,ChurnSeasonTable,4,FALSE)),1) | X40: =X39+R40-R28*(AnnualChurn*VLOOKUP(B40,ChurnSeasonTable,4,FALSE))*POWER(1-(AnnualChurn*VLOOKUP(B40,ChurnSeasonTable,4,FALSE)),0)+R16*(AnnualChurn*VLOOKUP(B40,ChurnSeasonTable,4,FALSE))*POWER(1-(AnnualChurn*VLOOKUP(B40,ChurnSeasonTable,4,FALSE)),1) | Y40: =S40+T40+U40+V40+W40+X40 | Z40: =S40*BlendedPriceEssMonthly*E40+T40*BlendedPricePremMonthly*E40+U40*BlendedPriceEliteMonthly*E40+V40*BlendedPriceEssAnnual*E40/12+W40*BlendedPricePremAnnual*E40/12+X40*BlendedPriceEliteAnnual*E40/12 | AA40: =Z40*12 | AB40: =S40*BlendedPriceEssMonthly*E40+T40*BlendedPricePremMonthly*E40+U40*BlendedPriceEliteMonthly*E40 | AC40: =P40*BlendedPriceEssAnnual*E40+Q40*BlendedPricePremAnnual*E40+R40*BlendedPriceEliteAnnual*E40 | AD40: =P28*POWER(1-(AnnualChurn*VLOOKUP(B40,ChurnSeasonTable,4,FALSE)),1)*BlendedPriceEssAnnual*E40+P16*POWER(1-(AnnualChurn*VLOOKUP(B40,ChurnSeasonTable,4,FALSE)),2)*BlendedPriceEssAnnual*E40+Q28*POWER(1-(AnnualChurn*VLOOKUP(B40,ChurnSeasonTable,4,FALSE)),1)*BlendedPricePremAnnual*E40+Q16*POWER(1-(AnnualChurn*VLOOKUP(B40,ChurnSeasonTable,4,FALSE)),2)*BlendedPricePremAnnual*E40+R28*POWER(1-(AnnualChurn*VLOOKUP(B40,ChurnSeasonTable,4,FALSE)),1)*BlendedPriceEliteAnnual*E40+R16*POWER(1-(AnnualChurn*VLOOKUP(B40,ChurnSeasonTable,4,FALSE)),2)*BlendedPriceEliteAnnual*E40 | AE40: =AB40+AC40+AD40 | AF40: =SUM(AE29:AE40) | AG40: =OR(AG39,IF(VATAgentMode,SUM($AE29:$AE40)-SUM($AL29:$AL40)>=VATThreshold,SUM($AE29:$AE40)>=VATThreshold)) | AH40: =IF(AG40,IF(VATAgentMode,AE40-((AE40-AL40)-(AE40-AL40)/(1+VATRate)),AE40/(1+VATRate)),AE40) | AI40: =AE40-AH40 | AJ40: =IF(AG40=0,0,IF(B40=1,SUMPRODUCT(--(($C$5:$C40=$C40-1)*($B$5:$B40>=10)*($B$5:$B40<=12)),$AI$5:$AI40),IF(B40=4,SUMPRODUCT(--(($C$5:$C40=$C40)*($B$5:$B40>=1)*($B$5:$B40<=3)),$AI$5:$AI40),IF(B40=7,SUMPRODUCT(--(($C$5:$C40=$C40)*($B$5:$B40>=4)*($B$5:$B40<=6)),$AI$5:$AI40),IF(B40=10,SUMPRODUCT(--(($C$5:$C40=$C40)*($B$5:$B40>=7)*($B$5:$B40<=9)),$AI$5:$AI40),0))))) | AK40: =AK39+AI40-AJ40 | AL40: =IF(ProviderDelay>=1,S39*BlendedProvPayEss+T39*BlendedProvPayPrem+U39*BlendedProvPayElite+V39*BlendedProvPayEss+W39*BlendedProvPayPrem+X39*BlendedProvPayElite,S40*BlendedProvPayEss+T40*BlendedProvPayPrem+U40*BlendedProvPayElite+V40*BlendedProvPayEss+W40*BlendedProvPayPrem+X40*BlendedProvPayElite) | AM40: =AE40*PaymentFee | AN40: =Y40*OpsAI | AO40: =MonthlyFixed | AP40: =I40*ReferralReward | AQ40: =G40 | AR40: =AH40-AL40-AM40-AN40-AO40-AP40-AQ40 | AS40: =AS39+AE40-(AL40+AM40+AN40+AO40+AP40+AQ40+AJ40) | AT40: =IF(Y40>0,Z40/Y40,0) | AU40: =IF(Y39>0,MAX(0,(Y39+J40-Y40)/Y39),0)
A41: 37 | B41: =MOD(A41-1+LaunchMonth-1,12)+1 | C41: =INT((A41-1+LaunchMonth-1)/12)+1 | D41: =VLOOKUP(B41,SeasonTable,2,FALSE) | E41: =(1+InflationRate)^INT((A41-1)/12) | F41: =MonthlyChurn*VLOOKUP(B41,ChurnSeasonTable,4,FALSE) | G41: =MIN(MAX(MktMin19plus,AE40*MktPct19plus),MAX(0,AS40-CashBuffer)) | H41: =IF(G41>0,MAX(1,ROUND(G41/CAC*D41,0)),0) | I41: =IF(H41>0,ROUND(H41*ReferralMix/(1-ReferralMix),0),0) | J41: =H41+I41 | K41: =ROUND(J41*(1-AnnualMix),0) | L41: =J41-K41 | M41: =ROUND(K41*EssentialMix,0) | N41: =ROUND(K41*PremiumMix,0) | O41: =K41-M41-N41 | P41: =ROUND(L41*EssentialMix,0) | Q41: =ROUND(L41*PremiumMix,0) | R41: =L41-P41-Q41 | S41: =M41+M40+M39+MAX(0,S40-M40-M39)*(1-F41) | T41: =N41+N40+N39+MAX(0,T40-N40-N39)*(1-F41) | U41: =O41+O40+O39+MAX(0,U40-O40-O39)*(1-F41) | V41: =V40+P41-P29*(AnnualChurn*VLOOKUP(B41,ChurnSeasonTable,4,FALSE))*POWER(1-(AnnualChurn*VLOOKUP(B41,ChurnSeasonTable,4,FALSE)),0)+P17*(AnnualChurn*VLOOKUP(B41,ChurnSeasonTable,4,FALSE))*POWER(1-(AnnualChurn*VLOOKUP(B41,ChurnSeasonTable,4,FALSE)),1)+P5*(AnnualChurn*VLOOKUP(B41,ChurnSeasonTable,4,FALSE))*POWER(1-(AnnualChurn*VLOOKUP(B41,ChurnSeasonTable,4,FALSE)),2) | W41: =W40+Q41-Q29*(AnnualChurn*VLOOKUP(B41,ChurnSeasonTable,4,FALSE))*POWER(1-(AnnualChurn*VLOOKUP(B41,ChurnSeasonTable,4,FALSE)),0)+Q17*(AnnualChurn*VLOOKUP(B41,ChurnSeasonTable,4,FALSE))*POWER(1-(AnnualChurn*VLOOKUP(B41,ChurnSeasonTable,4,FALSE)),1)+Q5*(AnnualChurn*VLOOKUP(B41,ChurnSeasonTable,4,FALSE))*POWER(1-(AnnualChurn*VLOOKUP(B41,ChurnSeasonTable,4,FALSE)),2) | X41: =X40+R41-R29*(AnnualChurn*VLOOKUP(B41,ChurnSeasonTable,4,FALSE))*POWER(1-(AnnualChurn*VLOOKUP(B41,ChurnSeasonTable,4,FALSE)),0)+R17*(AnnualChurn*VLOOKUP(B41,ChurnSeasonTable,4,FALSE))*POWER(1-(AnnualChurn*VLOOKUP(B41,ChurnSeasonTable,4,FALSE)),1)+R5*(AnnualChurn*VLOOKUP(B41,ChurnSeasonTable,4,FALSE))*POWER(1-(AnnualChurn*VLOOKUP(B41,ChurnSeasonTable,4,FALSE)),2) | Y41: =S41+T41+U41+V41+W41+X41 | Z41: =S41*BlendedPriceEssMonthly*E41+T41*BlendedPricePremMonthly*E41+U41*BlendedPriceEliteMonthly*E41+V41*BlendedPriceEssAnnual*E41/12+W41*BlendedPricePremAnnual*E41/12+X41*BlendedPriceEliteAnnual*E41/12 | AA41: =Z41*12 | AB41: =S41*BlendedPriceEssMonthly*E41+T41*BlendedPricePremMonthly*E41+U41*BlendedPriceEliteMonthly*E41 | AC41: =P41*BlendedPriceEssAnnual*E41+Q41*BlendedPricePremAnnual*E41+R41*BlendedPriceEliteAnnual*E41 | AD41: =P29*POWER(1-(AnnualChurn*VLOOKUP(B41,ChurnSeasonTable,4,FALSE)),1)*BlendedPriceEssAnnual*E41+P17*POWER(1-(AnnualChurn*VLOOKUP(B41,ChurnSeasonTable,4,FALSE)),2)*BlendedPriceEssAnnual*E41+P5*POWER(1-(AnnualChurn*VLOOKUP(B41,ChurnSeasonTable,4,FALSE)),3)*BlendedPriceEssAnnual*E41+Q29*POWER(1-(AnnualChurn*VLOOKUP(B41,ChurnSeasonTable,4,FALSE)),1)*BlendedPricePremAnnual*E41+Q17*POWER(1-(AnnualChurn*VLOOKUP(B41,ChurnSeasonTable,4,FALSE)),2)*BlendedPricePremAnnual*E41+Q5*POWER(1-(AnnualChurn*VLOOKUP(B41,ChurnSeasonTable,4,FALSE)),3)*BlendedPricePremAnnual*E41+R29*POWER(1-(AnnualChurn*VLOOKUP(B41,ChurnSeasonTable,4,FALSE)),1)*BlendedPriceEliteAnnual*E41+R17*POWER(1-(AnnualChurn*VLOOKUP(B41,ChurnSeasonTable,4,FALSE)),2)*BlendedPriceEliteAnnual*E41+R5*POWER(1-(AnnualChurn*VLOOKUP(B41,ChurnSeasonTable,4,FALSE)),3)*BlendedPriceEliteAnnual*E41 | AE41: =AB41+AC41+AD41 | AF41: =SUM(AE30:AE41) | AG41: =OR(AG40,IF(VATAgentMode,SUM($AE30:$AE41)-SUM($AL30:$AL41)>=VATThreshold,SUM($AE30:$AE41)>=VATThreshold)) | AH41: =IF(AG41,IF(VATAgentMode,AE41-((AE41-AL41)-(AE41-AL41)/(1+VATRate)),AE41/(1+VATRate)),AE41) | AI41: =AE41-AH41 | AJ41: =IF(AG41=0,0,IF(B41=1,SUMPRODUCT(--(($C$5:$C41=$C41-1)*($B$5:$B41>=10)*($B$5:$B41<=12)),$AI$5:$AI41),IF(B41=4,SUMPRODUCT(--(($C$5:$C41=$C41)*($B$5:$B41>=1)*($B$5:$B41<=3)),$AI$5:$AI41),IF(B41=7,SUMPRODUCT(--(($C$5:$C41=$C41)*($B$5:$B41>=4)*($B$5:$B41<=6)),$AI$5:$AI41),IF(B41=10,SUMPRODUCT(--(($C$5:$C41=$C41)*($B$5:$B41>=7)*($B$5:$B41<=9)),$AI$5:$AI41),0))))) | AK41: =AK40+AI41-AJ41 | AL41: =IF(ProviderDelay>=1,S40*BlendedProvPayEss+T40*BlendedProvPayPrem+U40*BlendedProvPayElite+V40*BlendedProvPayEss+W40*BlendedProvPayPrem+X40*BlendedProvPayElite,S41*BlendedProvPayEss+T41*BlendedProvPayPrem+U41*BlendedProvPayElite+V41*BlendedProvPayEss+W41*BlendedProvPayPrem+X41*BlendedProvPayElite) | AM41: =AE41*PaymentFee | AN41: =Y41*OpsAI | AO41: =MonthlyFixed | AP41: =I41*ReferralReward | AQ41: =G41 | AR41: =AH41-AL41-AM41-AN41-AO41-AP41-AQ41 | AS41: =AS40+AE41-(AL41+AM41+AN41+AO41+AP41+AQ41+AJ41) | AT41: =IF(Y41>0,Z41/Y41,0) | AU41: =IF(Y40>0,MAX(0,(Y40+J41-Y41)/Y40),0)
A42: 38 | B42: =MOD(A42-1+LaunchMonth-1,12)+1 | C42: =INT((A42-1+LaunchMonth-1)/12)+1 | D42: =VLOOKUP(B42,SeasonTable,2,FALSE) | E42: =(1+InflationRate)^INT((A42-1)/12) | F42: =MonthlyChurn*VLOOKUP(B42,ChurnSeasonTable,4,FALSE) | G42: =MIN(MAX(MktMin19plus,AE41*MktPct19plus),MAX(0,AS41-CashBuffer)) | H42: =IF(G42>0,MAX(1,ROUND(G42/CAC*D42,0)),0) | I42: =IF(H42>0,ROUND(H42*ReferralMix/(1-ReferralMix),0),0) | J42: =H42+I42 | K42: =ROUND(J42*(1-AnnualMix),0) | L42: =J42-K42 | M42: =ROUND(K42*EssentialMix,0) | N42: =ROUND(K42*PremiumMix,0) | O42: =K42-M42-N42 | P42: =ROUND(L42*EssentialMix,0) | Q42: =ROUND(L42*PremiumMix,0) | R42: =L42-P42-Q42 | S42: =M42+M41+M40+MAX(0,S41-M41-M40)*(1-F42) | T42: =N42+N41+N40+MAX(0,T41-N41-N40)*(1-F42) | U42: =O42+O41+O40+MAX(0,U41-O41-O40)*(1-F42) | V42: =V41+P42-P30*(AnnualChurn*VLOOKUP(B42,ChurnSeasonTable,4,FALSE))*POWER(1-(AnnualChurn*VLOOKUP(B42,ChurnSeasonTable,4,FALSE)),0)+P18*(AnnualChurn*VLOOKUP(B42,ChurnSeasonTable,4,FALSE))*POWER(1-(AnnualChurn*VLOOKUP(B42,ChurnSeasonTable,4,FALSE)),1)+P6*(AnnualChurn*VLOOKUP(B42,ChurnSeasonTable,4,FALSE))*POWER(1-(AnnualChurn*VLOOKUP(B42,ChurnSeasonTable,4,FALSE)),2) | W42: =W41+Q42-Q30*(AnnualChurn*VLOOKUP(B42,ChurnSeasonTable,4,FALSE))*POWER(1-(AnnualChurn*VLOOKUP(B42,ChurnSeasonTable,4,FALSE)),0)+Q18*(AnnualChurn*VLOOKUP(B42,ChurnSeasonTable,4,FALSE))*POWER(1-(AnnualChurn*VLOOKUP(B42,ChurnSeasonTable,4,FALSE)),1)+Q6*(AnnualChurn*VLOOKUP(B42,ChurnSeasonTable,4,FALSE))*POWER(1-(AnnualChurn*VLOOKUP(B42,ChurnSeasonTable,4,FALSE)),2) | X42: =X41+R42-R30*(AnnualChurn*VLOOKUP(B42,ChurnSeasonTable,4,FALSE))*POWER(1-(AnnualChurn*VLOOKUP(B42,ChurnSeasonTable,4,FALSE)),0)+R18*(AnnualChurn*VLOOKUP(B42,ChurnSeasonTable,4,FALSE))*POWER(1-(AnnualChurn*VLOOKUP(B42,ChurnSeasonTable,4,FALSE)),1)+R6*(AnnualChurn*VLOOKUP(B42,ChurnSeasonTable,4,FALSE))*POWER(1-(AnnualChurn*VLOOKUP(B42,ChurnSeasonTable,4,FALSE)),2) | Y42: =S42+T42+U42+V42+W42+X42 | Z42: =S42*BlendedPriceEssMonthly*E42+T42*BlendedPricePremMonthly*E42+U42*BlendedPriceEliteMonthly*E42+V42*BlendedPriceEssAnnual*E42/12+W42*BlendedPricePremAnnual*E42/12+X42*BlendedPriceEliteAnnual*E42/12 | AA42: =Z42*12 | AB42: =S42*BlendedPriceEssMonthly*E42+T42*BlendedPricePremMonthly*E42+U42*BlendedPriceEliteMonthly*E42 | AC42: =P42*BlendedPriceEssAnnual*E42+Q42*BlendedPricePremAnnual*E42+R42*BlendedPriceEliteAnnual*E42 | AD42: =P30*POWER(1-(AnnualChurn*VLOOKUP(B42,ChurnSeasonTable,4,FALSE)),1)*BlendedPriceEssAnnual*E42+P18*POWER(1-(AnnualChurn*VLOOKUP(B42,ChurnSeasonTable,4,FALSE)),2)*BlendedPriceEssAnnual*E42+P6*POWER(1-(AnnualChurn*VLOOKUP(B42,ChurnSeasonTable,4,FALSE)),3)*BlendedPriceEssAnnual*E42+Q30*POWER(1-(AnnualChurn*VLOOKUP(B42,ChurnSeasonTable,4,FALSE)),1)*BlendedPricePremAnnual*E42+Q18*POWER(1-(AnnualChurn*VLOOKUP(B42,ChurnSeasonTable,4,FALSE)),2)*BlendedPricePremAnnual*E42+Q6*POWER(1-(AnnualChurn*VLOOKUP(B42,ChurnSeasonTable,4,FALSE)),3)*BlendedPricePremAnnual*E42+R30*POWER(1-(AnnualChurn*VLOOKUP(B42,ChurnSeasonTable,4,FALSE)),1)*BlendedPriceEliteAnnual*E42+R18*POWER(1-(AnnualChurn*VLOOKUP(B42,ChurnSeasonTable,4,FALSE)),2)*BlendedPriceEliteAnnual*E42+R6*POWER(1-(AnnualChurn*VLOOKUP(B42,ChurnSeasonTable,4,FALSE)),3)*BlendedPriceEliteAnnual*E42 | AE42: =AB42+AC42+AD42 | AF42: =SUM(AE31:AE42) | AG42: =OR(AG41,IF(VATAgentMode,SUM($AE31:$AE42)-SUM($AL31:$AL42)>=VATThreshold,SUM($AE31:$AE42)>=VATThreshold)) | AH42: =IF(AG42,IF(VATAgentMode,AE42-((AE42-AL42)-(AE42-AL42)/(1+VATRate)),AE42/(1+VATRate)),AE42) | AI42: =AE42-AH42 | AJ42: =IF(AG42=0,0,IF(B42=1,SUMPRODUCT(--(($C$5:$C42=$C42-1)*($B$5:$B42>=10)*($B$5:$B42<=12)),$AI$5:$AI42),IF(B42=4,SUMPRODUCT(--(($C$5:$C42=$C42)*($B$5:$B42>=1)*($B$5:$B42<=3)),$AI$5:$AI42),IF(B42=7,SUMPRODUCT(--(($C$5:$C42=$C42)*($B$5:$B42>=4)*($B$5:$B42<=6)),$AI$5:$AI42),IF(B42=10,SUMPRODUCT(--(($C$5:$C42=$C42)*($B$5:$B42>=7)*($B$5:$B42<=9)),$AI$5:$AI42),0))))) | AK42: =AK41+AI42-AJ42 | AL42: =IF(ProviderDelay>=1,S41*BlendedProvPayEss+T41*BlendedProvPayPrem+U41*BlendedProvPayElite+V41*BlendedProvPayEss+W41*BlendedProvPayPrem+X41*BlendedProvPayElite,S42*BlendedProvPayEss+T42*BlendedProvPayPrem+U42*BlendedProvPayElite+V42*BlendedProvPayEss+W42*BlendedProvPayPrem+X42*BlendedProvPayElite) | AM42: =AE42*PaymentFee | AN42: =Y42*OpsAI | AO42: =MonthlyFixed | AP42: =I42*ReferralReward | AQ42: =G42 | AR42: =AH42-AL42-AM42-AN42-AO42-AP42-AQ42 | AS42: =AS41+AE42-(AL42+AM42+AN42+AO42+AP42+AQ42+AJ42) | AT42: =IF(Y42>0,Z42/Y42,0) | AU42: =IF(Y41>0,MAX(0,(Y41+J42-Y42)/Y41),0)
A43: 39 | B43: =MOD(A43-1+LaunchMonth-1,12)+1 | C43: =INT((A43-1+LaunchMonth-1)/12)+1 | D43: =VLOOKUP(B43,SeasonTable,2,FALSE) | E43: =(1+InflationRate)^INT((A43-1)/12) | F43: =MonthlyChurn*VLOOKUP(B43,ChurnSeasonTable,4,FALSE) | G43: =MIN(MAX(MktMin19plus,AE42*MktPct19plus),MAX(0,AS42-CashBuffer)) | H43: =IF(G43>0,MAX(1,ROUND(G43/CAC*D43,0)),0) | I43: =IF(H43>0,ROUND(H43*ReferralMix/(1-ReferralMix),0),0) | J43: =H43+I43 | K43: =ROUND(J43*(1-AnnualMix),0) | L43: =J43-K43 | M43: =ROUND(K43*EssentialMix,0) | N43: =ROUND(K43*PremiumMix,0) | O43: =K43-M43-N43 | P43: =ROUND(L43*EssentialMix,0) | Q43: =ROUND(L43*PremiumMix,0) | R43: =L43-P43-Q43 | S43: =M43+M42+M41+MAX(0,S42-M42-M41)*(1-F43) | T43: =N43+N42+N41+MAX(0,T42-N42-N41)*(1-F43) | U43: =O43+O42+O41+MAX(0,U42-O42-O41)*(1-F43) | V43: =V42+P43-P31*(AnnualChurn*VLOOKUP(B43,ChurnSeasonTable,4,FALSE))*POWER(1-(AnnualChurn*VLOOKUP(B43,ChurnSeasonTable,4,FALSE)),0)+P19*(AnnualChurn*VLOOKUP(B43,ChurnSeasonTable,4,FALSE))*POWER(1-(AnnualChurn*VLOOKUP(B43,ChurnSeasonTable,4,FALSE)),1)+P7*(AnnualChurn*VLOOKUP(B43,ChurnSeasonTable,4,FALSE))*POWER(1-(AnnualChurn*VLOOKUP(B43,ChurnSeasonTable,4,FALSE)),2) | W43: =W42+Q43-Q31*(AnnualChurn*VLOOKUP(B43,ChurnSeasonTable,4,FALSE))*POWER(1-(AnnualChurn*VLOOKUP(B43,ChurnSeasonTable,4,FALSE)),0)+Q19*(AnnualChurn*VLOOKUP(B43,ChurnSeasonTable,4,FALSE))*POWER(1-(AnnualChurn*VLOOKUP(B43,ChurnSeasonTable,4,FALSE)),1)+Q7*(AnnualChurn*VLOOKUP(B43,ChurnSeasonTable,4,FALSE))*POWER(1-(AnnualChurn*VLOOKUP(B43,ChurnSeasonTable,4,FALSE)),2) | X43: =X42+R43-R31*(AnnualChurn*VLOOKUP(B43,ChurnSeasonTable,4,FALSE))*POWER(1-(AnnualChurn*VLOOKUP(B43,ChurnSeasonTable,4,FALSE)),0)+R19*(AnnualChurn*VLOOKUP(B43,ChurnSeasonTable,4,FALSE))*POWER(1-(AnnualChurn*VLOOKUP(B43,ChurnSeasonTable,4,FALSE)),1)+R7*(AnnualChurn*VLOOKUP(B43,ChurnSeasonTable,4,FALSE))*POWER(1-(AnnualChurn*VLOOKUP(B43,ChurnSeasonTable,4,FALSE)),2) | Y43: =S43+T43+U43+V43+W43+X43 | Z43: =S43*BlendedPriceEssMonthly*E43+T43*BlendedPricePremMonthly*E43+U43*BlendedPriceEliteMonthly*E43+V43*BlendedPriceEssAnnual*E43/12+W43*BlendedPricePremAnnual*E43/12+X43*BlendedPriceEliteAnnual*E43/12 | AA43: =Z43*12 | AB43: =S43*BlendedPriceEssMonthly*E43+T43*BlendedPricePremMonthly*E43+U43*BlendedPriceEliteMonthly*E43 | AC43: =P43*BlendedPriceEssAnnual*E43+Q43*BlendedPricePremAnnual*E43+R43*BlendedPriceEliteAnnual*E43 | AD43: =P31*POWER(1-(AnnualChurn*VLOOKUP(B43,ChurnSeasonTable,4,FALSE)),1)*BlendedPriceEssAnnual*E43+P19*POWER(1-(AnnualChurn*VLOOKUP(B43,ChurnSeasonTable,4,FALSE)),2)*BlendedPriceEssAnnual*E43+P7*POWER(1-(AnnualChurn*VLOOKUP(B43,ChurnSeasonTable,4,FALSE)),3)*BlendedPriceEssAnnual*E43+Q31*POWER(1-(AnnualChurn*VLOOKUP(B43,ChurnSeasonTable,4,FALSE)),1)*BlendedPricePremAnnual*E43+Q19*POWER(1-(AnnualChurn*VLOOKUP(B43,ChurnSeasonTable,4,FALSE)),2)*BlendedPricePremAnnual*E43+Q7*POWER(1-(AnnualChurn*VLOOKUP(B43,ChurnSeasonTable,4,FALSE)),3)*BlendedPricePremAnnual*E43+R31*POWER(1-(AnnualChurn*VLOOKUP(B43,ChurnSeasonTable,4,FALSE)),1)*BlendedPriceEliteAnnual*E43+R19*POWER(1-(AnnualChurn*VLOOKUP(B43,ChurnSeasonTable,4,FALSE)),2)*BlendedPriceEliteAnnual*E43+R7*POWER(1-(AnnualChurn*VLOOKUP(B43,ChurnSeasonTable,4,FALSE)),3)*BlendedPriceEliteAnnual*E43 | AE43: =AB43+AC43+AD43 | AF43: =SUM(AE32:AE43) | AG43: =OR(AG42,IF(VATAgentMode,SUM($AE32:$AE43)-SUM($AL32:$AL43)>=VATThreshold,SUM($AE32:$AE43)>=VATThreshold)) | AH43: =IF(AG43,IF(VATAgentMode,AE43-((AE43-AL43)-(AE43-AL43)/(1+VATRate)),AE43/(1+VATRate)),AE43) | AI43: =AE43-AH43 | AJ43: =IF(AG43=0,0,IF(B43=1,SUMPRODUCT(--(($C$5:$C43=$C43-1)*($B$5:$B43>=10)*($B$5:$B43<=12)),$AI$5:$AI43),IF(B43=4,SUMPRODUCT(--(($C$5:$C43=$C43)*($B$5:$B43>=1)*($B$5:$B43<=3)),$AI$5:$AI43),IF(B43=7,SUMPRODUCT(--(($C$5:$C43=$C43)*($B$5:$B43>=4)*($B$5:$B43<=6)),$AI$5:$AI43),IF(B43=10,SUMPRODUCT(--(($C$5:$C43=$C43)*($B$5:$B43>=7)*($B$5:$B43<=9)),$AI$5:$AI43),0))))) | AK43: =AK42+AI43-AJ43 | AL43: =IF(ProviderDelay>=1,S42*BlendedProvPayEss+T42*BlendedProvPayPrem+U42*BlendedProvPayElite+V42*BlendedProvPayEss+W42*BlendedProvPayPrem+X42*BlendedProvPayElite,S43*BlendedProvPayEss+T43*BlendedProvPayPrem+U43*BlendedProvPayElite+V43*BlendedProvPayEss+W43*BlendedProvPayPrem+X43*BlendedProvPayElite) | AM43: =AE43*PaymentFee | AN43: =Y43*OpsAI | AO43: =MonthlyFixed | AP43: =I43*ReferralReward | AQ43: =G43 | AR43: =AH43-AL43-AM43-AN43-AO43-AP43-AQ43 | AS43: =AS42+AE43-(AL43+AM43+AN43+AO43+AP43+AQ43+AJ43) | AT43: =IF(Y43>0,Z43/Y43,0) | AU43: =IF(Y42>0,MAX(0,(Y42+J43-Y43)/Y42),0)
A44: 40 | B44: =MOD(A44-1+LaunchMonth-1,12)+1 | C44: =INT((A44-1+LaunchMonth-1)/12)+1 | D44: =VLOOKUP(B44,SeasonTable,2,FALSE) | E44: =(1+InflationRate)^INT((A44-1)/12) | F44: =MonthlyChurn*VLOOKUP(B44,ChurnSeasonTable,4,FALSE) | G44: =MIN(MAX(MktMin19plus,AE43*MktPct19plus),MAX(0,AS43-CashBuffer)) | H44: =IF(G44>0,MAX(1,ROUND(G44/CAC*D44,0)),0) | I44: =IF(H44>0,ROUND(H44*ReferralMix/(1-ReferralMix),0),0) | J44: =H44+I44 | K44: =ROUND(J44*(1-AnnualMix),0) | L44: =J44-K44 | M44: =ROUND(K44*EssentialMix,0) | N44: =ROUND(K44*PremiumMix,0) | O44: =K44-M44-N44 | P44: =ROUND(L44*EssentialMix,0) | Q44: =ROUND(L44*PremiumMix,0) | R44: =L44-P44-Q44 | S44: =M44+M43+M42+MAX(0,S43-M43-M42)*(1-F44) | T44: =N44+N43+N42+MAX(0,T43-N43-N42)*(1-F44) | U44: =O44+O43+O42+MAX(0,U43-O43-O42)*(1-F44) | V44: =V43+P44-P32*(AnnualChurn*VLOOKUP(B44,ChurnSeasonTable,4,FALSE))*POWER(1-(AnnualChurn*VLOOKUP(B44,ChurnSeasonTable,4,FALSE)),0)+P20*(AnnualChurn*VLOOKUP(B44,ChurnSeasonTable,4,FALSE))*POWER(1-(AnnualChurn*VLOOKUP(B44,ChurnSeasonTable,4,FALSE)),1)+P8*(AnnualChurn*VLOOKUP(B44,ChurnSeasonTable,4,FALSE))*POWER(1-(AnnualChurn*VLOOKUP(B44,ChurnSeasonTable,4,FALSE)),2) | W44: =W43+Q44-Q32*(AnnualChurn*VLOOKUP(B44,ChurnSeasonTable,4,FALSE))*POWER(1-(AnnualChurn*VLOOKUP(B44,ChurnSeasonTable,4,FALSE)),0)+Q20*(AnnualChurn*VLOOKUP(B44,ChurnSeasonTable,4,FALSE))*POWER(1-(AnnualChurn*VLOOKUP(B44,ChurnSeasonTable,4,FALSE)),1)+Q8*(AnnualChurn*VLOOKUP(B44,ChurnSeasonTable,4,FALSE))*POWER(1-(AnnualChurn*VLOOKUP(B44,ChurnSeasonTable,4,FALSE)),2) | X44: =X43+R44-R32*(AnnualChurn*VLOOKUP(B44,ChurnSeasonTable,4,FALSE))*POWER(1-(AnnualChurn*VLOOKUP(B44,ChurnSeasonTable,4,FALSE)),0)+R20*(AnnualChurn*VLOOKUP(B44,ChurnSeasonTable,4,FALSE))*POWER(1-(AnnualChurn*VLOOKUP(B44,ChurnSeasonTable,4,FALSE)),1)+R8*(AnnualChurn*VLOOKUP(B44,ChurnSeasonTable,4,FALSE))*POWER(1-(AnnualChurn*VLOOKUP(B44,ChurnSeasonTable,4,FALSE)),2) | Y44: =S44+T44+U44+V44+W44+X44 | Z44: =S44*BlendedPriceEssMonthly*E44+T44*BlendedPricePremMonthly*E44+U44*BlendedPriceEliteMonthly*E44+V44*BlendedPriceEssAnnual*E44/12+W44*BlendedPricePremAnnual*E44/12+X44*BlendedPriceEliteAnnual*E44/12 | AA44: =Z44*12 | AB44: =S44*BlendedPriceEssMonthly*E44+T44*BlendedPricePremMonthly*E44+U44*BlendedPriceEliteMonthly*E44 | AC44: =P44*BlendedPriceEssAnnual*E44+Q44*BlendedPricePremAnnual*E44+R44*BlendedPriceEliteAnnual*E44 | AD44: =P32*POWER(1-(AnnualChurn*VLOOKUP(B44,ChurnSeasonTable,4,FALSE)),1)*BlendedPriceEssAnnual*E44+P20*POWER(1-(AnnualChurn*VLOOKUP(B44,ChurnSeasonTable,4,FALSE)),2)*BlendedPriceEssAnnual*E44+P8*POWER(1-(AnnualChurn*VLOOKUP(B44,ChurnSeasonTable,4,FALSE)),3)*BlendedPriceEssAnnual*E44+Q32*POWER(1-(AnnualChurn*VLOOKUP(B44,ChurnSeasonTable,4,FALSE)),1)*BlendedPricePremAnnual*E44+Q20*POWER(1-(AnnualChurn*VLOOKUP(B44,ChurnSeasonTable,4,FALSE)),2)*BlendedPricePremAnnual*E44+Q8*POWER(1-(AnnualChurn*VLOOKUP(B44,ChurnSeasonTable,4,FALSE)),3)*BlendedPricePremAnnual*E44+R32*POWER(1-(AnnualChurn*VLOOKUP(B44,ChurnSeasonTable,4,FALSE)),1)*BlendedPriceEliteAnnual*E44+R20*POWER(1-(AnnualChurn*VLOOKUP(B44,ChurnSeasonTable,4,FALSE)),2)*BlendedPriceEliteAnnual*E44+R8*POWER(1-(AnnualChurn*VLOOKUP(B44,ChurnSeasonTable,4,FALSE)),3)*BlendedPriceEliteAnnual*E44 | AE44: =AB44+AC44+AD44 | AF44: =SUM(AE33:AE44) | AG44: =OR(AG43,IF(VATAgentMode,SUM($AE33:$AE44)-SUM($AL33:$AL44)>=VATThreshold,SUM($AE33:$AE44)>=VATThreshold)) | AH44: =IF(AG44,IF(VATAgentMode,AE44-((AE44-AL44)-(AE44-AL44)/(1+VATRate)),AE44/(1+VATRate)),AE44) | AI44: =AE44-AH44 | AJ44: =IF(AG44=0,0,IF(B44=1,SUMPRODUCT(--(($C$5:$C44=$C44-1)*($B$5:$B44>=10)*($B$5:$B44<=12)),$AI$5:$AI44),IF(B44=4,SUMPRODUCT(--(($C$5:$C44=$C44)*($B$5:$B44>=1)*($B$5:$B44<=3)),$AI$5:$AI44),IF(B44=7,SUMPRODUCT(--(($C$5:$C44=$C44)*($B$5:$B44>=4)*($B$5:$B44<=6)),$AI$5:$AI44),IF(B44=10,SUMPRODUCT(--(($C$5:$C44=$C44)*($B$5:$B44>=7)*($B$5:$B44<=9)),$AI$5:$AI44),0))))) | AK44: =AK43+AI44-AJ44 | AL44: =IF(ProviderDelay>=1,S43*BlendedProvPayEss+T43*BlendedProvPayPrem+U43*BlendedProvPayElite+V43*BlendedProvPayEss+W43*BlendedProvPayPrem+X43*BlendedProvPayElite,S44*BlendedProvPayEss+T44*BlendedProvPayPrem+U44*BlendedProvPayElite+V44*BlendedProvPayEss+W44*BlendedProvPayPrem+X44*BlendedProvPayElite) | AM44: =AE44*PaymentFee | AN44: =Y44*OpsAI | AO44: =MonthlyFixed | AP44: =I44*ReferralReward | AQ44: =G44 | AR44: =AH44-AL44-AM44-AN44-AO44-AP44-AQ44 | AS44: =AS43+AE44-(AL44+AM44+AN44+AO44+AP44+AQ44+AJ44) | AT44: =IF(Y44>0,Z44/Y44,0) | AU44: =IF(Y43>0,MAX(0,(Y43+J44-Y44)/Y43),0)
A45: 41 | B45: =MOD(A45-1+LaunchMonth-1,12)+1 | C45: =INT((A45-1+LaunchMonth-1)/12)+1 | D45: =VLOOKUP(B45,SeasonTable,2,FALSE) | E45: =(1+InflationRate)^INT((A45-1)/12) | F45: =MonthlyChurn*VLOOKUP(B45,ChurnSeasonTable,4,FALSE) | G45: =MIN(MAX(MktMin19plus,AE44*MktPct19plus),MAX(0,AS44-CashBuffer)) | H45: =IF(G45>0,MAX(1,ROUND(G45/CAC*D45,0)),0) | I45: =IF(H45>0,ROUND(H45*ReferralMix/(1-ReferralMix),0),0) | J45: =H45+I45 | K45: =ROUND(J45*(1-AnnualMix),0) | L45: =J45-K45 | M45: =ROUND(K45*EssentialMix,0) | N45: =ROUND(K45*PremiumMix,0) | O45: =K45-M45-N45 | P45: =ROUND(L45*EssentialMix,0) | Q45: =ROUND(L45*PremiumMix,0) | R45: =L45-P45-Q45 | S45: =M45+M44+M43+MAX(0,S44-M44-M43)*(1-F45) | T45: =N45+N44+N43+MAX(0,T44-N44-N43)*(1-F45) | U45: =O45+O44+O43+MAX(0,U44-O44-O43)*(1-F45) | V45: =V44+P45-P33*(AnnualChurn*VLOOKUP(B45,ChurnSeasonTable,4,FALSE))*POWER(1-(AnnualChurn*VLOOKUP(B45,ChurnSeasonTable,4,FALSE)),0)+P21*(AnnualChurn*VLOOKUP(B45,ChurnSeasonTable,4,FALSE))*POWER(1-(AnnualChurn*VLOOKUP(B45,ChurnSeasonTable,4,FALSE)),1)+P9*(AnnualChurn*VLOOKUP(B45,ChurnSeasonTable,4,FALSE))*POWER(1-(AnnualChurn*VLOOKUP(B45,ChurnSeasonTable,4,FALSE)),2) | W45: =W44+Q45-Q33*(AnnualChurn*VLOOKUP(B45,ChurnSeasonTable,4,FALSE))*POWER(1-(AnnualChurn*VLOOKUP(B45,ChurnSeasonTable,4,FALSE)),0)+Q21*(AnnualChurn*VLOOKUP(B45,ChurnSeasonTable,4,FALSE))*POWER(1-(AnnualChurn*VLOOKUP(B45,ChurnSeasonTable,4,FALSE)),1)+Q9*(AnnualChurn*VLOOKUP(B45,ChurnSeasonTable,4,FALSE))*POWER(1-(AnnualChurn*VLOOKUP(B45,ChurnSeasonTable,4,FALSE)),2) | X45: =X44+R45-R33*(AnnualChurn*VLOOKUP(B45,ChurnSeasonTable,4,FALSE))*POWER(1-(AnnualChurn*VLOOKUP(B45,ChurnSeasonTable,4,FALSE)),0)+R21*(AnnualChurn*VLOOKUP(B45,ChurnSeasonTable,4,FALSE))*POWER(1-(AnnualChurn*VLOOKUP(B45,ChurnSeasonTable,4,FALSE)),1)+R9*(AnnualChurn*VLOOKUP(B45,ChurnSeasonTable,4,FALSE))*POWER(1-(AnnualChurn*VLOOKUP(B45,ChurnSeasonTable,4,FALSE)),2) | Y45: =S45+T45+U45+V45+W45+X45 | Z45: =S45*BlendedPriceEssMonthly*E45+T45*BlendedPricePremMonthly*E45+U45*BlendedPriceEliteMonthly*E45+V45*BlendedPriceEssAnnual*E45/12+W45*BlendedPricePremAnnual*E45/12+X45*BlendedPriceEliteAnnual*E45/12 | AA45: =Z45*12 | AB45: =S45*BlendedPriceEssMonthly*E45+T45*BlendedPricePremMonthly*E45+U45*BlendedPriceEliteMonthly*E45 | AC45: =P45*BlendedPriceEssAnnual*E45+Q45*BlendedPricePremAnnual*E45+R45*BlendedPriceEliteAnnual*E45 | AD45: =P33*POWER(1-(AnnualChurn*VLOOKUP(B45,ChurnSeasonTable,4,FALSE)),1)*BlendedPriceEssAnnual*E45+P21*POWER(1-(AnnualChurn*VLOOKUP(B45,ChurnSeasonTable,4,FALSE)),2)*BlendedPriceEssAnnual*E45+P9*POWER(1-(AnnualChurn*VLOOKUP(B45,ChurnSeasonTable,4,FALSE)),3)*BlendedPriceEssAnnual*E45+Q33*POWER(1-(AnnualChurn*VLOOKUP(B45,ChurnSeasonTable,4,FALSE)),1)*BlendedPricePremAnnual*E45+Q21*POWER(1-(AnnualChurn*VLOOKUP(B45,ChurnSeasonTable,4,FALSE)),2)*BlendedPricePremAnnual*E45+Q9*POWER(1-(AnnualChurn*VLOOKUP(B45,ChurnSeasonTable,4,FALSE)),3)*BlendedPricePremAnnual*E45+R33*POWER(1-(AnnualChurn*VLOOKUP(B45,ChurnSeasonTable,4,FALSE)),1)*BlendedPriceEliteAnnual*E45+R21*POWER(1-(AnnualChurn*VLOOKUP(B45,ChurnSeasonTable,4,FALSE)),2)*BlendedPriceEliteAnnual*E45+R9*POWER(1-(AnnualChurn*VLOOKUP(B45,ChurnSeasonTable,4,FALSE)),3)*BlendedPriceEliteAnnual*E45 | AE45: =AB45+AC45+AD45 | AF45: =SUM(AE34:AE45) | AG45: =OR(AG44,IF(VATAgentMode,SUM($AE34:$AE45)-SUM($AL34:$AL45)>=VATThreshold,SUM($AE34:$AE45)>=VATThreshold)) | AH45: =IF(AG45,IF(VATAgentMode,AE45-((AE45-AL45)-(AE45-AL45)/(1+VATRate)),AE45/(1+VATRate)),AE45) | AI45: =AE45-AH45 | AJ45: =IF(AG45=0,0,IF(B45=1,SUMPRODUCT(--(($C$5:$C45=$C45-1)*($B$5:$B45>=10)*($B$5:$B45<=12)),$AI$5:$AI45),IF(B45=4,SUMPRODUCT(--(($C$5:$C45=$C45)*($B$5:$B45>=1)*($B$5:$B45<=3)),$AI$5:$AI45),IF(B45=7,SUMPRODUCT(--(($C$5:$C45=$C45)*($B$5:$B45>=4)*($B$5:$B45<=6)),$AI$5:$AI45),IF(B45=10,SUMPRODUCT(--(($C$5:$C45=$C45)*($B$5:$B45>=7)*($B$5:$B45<=9)),$AI$5:$AI45),0))))) | AK45: =AK44+AI45-AJ45 | AL45: =IF(ProviderDelay>=1,S44*BlendedProvPayEss+T44*BlendedProvPayPrem+U44*BlendedProvPayElite+V44*BlendedProvPayEss+W44*BlendedProvPayPrem+X44*BlendedProvPayElite,S45*BlendedProvPayEss+T45*BlendedProvPayPrem+U45*BlendedProvPayElite+V45*BlendedProvPayEss+W45*BlendedProvPayPrem+X45*BlendedProvPayElite) | AM45: =AE45*PaymentFee | AN45: =Y45*OpsAI | AO45: =MonthlyFixed | AP45: =I45*ReferralReward | AQ45: =G45 | AR45: =AH45-AL45-AM45-AN45-AO45-AP45-AQ45 | AS45: =AS44+AE45-(AL45+AM45+AN45+AO45+AP45+AQ45+AJ45) | AT45: =IF(Y45>0,Z45/Y45,0) | AU45: =IF(Y44>0,MAX(0,(Y44+J45-Y45)/Y44),0)
A46: 42 | B46: =MOD(A46-1+LaunchMonth-1,12)+1 | C46: =INT((A46-1+LaunchMonth-1)/12)+1 | D46: =VLOOKUP(B46,SeasonTable,2,FALSE) | E46: =(1+InflationRate)^INT((A46-1)/12) | F46: =MonthlyChurn*VLOOKUP(B46,ChurnSeasonTable,4,FALSE) | G46: =MIN(MAX(MktMin19plus,AE45*MktPct19plus),MAX(0,AS45-CashBuffer)) | H46: =IF(G46>0,MAX(1,ROUND(G46/CAC*D46,0)),0) | I46: =IF(H46>0,ROUND(H46*ReferralMix/(1-ReferralMix),0),0) | J46: =H46+I46 | K46: =ROUND(J46*(1-AnnualMix),0) | L46: =J46-K46 | M46: =ROUND(K46*EssentialMix,0) | N46: =ROUND(K46*PremiumMix,0) | O46: =K46-M46-N46 | P46: =ROUND(L46*EssentialMix,0) | Q46: =ROUND(L46*PremiumMix,0) | R46: =L46-P46-Q46 | S46: =M46+M45+M44+MAX(0,S45-M45-M44)*(1-F46) | T46: =N46+N45+N44+MAX(0,T45-N45-N44)*(1-F46) | U46: =O46+O45+O44+MAX(0,U45-O45-O44)*(1-F46) | V46: =V45+P46-P34*(AnnualChurn*VLOOKUP(B46,ChurnSeasonTable,4,FALSE))*POWER(1-(AnnualChurn*VLOOKUP(B46,ChurnSeasonTable,4,FALSE)),0)+P22*(AnnualChurn*VLOOKUP(B46,ChurnSeasonTable,4,FALSE))*POWER(1-(AnnualChurn*VLOOKUP(B46,ChurnSeasonTable,4,FALSE)),1)+P10*(AnnualChurn*VLOOKUP(B46,ChurnSeasonTable,4,FALSE))*POWER(1-(AnnualChurn*VLOOKUP(B46,ChurnSeasonTable,4,FALSE)),2) | W46: =W45+Q46-Q34*(AnnualChurn*VLOOKUP(B46,ChurnSeasonTable,4,FALSE))*POWER(1-(AnnualChurn*VLOOKUP(B46,ChurnSeasonTable,4,FALSE)),0)+Q22*(AnnualChurn*VLOOKUP(B46,ChurnSeasonTable,4,FALSE))*POWER(1-(AnnualChurn*VLOOKUP(B46,ChurnSeasonTable,4,FALSE)),1)+Q10*(AnnualChurn*VLOOKUP(B46,ChurnSeasonTable,4,FALSE))*POWER(1-(AnnualChurn*VLOOKUP(B46,ChurnSeasonTable,4,FALSE)),2) | X46: =X45+R46-R34*(AnnualChurn*VLOOKUP(B46,ChurnSeasonTable,4,FALSE))*POWER(1-(AnnualChurn*VLOOKUP(B46,ChurnSeasonTable,4,FALSE)),0)+R22*(AnnualChurn*VLOOKUP(B46,ChurnSeasonTable,4,FALSE))*POWER(1-(AnnualChurn*VLOOKUP(B46,ChurnSeasonTable,4,FALSE)),1)+R10*(AnnualChurn*VLOOKUP(B46,ChurnSeasonTable,4,FALSE))*POWER(1-(AnnualChurn*VLOOKUP(B46,ChurnSeasonTable,4,FALSE)),2) | Y46: =S46+T46+U46+V46+W46+X46 | Z46: =S46*BlendedPriceEssMonthly*E46+T46*BlendedPricePremMonthly*E46+U46*BlendedPriceEliteMonthly*E46+V46*BlendedPriceEssAnnual*E46/12+W46*BlendedPricePremAnnual*E46/12+X46*BlendedPriceEliteAnnual*E46/12 | AA46: =Z46*12 | AB46: =S46*BlendedPriceEssMonthly*E46+T46*BlendedPricePremMonthly*E46+U46*BlendedPriceEliteMonthly*E46 | AC46: =P46*BlendedPriceEssAnnual*E46+Q46*BlendedPricePremAnnual*E46+R46*BlendedPriceEliteAnnual*E46 | AD46: =P34*POWER(1-(AnnualChurn*VLOOKUP(B46,ChurnSeasonTable,4,FALSE)),1)*BlendedPriceEssAnnual*E46+P22*POWER(1-(AnnualChurn*VLOOKUP(B46,ChurnSeasonTable,4,FALSE)),2)*BlendedPriceEssAnnual*E46+P10*POWER(1-(AnnualChurn*VLOOKUP(B46,ChurnSeasonTable,4,FALSE)),3)*BlendedPriceEssAnnual*E46+Q34*POWER(1-(AnnualChurn*VLOOKUP(B46,ChurnSeasonTable,4,FALSE)),1)*BlendedPricePremAnnual*E46+Q22*POWER(1-(AnnualChurn*VLOOKUP(B46,ChurnSeasonTable,4,FALSE)),2)*BlendedPricePremAnnual*E46+Q10*POWER(1-(AnnualChurn*VLOOKUP(B46,ChurnSeasonTable,4,FALSE)),3)*BlendedPricePremAnnual*E46+R34*POWER(1-(AnnualChurn*VLOOKUP(B46,ChurnSeasonTable,4,FALSE)),1)*BlendedPriceEliteAnnual*E46+R22*POWER(1-(AnnualChurn*VLOOKUP(B46,ChurnSeasonTable,4,FALSE)),2)*BlendedPriceEliteAnnual*E46+R10*POWER(1-(AnnualChurn*VLOOKUP(B46,ChurnSeasonTable,4,FALSE)),3)*BlendedPriceEliteAnnual*E46 | AE46: =AB46+AC46+AD46 | AF46: =SUM(AE35:AE46) | AG46: =OR(AG45,IF(VATAgentMode,SUM($AE35:$AE46)-SUM($AL35:$AL46)>=VATThreshold,SUM($AE35:$AE46)>=VATThreshold)) | AH46: =IF(AG46,IF(VATAgentMode,AE46-((AE46-AL46)-(AE46-AL46)/(1+VATRate)),AE46/(1+VATRate)),AE46) | AI46: =AE46-AH46 | AJ46: =IF(AG46=0,0,IF(B46=1,SUMPRODUCT(--(($C$5:$C46=$C46-1)*($B$5:$B46>=10)*($B$5:$B46<=12)),$AI$5:$AI46),IF(B46=4,SUMPRODUCT(--(($C$5:$C46=$C46)*($B$5:$B46>=1)*($B$5:$B46<=3)),$AI$5:$AI46),IF(B46=7,SUMPRODUCT(--(($C$5:$C46=$C46)*($B$5:$B46>=4)*($B$5:$B46<=6)),$AI$5:$AI46),IF(B46=10,SUMPRODUCT(--(($C$5:$C46=$C46)*($B$5:$B46>=7)*($B$5:$B46<=9)),$AI$5:$AI46),0))))) | AK46: =AK45+AI46-AJ46 | AL46: =IF(ProviderDelay>=1,S45*BlendedProvPayEss+T45*BlendedProvPayPrem+U45*BlendedProvPayElite+V45*BlendedProvPayEss+W45*BlendedProvPayPrem+X45*BlendedProvPayElite,S46*BlendedProvPayEss+T46*BlendedProvPayPrem+U46*BlendedProvPayElite+V46*BlendedProvPayEss+W46*BlendedProvPayPrem+X46*BlendedProvPayElite) | AM46: =AE46*PaymentFee | AN46: =Y46*OpsAI | AO46: =MonthlyFixed | AP46: =I46*ReferralReward | AQ46: =G46 | AR46: =AH46-AL46-AM46-AN46-AO46-AP46-AQ46 | AS46: =AS45+AE46-(AL46+AM46+AN46+AO46+AP46+AQ46+AJ46) | AT46: =IF(Y46>0,Z46/Y46,0) | AU46: =IF(Y45>0,MAX(0,(Y45+J46-Y46)/Y45),0)
A47: 43 | B47: =MOD(A47-1+LaunchMonth-1,12)+1 | C47: =INT((A47-1+LaunchMonth-1)/12)+1 | D47: =VLOOKUP(B47,SeasonTable,2,FALSE) | E47: =(1+InflationRate)^INT((A47-1)/12) | F47: =MonthlyChurn*VLOOKUP(B47,ChurnSeasonTable,4,FALSE) | G47: =MIN(MAX(MktMin19plus,AE46*MktPct19plus),MAX(0,AS46-CashBuffer)) | H47: =IF(G47>0,MAX(1,ROUND(G47/CAC*D47,0)),0) | I47: =IF(H47>0,ROUND(H47*ReferralMix/(1-ReferralMix),0),0) | J47: =H47+I47 | K47: =ROUND(J47*(1-AnnualMix),0) | L47: =J47-K47 | M47: =ROUND(K47*EssentialMix,0) | N47: =ROUND(K47*PremiumMix,0) | O47: =K47-M47-N47 | P47: =ROUND(L47*EssentialMix,0) | Q47: =ROUND(L47*PremiumMix,0) | R47: =L47-P47-Q47 | S47: =M47+M46+M45+MAX(0,S46-M46-M45)*(1-F47) | T47: =N47+N46+N45+MAX(0,T46-N46-N45)*(1-F47) | U47: =O47+O46+O45+MAX(0,U46-O46-O45)*(1-F47) | V47: =V46+P47-P35*(AnnualChurn*VLOOKUP(B47,ChurnSeasonTable,4,FALSE))*POWER(1-(AnnualChurn*VLOOKUP(B47,ChurnSeasonTable,4,FALSE)),0)+P23*(AnnualChurn*VLOOKUP(B47,ChurnSeasonTable,4,FALSE))*POWER(1-(AnnualChurn*VLOOKUP(B47,ChurnSeasonTable,4,FALSE)),1)+P11*(AnnualChurn*VLOOKUP(B47,ChurnSeasonTable,4,FALSE))*POWER(1-(AnnualChurn*VLOOKUP(B47,ChurnSeasonTable,4,FALSE)),2) | W47: =W46+Q47-Q35*(AnnualChurn*VLOOKUP(B47,ChurnSeasonTable,4,FALSE))*POWER(1-(AnnualChurn*VLOOKUP(B47,ChurnSeasonTable,4,FALSE)),0)+Q23*(AnnualChurn*VLOOKUP(B47,ChurnSeasonTable,4,FALSE))*POWER(1-(AnnualChurn*VLOOKUP(B47,ChurnSeasonTable,4,FALSE)),1)+Q11*(AnnualChurn*VLOOKUP(B47,ChurnSeasonTable,4,FALSE))*POWER(1-(AnnualChurn*VLOOKUP(B47,ChurnSeasonTable,4,FALSE)),2) | X47: =X46+R47-R35*(AnnualChurn*VLOOKUP(B47,ChurnSeasonTable,4,FALSE))*POWER(1-(AnnualChurn*VLOOKUP(B47,ChurnSeasonTable,4,FALSE)),0)+R23*(AnnualChurn*VLOOKUP(B47,ChurnSeasonTable,4,FALSE))*POWER(1-(AnnualChurn*VLOOKUP(B47,ChurnSeasonTable,4,FALSE)),1)+R11*(AnnualChurn*VLOOKUP(B47,ChurnSeasonTable,4,FALSE))*POWER(1-(AnnualChurn*VLOOKUP(B47,ChurnSeasonTable,4,FALSE)),2) | Y47: =S47+T47+U47+V47+W47+X47 | Z47: =S47*BlendedPriceEssMonthly*E47+T47*BlendedPricePremMonthly*E47+U47*BlendedPriceEliteMonthly*E47+V47*BlendedPriceEssAnnual*E47/12+W47*BlendedPricePremAnnual*E47/12+X47*BlendedPriceEliteAnnual*E47/12 | AA47: =Z47*12 | AB47: =S47*BlendedPriceEssMonthly*E47+T47*BlendedPricePremMonthly*E47+U47*BlendedPriceEliteMonthly*E47 | AC47: =P47*BlendedPriceEssAnnual*E47+Q47*BlendedPricePremAnnual*E47+R47*BlendedPriceEliteAnnual*E47 | AD47: =P35*POWER(1-(AnnualChurn*VLOOKUP(B47,ChurnSeasonTable,4,FALSE)),1)*BlendedPriceEssAnnual*E47+P23*POWER(1-(AnnualChurn*VLOOKUP(B47,ChurnSeasonTable,4,FALSE)),2)*BlendedPriceEssAnnual*E47+P11*POWER(1-(AnnualChurn*VLOOKUP(B47,ChurnSeasonTable,4,FALSE)),3)*BlendedPriceEssAnnual*E47+Q35*POWER(1-(AnnualChurn*VLOOKUP(B47,ChurnSeasonTable,4,FALSE)),1)*BlendedPricePremAnnual*E47+Q23*POWER(1-(AnnualChurn*VLOOKUP(B47,ChurnSeasonTable,4,FALSE)),2)*BlendedPricePremAnnual*E47+Q11*POWER(1-(AnnualChurn*VLOOKUP(B47,ChurnSeasonTable,4,FALSE)),3)*BlendedPricePremAnnual*E47+R35*POWER(1-(AnnualChurn*VLOOKUP(B47,ChurnSeasonTable,4,FALSE)),1)*BlendedPriceEliteAnnual*E47+R23*POWER(1-(AnnualChurn*VLOOKUP(B47,ChurnSeasonTable,4,FALSE)),2)*BlendedPriceEliteAnnual*E47+R11*POWER(1-(AnnualChurn*VLOOKUP(B47,ChurnSeasonTable,4,FALSE)),3)*BlendedPriceEliteAnnual*E47 | AE47: =AB47+AC47+AD47 | AF47: =SUM(AE36:AE47) | AG47: =OR(AG46,IF(VATAgentMode,SUM($AE36:$AE47)-SUM($AL36:$AL47)>=VATThreshold,SUM($AE36:$AE47)>=VATThreshold)) | AH47: =IF(AG47,IF(VATAgentMode,AE47-((AE47-AL47)-(AE47-AL47)/(1+VATRate)),AE47/(1+VATRate)),AE47) | AI47: =AE47-AH47 | AJ47: =IF(AG47=0,0,IF(B47=1,SUMPRODUCT(--(($C$5:$C47=$C47-1)*($B$5:$B47>=10)*($B$5:$B47<=12)),$AI$5:$AI47),IF(B47=4,SUMPRODUCT(--(($C$5:$C47=$C47)*($B$5:$B47>=1)*($B$5:$B47<=3)),$AI$5:$AI47),IF(B47=7,SUMPRODUCT(--(($C$5:$C47=$C47)*($B$5:$B47>=4)*($B$5:$B47<=6)),$AI$5:$AI47),IF(B47=10,SUMPRODUCT(--(($C$5:$C47=$C47)*($B$5:$B47>=7)*($B$5:$B47<=9)),$AI$5:$AI47),0))))) | AK47: =AK46+AI47-AJ47 | AL47: =IF(ProviderDelay>=1,S46*BlendedProvPayEss+T46*BlendedProvPayPrem+U46*BlendedProvPayElite+V46*BlendedProvPayEss+W46*BlendedProvPayPrem+X46*BlendedProvPayElite,S47*BlendedProvPayEss+T47*BlendedProvPayPrem+U47*BlendedProvPayElite+V47*BlendedProvPayEss+W47*BlendedProvPayPrem+X47*BlendedProvPayElite) | AM47: =AE47*PaymentFee | AN47: =Y47*OpsAI | AO47: =MonthlyFixed | AP47: =I47*ReferralReward | AQ47: =G47 | AR47: =AH47-AL47-AM47-AN47-AO47-AP47-AQ47 | AS47: =AS46+AE47-(AL47+AM47+AN47+AO47+AP47+AQ47+AJ47) | AT47: =IF(Y47>0,Z47/Y47,0) | AU47: =IF(Y46>0,MAX(0,(Y46+J47-Y47)/Y46),0)
A48: 44 | B48: =MOD(A48-1+LaunchMonth-1,12)+1 | C48: =INT((A48-1+LaunchMonth-1)/12)+1 | D48: =VLOOKUP(B48,SeasonTable,2,FALSE) | E48: =(1+InflationRate)^INT((A48-1)/12) | F48: =MonthlyChurn*VLOOKUP(B48,ChurnSeasonTable,4,FALSE) | G48: =MIN(MAX(MktMin19plus,AE47*MktPct19plus),MAX(0,AS47-CashBuffer)) | H48: =IF(G48>0,MAX(1,ROUND(G48/CAC*D48,0)),0) | I48: =IF(H48>0,ROUND(H48*ReferralMix/(1-ReferralMix),0),0) | J48: =H48+I48 | K48: =ROUND(J48*(1-AnnualMix),0) | L48: =J48-K48 | M48: =ROUND(K48*EssentialMix,0) | N48: =ROUND(K48*PremiumMix,0) | O48: =K48-M48-N48 | P48: =ROUND(L48*EssentialMix,0) | Q48: =ROUND(L48*PremiumMix,0) | R48: =L48-P48-Q48 | S48: =M48+M47+M46+MAX(0,S47-M47-M46)*(1-F48) | T48: =N48+N47+N46+MAX(0,T47-N47-N46)*(1-F48) | U48: =O48+O47+O46+MAX(0,U47-O47-O46)*(1-F48) | V48: =V47+P48-P36*(AnnualChurn*VLOOKUP(B48,ChurnSeasonTable,4,FALSE))*POWER(1-(AnnualChurn*VLOOKUP(B48,ChurnSeasonTable,4,FALSE)),0)+P24*(AnnualChurn*VLOOKUP(B48,ChurnSeasonTable,4,FALSE))*POWER(1-(AnnualChurn*VLOOKUP(B48,ChurnSeasonTable,4,FALSE)),1)+P12*(AnnualChurn*VLOOKUP(B48,ChurnSeasonTable,4,FALSE))*POWER(1-(AnnualChurn*VLOOKUP(B48,ChurnSeasonTable,4,FALSE)),2) | W48: =W47+Q48-Q36*(AnnualChurn*VLOOKUP(B48,ChurnSeasonTable,4,FALSE))*POWER(1-(AnnualChurn*VLOOKUP(B48,ChurnSeasonTable,4,FALSE)),0)+Q24*(AnnualChurn*VLOOKUP(B48,ChurnSeasonTable,4,FALSE))*POWER(1-(AnnualChurn*VLOOKUP(B48,ChurnSeasonTable,4,FALSE)),1)+Q12*(AnnualChurn*VLOOKUP(B48,ChurnSeasonTable,4,FALSE))*POWER(1-(AnnualChurn*VLOOKUP(B48,ChurnSeasonTable,4,FALSE)),2) | X48: =X47+R48-R36*(AnnualChurn*VLOOKUP(B48,ChurnSeasonTable,4,FALSE))*POWER(1-(AnnualChurn*VLOOKUP(B48,ChurnSeasonTable,4,FALSE)),0)+R24*(AnnualChurn*VLOOKUP(B48,ChurnSeasonTable,4,FALSE))*POWER(1-(AnnualChurn*VLOOKUP(B48,ChurnSeasonTable,4,FALSE)),1)+R12*(AnnualChurn*VLOOKUP(B48,ChurnSeasonTable,4,FALSE))*POWER(1-(AnnualChurn*VLOOKUP(B48,ChurnSeasonTable,4,FALSE)),2) | Y48: =S48+T48+U48+V48+W48+X48 | Z48: =S48*BlendedPriceEssMonthly*E48+T48*BlendedPricePremMonthly*E48+U48*BlendedPriceEliteMonthly*E48+V48*BlendedPriceEssAnnual*E48/12+W48*BlendedPricePremAnnual*E48/12+X48*BlendedPriceEliteAnnual*E48/12 | AA48: =Z48*12 | AB48: =S48*BlendedPriceEssMonthly*E48+T48*BlendedPricePremMonthly*E48+U48*BlendedPriceEliteMonthly*E48 | AC48: =P48*BlendedPriceEssAnnual*E48+Q48*BlendedPricePremAnnual*E48+R48*BlendedPriceEliteAnnual*E48 | AD48: =P36*POWER(1-(AnnualChurn*VLOOKUP(B48,ChurnSeasonTable,4,FALSE)),1)*BlendedPriceEssAnnual*E48+P24*POWER(1-(AnnualChurn*VLOOKUP(B48,ChurnSeasonTable,4,FALSE)),2)*BlendedPriceEssAnnual*E48+P12*POWER(1-(AnnualChurn*VLOOKUP(B48,ChurnSeasonTable,4,FALSE)),3)*BlendedPriceEssAnnual*E48+Q36*POWER(1-(AnnualChurn*VLOOKUP(B48,ChurnSeasonTable,4,FALSE)),1)*BlendedPricePremAnnual*E48+Q24*POWER(1-(AnnualChurn*VLOOKUP(B48,ChurnSeasonTable,4,FALSE)),2)*BlendedPricePremAnnual*E48+Q12*POWER(1-(AnnualChurn*VLOOKUP(B48,ChurnSeasonTable,4,FALSE)),3)*BlendedPricePremAnnual*E48+R36*POWER(1-(AnnualChurn*VLOOKUP(B48,ChurnSeasonTable,4,FALSE)),1)*BlendedPriceEliteAnnual*E48+R24*POWER(1-(AnnualChurn*VLOOKUP(B48,ChurnSeasonTable,4,FALSE)),2)*BlendedPriceEliteAnnual*E48+R12*POWER(1-(AnnualChurn*VLOOKUP(B48,ChurnSeasonTable,4,FALSE)),3)*BlendedPriceEliteAnnual*E48 | AE48: =AB48+AC48+AD48 | AF48: =SUM(AE37:AE48) | AG48: =OR(AG47,IF(VATAgentMode,SUM($AE37:$AE48)-SUM($AL37:$AL48)>=VATThreshold,SUM($AE37:$AE48)>=VATThreshold)) | AH48: =IF(AG48,IF(VATAgentMode,AE48-((AE48-AL48)-(AE48-AL48)/(1+VATRate)),AE48/(1+VATRate)),AE48) | AI48: =AE48-AH48 | AJ48: =IF(AG48=0,0,IF(B48=1,SUMPRODUCT(--(($C$5:$C48=$C48-1)*($B$5:$B48>=10)*($B$5:$B48<=12)),$AI$5:$AI48),IF(B48=4,SUMPRODUCT(--(($C$5:$C48=$C48)*($B$5:$B48>=1)*($B$5:$B48<=3)),$AI$5:$AI48),IF(B48=7,SUMPRODUCT(--(($C$5:$C48=$C48)*($B$5:$B48>=4)*($B$5:$B48<=6)),$AI$5:$AI48),IF(B48=10,SUMPRODUCT(--(($C$5:$C48=$C48)*($B$5:$B48>=7)*($B$5:$B48<=9)),$AI$5:$AI48),0))))) | AK48: =AK47+AI48-AJ48 | AL48: =IF(ProviderDelay>=1,S47*BlendedProvPayEss+T47*BlendedProvPayPrem+U47*BlendedProvPayElite+V47*BlendedProvPayEss+W47*BlendedProvPayPrem+X47*BlendedProvPayElite,S48*BlendedProvPayEss+T48*BlendedProvPayPrem+U48*BlendedProvPayElite+V48*BlendedProvPayEss+W48*BlendedProvPayPrem+X48*BlendedProvPayElite) | AM48: =AE48*PaymentFee | AN48: =Y48*OpsAI | AO48: =MonthlyFixed | AP48: =I48*ReferralReward | AQ48: =G48 | AR48: =AH48-AL48-AM48-AN48-AO48-AP48-AQ48 | AS48: =AS47+AE48-(AL48+AM48+AN48+AO48+AP48+AQ48+AJ48) | AT48: =IF(Y48>0,Z48/Y48,0) | AU48: =IF(Y47>0,MAX(0,(Y47+J48-Y48)/Y47),0)
A49: 45 | B49: =MOD(A49-1+LaunchMonth-1,12)+1 | C49: =INT((A49-1+LaunchMonth-1)/12)+1 | D49: =VLOOKUP(B49,SeasonTable,2,FALSE) | E49: =(1+InflationRate)^INT((A49-1)/12) | F49: =MonthlyChurn*VLOOKUP(B49,ChurnSeasonTable,4,FALSE) | G49: =MIN(MAX(MktMin19plus,AE48*MktPct19plus),MAX(0,AS48-CashBuffer)) | H49: =IF(G49>0,MAX(1,ROUND(G49/CAC*D49,0)),0) | I49: =IF(H49>0,ROUND(H49*ReferralMix/(1-ReferralMix),0),0) | J49: =H49+I49 | K49: =ROUND(J49*(1-AnnualMix),0) | L49: =J49-K49 | M49: =ROUND(K49*EssentialMix,0) | N49: =ROUND(K49*PremiumMix,0) | O49: =K49-M49-N49 | P49: =ROUND(L49*EssentialMix,0) | Q49: =ROUND(L49*PremiumMix,0) | R49: =L49-P49-Q49 | S49: =M49+M48+M47+MAX(0,S48-M48-M47)*(1-F49) | T49: =N49+N48+N47+MAX(0,T48-N48-N47)*(1-F49) | U49: =O49+O48+O47+MAX(0,U48-O48-O47)*(1-F49) | V49: =V48+P49-P37*(AnnualChurn*VLOOKUP(B49,ChurnSeasonTable,4,FALSE))*POWER(1-(AnnualChurn*VLOOKUP(B49,ChurnSeasonTable,4,FALSE)),0)+P25*(AnnualChurn*VLOOKUP(B49,ChurnSeasonTable,4,FALSE))*POWER(1-(AnnualChurn*VLOOKUP(B49,ChurnSeasonTable,4,FALSE)),1)+P13*(AnnualChurn*VLOOKUP(B49,ChurnSeasonTable,4,FALSE))*POWER(1-(AnnualChurn*VLOOKUP(B49,ChurnSeasonTable,4,FALSE)),2) | W49: =W48+Q49-Q37*(AnnualChurn*VLOOKUP(B49,ChurnSeasonTable,4,FALSE))*POWER(1-(AnnualChurn*VLOOKUP(B49,ChurnSeasonTable,4,FALSE)),0)+Q25*(AnnualChurn*VLOOKUP(B49,ChurnSeasonTable,4,FALSE))*POWER(1-(AnnualChurn*VLOOKUP(B49,ChurnSeasonTable,4,FALSE)),1)+Q13*(AnnualChurn*VLOOKUP(B49,ChurnSeasonTable,4,FALSE))*POWER(1-(AnnualChurn*VLOOKUP(B49,ChurnSeasonTable,4,FALSE)),2) | X49: =X48+R49-R37*(AnnualChurn*VLOOKUP(B49,ChurnSeasonTable,4,FALSE))*POWER(1-(AnnualChurn*VLOOKUP(B49,ChurnSeasonTable,4,FALSE)),0)+R25*(AnnualChurn*VLOOKUP(B49,ChurnSeasonTable,4,FALSE))*POWER(1-(AnnualChurn*VLOOKUP(B49,ChurnSeasonTable,4,FALSE)),1)+R13*(AnnualChurn*VLOOKUP(B49,ChurnSeasonTable,4,FALSE))*POWER(1-(AnnualChurn*VLOOKUP(B49,ChurnSeasonTable,4,FALSE)),2) | Y49: =S49+T49+U49+V49+W49+X49 | Z49: =S49*BlendedPriceEssMonthly*E49+T49*BlendedPricePremMonthly*E49+U49*BlendedPriceEliteMonthly*E49+V49*BlendedPriceEssAnnual*E49/12+W49*BlendedPricePremAnnual*E49/12+X49*BlendedPriceEliteAnnual*E49/12 | AA49: =Z49*12 | AB49: =S49*BlendedPriceEssMonthly*E49+T49*BlendedPricePremMonthly*E49+U49*BlendedPriceEliteMonthly*E49 | AC49: =P49*BlendedPriceEssAnnual*E49+Q49*BlendedPricePremAnnual*E49+R49*BlendedPriceEliteAnnual*E49 | AD49: =P37*POWER(1-(AnnualChurn*VLOOKUP(B49,ChurnSeasonTable,4,FALSE)),1)*BlendedPriceEssAnnual*E49+P25*POWER(1-(AnnualChurn*VLOOKUP(B49,ChurnSeasonTable,4,FALSE)),2)*BlendedPriceEssAnnual*E49+P13*POWER(1-(AnnualChurn*VLOOKUP(B49,ChurnSeasonTable,4,FALSE)),3)*BlendedPriceEssAnnual*E49+Q37*POWER(1-(AnnualChurn*VLOOKUP(B49,ChurnSeasonTable,4,FALSE)),1)*BlendedPricePremAnnual*E49+Q25*POWER(1-(AnnualChurn*VLOOKUP(B49,ChurnSeasonTable,4,FALSE)),2)*BlendedPricePremAnnual*E49+Q13*POWER(1-(AnnualChurn*VLOOKUP(B49,ChurnSeasonTable,4,FALSE)),3)*BlendedPricePremAnnual*E49+R37*POWER(1-(AnnualChurn*VLOOKUP(B49,ChurnSeasonTable,4,FALSE)),1)*BlendedPriceEliteAnnual*E49+R25*POWER(1-(AnnualChurn*VLOOKUP(B49,ChurnSeasonTable,4,FALSE)),2)*BlendedPriceEliteAnnual*E49+R13*POWER(1-(AnnualChurn*VLOOKUP(B49,ChurnSeasonTable,4,FALSE)),3)*BlendedPriceEliteAnnual*E49 | AE49: =AB49+AC49+AD49 | AF49: =SUM(AE38:AE49) | AG49: =OR(AG48,IF(VATAgentMode,SUM($AE38:$AE49)-SUM($AL38:$AL49)>=VATThreshold,SUM($AE38:$AE49)>=VATThreshold)) | AH49: =IF(AG49,IF(VATAgentMode,AE49-((AE49-AL49)-(AE49-AL49)/(1+VATRate)),AE49/(1+VATRate)),AE49) | AI49: =AE49-AH49 | AJ49: =IF(AG49=0,0,IF(B49=1,SUMPRODUCT(--(($C$5:$C49=$C49-1)*($B$5:$B49>=10)*($B$5:$B49<=12)),$AI$5:$AI49),IF(B49=4,SUMPRODUCT(--(($C$5:$C49=$C49)*($B$5:$B49>=1)*($B$5:$B49<=3)),$AI$5:$AI49),IF(B49=7,SUMPRODUCT(--(($C$5:$C49=$C49)*($B$5:$B49>=4)*($B$5:$B49<=6)),$AI$5:$AI49),IF(B49=10,SUMPRODUCT(--(($C$5:$C49=$C49)*($B$5:$B49>=7)*($B$5:$B49<=9)),$AI$5:$AI49),0))))) | AK49: =AK48+AI49-AJ49 | AL49: =IF(ProviderDelay>=1,S48*BlendedProvPayEss+T48*BlendedProvPayPrem+U48*BlendedProvPayElite+V48*BlendedProvPayEss+W48*BlendedProvPayPrem+X48*BlendedProvPayElite,S49*BlendedProvPayEss+T49*BlendedProvPayPrem+U49*BlendedProvPayElite+V49*BlendedProvPayEss+W49*BlendedProvPayPrem+X49*BlendedProvPayElite) | AM49: =AE49*PaymentFee | AN49: =Y49*OpsAI | AO49: =MonthlyFixed | AP49: =I49*ReferralReward | AQ49: =G49 | AR49: =AH49-AL49-AM49-AN49-AO49-AP49-AQ49 | AS49: =AS48+AE49-(AL49+AM49+AN49+AO49+AP49+AQ49+AJ49) | AT49: =IF(Y49>0,Z49/Y49,0) | AU49: =IF(Y48>0,MAX(0,(Y48+J49-Y49)/Y48),0)
A50: 46 | B50: =MOD(A50-1+LaunchMonth-1,12)+1 | C50: =INT((A50-1+LaunchMonth-1)/12)+1 | D50: =VLOOKUP(B50,SeasonTable,2,FALSE) | E50: =(1+InflationRate)^INT((A50-1)/12) | F50: =MonthlyChurn*VLOOKUP(B50,ChurnSeasonTable,4,FALSE) | G50: =MIN(MAX(MktMin19plus,AE49*MktPct19plus),MAX(0,AS49-CashBuffer)) | H50: =IF(G50>0,MAX(1,ROUND(G50/CAC*D50,0)),0) | I50: =IF(H50>0,ROUND(H50*ReferralMix/(1-ReferralMix),0),0) | J50: =H50+I50 | K50: =ROUND(J50*(1-AnnualMix),0) | L50: =J50-K50 | M50: =ROUND(K50*EssentialMix,0) | N50: =ROUND(K50*PremiumMix,0) | O50: =K50-M50-N50 | P50: =ROUND(L50*EssentialMix,0) | Q50: =ROUND(L50*PremiumMix,0) | R50: =L50-P50-Q50 | S50: =M50+M49+M48+MAX(0,S49-M49-M48)*(1-F50) | T50: =N50+N49+N48+MAX(0,T49-N49-N48)*(1-F50) | U50: =O50+O49+O48+MAX(0,U49-O49-O48)*(1-F50) | V50: =V49+P50-P38*(AnnualChurn*VLOOKUP(B50,ChurnSeasonTable,4,FALSE))*POWER(1-(AnnualChurn*VLOOKUP(B50,ChurnSeasonTable,4,FALSE)),0)+P26*(AnnualChurn*VLOOKUP(B50,ChurnSeasonTable,4,FALSE))*POWER(1-(AnnualChurn*VLOOKUP(B50,ChurnSeasonTable,4,FALSE)),1)+P14*(AnnualChurn*VLOOKUP(B50,ChurnSeasonTable,4,FALSE))*POWER(1-(AnnualChurn*VLOOKUP(B50,ChurnSeasonTable,4,FALSE)),2) | W50: =W49+Q50-Q38*(AnnualChurn*VLOOKUP(B50,ChurnSeasonTable,4,FALSE))*POWER(1-(AnnualChurn*VLOOKUP(B50,ChurnSeasonTable,4,FALSE)),0)+Q26*(AnnualChurn*VLOOKUP(B50,ChurnSeasonTable,4,FALSE))*POWER(1-(AnnualChurn*VLOOKUP(B50,ChurnSeasonTable,4,FALSE)),1)+Q14*(AnnualChurn*VLOOKUP(B50,ChurnSeasonTable,4,FALSE))*POWER(1-(AnnualChurn*VLOOKUP(B50,ChurnSeasonTable,4,FALSE)),2) | X50: =X49+R50-R38*(AnnualChurn*VLOOKUP(B50,ChurnSeasonTable,4,FALSE))*POWER(1-(AnnualChurn*VLOOKUP(B50,ChurnSeasonTable,4,FALSE)),0)+R26*(AnnualChurn*VLOOKUP(B50,ChurnSeasonTable,4,FALSE))*POWER(1-(AnnualChurn*VLOOKUP(B50,ChurnSeasonTable,4,FALSE)),1)+R14*(AnnualChurn*VLOOKUP(B50,ChurnSeasonTable,4,FALSE))*POWER(1-(AnnualChurn*VLOOKUP(B50,ChurnSeasonTable,4,FALSE)),2) | Y50: =S50+T50+U50+V50+W50+X50 | Z50: =S50*BlendedPriceEssMonthly*E50+T50*BlendedPricePremMonthly*E50+U50*BlendedPriceEliteMonthly*E50+V50*BlendedPriceEssAnnual*E50/12+W50*BlendedPricePremAnnual*E50/12+X50*BlendedPriceEliteAnnual*E50/12 | AA50: =Z50*12 | AB50: =S50*BlendedPriceEssMonthly*E50+T50*BlendedPricePremMonthly*E50+U50*BlendedPriceEliteMonthly*E50 | AC50: =P50*BlendedPriceEssAnnual*E50+Q50*BlendedPricePremAnnual*E50+R50*BlendedPriceEliteAnnual*E50 | AD50: =P38*POWER(1-(AnnualChurn*VLOOKUP(B50,ChurnSeasonTable,4,FALSE)),1)*BlendedPriceEssAnnual*E50+P26*POWER(1-(AnnualChurn*VLOOKUP(B50,ChurnSeasonTable,4,FALSE)),2)*BlendedPriceEssAnnual*E50+P14*POWER(1-(AnnualChurn*VLOOKUP(B50,ChurnSeasonTable,4,FALSE)),3)*BlendedPriceEssAnnual*E50+Q38*POWER(1-(AnnualChurn*VLOOKUP(B50,ChurnSeasonTable,4,FALSE)),1)*BlendedPricePremAnnual*E50+Q26*POWER(1-(AnnualChurn*VLOOKUP(B50,ChurnSeasonTable,4,FALSE)),2)*BlendedPricePremAnnual*E50+Q14*POWER(1-(AnnualChurn*VLOOKUP(B50,ChurnSeasonTable,4,FALSE)),3)*BlendedPricePremAnnual*E50+R38*POWER(1-(AnnualChurn*VLOOKUP(B50,ChurnSeasonTable,4,FALSE)),1)*BlendedPriceEliteAnnual*E50+R26*POWER(1-(AnnualChurn*VLOOKUP(B50,ChurnSeasonTable,4,FALSE)),2)*BlendedPriceEliteAnnual*E50+R14*POWER(1-(AnnualChurn*VLOOKUP(B50,ChurnSeasonTable,4,FALSE)),3)*BlendedPriceEliteAnnual*E50 | AE50: =AB50+AC50+AD50 | AF50: =SUM(AE39:AE50) | AG50: =OR(AG49,IF(VATAgentMode,SUM($AE39:$AE50)-SUM($AL39:$AL50)>=VATThreshold,SUM($AE39:$AE50)>=VATThreshold)) | AH50: =IF(AG50,IF(VATAgentMode,AE50-((AE50-AL50)-(AE50-AL50)/(1+VATRate)),AE50/(1+VATRate)),AE50) | AI50: =AE50-AH50 | AJ50: =IF(AG50=0,0,IF(B50=1,SUMPRODUCT(--(($C$5:$C50=$C50-1)*($B$5:$B50>=10)*($B$5:$B50<=12)),$AI$5:$AI50),IF(B50=4,SUMPRODUCT(--(($C$5:$C50=$C50)*($B$5:$B50>=1)*($B$5:$B50<=3)),$AI$5:$AI50),IF(B50=7,SUMPRODUCT(--(($C$5:$C50=$C50)*($B$5:$B50>=4)*($B$5:$B50<=6)),$AI$5:$AI50),IF(B50=10,SUMPRODUCT(--(($C$5:$C50=$C50)*($B$5:$B50>=7)*($B$5:$B50<=9)),$AI$5:$AI50),0))))) | AK50: =AK49+AI50-AJ50 | AL50: =IF(ProviderDelay>=1,S49*BlendedProvPayEss+T49*BlendedProvPayPrem+U49*BlendedProvPayElite+V49*BlendedProvPayEss+W49*BlendedProvPayPrem+X49*BlendedProvPayElite,S50*BlendedProvPayEss+T50*BlendedProvPayPrem+U50*BlendedProvPayElite+V50*BlendedProvPayEss+W50*BlendedProvPayPrem+X50*BlendedProvPayElite) | AM50: =AE50*PaymentFee | AN50: =Y50*OpsAI | AO50: =MonthlyFixed | AP50: =I50*ReferralReward | AQ50: =G50 | AR50: =AH50-AL50-AM50-AN50-AO50-AP50-AQ50 | AS50: =AS49+AE50-(AL50+AM50+AN50+AO50+AP50+AQ50+AJ50) | AT50: =IF(Y50>0,Z50/Y50,0) | AU50: =IF(Y49>0,MAX(0,(Y49+J50-Y50)/Y49),0)
