Workbook
Name InitialInvestment: Inputs!$B$5
Name PriceEssMonthly: Inputs!$B$8
Name PricePremMonthly: Inputs!$B$9
Name PriceEssAnnual: Inputs!$B$10
Name PricePremAnnual: Inputs!$B$11
Name AnnualMix: Inputs!$B$14
Name EssentialMix: Inputs!$B$15
Name MonthlyChurn: Inputs!$B$18
Name AnnualChurn: Inputs!$B$19
Name CAC: Inputs!$B$22
Name ProviderShare: Inputs!$B$23
Name PaymentFee: Inputs!$B$24
Name OpsAI: Inputs!$B$25
Name ProviderDelay: Inputs!$B$27
Name MonthlyFixed: Inputs!$B$28
Name MktFixed1_3: Inputs!$B$31
Name MktFixed4_6: Inputs!$B$32
Name MktPct7_12: Inputs!$B$33
Name MktPct13_18: Inputs!$B$34
Name MktPct19plus: Inputs!$B$35
Name MktMin7_12: Inputs!$B$36
Name MktMin13_18: Inputs!$B$37
Name MktMin19plus: Inputs!$B$38
Name CashBuffer: Inputs!$B$39
Name InflationRate: Inputs!$B$48
Name ReferralMix: Inputs!$B$49
Name ReferralReward: Inputs!$B$50
Name LaunchMonth: Inputs!$B$51
Name AcqSeasonTable: Inputs!$A$55:$C$66
Name ChurnSeasonTable: Inputs!$A$55:$D$66
Name SeasonTable: Inputs!$A$55:$B$66
Name VATRate: Inputs!$B$42
Name VATThreshold: Inputs!$B$43
Name MRR_Month12: Model!$V$16
Name ARR_Month12: Model!$W$16
Name Cust_Month12: Model!$U$16
Name Cash_Month12: Model!$AO$16
Name MRR_Month24: Model!$V$28
Name ARR_Month24: Model!$W$28
Name Cust_Month24: Model!$U$28
Name Cash_Month24: Model!$AO$28
Name MRR_Month60: Model!$V$64
Name ARR_Month60: Model!$W$64
Name Cust_Month60: Model!$U$64
Name Cash_Month60: Model!$AO$64
Name WinterPivotSeasonTable: Inputs!$A$55:$E$66
Name WinterPivotChurnTable: Inputs!$A$55:$F$66

Sheet Headlines
A1: GardensSorted — Financial Headlines
A2: Calendar VAT quarters | seasonal churn | provider delay | referrals | inflation
A4: KEY METRICS
A5: Y1 ARR | C5: Y2 ARR | E5: Y5 ARR | G5: Cash Y5
A6: =Model!W16 | C6: =Model!W28 | E6: =Model!W64 | G6: =Model!AO64
A8: SNAPSHOT
A9: Metric | B9: Year 1 | C9: Year 2 | D9: Year 5
A10: End customers | B10: =Model!U16 | C10: =Model!U28 | D10: =Model!U64
A11: ARR | B11: =Model!W16 | C11: =Model!W28 | D11: =Model!W64
A12: Gross revenue | B12: =SUM(Model!AA5:AA16) | C12: =SUM(Model!AA17:AA28) | D12: =SUM(Model!AA53:AA64)
A13: Net revenue | B13: =SUM(Model!AD5:AD16) | C13: =SUM(Model!AD17:AD28) | D13: =SUM(Model!AD53:AD64)
A14: VAT paid (calendar Q) | B14: =SUM(Model!AF5:AF16) | C14: =SUM(Model!AF17:AF28) | D14: =SUM(Model!AF53:AF64)
A15: Annual profit | B15: =SUM(Model!AN5:AN16) | C15: =SUM(Model!AN17:AN28) | D15: =SUM(Model!AN53:AN64)
A16: Cash balance | B16: =Model!AO16 | C16: =Model!AO28 | D16: =Model!AO64
A17: Avg logo churn | B17: =AVERAGE(Model!AQ6:AQ16) | C17: =AVERAGE(Model!AQ18:AQ28) | D17: =AVERAGE(Model!AQ54:AQ64)
A18: Platform margin | B18: ='5 Year Summary'!T4 | C18: ='5 Year Summary'!T5 | D18: ='5 Year Summary'!T8
A20: MILESTONES
A21: VAT registration | B21: =IFERROR("Month "&MATCH(TRUE,Model!AC5:Model!AC64,0),"Not in 60 mo")
A22: First profitable month | B22: =IFERROR("Month "&MATCH(1,IF(Model!AN5:AN64>0,1),0),"Not in 60 mo")
A23: Cash payback £17k | B23: =IFERROR("Month "&MATCH(1,IF(Model!AO5:AO64>=InitialInvestment,1),0),"Not in 60 mo")
A24: Provider payment delay | B24: =ProviderDelay&" month(s)"
A25: Fixed platform cost | B25: =MonthlyFixed
A27: MODEL COMPLETENESS
A28: ✓ SaaS cohorts — monthly (3-mo min) & annual (12-mo) subs, MRR/ARR, tier pricing
A29: ✓ VAT at £90k threshold — calendar quarter payments (Jan/Apr/Jul/Oct)
A30: ✓ Seasonal acquisition (col B) & churn (col D) — gardening seasonality
A31: ✓ Referrals 15% / £15 | Inflation 2.5%/yr | Upfront billing | £17k startup
A32: ✓ Provider delay 1 mo (customer upfront → cash float) | Fixed platform £250/mo
A33: ✓ Per-customer ops/AI £5/mo | Marketing phased with cash cap | No salaries (AI ops)
A34: ✓ Sensitivity tabs — churn, mix, CAC, scenarios, winter pivot
A36: NOT MODELLED (by design or later)
A37: • Corporation tax (~19–25%) — add when consistently profitable
A38: • Route density / travel efficiency in clustered postcodes
A39: • Cross-sell to other Sorted brands | Geographic rollout phasing
... A43: WHERE TO GO NEXT
A44: Inputs | B44: All assumptions
A45: 5 Year Summary | B45: Annual P&L
A46: 24 Month Forecast | B46: Monthly detail
A47: Unit Economics | B47: LTV & CAC

Sheet Assumptions
A1: Assumptions & Methodology (values linked to Inputs sheet)
A2: Edit yellow cells on the Inputs sheet — all tabs update automatically.
A4: Parameter | B4: Live Value | C4: Notes
A5: Initial investment | B5: =InitialInvestment | C5: Total startup capital
A6: Essential Monthly | B6: =PriceEssMonthly | C6: 3-month minimum term
A7: Premium Monthly | B7: =PricePremMonthly | C7: 3-month minimum term
A8: Essential Annual | B8: =PriceEssAnnual | C8: 12-month commitment
A9: Premium Annual | B9: =PricePremAnnual | C9: 12-month commitment
A10: Annual plan mix | B10: =AnnualMix | C10: Industry B2C: 15–25%
A11: Essential tier mix | B11: =EssentialMix | C11: Within each billing type
A12: Monthly churn (post min term) | B12: =MonthlyChurn | C12: Home services B2C: 4–7%/mo
A13: Annual churn (at renewal) | B13: =AnnualChurn | C13: B2C annual: 15–25%
A14: CAC | B14: =CAC | C14: Paid acquisition; base £70 (industry £50–80 paid, £100–120 conservative)
A15: Provider share | B15: =ProviderShare | C15: Contractor payout
A16: Payment fees | B16: =PaymentFee | C16: Stripe processing
A17: Ops + AI per customer | B17: =OpsAI | C17: Per active subscriber/month
A18: Months 1–3 marketing | B18: =MktFixed1_3 | C18: Soft launch
A19: Months 4–6 marketing | B19: =MktFixed4_6 | C19: Ramp phase
A20: Cash buffer | B20: =CashBuffer | C20: Marketing cap reserve
A21: VAT rate | B21: =VATRate | C21: Once registered
A22: VAT threshold | B22: =VATThreshold | C22: Rolling 12-mo gross
A23: Inflation | B23: =InflationRate | C23: Annual price uplift
A24: Referral mix | B24: =ReferralMix | C24: Zero-CAC channel
A25: Referral reward | B25: =ReferralReward | C25: Per referral
A26: Launch month | B26: =LaunchMonth | C26: Seasonality anchor
A27: Seasonal churn table | B27: Inputs col D
A28: VAT payment | B28: Calendar quarters (Jan/Apr/Jul/Oct) | C28: Preceding calendar quarter
A29: Winter pivot seasonality | B29: Inputs cols E & F | C29: Sens - Winter Pivot tab — gutter/leaf/patio Oct–Feb

Sheet Inputs
A1: Sorted — SaaS Forecast Inputs (edit yellow cells)
A2: All forecast sheets recalculate automatically when you change inputs below.
A3: Parameter | B3: Value | C3: Notes
A4: INITIAL INVESTMENT
A5: Initial investment (£) | B5: 17000 | C5: Total startup capital available
A7: SUBSCRIPTION PRICING
A8: Essential Monthly (£/mo) | B8: 29.95 | C8: 3-month minimum term
A9: Premium Monthly (£/mo) | B9: 49.95 | C9: 3-month minimum term
A10: Essential Annual (£/yr) | B10: 299.95 | C10: 12-month commitment
A11: Premium Annual (£/yr) | B11: 499.95 | C11: 12-month commitment
A13: PLAN MIX
A14: Annual plan mix (%) | B14: 0.2 | C14: Industry B2C benchmark: 15–25%
A15: Essential tier mix (%) | B15: 0.7 | C15: Within each billing type
A17: CHURN (edit for sensitivity)
A18: Monthly plan churn — post min term (%/mo) | B18: 0.055 | C18: Home services B2C: 4–7%. Applied after month 3.
A19: Annual plan churn — at renewal (%/yr) | B19: 0.2 | C19: B2C annual renewal: 15–25%
A21: UNIT ECONOMICS
A22: Customer Acquisition Cost — CAC (£) | B22: 70 | C22: Paid acquisition per customer. Base £50–80 (B2C home services); ~⅓ yr-1 revenue ≈ £100–120 conservative
A23: Provider payout share (%) | B23: 0.6 | C23: Contractor share of revenue
A24: Payment processing fee (%) | B24: 0.03 | C24: Stripe/card fees
A25: Ops + AI cost per customer (£/mo) | B25: 5 | C25: Support, hosting, AI per active sub
A26: CASH TIMING
A27: Provider payment delay (months) | B27: 1 | C27: Providers invoiced ~30 days after service — cash float benefit
A28: Monthly fixed platform cost (£) | B28: 250 | C28: Hosting, AI base, tools — excludes per-customer ops
A29: VAT payment timing | B29: Calendar quarters | C29: Jan/Apr/Jul/Oct for preceding calendar quarter (UK)
A30: MARKETING SPEND
A31: Months 1–3 fixed spend (£/mo) | B31: 1500 | C31: Soft launch phase
A32: Months 4–6 fixed spend (£/mo) | B32: 2500 | C32: Ramp phase — capped by cash buffer from month 4
A33: Months 7–12 — % of prior month revenue | B33: 0.12 | C33: Scales with revenue
A34: Months 13–18 — % of prior month revenue | B34: 0.1
A35: Months 19+ — % of prior month revenue | B35: 0.08
A36: Min marketing months 7–12 (£/mo) | B36: 3000 | C36: Floor spend
A37: Min marketing months 13–18 (£/mo) | B37: 4000 | C37: Floor spend
A38: Min marketing months 19+ (£/mo) | B38: 5000 | C38: Floor spend
A39: Cash buffer retained (£) | B39: 2000 | C39: Min cash kept before marketing cap
A41: VAT
A42: VAT rate (%) | B42: 0.2 | C42: Standard rate once registered
A43: VAT registration threshold (£) | B43: 90000 | C43: Rolling 12-month gross turnover
A44: Prices are VAT-inclusive | B44: Yes | C44: B2C VAT-inclusive pricing; VAT paid quarterly to HMRC
A47: GROWTH & PRICING
A48: Annual price increase / inflation (%) | B48: 0.025 | C48: Applied each model year to all subs
A49: Referral mix (% of new customers) | B49: 0.15 | C49: 10–20% industry benchmark
A50: Referral reward (£ per referral) | B50: 15 | C50: One-off — no marketing cost
A51: Launch calendar month (1=Jan … 12=Dec) | B51: 3 | C51: March = pre-season launch
A53: SEASONALITY — acquisition multiplier by calendar month
A54: Month | B54: Multiplier | C54: Notes | D54: Churn mult | E54: Pivot acq | F54: Pivot churn
A55: 1 | B55: 0.56 | C55: Low | pivot acq ×1.29, churn ×0.79 | D55: 1.37 | E55: 0.72 | F55: 1.08
A56: 2 | B56: 0.66 | C56: Pre-season | pivot acq ×1.24, churn ×0.82 | D56: 1.28 | E56: 0.82 | F56: 1.05
A57: 3 | B57: 0.87 | C57: Spring | churn ×1.04 | D57: 1.04 | E57: 0.87 | F57: 1.04
A58: 4 | B58: 1.07 | C58: Ramp | churn ×0.85 | D58: 0.85 | E58: 1.07 | F58: 0.85
A59: 5 | B59: 1.17 | C59: Peak | churn ×0.76 | D59: 0.76 | E59: 1.17 | F59: 0.76
A60: 6 | B60: 1.22 | C60: Peak | churn ×0.71 | D60: 0.71 | E60: 1.22 | F60: 0.71
A61: 7 | B61: 1.22 | C61: Peak | churn ×0.71 | D61: 0.71 | E61: 1.22 | F61: 0.71
A62: 8 | B62: 1.17 | C62: Peak | churn ×0.76 | D62: 0.76 | E62: 1.17 | F62: 0.76
A63: 9 | B63: 1.02 | C63: Shoulder | churn ×0.90 | D63: 0.9 | E63: 1.02 | F63: 0.9
A64: 10 | B64: 0.82 | C64: Wind-down | pivot acq ×1.22, churn ×0.94 | D64: 1.04 | E64: 1 | F64: 0.98
A65: 11 | B65: 0.61 | C65: Low | pivot acq ×1.72, churn ×0.77 | D65: 1.23 | E65: 1.05 | F65: 0.95
A66: 12 | B66: 0.56 | C66: Low | pivot acq ×1.39, churn ×0.79 | D66: 1.37 | E66: 0.78 | F66: 1.08
A67: WINTER PIVOT SEASONALITY (property care — gutter, leaf, patio)
A68: Used by Sens - Winter Pivot scenario. Oct–Nov boosted for leaf/gutter; winter churn reduced (customers stay on year-round plan).
A69: Start on Headlines tab.
A70: Edit yellow cells — all tabs recalculate.
A71: Seasonality affects paid acquisition by calendar month.
A72: VAT applies once rolling 12-mo gross exceeds threshold.

Sheet 5 Year Summary
A1: 5-Year Summary
A3: Year | B3: Cust | C3: MRR | D3: ARR | E3: Paid | F3: Referrals | G3: Gross | H3: Net | I3: VAcc | J3: VPay | K3: VBal | L3: Prov | M3: Fees | N3: Ops | O3: Fixed | P3: Ref£ | Q3: Mkt | R3: Profit | S3: Cash | T3: Margin | U3: Prov# | V3: MRRGr | W3: Churn | X3: CumPft
A4: Year 1 | B4: =Model!U16 | C4: =Model!V16 | D4: =Model!W16 | E4: =SUM(Model!H5:H16) | F4: =SUM(Model!I5:I16) | G4: =SUM(Model!AA5:AA16) | H4: =SUM(Model!AD5:AD16) | I4: =SUM(Model!AE5:AE16) | J4: =SUM(Model!AF5:AF16) | K4: =Model!AG16 | L4: =SUM(Model!AH5:AH16) | M4: =SUM(Model!AI5:AI16) | N4: =SUM(Model!AJ5:AJ16) | O4: =SUM(Model!AK5:AK16) | P4: =SUM(Model!AL5:AL16) | Q4: =SUM(Model!AM5:AM16) | R4: =SUM(Model!AN5:AN16) | S4: =Model!AO16 | T4: =IF(G4>0,(H4-L4-M4-N4-O4)/G4,0) | U4: =ROUNDUP(B4/140,0) | V4: — | W4: =AVERAGE(Model!AQ6:AQ16) | X4: =SUM($R$4:R4)
A5: Year 2 | B5: =Model!U28 | C5: =Model!V28 | D5: =Model!W28 | E5: =SUM(Model!H17:H28) | F5: =SUM(Model!I17:I28) | G5: =SUM(Model!AA17:AA28) | H5: =SUM(Model!AD17:AD28) | I5: =SUM(Model!AE17:AE28) | J5: =SUM(Model!AF17:AF28) | K5: =Model!AG28 | L5: =SUM(Model!AH17:AH28) | M5: =SUM(Model!AI17:AI28) | N5: =SUM(Model!AJ17:AJ28) | O5: =SUM(Model!AK17:AK28) | P5: =SUM(Model!AL17:AL28) | Q5: =SUM(Model!AM17:AM28) | R5: =SUM(Model!AN17:AN28) | S5: =Model!AO28 | T5: =IF(G5>0,(H5-L5-M5-N5-O5)/G5,0) | U5: =ROUNDUP(B5/140,0) | V5: =(C5-C4)/C4 | W5: =AVERAGE(Model!AQ18:AQ28) | X5: =SUM($R$4:R5)
A6: Year 3 | B6: =Model!U40 | C6: =Model!V40 | D6: =Model!W40 | E6: =SUM(Model!H29:H40) | F6: =SUM(Model!I29:I40) | G6: =SUM(Model!AA29:AA40) | H6: =SUM(Model!AD29:AD40) | I6: =SUM(Model!AE29:AE40) | J6: =SUM(Model!AF29:AF40) | K6: =Model!AG40 | L6: =SUM(Model!AH29:AH40) | M6: =SUM(Model!AI29:AI40) | N6: =SUM(Model!AJ29:AJ40) | O6: =SUM(Model!AK29:AK40) | P6: =SUM(Model!AL29:AL40) | Q6: =SUM(Model!AM29:AM40) | R6: =SUM(Model!AN29:AN40) | S6: =Model!AO40 | T6: =IF(G6>0,(H6-L6-M6-N6-O6)/G6,0) | U6: =ROUNDUP(B6/140,0) | V6: =(C6-C5)/C5 | W6: =AVERAGE(Model!AQ30:AQ40) | X6: =SUM($R$4:R6)
A7: Year 4 | B7: =Model!U52 | C7: =Model!V52 | D7: =Model!W52 | E7: =SUM(Model!H41:H52) | F7: =SUM(Model!I41:I52) | G7: =SUM(Model!AA41:AA52) | H7: =SUM(Model!AD41:AD52) | I7: =SUM(Model!AE41:AE52) | J7: =SUM(Model!AF41:AF52) | K7: =Model!AG52 | L7: =SUM(Model!AH41:AH52) | M7: =SUM(Model!AI41:AI52) | N7: =SUM(Model!AJ41:AJ52) | O7: =SUM(Model!AK41:AK52) | P7: =SUM(Model!AL41:AL52) | Q7: =SUM(Model!AM41:AM52) | R7: =SUM(Model!AN41:AN52) | S7: =Model!AO52 | T7: =IF(G7>0,(H7-L7-M7-N7-O7)/G7,0) | U7: =ROUNDUP(B7/140,0) | V7: =(C7-C6)/C6 | W7: =AVERAGE(Model!AQ42:AQ52) | X7: =SUM($R$4:R7)
A8: Year 5 | B8: =Model!U64 | C8: =Model!V64 | D8: =Model!W64 | E8: =SUM(Model!H53:H64) | F8: =SUM(Model!I53:I64) | G8: =SUM(Model!AA53:AA64) | H8: =SUM(Model!AD53:AD64) | I8: =SUM(Model!AE53:AE64) | J8: =SUM(Model!AF53:AF64) | K8: =Model!AG64 | L8: =SUM(Model!AH53:AH64) | M8: =SUM(Model!AI53:AI64) | N8: =SUM(Model!AJ53:AJ64) | O8: =SUM(Model!AK53:AK64) | P8: =SUM(Model!AL53:AL64) | Q8: =SUM(Model!AM53:AM64) | R8: =SUM(Model!AN53:AN64) | S8: =Model!AO64 | T8: =IF(G8>0,(H8-L8-M8-N8-O8)/G8,0) | U8: =ROUNDUP(B8/140,0) | V8: =(C8-C7)/C7 | W8: =AVERAGE(Model!AQ54:AQ64) | X8: =SUM($R$4:R8)
A10: VAT registration | B10: =IFERROR("Month "&MATCH(TRUE,Model!AC5:Model!AC64,0),"Not in 60 mo")
A11: VAT payments | B11: Calendar: Jan=Q4 prior yr, Apr=Q1, Jul=Q2, Oct=Q3

Sheet 24 Month Forecast
A1: 24-Month Forecast
A3: Month | B3: CalMo | C3: Paid | D3: Referral | E3: Total | F3: Cust | G3: EffChurn | H3: MRR | I3: ARR | J3: Gross | K3: Net | L3: VAcc | M3: VPay | N3: VBal | O3: Prov | P3: Fees | Q3: Ops | R3: Fixed | S3: Ref£ | T3: Mkt | U3: Pft | V3: Cash | W3: Churn
A4: Month 1 | B4: =Model!B5 | C4: =Model!H5 | D4: =Model!I5 | E4: =Model!J5 | F4: =Model!U5 | G4: =Model!F5 | H4: =Model!V5 | I4: =Model!W5 | J4: =Model!AA5 | K4: =Model!AD5 | L4: =Model!AE5 | M4: =Model!AF5 | N4: =Model!AG5 | O4: =Model!AH5 | P4: =Model!AI5 | Q4: =Model!AJ5 | R4: =Model!AK5 | ... V4: =Model!AO5 | W4: =Model!AQ5
A5: Month 2 | B5: =Model!B6 | C5: =Model!H6 | D5: =Model!I6 | E5: =Model!J6 | F5: =Model!U6 | G5: =Model!F6 | H5: =Model!V6 | I5: =Model!W6 | J5: =Model!AA6 | K5: =Model!AD6 | L5: =Model!AE6 | M5: =Model!AF6 | N5: =Model!AG6 | O5: =Model!AH6 | P5: =Model!AI6 | Q5: =Model!AJ6 | R5: =Model!AK6 | ... V5: =Model!AO6 | W5: =Model!AQ6
A6: Month 3 | B6: =Model!B7 | C6: =Model!H7 | D6: =Model!I7 | E6: =Model!J7 | F6: =Model!U7 | G6: =Model!F7 | H6: =Model!V7 | I6: =Model!W7 | J6: =Model!AA7 | K6: =Model!AD7 | L6: =Model!AE7 | M6: =Model!AF7 | N6: =Model!AG7 | O6: =Model!AH7 | P6: =Model!AI7 | Q6: =Model!AJ7 | R6: =Model!AK7 | ... V6: =Model!AO7 | W6: =Model!AQ7
A7: Month 4 | B7: =Model!B8 | C7: =Model!H8 | D7: =Model!I8 | E7: =Model!J8 | F7: =Model!U8 | G7: =Model!F8 | H7: =Model!V8 | I7: =Model!W8 | J7: =Model!AA8 | K7: =Model!AD8 | L7: =Model!AE8 | M7: =Model!AF8 | N7: =Model!AG8 | O7: =Model!AH8 | P7: =Model!AI8 | Q7: =Model!AJ8 | R7: =Model!AK8 | ... V7: =Model!AO8 | W7: =Model!AQ8
A8: Month 5 | B8: =Model!B9 | C8: =Model!H9 | D8: =Model!I9 | E8: =Model!J9 | F8: =Model!U9 | G8: =Model!F9 | H8: =Model!V9 | I8: =Model!W9 | J8: =Model!AA9 | K8: =Model!AD9 | L8: =Model!AE9 | M8: =Model!AF9 | N8: =Model!AG9 | O8: =Model!AH9 | P8: =Model!AI9 | Q8: =Model!AJ9 | R8: =Model!AK9 | ... V8: =Model!AO9 | W8: =Model!AQ9
A9: Month 6 | B9: =Model!B10 | C9: =Model!H10 | D9: =Model!I10 | E9: =Model!J10 | F9: =Model!U10 | G9: =Model!F10 | H9: =Model!V10 | I9: =Model!W10 | J9: =Model!AA10 | K9: =Model!AD10 | L9: =Model!AE10 | M9: =Model!AF10 | N9: =Model!AG10 | O9: =Model!AH10 | P9: =Model!AI10 | Q9: =Model!AJ10 | R9: =Model!AK10 | ... V9: =Model!AO10 | W9: =Model!AQ10
A10: Month 7 | B10: =Model!B11 | C10: =Model!H11 | D10: =Model!I11 | E10: =Model!J11 | F10: =Model!U11 | G10: =Model!F11 | H10: =Model!V11 | I10: =Model!W11 | J10: =Model!AA11 | K10: =Model!AD11 | L10: =Model!AE11 | M10: =Model!AF11 | N10: =Model!AG11 | O10: =Model!AH11 | P10: =Model!AI11 | Q10: =Model!AJ11 | R10: =Model!AK11 | ... V10: =Model!AO11 | W10: =Model!AQ11
A11: Month 8 | B11: =Model!B12 | C11: =Model!H12 | D11: =Model!I12 | E11: =Model!J12 | F11: =Model!U12 | G11: =Model!F12 | H11: =Model!V12 | I11: =Model!W12 | J11: =Model!AA12 | K11: =Model!AD12 | L11: =Model!AE12 | M11: =Model!AF12 | N11: =Model!AG12 | O11: =Model!AH12 | P11: =Model!AI12 | Q11: =Model!AJ12 | R11: =Model!AK12 | ... V11: =Model!AO12 | W11: =Model!AQ12
A12: Month 9 | B12: =Model!B13 | C12: =Model!H13 | D12: =Model!I13 | E12: =Model!J13 | F12: =Model!U13 | G12: =Model!F13 | H12: =Model!V13 | I12: =Model!W13 | J12: =Model!AA13 | K12: =Model!AD13 | L12: =Model!AE13 | M12: =Model!AF13 | N12: =Model!AG13 | O12: =Model!AH13 | P12: =Model!AI13 | Q12: =Model!AJ13 | R12: =Model!AK13 | ... V12: =Model!AO13 | W12: =Model!AQ13
A13: Month 10 | B13: =Model!B14 | C13: =Model!H14 | D13: =Model!I14 | E13: =Model!J14 | F13: =Model!U14 | G13: =Model!F14 | H13: =Model!V14 | I13: =Model!W14 | J13: =Model!AA14 | K13: =Model!AD14 | L13: =Model!AE14 | M13: =Model!AF14 | N13: =Model!AG14 | O13: =Model!AH14 | P13: =Model!AI14 | Q13: =Model!AJ14 | R13: =Model!AK14 | ... V13: =Model!AO14 | W13: =Model!AQ14
A14: Month 11 | B14: =Model!B15 | C14: =Model!H15 | D14: =Model!I15 | E14: =Model!J15 | F14: =Model!U15 | G14: =Model!F15 | H14: =Model!V15 | I14: =Model!W15 | J14: =Model!AA15 | K14: =Model!AD15 | L14: =Model!AE15 | M14: =Model!AF15 | N14: =Model!AG15 | O14: =Model!AH15 | P14: =Model!AI15 | Q14: =Model!AJ15 | R14: =Model!AK15 | ... V14: =Model!AO15 | W14: =Model!AQ15
A15: Month 12 | B15: =Model!B16 | C15: =Model!H16 | D15: =Model!I16 | E15: =Model!J16 | F15: =Model!U16 | G15: =Model!F16 | H15: =Model!V16 | I15: =Model!W16 | J15: =Model!AA16 | K15: =Model!AD16 | L15: =Model!AE16 | M15: =Model!AF16 | N15: =Model!AG16 | O15: =Model!AH16 | P15: =Model!AI16 | Q15: =Model!AJ16 | R15: =Model!AK16 | ... V15: =Model!AO16 | W15: =Model!AQ16
... A27: Month 24 | B27: =Model!B28 | C27: =Model!H28 | D27: =Model!I28 | E27: =Model!J28 | F27: =Model!U28 | G27: =Model!F28 | H27: =Model!V28 | I27: =Model!W28 | J27: =Model!AA28 | K27: =Model!AD28 | L27: =Model!AE28 | M27: =Model!AF28 | N27: =Model!AG28 | O27: =Model!AH28 | P27: =Model!AI28 | Q27: =Model!AJ28 | R27: =Model!AK28 | ... V27: =Model!AO28 | W27: =Model!AQ28

Sheet Unit Economics
A1: Unit Economics (calculated from Inputs)
A3: Metric | B3: Value | C3: Unit
A4: Blended ARPU (MRR per customer) | B4: =EssentialMix*(1-AnnualMix)*PriceEssMonthly+(1-EssentialMix)*(1-AnnualMix)*PricePremMonthly+EssentialMix*AnnualMix*PriceEssAnnual/12+(1-EssentialMix)*AnnualMix*PricePremAnnual/12 | C4: £/mo
A5: Monthly plan ARPU | B5: =EssentialMix*PriceEssMonthly+(1-EssentialMix)*PricePremMonthly | C5: £/mo
A6: Annual plan ARPU (normalised) | B6: =EssentialMix*PriceEssAnnual/12+(1-EssentialMix)*PricePremAnnual/12 | C6: £/mo
A8: Provider cost per customer | B8: =B4*ProviderShare | C8: £/mo
A9: Payment fees per customer | B9: =B4*PaymentFee | C9: £/mo
A10: Ops + AI per customer | B10: =OpsAI | C10: £/mo
A12: Gross margin per customer (pre-marketing) | B12: =B4*(1-ProviderShare-PaymentFee)-OpsAI | C12: £/mo
A13: CAC | B13: =CAC | C13: £
A14: Months to recover CAC | B14: =B13/B12 | C14: months
A16: Customer lifetime — monthly plan (post min term) | B16: =1/MonthlyChurn | C16: months
A17: Expected annual renewals — annual plan | B17: =1/AnnualChurn | C17: renewals
A18: LTV — monthly plan (simplified) | B18: =B5*(1-ProviderShare-PaymentFee)*(1/MonthlyChurn) | C18: £
A19: LTV — annual plan (simplified) | B19: =B6*12*(1-ProviderShare-PaymentFee)*(1/AnnualChurn) | C19: £
A20: LTV:CAC — monthly plan | B20: =B18/CAC | C20: x
A21: LTV:CAC — blended | B21: =B4*(1-ProviderShare-PaymentFee)*((1-AnnualMix)/MonthlyChurn+AnnualMix*12/AnnualChurn)/CAC | C21: x
A22: Inflated ARPU (Year 2 prices) | B22: =B4*(1+InflationRate) | C22: £/mo
A23: Effective CAC (paid customers only) | B23: =CAC | C23: £
A24: Blended CAC (incl. referrals) | B24: =CAC*(1-ReferralMix) | C24: £/customer
A25: Monthly fixed platform cost | B25: =MonthlyFixed | C25: £/mo

Sheet Sens - Scenarios
A1: Scenario Comparison — Conservative / Base / Aggressive (full model engine)
A2: Edit yellow cells in Conservative & Aggressive columns. Base uses live Inputs (£70 CAC). Marketing spend: Inputs rows 31–39.
A4: Parameter | B4: Conservative | C4: Base (live Inputs) | D4: Aggressive
A5: Monthly churn (post min term) | B5: 0.07 | C5: =MonthlyChurn | D5: 0.04
A6: Annual churn (at renewal) | B6: 0.25 | C6: =AnnualChurn | D6: 0.15
A7: Annual plan mix | B7: 0.15 | C7: =AnnualMix | D7: 0.3
A8: CAC (£) | B8: 110 | C8: =CAC | D8: 40
A11: OUTPUT METRICS
A12: Metric | B12: Conservative | C12: Base | D12: Aggressive
A13: End Year 1 — Customers | B13: ='Scenario Engine'!U$16 | C13: ='Scenario Engine'!BM$16 | D13: ='Scenario Engine'!DE$16
A14: End Year 1 — MRR (£) | B14: ='Scenario Engine'!V$16 | C14: ='Scenario Engine'!BN$16 | D14: ='Scenario Engine'!DF$16
A15: End Year 1 — ARR (£) | B15: ='Scenario Engine'!W$16 | C15: ='Scenario Engine'!BO$16 | D15: ='Scenario Engine'!DG$16
A16: End Year 1 — Cash Balance (£) | B16: ='Scenario Engine'!AO$16 | C16: ='Scenario Engine'!CG$16 | D16: ='Scenario Engine'!DY$16
A17: Year 1 — Gross Revenue (£) | B17: =SUM('Scenario Engine'!AA$5:'Scenario Engine'!AA$16) | C17: =SUM('Scenario Engine'!BS$5:'Scenario Engine'!BS$16) | D17: =SUM('Scenario Engine'!DK$5:'Scenario Engine'!DK$16)
A18: Year 1 — Net Revenue (£) | B18: =SUM('Scenario Engine'!AD$5:'Scenario Engine'!AD$16) | C18: =SUM('Scenario Engine'!BV$5:'Scenario Engine'!BV$16) | D18: =SUM('Scenario Engine'!DN$5:'Scenario Engine'!DN$16)
A19: Year 1 — Profit (£) | B19: =SUM('Scenario Engine'!AN$5:'Scenario Engine'!AN$16) | C19: =SUM('Scenario Engine'!CF$5:'Scenario Engine'!CF$16) | D19: =SUM('Scenario Engine'!DX$5:'Scenario Engine'!DX$16)
A20: End Year 2 — Customers | B20: ='Scenario Engine'!U$28 | C20: ='Scenario Engine'!BM$28 | D20: ='Scenario Engine'!DE$28
A21: End Year 2 — MRR (£) | B21: ='Scenario Engine'!V$28 | C21: ='Scenario Engine'!BN$28 | D21: ='Scenario Engine'!DF$28
A22: End Year 2 — ARR (£) | B22: ='Scenario Engine'!W$28 | C22: ='Scenario Engine'!BO$28 | D22: ='Scenario Engine'!DG$28
A23: End Year 2 — Cash Balance (£) | B23: ='Scenario Engine'!AO$28 | C23: ='Scenario Engine'!CG$28 | D23: ='Scenario Engine'!DY$28
A24: Year 2 — Gross Revenue (£) | B24: =SUM('Scenario Engine'!AA$17:'Scenario Engine'!AA$28) | C24: =SUM('Scenario Engine'!BS$17:'Scenario Engine'!BS$28) | D24: =SUM('Scenario Engine'!DK$17:'Scenario Engine'!DK$28)
A25: End Year 5 — Customers | B25: ='Scenario Engine'!U$64 | C25: ='Scenario Engine'!BM$64 | D25: ='Scenario Engine'!DE$64
A26: End Year 5 — MRR (£) | B26: ='Scenario Engine'!V$64 | C26: ='Scenario Engine'!BN$64 | D26: ='Scenario Engine'!DF$64
A27: End Year 5 — ARR (£) | B27: ='Scenario Engine'!W$64 | C27: ='Scenario Engine'!BO$64 | D27: ='Scenario Engine'!DG$64
A28: End Year 5 — Cash Balance (£) | B28: ='Scenario Engine'!AO$64 | C28: ='Scenario Engine'!CG$64 | D28: ='Scenario Engine'!DY$64

Sheet Sens - Churn
A1: Churn Sensitivity — full model (seasonal churn, VAT, referrals)
A2: Edit churn in column A (yellow). Live model outputs in section below for comparison.
A4: Current Monthly Churn (Inputs) | B4: =MonthlyChurn
A5: Live Y1 MRR | B5: =Model!V16
A6: Live Y2 MRR | B6: =Model!V28
A7: Live Y2 ARR | B7: =Model!W28
A8: Live Y5 ARR | B8: =Model!W64
A9: Live Y5 Cash | B9: =Model!AO64
A12: Monthly Churn | B12: Y1 MRR | C12: Y1 Cust | D12: Y2 MRR | E12: Y2 ARR | F12: Y2 Cash | G12: Y5 ARR
A13: 0.03 | B13: ='Scenario Engine'!EX$16 | C13: ='Scenario Engine'!EW$16 | D13: ='Scenario Engine'!EX$28 | E13: ='Scenario Engine'!EY$28 | F13: ='Scenario Engine'!FQ$28 | G13: ='Scenario Engine'!EY$64
A14: 0.035 | B14: ='Scenario Engine'!GP$16 | C14: ='Scenario Engine'!GO$16 | D14: ='Scenario Engine'!GP$28 | E14: ='Scenario Engine'!GQ$28 | F14: ='Scenario Engine'!HI$28 | G14: ='Scenario Engine'!GQ$64
A15: 0.04 | B15: ='Scenario Engine'!IH$16 | C15: ='Scenario Engine'!IG$16 | D15: ='Scenario Engine'!IH$28 | E15: ='Scenario Engine'!II$28 | F15: ='Scenario Engine'!JA$28 | G15: ='Scenario Engine'!II$64
A16: 0.045 | B16: ='Scenario Engine'!JZ$16 | C16: ='Scenario Engine'!JY$16 | D16: ='Scenario Engine'!JZ$28 | E16: ='Scenario Engine'!KA$28 | F16: ='Scenario Engine'!KS$28 | G16: ='Scenario Engine'!KA$64
A17: 0.05 | B17: ='Scenario Engine'!LR$16 | C17: ='Scenario Engine'!LQ$16 | D17: ='Scenario Engine'!LR$28 | E17: ='Scenario Engine'!LS$28 | F17: ='Scenario Engine'!MK$28 | G17: ='Scenario Engine'!LS$64
A18: 0.055 | B18: ='Scenario Engine'!NJ$16 | C18: ='Scenario Engine'!NI$16 | D18: ='Scenario Engine'!NJ$28 | E18: ='Scenario Engine'!NK$28 | F18: ='Scenario Engine'!OC$28 | G18: ='Scenario Engine'!NK$64
A19: 0.06 | B19: ='Scenario Engine'!PB$16 | C19: ='Scenario Engine'!PA$16 | D19: ='Scenario Engine'!PB$28 | E19: ='Scenario Engine'!PC$28 | F19: ='Scenario Engine'!PU$28 | G19: ='Scenario Engine'!PC$64
A20: 0.065 | B20: ='Scenario Engine'!QT$16 | C20: ='Scenario Engine'!QS$16 | D20: ='Scenario Engine'!QT$28 | E20: ='Scenario Engine'!QU$28 | F20: ='Scenario Engine'!RM$28 | G20: ='Scenario Engine'!QU$64
A21: 0.07 | B21: ='Scenario Engine'!SL$16 | C21: ='Scenario Engine'!SK$16 | D21: ='Scenario Engine'!SL$28 | E21: ='Scenario Engine'!SM$28 | F21: ='Scenario Engine'!TE$28 | G21: ='Scenario Engine'!SM$64
A22: 0.07 | B22: ='Scenario Engine'!KZ$16 | C22: ='Scenario Engine'!KY$16 | D22: ='Scenario Engine'!KZ$28 | E22: ='Scenario Engine'!LA$28 | F22: ='Scenario Engine'!LK$28 | G22: ='Scenario Engine'!LA$64

Sheet Sens - Annual Mix
A1: Annual Plan Mix Sensitivity — full model engine
A2: Edit mix % in column A (yellow).
A4: Current (Inputs) | B4: =AnnualMix
A7: Annual Mix | B7: Y1 MRR | C7: Blended ARPU | D7: Y2 MRR | E7: Y2 ARR | F7: Y5 ARR | G7: Y5 Cash
A9: 0.1 | B9: ='Scenario Engine'!UD$16 | C9: =IF('Scenario Engine'!UC$16>0,'Scenario Engine'!UD$16/'Scenario Engine'!UC$16,0) | D9: ='Scenario Engine'!UD$28 | E9: ='Scenario Engine'!UE$28 | F9: ='Scenario Engine'!UE$64 | G9: ='Scenario Engine'!UW$64
A10: 0.15 | B10: ='Scenario Engine'!VV$16 | C10: =IF('Scenario Engine'!VU$16>0,'Scenario Engine'!VV$16/'Scenario Engine'!VU$16,0) | D10: ='Scenario Engine'!VV$28 | E10: ='Scenario Engine'!VW$28 | F10: ='Scenario Engine'!VW$64 | G10: ='Scenario Engine'!WO$64
A11: 0.2 | B11: ='Scenario Engine'!XN$16 | C11: =IF('Scenario Engine'!XM$16>0,'Scenario Engine'!XN$16/'Scenario Engine'!XM$16,0) | D11: ='Scenario Engine'!XN$28 | E11: ='Scenario Engine'!XO$28 | F11: ='Scenario Engine'!XO$64 | G11: ='Scenario Engine'!YG$64
A12: 0.25 | B12: ='Scenario Engine'!ZF$16 | C12: =IF('Scenario Engine'!ZE$16>0,'Scenario Engine'!ZF$16/'Scenario Engine'!ZE$16,0) | D12: ='Scenario Engine'!ZF$28 | E12: ='Scenario Engine'!ZG$28 | F12: ='Scenario Engine'!ZG$64 | G12: ='Scenario Engine'!ZY$64
A13: 0.3 | B13: ='Scenario Engine'!AAX$16 | C13: =IF('Scenario Engine'!AAW$16>0,'Scenario Engine'!AAX$16/'Scenario Engine'!AAW$16,0) | D13: ='Scenario Engine'!AAX$28 | E13: ='Scenario Engine'!AAY$28 | F13: ='Scenario Engine'!AAY$64 | G13: ='Scenario Engine'!ABQ$64
A14: 0.35 | B14: ='Scenario Engine'!ACP$16 | C14: =IF('Scenario Engine'!ACO$16>0,'Scenario Engine'!ACP$16/'Scenario Engine'!ACO$16,0) | D14: ='Scenario Engine'!ACP$28 | E14: ='Scenario Engine'!ACQ$28 | F14: ='Scenario Engine'!ACQ$64 | G14: ='Scenario Engine'!ADI$64
A15: 0.4 | B15: ='Scenario Engine'!AEH$16 | C15: =IF('Scenario Engine'!AEG$16>0,'Scenario Engine'!AEH$16/'Scenario Engine'!AEG$16,0) | D15: ='Scenario Engine'!AEH$28 | E15: ='Scenario Engine'!AEI$28 | F15: ='Scenario Engine'!AEI$64 | G15: ='Scenario Engine'!AFA$64

Sheet Sens - CAC & Marketing
A1: CAC Sensitivity — full model engine (home services benchmarks)
A2: Edit CAC in column A (yellow). Sweep spans optimistic (£40) to conservative (£120).
A4: Current (Inputs) | B4: =CAC
A7: CAC (£) | B7: Y1 New Cust | C7: Y1 End Cust | D7: Y1 MRR | E7: Y2 MRR | F7: Y2 Cash | G7: Y5 Cash
A9: 40 | B9: =SUM('Scenario Engine'!AFL$5:'Scenario Engine'!AFL$16) | C9: ='Scenario Engine'!AFY$16 | D9: ='Scenario Engine'!AFZ$16 | E9: ='Scenario Engine'!AFZ$28 | F9: ='Scenario Engine'!AGS$28 | G9: ='Scenario Engine'!AGS$64
A10: 50 | B10: =SUM('Scenario Engine'!AHD$5:'Scenario Engine'!AHD$16) | C10: ='Scenario Engine'!AHQ$16 | D10: ='Scenario Engine'!AHR$16 | E10: ='Scenario Engine'!AHR$28 | F10: ='Scenario Engine'!AIK$28 | G10: ='Scenario Engine'!AIK$64
A11: 60 | B11: =SUM('Scenario Engine'!AIV$5:'Scenario Engine'!AIV$16) | C11: ='Scenario Engine'!AJI$16 | D11: ='Scenario Engine'!AJJ$16 | E11: ='Scenario Engine'!AJJ$28 | F11: ='Scenario Engine'!AKC$28 | G11: ='Scenario Engine'!AKC$64
A12: 70 | B12: =SUM('Scenario Engine'!AKN$5:'Scenario Engine'!AKN$16) | C12: ='Scenario Engine'!ALA$16 | D12: ='Scenario Engine'!ALB$16 | E12: ='Scenario Engine'!ALB$28 | F12: ='Scenario Engine'!ALU$28 | G12: ='Scenario Engine'!ALU$64
A13: 80 | B13: =SUM('Scenario Engine'!AMF$5:'Scenario Engine'!AMF$16) | C13: ='Scenario Engine'!AMS$16 | D13: ='Scenario Engine'!AMT$16 | E13: ='Scenario Engine'!AMT$28 | F13: ='Scenario Engine'!ANM$28 | G13: ='Scenario Engine'!ANM$64
A14: 100 | B14: =SUM('Scenario Engine'!ANX$5:'Scenario Engine'!ANX$16) | C14: ='Scenario Engine'!AOK$16 | D14: ='Scenario Engine'!AOL$16 | E14: ='Scenario Engine'!AOL$28 | F14: ='Scenario Engine'!APE$28 | G14: ='Scenario Engine'!APE$64
A15: 120 | B15: =SUM('Scenario Engine'!APP$5:'Scenario Engine'!APP$16) | C15: ='Scenario Engine'!AQC$16 | D15: ='Scenario Engine'!AQD$16 | E15: ='Scenario Engine'!AQD$28 | F15: ='Scenario Engine'!AQW$28 | G15: ='Scenario Engine'!AQW$64

Sheet Sens - Winter Pivot
A1: Winter Pivot — Property Care Scenario (gutter, leaf, patio)
A2: Compares base garden seasonality vs year-round property care. Edit yellow cells. Pivot seasonality: Inputs cols E & F.
A4: SCENARIO ASSUMPTIONS
A5: Positioning | B5: Year-round property care subscription (mowing pauses Dec–Feb; gutter, leaf & patio included on Premium)
A6: Essential tier mix | B6: 0.65
A7: Premium price uplift (£/mo) | B7: 10
A8: Same as base | B8: CAC, churn rates, marketing & pricing otherwise from Inputs
A11: SEASONALITY COMPARISON (calendar month)
A12: Month | B12: Base acq | C12: Pivot acq | D12: Δ acq | E12: Base churn× | F12: Pivot churn× | G12: Δ churn
A13: Jan | B13: =Inputs!B55 | C13: =Inputs!E55 | D13: =C13-B13 | E13: =Inputs!D55 | F13: =Inputs!F55 | G13: =F13-E13
A14: Feb | B14: =Inputs!B56 | C14: =Inputs!E56 | D14: =C14-B14 | E14: =Inputs!D56 | F14: =Inputs!F56 | G14: =F14-E14
A15: Mar | B15: =Inputs!B57 | C15: =Inputs!E57 | D15: =C15-B15 | E15: =Inputs!D57 | F15: =Inputs!F57 | G15: =F15-E15
A16: Apr | B16: =Inputs!B58 | C16: =Inputs!E58 | D16: =C16-B16 | E16: =Inputs!D58 | F16: =Inputs!F58 | G16: =F16-E16
A17: May | B17: =Inputs!B59 | C17: =Inputs!E59 | D17: =C17-B17 | E17: =Inputs!D59 | F17: =Inputs!F59 | G17: =F17-E17
A18: Jun | B18: =Inputs!B60 | C18: =Inputs!E60 | D18: =C18-B18 | E18: =Inputs!D60 | F18: =Inputs!F60 | G18: =F18-E18
A19: Jul | B19: =Inputs!B61 | C19: =Inputs!E61 | D19: =C19-B19 | E19: =Inputs!D61 | F19: =Inputs!F61 | G19: =F19-E19
A20: Aug | B20: =Inputs!B62 | C20: =Inputs!E62 | D20: =C20-B20 | E20: =Inputs!D62 | F20: =Inputs!F62 | G20: =F20-E20
A21: Sep | B21: =Inputs!B63 | C21: =Inputs!E63 | D21: =C21-B21 | E21: =Inputs!D63 | F21: =Inputs!F63 | G21: =F21-E21
A22: Oct | B22: =Inputs!B64 | C22: =Inputs!E64 | D22: =C22-B22 | E22: =Inputs!D64 | F22: =Inputs!F64 | G22: =F22-E22
A23: Nov | B23: =Inputs!B65 | C23: =Inputs!E65 | D23: =C23-B23 | E23: =Inputs!D65 | F23: =Inputs!F65 | G23: =F23-E23
A24: Dec | B24: =Inputs!B66 | C24: =Inputs!E66 | D24: =C24-B24 | E24: =Inputs!D66 | F24: =Inputs!F66 | G24: =F24-E24
A27: OUTPUT COMPARISON — Base vs Winter Pivot (full model engine)
A28: Base = standard seasonality (Inputs cols B & D). Winter Pivot = cols E & F + Premium property care bundle.
A30: Metric | B30: Base | C30: Winter Pivot | D30: Delta
A31: End Year 1 — Customers | B31: ='Scenario Engine'!BM$16 | C31: ='Scenario Engine'!ARU$16 | D31: =C31-B31
A32: End Year 1 — MRR (£) | B32: ='Scenario Engine'!BN$16 | C32: ='Scenario Engine'!ARV$16 | D32: =C32-B32
A33: End Year 1 — ARR (£) | B33: ='Scenario Engine'!BO$16 | C33: ='Scenario Engine'!ARW$16 | D33: =C33-B33
A34: End Year 1 — Cash (£) | B34: ='Scenario Engine'!CG$16 | C34: ='Scenario Engine'!ASO$16 | D34: =C34-B34
A35: Year 1 — Gross Revenue (£) | B35: =SUM('Scenario Engine'!BS$5:'Scenario Engine'!BS$16) | C35: =SUM('Scenario Engine'!ASA$5:'Scenario Engine'!ASA$16) | D35: =C35-B35
A36: Year 1 — Profit (£) | B36: =SUM('Scenario Engine'!CF$5:'Scenario Engine'!CF$16) | C36: =SUM('Scenario Engine'!ASN$5:'Scenario Engine'!ASN$16) | D36: =C36-B36
A37: End Year 2 — Customers | B37: ='Scenario Engine'!BM$28 | C37: ='Scenario Engine'!ARU$28 | D37: =C37-B37
A38: End Year 2 — MRR (£) | B38: ='Scenario Engine'!BN$28 | C38: ='Scenario Engine'!ARV$28 | D38: =C38-B38
A39: End Year 2 — Cash (£) | B39: ='Scenario Engine'!CG$28 | C39: ='Scenario Engine'!ASO$28 | D39: =C39-B39
A40: End Year 5 — Customers | B40: ='Scenario Engine'!BM$64 | C40: ='Scenario Engine'!ARU$64 | D40: =C40-B40
A41: End Year 5 — MRR (£) | B41: ='Scenario Engine'!BN$64 | C41: ='Scenario Engine'!ARV$64 | D41: =C41-B41
A42: End Year 5 — Cash (£) | B42: ='Scenario Engine'!CG$64 | C42: ='Scenario Engine'!ASO$64 | D42: =C42-B42

Sheet Model
A1: 60-Month Model — hover row 4 headers for column descriptions
A2: Hover any column header in row 4 for a full description.
A4: Mo | B4: Cal | C4: CY | D4: Acq | E4: Infl | F4: ECh | G4: Mkt | H4: Paid | I4: Ref | J4: Tot | K4: NMo | L4: NAn | M4: NEsM | N4: NPrM | O4: NEsA | P4: NPrA | Q4: AEsM | R4: APrM | S4: AEsA | T4: APrA | U4: Cust | V4: MRR | W4: ARR | X4: Mo$ | Y4: NwAn | Z4: Ren | AA4: Gross | AB4: R12 | AC4: VAT | AD4: Net | AE4: VAcc | AF4: VPay | AG4: VBal | AH4: Prov | AI4: Fee | AJ4: Ops | AK4: Fix | AL4: Ref$ | AM4: Mkt | AN4: Pft | AO4: Cash | AP4: ARPU | AQ4: Chrn
A5: 1 | B5: =MOD(A5-1+LaunchMonth-1,12)+1 | C5: =INT((A5-1+LaunchMonth-1)/12)+1 | D5: =VLOOKUP(B5,SeasonTable,2,FALSE) | E5: =(1+InflationRate)^INT((A5-1)/12) | F5: =MonthlyChurn*VLOOKUP(B5,ChurnSeasonTable,4,FALSE) | G5: =MktFixed1_3 | H5: =IF(G5>0,MAX(1,ROUND(G5/CAC*D5,0)),0) | I5: =IF(H5>0,ROUND(H5*ReferralMix/(1-ReferralMix),0),0) | J5: =H5+I5 | K5: =ROUND(J5*(1-AnnualMix),0) | L5: =J5-K5 | M5: =ROUND(K5*EssentialMix,0) | N5: =K5-M5 | O5: =ROUND(L5*EssentialMix,0) | P5: =L5-O5 | Q5: =M5 | R5: =N5 | S5: =O5 | T5: =P5 | U5: =Q5+R5+S5+T5 | V5: =Q5*PriceEssMonthly*E5+R5*PricePremMonthly*E5+S5*PriceEssAnnual*E5/12+T5*PricePremAnnual*E5/12 | W5: =V5*12 | X5: =Q5*PriceEssMonthly*E5+R5*PricePremMonthly*E5 | Y5: =O5*PriceEssAnnual*E5+P5*PricePremAnnual*E5 | Z5: =0+0 | AA5: =X5+Y5+Z5 | AB5: =SUM(AA$5:AA5) | AC5: =AB5>=VATThreshold | AD5: =IF(AC5,AA5/(1+VATRate),AA5) | AE5: =AA5-AD5 | AF5: =IF(AC5=0,0,IF(B5=1,SUMPRODUCT(--(($C$5:$C5=$C5-1)*($B$5:$B5>=10)*($B$5:$B5<=12)),$AE$5:$AE5),IF(B5=4,SUMPRODUCT(--(($C$5:$C5=$C5)*($B$5:$B5>=1)*($B$5:$B5<=3)),$AE$5:$AE5),IF(B5=7,SUMPRODUCT(--(($C$5:$C5=$C5)*($B$5:$B5>=4)*($B$5:$B5<=6)),$AE$5:$AE5),IF(B5=10,SUMPRODUCT(--(($C$5:$C5=$C5)*($B$5:$B5>=7)*($B$5:$B5<=9)),$AE$5:$AE5),0))))) | AG5: =AE5-AF5 | AH5: =IF(ProviderDelay>=1,0,AD5*ProviderShare) | AI5: =AA5*PaymentFee | AJ5: =U5*OpsAI | AK5: =MonthlyFixed | AL5: =I5*ReferralReward | AM5: =G5 | AN5: =AD5-AH5-AI5-AJ5-AK5-AL5-AM5 | AO5: =InitialInvestment+AA5-(AH5+AI5+AJ5+AK5+AL5+AM5+AF5) | AP5: =IF(U5>0,V5/U5,0) | AQ5: 0
A6: 2 | B6: =MOD(A6-1+LaunchMonth-1,12)+1 | C6: =INT((A6-1+LaunchMonth-1)/12)+1 | D6: =VLOOKUP(B6,SeasonTable,2,FALSE) | E6: =(1+InflationRate)^INT((A6-1)/12) | F6: =MonthlyChurn*VLOOKUP(B6,ChurnSeasonTable,4,FALSE) | G6: =MktFixed1_3 | H6: =IF(G6>0,MAX(1,ROUND(G6/CAC*D6,0)),0) | I6: =IF(H6>0,ROUND(H6*ReferralMix/(1-ReferralMix),0),0) | J6: =H6+I6 | K6: =ROUND(J6*(1-AnnualMix),0) | L6: =J6-K6 | M6: =ROUND(K6*EssentialMix,0) | N6: =K6-M6 | O6: =ROUND(L6*EssentialMix,0) | P6: =L6-O6 | Q6: =M6+M5 | R6: =N6+N5 | S6: =SUM(O$5:O6) | T6: =SUM(P$5:P6) | U6: =Q6+R6+S6+T6 | V6: =Q6*PriceEssMonthly*E6+R6*PricePremMonthly*E6+S6*PriceEssAnnual*E6/12+T6*PricePremAnnual*E6/12 | W6: =V6*12 | X6: =Q6*PriceEssMonthly*E6+R6*PricePremMonthly*E6 | Y6: =O6*PriceEssAnnual*E6+P6*PricePremAnnual*E6 | Z6: =0+0 | AA6: =X6+Y6+Z6 | AB6: =SUM(AA$5:AA6) | AC6: =OR(AC5,AB6>=VATThreshold) | AD6: =IF(AC6,AA6/(1+VATRate),AA6) | AE6: =AA6-AD6 | AF6: =IF(AC6=0,0,IF(B6=1,SUMPRODUCT(--(($C$5:$C6=$C6-1)*($B$5:$B6>=10)*($B$5:$B6<=12)),$AE$5:$AE6),IF(B6=4,SUMPRODUCT(--(($C$5:$C6=$C6)*($B$5:$B6>=1)*($B$5:$B6<=3)),$AE$5:$AE6),IF(B6=7,SUMPRODUCT(--(($C$5:$C6=$C6)*($B$5:$B6>=4)*($B$5:$B6<=6)),$AE$5:$AE6),IF(B6=10,SUMPRODUCT(--(($C$5:$C6=$C6)*($B$5:$B6>=7)*($B$5:$B6<=9)),$AE$5:$AE6),0))))) | AG6: =AG5+AE6-AF6 | AH6: =IF(ProviderDelay>=1,AD5*ProviderShare,AD6*ProviderShare) | AI6: =AA6*PaymentFee | AJ6: =U6*OpsAI | AK6: =MonthlyFixed | AL6: =I6*ReferralReward | AM6: =G6 | AN6: =AD6-AH6-AI6-AJ6-AK6-AL6-AM6 | AO6: =AO5+AA6-(AH6+AI6+AJ6+AK6+AL6+AM6+AF6) | AP6: =IF(U6>0,V6/U6,0) | AQ6: =IF(U5>0,MAX(0,(U5+J6-U6)/U5),0)
A7: 3 | B7: =MOD(A7-1+LaunchMonth-1,12)+1 | C7: =INT((A7-1+LaunchMonth-1)/12)+1 | D7: =VLOOKUP(B7,SeasonTable,2,FALSE) | E7: =(1+InflationRate)^INT((A7-1)/12) | F7: =MonthlyChurn*VLOOKUP(B7,ChurnSeasonTable,4,FALSE) | G7: =MktFixed1_3 | H7: =IF(G7>0,MAX(1,ROUND(G7/CAC*D7,0)),0) | I7: =IF(H7>0,ROUND(H7*ReferralMix/(1-ReferralMix),0),0) | J7: =H7+I7 | K7: =ROUND(J7*(1-AnnualMix),0) | L7: =J7-K7 | M7: =ROUND(K7*EssentialMix,0) | N7: =K7-M7 | O7: =ROUND(L7*EssentialMix,0) | P7: =L7-O7 | Q7: =M7+M6+M5 | R7: =N7+N6+N5 | S7: =SUM(O$5:O7) | T7: =SUM(P$5:P7) | U7: =Q7+R7+S7+T7 | V7: =Q7*PriceEssMonthly*E7+R7*PricePremMonthly*E7+S7*PriceEssAnnual*E7/12+T7*PricePremAnnual*E7/12 | W7: =V7*12 | X7: =Q7*PriceEssMonthly*E7+R7*PricePremMonthly*E7 | Y7: =O7*PriceEssAnnual*E7+P7*PricePremAnnual*E7 | Z7: =0+0 | AA7: =X7+Y7+Z7 | AB7: =SUM(AA$5:AA7) | AC7: =OR(AC6,AB7>=VATThreshold) | AD7: =IF(AC7,AA7/(1+VATRate),AA7) | AE7: =AA7-AD7 | AF7: =IF(AC7=0,0,IF(B7=1,SUMPRODUCT(--(($C$5:$C7=$C7-1)*($B$5:$B7>=10)*($B$5:$B7<=12)),$AE$5:$AE7),IF(B7=4,SUMPRODUCT(--(($C$5:$C7=$C7)*($B$5:$B7>=1)*($B$5:$B7<=3)),$AE$5:$AE7),IF(B7=7,SUMPRODUCT(--(($C$5:$C7=$C7)*($B$5:$B7>=4)*($B$5:$B7<=6)),$AE$5:$AE7),IF(B7=10,SUMPRODUCT(--(($C$5:$C7=$C7)*($B$5:$B7>=7)*($B$5:$B7<=9)),$AE$5:$AE7),0))))) | AG7: =AG6+AE7-AF7 | AH7: =IF(ProviderDelay>=1,AD6*ProviderShare,AD7*ProviderShare) | AI7: =AA7*PaymentFee | AJ7: =U7*OpsAI | AK7: =MonthlyFixed | AL7: =I7*ReferralReward | AM7: =G7 | AN7: =AD7-AH7-AI7-AJ7-AK7-AL7-AM7 | AO7: =AO6+AA7-(AH7+AI7+AJ7+AK7+AL7+AM7+AF7) | AP7: =IF(U7>0,V7/U7,0) | AQ7: =IF(U6>0,MAX(0,(U6+J7-U7)/U6),0)
A8: 4 | B8: =MOD(A8-1+LaunchMonth-1,12)+1 | C8: =INT((A8-1+LaunchMonth-1)/12)+1 | D8: =VLOOKUP(B8,SeasonTable,2,FALSE) | E8: =(1+InflationRate)^INT((A8-1)/12) | F8: =MonthlyChurn*VLOOKUP(B8,ChurnSeasonTable,4,FALSE) | G8: =MIN(MktFixed4_6,MAX(0,AO7-CashBuffer)) | H8: =IF(G8>0,MAX(1,ROUND(G8/CAC*D8,0)),0) | I8: =IF(H8>0,ROUND(H8*ReferralMix/(1-ReferralMix),0),0) | J8: =H8+I8 | K8: =ROUND(J8*(1-AnnualMix),0) | L8: =J8-K8 | M8: =ROUND(K8*EssentialMix,0) | N8: =K8-M8 | O8: =ROUND(L8*EssentialMix,0) | P8: =L8-O8 | Q8: =M8+M7+M6+MAX(0,Q7-M7-M6)*(1-F8) | R8: =N8+N7+N6+MAX(0,R7-N7-N6)*(1-F8) | S8: =SUM(O$5:O8) | T8: =SUM(P$5:P8) | U8: =Q8+R8+S8+T8 | V8: =Q8*PriceEssMonthly*E8+R8*PricePremMonthly*E8+S8*PriceEssAnnual*E8/12+T8*PricePremAnnual*E8/12 | W8: =V8*12 | X8: =Q8*PriceEssMonthly*E8+R8*PricePremMonthly*E8 | Y8: =O8*PriceEssAnnual*E8+P8*PricePremAnnual*E8 | Z8: =0+0 | AA8: =X8+Y8+Z8 | AB8: =SUM(AA$5:AA8) | AC8: =OR(AC7,AB8>=VATThreshold) | AD8: =IF(AC8,AA8/(1+VATRate),AA8) | AE8: =AA8-AD8 | AF8: =IF(AC8=0,0,IF(B8=1,SUMPRODUCT(--(($C$5:$C8=$C8-1)*($B$5:$B8>=10)*($B$5:$B8<=12)),$AE$5:$AE8),IF(B8=4,SUMPRODUCT(--(($C$5:$C8=$C8)*($B$5:$B8>=1)*($B$5:$B8<=3)),$AE$5:$AE8),IF(B8=7,SUMPRODUCT(--(($C$5:$C8=$C8)*($B$5:$B8>=4)*($B$5:$B8<=6)),$AE$5:$AE8),IF(B8=10,SUMPRODUCT(--(($C$5:$C8=$C8)*($B$5:$B8>=7)*($B$5:$B8<=9)),$AE$5:$AE8),0))))) | AG8: =AG7+AE8-AF8 | AH8: =IF(ProviderDelay>=1,AD7*ProviderShare,AD8*ProviderShare) | AI8: =AA8*PaymentFee | AJ8: =U8*OpsAI | AK8: =MonthlyFixed | AL8: =I8*ReferralReward | AM8: =G8 | AN8: =AD8-AH8-AI8-AJ8-AK8-AL8-AM8 | AO8: =AO7+AA8-(AH8+AI8+AJ8+AK8+AL8+AM8+AF8) | AP8: =IF(U8>0,V8/U8,0) | AQ8: =IF(U7>0,MAX(0,(U7+J8-U8)/U7),0)
A9: 5 | B9: =MOD(A9-1+LaunchMonth-1,12)+1 | C9: =INT((A9-1+LaunchMonth-1)/12)+1 | D9: =VLOOKUP(B9,SeasonTable,2,FALSE) | E9: =(1+InflationRate)^INT((A9-1)/12) | F9: =MonthlyChurn*VLOOKUP(B9,ChurnSeasonTable,4,FALSE) | G9: =MIN(MktFixed4_6,MAX(0,AO8-CashBuffer)) | H9: =IF(G9>0,MAX(1,ROUND(G9/CAC*D9,0)),0) | I9: =IF(H9>0,ROUND(H9*ReferralMix/(1-ReferralMix),0),0) | J9: =H9+I9 | K9: =ROUND(J9*(1-AnnualMix),0) | L9: =J9-K9 | M9: =ROUND(K9*EssentialMix,0) | N9: =K9-M9 | O9: =ROUND(L9*EssentialMix,0) | P9: =L9-O9 | Q9: =M9+M8+M7+MAX(0,Q8-M8-M7)*(1-F9) | R9: =N9+N8+N7+MAX(0,R8-N8-N7)*(1-F9) | S9: =SUM(O$5:O9) | T9: =SUM(P$5:P9) | U9: =Q9+R9+S9+T9 | V9: =Q9*PriceEssMonthly*E9+R9*PricePremMonthly*E9+S9*PriceEssAnnual*E9/12+T9*PricePremAnnual*E9/12 | W9: =V9*12 | X9: =Q9*PriceEssMonthly*E9+R9*PricePremMonthly*E9 | Y9: =O9*PriceEssAnnual*E9+P9*PricePremAnnual*E9 | Z9: =0+0 | AA9: =X9+Y9+Z9 | AB9: =SUM(AA$5:AA9) | AC9: =OR(AC8,AB9>=VATThreshold) | AD9: =IF(AC9,AA9/(1+VATRate),AA9) | AE9: =AA9-AD9 | AF9: =IF(AC9=0,0,IF(B9=1,SUMPRODUCT(--(($C$5:$C9=$C9-1)*($B$5:$B9>=10)*($B$5:$B9<=12)),$AE$5:$AE9),IF(B9=4,SUMPRODUCT(--(($C$5:$C9=$C9)*($B$5:$B9>=1)*($B$5:$B9<=3)),$AE$5:$AE9),IF(B9=7,SUMPRODUCT(--(($C$5:$C9=$C9)*($B$5:$B9>=4)*($B$5:$B9<=6)),$AE$5:$AE9),IF(B9=10,SUMPRODUCT(--(($C$5:$C9=$C9)*($B$5:$B9>=7)*($B$5:$B9<=9)),$AE$5:$AE9),0))))) | AG9: =AG8+AE9-AF9 | AH9: =IF(ProviderDelay>=1,AD8*ProviderShare,AD9*ProviderShare) | AI9: =AA9*PaymentFee | AJ9: =U9*OpsAI | AK9: =MonthlyFixed | AL9: =I9*ReferralReward | AM9: =G9 | AN9: =AD9-AH9-AI9-AJ9-AK9-AL9-AM9 | AO9: =AO8+AA9-(AH9+AI9+AJ9+AK9+AL9+AM9+AF9) | AP9: =IF(U9>0,V9/U9,0) | AQ9: =IF(U8>0,MAX(0,(U8+J9-U9)/U8),0)
A10: 6 | B10: =MOD(A10-1+LaunchMonth-1,12)+1 | C10: =INT((A10-1+LaunchMonth-1)/12)+1 | D10: =VLOOKUP(B10,SeasonTable,2,FALSE) | E10: =(1+InflationRate)^INT((A10-1)/12) | F10: =MonthlyChurn*VLOOKUP(B10,ChurnSeasonTable,4,FALSE) | G10: =MIN(MktFixed4_6,MAX(0,AO9-CashBuffer)) | H10: =IF(G10>0,MAX(1,ROUND(G10/CAC*D10,0)),0) | I10: =IF(H10>0,ROUND(H10*ReferralMix/(1-ReferralMix),0),0) | J10: =H10+I10 | K10: =ROUND(J10*(1-AnnualMix),0) | L10: =J10-K10 | M10: =ROUND(K10*EssentialMix,0) | N10: =K10-M10 | O10: =ROUND(L10*EssentialMix,0) | P10: =L10-O10 | Q10: =M10+M9+M8+MAX(0,Q9-M9-M8)*(1-F10) | R10: =N10+N9+N8+MAX(0,R9-N9-N8)*(1-F10) | S10: =SUM(O$5:O10) | T10: =SUM(P$5:P10) | U10: =Q10+R10+S10+T10 | V10: =Q10*PriceEssMonthly*E10+R10*PricePremMonthly*E10+S10*PriceEssAnnual*E10/12+T10*PricePremAnnual*E10/12 | W10: =V10*12 | X10: =Q10*PriceEssMonthly*E10+R10*PricePremMonthly*E10 | Y10: =O10*PriceEssAnnual*E10+P10*PricePremAnnual*E10 | Z10: =0+0 | AA10: =X10+Y10+Z10 | AB10: =SUM(AA$5:AA10) | AC10: =OR(AC9,AB10>=VATThreshold) | AD10: =IF(AC10,AA10/(1+VATRate),AA10) | AE10: =AA10-AD10 | AF10: =IF(AC10=0,0,IF(B10=1,SUMPRODUCT(--(($C$5:$C10=$C10-1)*($B$5:$B10>=10)*($B$5:$B10<=12)),$AE$5:$AE10),IF(B10=4,SUMPRODUCT(--(($C$5:$C10=$C10)*($B$5:$B10>=1)*($B$5:$B10<=3)),$AE$5:$AE10),IF(B10=7,SUMPRODUCT(--(($C$5:$C10=$C10)*($B$5:$B10>=4)*($B$5:$B10<=6)),$AE$5:$AE10),IF(B10=10,SUMPRODUCT(--(($C$5:$C10=$C10)*($B$5:$B10>=7)*($B$5:$B10<=9)),$AE$5:$AE10),0))))) | AG10: =AG9+AE10-AF10 | AH10: =IF(ProviderDelay>=1,AD9*ProviderShare,AD10*ProviderShare) | AI10: =AA10*PaymentFee | AJ10: =U10*OpsAI | AK10: =MonthlyFixed | AL10: =I10*ReferralReward | AM10: =G10 | AN10: =AD10-AH10-AI10-AJ10-AK10-AL10-AM10 | AO10: =AO9+AA10-(AH10+AI10+AJ10+AK10+AL10+AM10+AF10) | AP10: =IF(U10>0,V10/U10,0) | AQ10: =IF(U9>0,MAX(0,(U9+J10-U10)/U9),0)
A11: 7 | B11: =MOD(A11-1+LaunchMonth-1,12)+1 | C11: =INT((A11-1+LaunchMonth-1)/12)+1 | D11: =VLOOKUP(B11,SeasonTable,2,FALSE) | E11: =(1+InflationRate)^INT((A11-1)/12) | F11: =MonthlyChurn*VLOOKUP(B11,ChurnSeasonTable,4,FALSE) | G11: =MIN(MAX(MktMin7_12,AA10*MktPct7_12),MAX(0,AO10-CashBuffer)) | H11: =IF(G11>0,MAX(1,ROUND(G11/CAC*D11,0)),0) | I11: =IF(H11>0,ROUND(H11*ReferralMix/(1-ReferralMix),0),0) | J11: =H11+I11 | K11: =ROUND(J11*(1-AnnualMix),0) | L11: =J11-K11 | M11: =ROUND(K11*EssentialMix,0) | N11: =K11-M11 | O11: =ROUND(L11*EssentialMix,0) | P11: =L11-O11 | Q11: =M11+M10+M9+MAX(0,Q10-M10-M9)*(1-F11) | R11: =N11+N10+N9+MAX(0,R10-N10-N9)*(1-F11) | S11: =SUM(O$5:O11) | T11: =SUM(P$5:P11) | U11: =Q11+R11+S11+T11 | V11: =Q11*PriceEssMonthly*E11+R11*PricePremMonthly*E11+S11*PriceEssAnnual*E11/12+T11*PricePremAnnual*E11/12 | W11: =V11*12 | X11: =Q11*PriceEssMonthly*E11+R11*PricePremMonthly*E11 | Y11: =O11*PriceEssAnnual*E11+P11*PricePremAnnual*E11 | Z11: =0+0 | AA11: =X11+Y11+Z11 | AB11: =SUM(AA$5:AA11) | AC11: =OR(AC10,AB11>=VATThreshold) | AD11: =IF(AC11,AA11/(1+VATRate),AA11) | AE11: =AA11-AD11 | AF11: =IF(AC11=0,0,IF(B11=1,SUMPRODUCT(--(($C$5:$C11=$C11-1)*($B$5:$B11>=10)*($B$5:$B11<=12)),$AE$5:$AE11),IF(B11=4,SUMPRODUCT(--(($C$5:$C11=$C11)*($B$5:$B11>=1)*($B$5:$B11<=3)),$AE$5:$AE11),IF(B11=7,SUMPRODUCT(--(($C$5:$C11=$C11)*($B$5:$B11>=4)*($B$5:$B11<=6)),$AE$5:$AE11),IF(B11=10,SUMPRODUCT(--(($C$5:$C11=$C11)*($B$5:$B11>=7)*($B$5:$B11<=9)),$AE$5:$AE11),0))))) | AG11: =AG10+AE11-AF11 | AH11: =IF(ProviderDelay>=1,AD10*ProviderShare,AD11*ProviderShare) | AI11: =AA11*PaymentFee | AJ11: =U11*OpsAI | AK11: =MonthlyFixed | AL11: =I11*ReferralReward | AM11: =G11 | AN11: =AD11-AH11-AI11-AJ11-AK11-AL11-AM11 | AO11: =AO10+AA11-(AH11+AI11+AJ11+AK11+AL11+AM11+AF11) | AP11: =IF(U11>0,V11/U11,0) | AQ11: =IF(U10>0,MAX(0,(U10+J11-U11)/U10),0)
A12: 8 | B12: =MOD(A12-1+LaunchMonth-1,12)+1 | C12: =INT((A12-1+LaunchMonth-1)/12)+1 | D12: =VLOOKUP(B12,SeasonTable,2,FALSE) | E12: =(1+InflationRate)^INT((A12-1)/12) | F12: =MonthlyChurn*VLOOKUP(B12,ChurnSeasonTable,4,FALSE) | G12: =MIN(MAX(MktMin7_12,AA11*MktPct7_12),MAX(0,AO11-CashBuffer)) | H12: =IF(G12>0,MAX(1,ROUND(G12/CAC*D12,0)),0) | I12: =IF(H12>0,ROUND(H12*ReferralMix/(1-ReferralMix),0),0) | J12: =H12+I12 | K12: =ROUND(J12*(1-AnnualMix),0) | L12: =J12-K12 | M12: =ROUND(K12*EssentialMix,0) | N12: =K12-M12 | O12: =ROUND(L12*EssentialMix,0) | P12: =L12-O12 | Q12: =M12+M11+M10+MAX(0,Q11-M11-M10)*(1-F12) | R12: =N12+N11+N10+MAX(0,R11-N11-N10)*(1-F12) | S12: =SUM(O$5:O12) | T12: =SUM(P$5:P12) | U12: =Q12+R12+S12+T12 | V12: =Q12*PriceEssMonthly*E12+R12*PricePremMonthly*E12+S12*PriceEssAnnual*E12/12+T12*PricePremAnnual*E12/12 | W12: =V12*12 | X12: =Q12*PriceEssMonthly*E12+R12*PricePremMonthly*E12 | Y12: =O12*PriceEssAnnual*E12+P12*PricePremAnnual*E12 | Z12: =0+0 | AA12: =X12+Y12+Z12 | AB12: =SUM(AA$5:AA12) | AC12: =OR(AC11,AB12>=VATThreshold) | AD12: =IF(AC12,AA12/(1+VATRate),AA12) | AE12: =AA12-AD12 | AF12: =IF(AC12=0,0,IF(B12=1,SUMPRODUCT(--(($C$5:$C12=$C12-1)*($B$5:$B12>=10)*($B$5:$B12<=12)),$AE$5:$AE12),IF(B12=4,SUMPRODUCT(--(($C$5:$C12=$C12)*($B$5:$B12>=1)*($B$5:$B12<=3)),$AE$5:$AE12),IF(B12=7,SUMPRODUCT(--(($C$5:$C12=$C12)*($B$5:$B12>=4)*($B$5:$B12<=6)),$AE$5:$AE12),IF(B12=10,SUMPRODUCT(--(($C$5:$C12=$C12)*($B$5:$B12>=7)*($B$5:$B12<=9)),$AE$5:$AE12),0))))) | AG12: =AG11+AE12-AF12 | AH12: =IF(ProviderDelay>=1,AD11*ProviderShare,AD12*ProviderShare) | AI12: =AA12*PaymentFee | AJ12: =U12*OpsAI | AK12: =MonthlyFixed | AL12: =I12*ReferralReward | AM12: =G12 | AN12: =AD12-AH12-AI12-AJ12-AK12-AL12-AM12 | AO12: =AO11+AA12-(AH12+AI12+AJ12+AK12+AL12+AM12+AF12) | AP12: =IF(U12>0,V12/U12,0) | AQ12: =IF(U11>0,MAX(0,(U11+J12-U12)/U11),0)
A13: 9 | B13: =MOD(A13-1+LaunchMonth-1,12)+1 | C13: =INT((A13-1+LaunchMonth-1)/12)+1 | D13: =VLOOKUP(B13,SeasonTable,2,FALSE) | E13: =(1+InflationRate)^INT((A13-1)/12) | F13: =MonthlyChurn*VLOOKUP(B13,ChurnSeasonTable,4,FALSE) | G13: =MIN(MAX(MktMin7_12,AA12*MktPct7_12),MAX(0,AO12-CashBuffer)) | H13: =IF(G13>0,MAX(1,ROUND(G13/CAC*D13,0)),0) | I13: =IF(H13>0,ROUND(H13*ReferralMix/(1-ReferralMix),0),0) | J13: =H13+I13 | K13: =ROUND(J13*(1-AnnualMix),0) | L13: =J13-K13 | M13: =ROUND(K13*EssentialMix,0) | N13: =K13-M13 | O13: =ROUND(L13*EssentialMix,0) | P13: =L13-O13 | Q13: =M13+M12+M11+MAX(0,Q12-M12-M11)*(1-F13) | R13: =N13+N12+N11+MAX(0,R12-N12-N11)*(1-F13) | S13: =SUM(O$5:O13) | T13: =SUM(P$5:P13) | U13: =Q13+R13+S13+T13 | V13: =Q13*PriceEssMonthly*E13+R13*PricePremMonthly*E13+S13*PriceEssAnnual*E13/12+T13*PricePremAnnual*E13/12 | W13: =V13*12 | X13: =Q13*PriceEssMonthly*E13+R13*PricePremMonthly*E13 | Y13: =O13*PriceEssAnnual*E13+P13*PricePremAnnual*E13 | Z13: =0+0 | AA13: =X13+Y13+Z13 | AB13: =SUM(AA$5:AA13) | AC13: =OR(AC12,AB13>=VATThreshold) | AD13: =IF(AC13,AA13/(1+VATRate),AA13) | AE13: =AA13-AD13 | AF13: =IF(AC13=0,0,IF(B13=1,SUMPRODUCT(--(($C$5:$C13=$C13-1)*($B$5:$B13>=10)*($B$5:$B13<=12)),$AE$5:$AE13),IF(B13=4,SUMPRODUCT(--(($C$5:$C13=$C13)*($B$5:$B13>=1)*($B$5:$B13<=3)),$AE$5:$AE13),IF(B13=7,SUMPRODUCT(--(($C$5:$C13=$C13)*($B$5:$B13>=4)*($B$5:$B13<=6)),$AE$5:$AE13),IF(B13=10,SUMPRODUCT(--(($C$5:$C13=$C13)*($B$5:$B13>=7)*($B$5:$B13<=9)),$AE$5:$AE13),0))))) | AG13: =AG12+AE13-AF13 | AH13: =IF(ProviderDelay>=1,AD12*ProviderShare,AD13*ProviderShare) | AI13: =AA13*PaymentFee | AJ13: =U13*OpsAI | AK13: =MonthlyFixed | AL13: =I13*ReferralReward | AM13: =G13 | AN13: =AD13-AH13-AI13-AJ13-AK13-AL13-AM13 | AO13: =AO12+AA13-(AH13+AI13+AJ13+AK13+AL13+AM13+AF13) | AP13: =IF(U13>0,V13/U13,0) | AQ13: =IF(U12>0,MAX(0,(U12+J13-U13)/U12),0)
A14: 10 | B14: =MOD(A14-1+LaunchMonth-1,12)+1 | C14: =INT((A14-1+LaunchMonth-1)/12)+1 | D14: =VLOOKUP(B14,SeasonTable,2,FALSE) | E14: =(1+InflationRate)^INT((A14-1)/12) | F14: =MonthlyChurn*VLOOKUP(B14,ChurnSeasonTable,4,FALSE) | G14: =MIN(MAX(MktMin7_12,AA13*MktPct7_12),MAX(0,AO13-CashBuffer)) | H14: =IF(G14>0,MAX(1,ROUND(G14/CAC*D14,0)),0) | I14: =IF(H14>0,ROUND(H14*ReferralMix/(1-ReferralMix),0),0) | J14: =H14+I14 | K14: =ROUND(J14*(1-AnnualMix),0) | L14: =J14-K14 | M14: =ROUND(K14*EssentialMix,0) | N14: =K14-M14 | O14: =ROUND(L14*EssentialMix,0) | P14: =L14-O14 | Q14: =M14+M13+M12+MAX(0,Q13-M13-M12)*(1-F14) | R14: =N14+N13+N12+MAX(0,R13-N13-N12)*(1-F14) | S14: =SUM(O$5:O14) | T14: =SUM(P$5:P14) | U14: =Q14+R14+S14+T14 | V14: =Q14*PriceEssMonthly*E14+R14*PricePremMonthly*E14+S14*PriceEssAnnual*E14/12+T14*PricePremAnnual*E14/12 | W14: =V14*12 | X14: =Q14*PriceEssMonthly*E14+R14*PricePremMonthly*E14 | Y14: =O14*PriceEssAnnual*E14+P14*PricePremAnnual*E14 | Z14: =0+0 | AA14: =X14+Y14+Z14 | AB14: =SUM(AA$5:AA14) | AC14: =OR(AC13,AB14>=VATThreshold) | AD14: =IF(AC14,AA14/(1+VATRate),AA14) | AE14: =AA14-AD14 | AF14: =IF(AC14=0,0,IF(B14=1,SUMPRODUCT(--(($C$5:$C14=$C14-1)*($B$5:$B14>=10)*($B$5:$B14<=12)),$AE$5:$AE14),IF(B14=4,SUMPRODUCT(--(($C$5:$C14=$C14)*($B$5:$B14>=1)*($B$5:$B14<=3)),$AE$5:$AE14),IF(B14=7,SUMPRODUCT(--(($C$5:$C14=$C14)*($B$5:$B14>=4)*($B$5:$B14<=6)),$AE$5:$AE14),IF(B14=10,SUMPRODUCT(--(($C$5:$C14=$C14)*($B$5:$B14>=7)*($B$5:$B14<=9)),$AE$5:$AE14),0))))) | AG14: =AG13+AE14-AF14 | AH14: =IF(ProviderDelay>=1,AD13*ProviderShare,AD14*ProviderShare) | AI14: =AA14*PaymentFee | AJ14: =U14*OpsAI | AK14: =MonthlyFixed | AL14: =I14*ReferralReward | AM14: =G14 | AN14: =AD14-AH14-AI14-AJ14-AK14-AL14-AM14 | AO14: =AO13+AA14-(AH14+AI14+AJ14+AK14+AL14+AM14+AF14) | AP14: =IF(U14>0,V14/U14,0) | AQ14: =IF(U13>0,MAX(0,(U13+J14-U14)/U13),0)
A15: 11 | B15: =MOD(A15-1+LaunchMonth-1,12)+1 | C15: =INT((A15-1+LaunchMonth-1)/12)+1 | D15: =VLOOKUP(B15,SeasonTable,2,FALSE) | E15: =(1+InflationRate)^INT((A15-1)/12) | F15: =MonthlyChurn*VLOOKUP(B15,ChurnSeasonTable,4,FALSE) | G15: =MIN(MAX(MktMin7_12,AA14*MktPct7_12),MAX(0,AO14-CashBuffer)) | H15: =IF(G15>0,MAX(1,ROUND(G15/CAC*D15,0)),0) | I15: =IF(H15>0,ROUND(H15*ReferralMix/(1-ReferralMix),0),0) | J15: =H15+I15 | K15: =ROUND(J15*(1-AnnualMix),0) | L15: =J15-K15 | M15: =ROUND(K15*EssentialMix,0) | N15: =K15-M15 | O15: =ROUND(L15*EssentialMix,0) | P15: =L15-O15 | Q15: =M15+M14+M13+MAX(0,Q14-M14-M13)*(1-F15) | R15: =N15+N14+N13+MAX(0,R14-N14-N13)*(1-F15) | S15: =SUM(O$5:O15) | T15: =SUM(P$5:P15) | U15: =Q15+R15+S15+T15 | V15: =Q15*PriceEssMonthly*E15+R15*PricePremMonthly*E15+S15*PriceEssAnnual*E15/12+T15*PricePremAnnual*E15/12 | W15: =V15*12 | X15: =Q15*PriceEssMonthly*E15+R15*PricePremMonthly*E15 | Y15: =O15*PriceEssAnnual*E15+P15*PricePremAnnual*E15 | Z15: =0+0 | AA15: =X15+Y15+Z15 | AB15: =SUM(AA$5:AA15) | AC15: =OR(AC14,AB15>=VATThreshold) | AD15: =IF(AC15,AA15/(1+VATRate),AA15) | AE15: =AA15-AD15 | AF15: =IF(AC15=0,0,IF(B15=1,SUMPRODUCT(--(($C$5:$C15=$C15-1)*($B$5:$B15>=10)*($B$5:$B15<=12)),$AE$5:$AE15),IF(B15=4,SUMPRODUCT(--(($C$5:$C15=$C15)*($B$5:$B15>=1)*($B$5:$B15<=3)),$AE$5:$AE15),IF(B15=7,SUMPRODUCT(--(($C$5:$C15=$C15)*($B$5:$B15>=4)*($B$5:$B15<=6)),$AE$5:$AE15),IF(B15=10,SUMPRODUCT(--(($C$5:$C15=$C15)*($B$5:$B15>=7)*($B$5:$B15<=9)),$AE$5:$AE15),0))))) | AG15: =AG14+AE15-AF15 | AH15: =IF(ProviderDelay>=1,AD14*ProviderShare,AD15*ProviderShare) | AI15: =AA15*PaymentFee | AJ15: =U15*OpsAI | AK15: =MonthlyFixed | AL15: =I15*ReferralReward | AM15: =G15 | AN15: =AD15-AH15-AI15-AJ15-AK15-AL15-AM15 | AO15: =AO14+AA15-(AH15+AI15+AJ15+AK15+AL15+AM15+AF15) | AP15: =IF(U15>0,V15/U15,0) | AQ15: =IF(U14>0,MAX(0,(U14+J15-U15)/U14),0)
A16: 12 | B16: =MOD(A16-1+LaunchMonth-1,12)+1 | C16: =INT((A16-1+LaunchMonth-1)/12)+1 | D16: =VLOOKUP(B16,SeasonTable,2,FALSE) | E16: =(1+InflationRate)^INT((A16-1)/12) | F16: =MonthlyChurn*VLOOKUP(B16,ChurnSeasonTable,4,FALSE) | G16: =MIN(MAX(MktMin7_12,AA15*MktPct7_12),MAX(0,AO15-CashBuffer)) | H16: =IF(G16>0,MAX(1,ROUND(G16/CAC*D16,0)),0) | I16: =IF(H16>0,ROUND(H16*ReferralMix/(1-ReferralMix),0),0) | J16: =H16+I16 | K16: =ROUND(J16*(1-AnnualMix),0) | L16: =J16-K16 | M16: =ROUND(K16*EssentialMix,0) | N16: =K16-M16 | O16: =ROUND(L16*EssentialMix,0) | P16: =L16-O16 | Q16: =M16+M15+M14+MAX(0,Q15-M15-M14)*(1-F16) | R16: =N16+N15+N14+MAX(0,R15-N15-N14)*(1-F16) | S16: =SUM(O$5:O16) | T16: =SUM(P$5:P16) | U16: =Q16+R16+S16+T16 | V16: =Q16*PriceEssMonthly*E16+R16*PricePremMonthly*E16+S16*PriceEssAnnual*E16/12+T16*PricePremAnnual*E16/12 | W16: =V16*12 | X16: =Q16*PriceEssMonthly*E16+R16*PricePremMonthly*E16 | Y16: =O16*PriceEssAnnual*E16+P16*PricePremAnnual*E16 | Z16: =0+0 | AA16: =X16+Y16+Z16 | AB16: =SUM(AA5:AA16) | AC16: =OR(AC15,AB16>=VATThreshold) | AD16: =IF(AC16,AA16/(1+VATRate),AA16) | AE16: =AA16-AD16 | AF16: =IF(AC16=0,0,IF(B16=1,SUMPRODUCT(--(($C$5:$C16=$C16-1)*($B$5:$B16>=10)*($B$5:$B16<=12)),$AE$5:$AE16),IF(B16=4,SUMPRODUCT(--(($C$5:$C16=$C16)*($B$5:$B16>=1)*($B$5:$B16<=3)),$AE$5:$AE16),IF(B16=7,SUMPRODUCT(--(($C$5:$C16=$C16)*($B$5:$B16>=4)*($B$5:$B16<=6)),$AE$5:$AE16),IF(B16=10,SUMPRODUCT(--(($C$5:$C16=$C16)*($B$5:$B16>=7)*($B$5:$B16<=9)),$AE$5:$AE16),0))))) | AG16: =AG15+AE16-AF16 | AH16: =IF(ProviderDelay>=1,AD15*ProviderShare,AD16*ProviderShare) | AI16: =AA16*PaymentFee | AJ16: =U16*OpsAI | AK16: =MonthlyFixed | AL16: =I16*ReferralReward | AM16: =G16 | AN16: =AD16-AH16-AI16-AJ16-AK16-AL16-AM16 | AO16: =AO15+AA16-(AH16+AI16+AJ16+AK16+AL16+AM16+AF16) | AP16: =IF(U16>0,V16/U16,0) | AQ16: =IF(U15>0,MAX(0,(U15+J16-U16)/U15),0)
A17: 13 | B17: =MOD(A17-1+LaunchMonth-1,12)+1 | C17: =INT((A17-1+LaunchMonth-1)/12)+1 | D17: =VLOOKUP(B17,SeasonTable,2,FALSE) | E17: =(1+InflationRate)^INT((A17-1)/12) | F17: =MonthlyChurn*VLOOKUP(B17,ChurnSeasonTable,4,FALSE) | G17: =MIN(MAX(MktMin13_18,AA16*MktPct13_18),MAX(0,AO16-CashBuffer)) | H17: =IF(G17>0,MAX(1,ROUND(G17/CAC*D17,0)),0) | I17: =IF(H17>0,ROUND(H17*ReferralMix/(1-ReferralMix),0),0) | J17: =H17+I17 | K17: =ROUND(J17*(1-AnnualMix),0) | L17: =J17-K17 | M17: =ROUND(K17*EssentialMix,0) | N17: =K17-M17 | O17: =ROUND(L17*EssentialMix,0) | P17: =L17-O17 | Q17: =M17+M16+M15+MAX(0,Q16-M16-M15)*(1-F17) | R17: =N17+N16+N15+MAX(0,R16-N16-N15)*(1-F17) | S17: =S16+O17-O5*(AnnualChurn*VLOOKUP(B17,ChurnSeasonTable,4,FALSE))*POWER(1-(AnnualChurn*VLOOKUP(B17,ChurnSeasonTable,4,FALSE)),0) | T17: =T16+P17-P5*(AnnualChurn*VLOOKUP(B17,ChurnSeasonTable,4,FALSE))*POWER(1-(AnnualChurn*VLOOKUP(B17,ChurnSeasonTable,4,FALSE)),0) | U17: =Q17+R17+S17+T17 | V17: =Q17*PriceEssMonthly*E17+R17*PricePremMonthly*E17+S17*PriceEssAnnual*E17/12+T17*PricePremAnnual*E17/12 | W17: =V17*12 | X17: =Q17*PriceEssMonthly*E17+R17*PricePremMonthly*E17 | Y17: =O17*PriceEssAnnual*E17+P17*PricePremAnnual*E17 | Z17: =O5*POWER(1-(AnnualChurn*VLOOKUP(B17,ChurnSeasonTable,4,FALSE)),1)*PriceEssAnnual*E17+P5*POWER(1-(AnnualChurn*VLOOKUP(B17,ChurnSeasonTable,4,FALSE)),1)*PricePremAnnual*E17 | AA17: =X17+Y17+Z17 | AB17: =SUM(AA6:AA17) | AC17: =OR(AC16,AB17>=VATThreshold) | AD17: =IF(AC17,AA17/(1+VATRate),AA17) | AE17: =AA17-AD17 | AF17: =IF(AC17=0,0,IF(B17=1,SUMPRODUCT(--(($C$5:$C17=$C17-1)*($B$5:$B17>=10)*($B$5:$B17<=12)),$AE$5:$AE17),IF(B17=4,SUMPRODUCT(--(($C$5:$C17=$C17)*($B$5:$B17>=1)*($B$5:$B17<=3)),$AE$5:$AE17),IF(B17=7,SUMPRODUCT(--(($C$5:$C17=$C17)*($B$5:$B17>=4)*($B$5:$B17<=6)),$AE$5:$AE17),IF(B17=10,SUMPRODUCT(--(($C$5:$C17=$C17)*($B$5:$B17>=7)*($B$5:$B17<=9)),$AE$5:$AE17),0))))) | AG17: =AG16+AE17-AF17 | AH17: =IF(ProviderDelay>=1,AD16*ProviderShare,AD17*ProviderShare) | AI17: =AA17*PaymentFee | AJ17: =U17*OpsAI | AK17: =MonthlyFixed | AL17: =I17*ReferralReward | AM17: =G17 | AN17: =AD17-AH17-AI17-AJ17-AK17-AL17-AM17 | AO17: =AO16+AA17-(AH17+AI17+AJ17+AK17+AL17+AM17+AF17) | AP17: =IF(U17>0,V17/U17,0) | AQ17: =IF(U16>0,MAX(0,(U16+J17-U17)/U16),0)
A18: 14 | B18: =MOD(A18-1+LaunchMonth-1,12)+1 | C18: =INT((A18-1+LaunchMonth-1)/12)+1 | D18: =VLOOKUP(B18,SeasonTable,2,FALSE) | E18: =(1+InflationRate)^INT((A18-1)/12) | F18: =MonthlyChurn*VLOOKUP(B18,ChurnSeasonTable,4,FALSE) | G18: =MIN(MAX(MktMin13_18,AA17*MktPct13_18),MAX(0,AO17-CashBuffer)) | H18: =IF(G18>0,MAX(1,ROUND(G18/CAC*D18,0)),0) | I18: =IF(H18>0,ROUND(H18*ReferralMix/(1-ReferralMix),0),0) | J18: =H18+I18 | K18: =ROUND(J18*(1-AnnualMix),0) | L18: =J18-K18 | M18: =ROUND(K18*EssentialMix,0) | N18: =K18-M18 | O18: =ROUND(L18*EssentialMix,0) | P18: =L18-O18 | Q18: =M18+M17+M16+MAX(0,Q17-M17-M16)*(1-F18) | R18: =N18+N17+N16+MAX(0,R17-N17-N16)*(1-F18) | S18: =S17+O18-O6*(AnnualChurn*VLOOKUP(B18,ChurnSeasonTable,4,FALSE))*POWER(1-(AnnualChurn*VLOOKUP(B18,ChurnSeasonTable,4,FALSE)),0) | T18: =T17+P18-P6*(AnnualChurn*VLOOKUP(B18,ChurnSeasonTable,4,FALSE))*POWER(1-(AnnualChurn*VLOOKUP(B18,ChurnSeasonTable,4,FALSE)),0) | U18: =Q18+R18+S18+T18 | V18: =Q18*PriceEssMonthly*E18+R18*PricePremMonthly*E18+S18*PriceEssAnnual*E18/12+T18*PricePremAnnual*E18/12 | W18: =V18*12 | X18: =Q18*PriceEssMonthly*E18+R18*PricePremMonthly*E18 | Y18: =O18*PriceEssAnnual*E18+P18*PricePremAnnual*E18 | Z18: =O6*POWER(1-(AnnualChurn*VLOOKUP(B18,ChurnSeasonTable,4,FALSE)),1)*PriceEssAnnual*E18+P6*POWER(1-(AnnualChurn*VLOOKUP(B18,ChurnSeasonTable,4,FALSE)),1)*PricePremAnnual*E18 | AA18: =X18+Y18+Z18 | AB18: =SUM(AA7:AA18) | AC18: =OR(AC17,AB18>=VATThreshold) | AD18: =IF(AC18,AA18/(1+VATRate),AA18) | AE18: =AA18-AD18 | AF18: =IF(AC18=0,0,IF(B18=1,SUMPRODUCT(--(($C$5:$C18=$C18-1)*($B$5:$B18>=10)*($B$5:$B18<=12)),$AE$5:$AE18),IF(B18=4,SUMPRODUCT(--(($C$5:$C18=$C18)*($B$5:$B18>=1)*($B$5:$B18<=3)),$AE$5:$AE18),IF(B18=7,SUMPRODUCT(--(($C$5:$C18=$C18)*($B$5:$B18>=4)*($B$5:$B18<=6)),$AE$5:$AE18),IF(B18=10,SUMPRODUCT(--(($C$5:$C18=$C18)*($B$5:$B18>=7)*($B$5:$B18<=9)),$AE$5:$AE18),0))))) | AG18: =AG17+AE18-AF18 | AH18: =IF(ProviderDelay>=1,AD17*ProviderShare,AD18*ProviderShare) | AI18: =AA18*PaymentFee | AJ18: =U18*OpsAI | AK18: =MonthlyFixed | AL18: =I18*ReferralReward | AM18: =G18 | AN18: =AD18-AH18-AI18-AJ18-AK18-AL18-AM18 | AO18: =AO17+AA18-(AH18+AI18+AJ18+AK18+AL18+AM18+AF18) | AP18: =IF(U18>0,V18/U18,0) | AQ18: =IF(U17>0,MAX(0,(U17+J18-U18)/U17),0)
A19: 15 | B19: =MOD(A19-1+LaunchMonth-1,12)+1 | C19: =INT((A19-1+LaunchMonth-1)/12)+1 | D19: =VLOOKUP(B19,SeasonTable,2,FALSE) | E19: =(1+InflationRate)^INT((A19-1)/12) | F19: =MonthlyChurn*VLOOKUP(B19,ChurnSeasonTable,4,FALSE) | G19: =MIN(MAX(MktMin13_18,AA18*MktPct13_18),MAX(0,AO18-CashBuffer)) | H19: =IF(G19>0,MAX(1,ROUND(G19/CAC*D19,0)),0) | I19: =IF(H19>0,ROUND(H19*ReferralMix/(1-ReferralMix),0),0) | J19: =H19+I19 | K19: =ROUND(J19*(1-AnnualMix),0) | L19: =J19-K19 | M19: =ROUND(K19*EssentialMix,0) | N19: =K19-M19 | O19: =ROUND(L19*EssentialMix,0) | P19: =L19-O19 | Q19: =M19+M18+M17+MAX(0,Q18-M18-M17)*(1-F19) | R19: =N19+N18+N17+MAX(0,R18-N18-N17)*(1-F19) | S19: =S18+O19-O7*(AnnualChurn*VLOOKUP(B19,ChurnSeasonTable,4,FALSE))*POWER(1-(AnnualChurn*VLOOKUP(B19,ChurnSeasonTable,4,FALSE)),0) | T19: =T18+P19-P7*(AnnualChurn*VLOOKUP(B19,ChurnSeasonTable,4,FALSE))*POWER(1-(AnnualChurn*VLOOKUP(B19,ChurnSeasonTable,4,FALSE)),0) | U19: =Q19+R19+S19+T19 | V19: =Q19*PriceEssMonthly*E19+R19*PricePremMonthly*E19+S19*PriceEssAnnual*E19/12+T19*PricePremAnnual*E19/12 | W19: =V19*12 | X19: =Q19*PriceEssMonthly*E19+R19*PricePremMonthly*E19 | Y19: =O19*PriceEssAnnual*E19+P19*PricePremAnnual*E19 | Z19: =O7*POWER(1-(AnnualChurn*VLOOKUP(B19,ChurnSeasonTable,4,FALSE)),1)*PriceEssAnnual*E19+P7*POWER(1-(AnnualChurn*VLOOKUP(B19,ChurnSeasonTable,4,FALSE)),1)*PricePremAnnual*E19 | AA19: =X19+Y19+Z19 | AB19: =SUM(AA8:AA19) | AC19: =OR(AC18,AB19>=VATThreshold) | AD19: =IF(AC19,AA19/(1+VATRate),AA19) | AE19: =AA19-AD19 | AF19: =IF(AC19=0,0,IF(B19=1,SUMPRODUCT(--(($C$5:$C19=$C19-1)*($B$5:$B19>=10)*($B$5:$B19<=12)),$AE$5:$AE19),IF(B19=4,SUMPRODUCT(--(($C$5:$C19=$C19)*($B$5:$B19>=1)*($B$5:$B19<=3)),$AE$5:$AE19),IF(B19=7,SUMPRODUCT(--(($C$5:$C19=$C19)*($B$5:$B19>=4)*($B$5:$B19<=6)),$AE$5:$AE19),IF(B19=10,SUMPRODUCT(--(($C$5:$C19=$C19)*($B$5:$B19>=7)*($B$5:$B19<=9)),$AE$5:$AE19),0))))) | AG19: =AG18+AE19-AF19 | AH19: =IF(ProviderDelay>=1,AD18*ProviderShare,AD19*ProviderShare) | AI19: =AA19*PaymentFee | AJ19: =U19*OpsAI | AK19: =MonthlyFixed | AL19: =I19*ReferralReward | AM19: =G19 | AN19: =AD19-AH19-AI19-AJ19-AK19-AL19-AM19 | AO19: =AO18+AA19-(AH19+AI19+AJ19+AK19+AL19+AM19+AF19) | AP19: =IF(U19>0,V19/U19,0) | AQ19: =IF(U18>0,MAX(0,(U18+J19-U19)/U18),0)
A20: 16 | B20: =MOD(A20-1+LaunchMonth-1,12)+1 | C20: =INT((A20-1+LaunchMonth-1)/12)+1 | D20: =VLOOKUP(B20,SeasonTable,2,FALSE) | E20: =(1+InflationRate)^INT((A20-1)/12) | F20: =MonthlyChurn*VLOOKUP(B20,ChurnSeasonTable,4,FALSE) | G20: =MIN(MAX(MktMin13_18,AA19*MktPct13_18),MAX(0,AO19-CashBuffer)) | H20: =IF(G20>0,MAX(1,ROUND(G20/CAC*D20,0)),0) | I20: =IF(H20>0,ROUND(H20*ReferralMix/(1-ReferralMix),0),0) | J20: =H20+I20 | K20: =ROUND(J20*(1-AnnualMix),0) | L20: =J20-K20 | M20: =ROUND(K20*EssentialMix,0) | N20: =K20-M20 | O20: =ROUND(L20*EssentialMix,0) | P20: =L20-O20 | Q20: =M20+M19+M18+MAX(0,Q19-M19-M18)*(1-F20) | R20: =N20+N19+N18+MAX(0,R19-N19-N18)*(1-F20) | S20: =S19+O20-O8*(AnnualChurn*VLOOKUP(B20,ChurnSeasonTable,4,FALSE))*POWER(1-(AnnualChurn*VLOOKUP(B20,ChurnSeasonTable,4,FALSE)),0) | T20: =T19+P20-P8*(AnnualChurn*VLOOKUP(B20,ChurnSeasonTable,4,FALSE))*POWER(1-(AnnualChurn*VLOOKUP(B20,ChurnSeasonTable,4,FALSE)),0) | U20: =Q20+R20+S20+T20 | V20: =Q20*PriceEssMonthly*E20+R20*PricePremMonthly*E20+S20*PriceEssAnnual*E20/12+T20*PricePremAnnual*E20/12 | W20: =V20*12 | X20: =Q20*PriceEssMonthly*E20+R20*PricePremMonthly*E20 | Y20: =O20*PriceEssAnnual*E20+P20*PricePremAnnual*E20 | Z20: =O8*POWER(1-(AnnualChurn*VLOOKUP(B20,ChurnSeasonTable,4,FALSE)),1)*PriceEssAnnual*E20+P8*POWER(1-(AnnualChurn*VLOOKUP(B20,ChurnSeasonTable,4,FALSE)),1)*PricePremAnnual*E20 | AA20: =X20+Y20+Z20 | AB20: =SUM(AA9:AA20) | AC20: =OR(AC19,AB20>=VATThreshold) | AD20: =IF(AC20,AA20/(1+VATRate),AA20) | AE20: =AA20-AD20 | AF20: =IF(AC20=0,0,IF(B20=1,SUMPRODUCT(--(($C$5:$C20=$C20-1)*($B$5:$B20>=10)*($B$5:$B20<=12)),$AE$5:$AE20),IF(B20=4,SUMPRODUCT(--(($C$5:$C20=$C20)*($B$5:$B20>=1)*($B$5:$B20<=3)),$AE$5:$AE20),IF(B20=7,SUMPRODUCT(--(($C$5:$C20=$C20)*($B$5:$B20>=4)*($B$5:$B20<=6)),$AE$5:$AE20),IF(B20=10,SUMPRODUCT(--(($C$5:$C20=$C20)*($B$5:$B20>=7)*($B$5:$B20<=9)),$AE$5:$AE20),0))))) | AG20: =AG19+AE20-AF20 | AH20: =IF(ProviderDelay>=1,AD19*ProviderShare,AD20*ProviderShare) | AI20: =AA20*PaymentFee | AJ20: =U20*OpsAI | AK20: =MonthlyFixed | AL20: =I20*ReferralReward | AM20: =G20 | AN20: =AD20-AH20-AI20-AJ20-AK20-AL20-AM20 | AO20: =AO19+AA20-(AH20+AI20+AJ20+AK20+AL20+AM20+AF20) | AP20: =IF(U20>0,V20/U20,0) | AQ20: =IF(U19>0,MAX(0,(U19+J20-U20)/U19),0)
A21: 17 | B21: =MOD(A21-1+LaunchMonth-1,12)+1 | C21: =INT((A21-1+LaunchMonth-1)/12)+1 | D21: =VLOOKUP(B21,SeasonTable,2,FALSE) | E21: =(1+InflationRate)^INT((A21-1)/12) | F21: =MonthlyChurn*VLOOKUP(B21,ChurnSeasonTable,4,FALSE) | G21: =MIN(MAX(MktMin13_18,AA20*MktPct13_18),MAX(0,AO20-CashBuffer)) | H21: =IF(G21>0,MAX(1,ROUND(G21/CAC*D21,0)),0) | I21: =IF(H21>0,ROUND(H21*ReferralMix/(1-ReferralMix),0),0) | J21: =H21+I21 | K21: =ROUND(J21*(1-AnnualMix),0) | L21: =J21-K21 | M21: =ROUND(K21*EssentialMix,0) | N21: =K21-M21 | O21: =ROUND(L21*EssentialMix,0) | P21: =L21-O21 | Q21: =M21+M20+M19+MAX(0,Q20-M20-M19)*(1-F21) | R21: =N21+N20+N19+MAX(0,R20-N20-N19)*(1-F21) | S21: =S20+O21-O9*(AnnualChurn*VLOOKUP(B21,ChurnSeasonTable,4,FALSE))*POWER(1-(AnnualChurn*VLOOKUP(B21,ChurnSeasonTable,4,FALSE)),0) | T21: =T20+P21-P9*(AnnualChurn*VLOOKUP(B21,ChurnSeasonTable,4,FALSE))*POWER(1-(AnnualChurn*VLOOKUP(B21,ChurnSeasonTable,4,FALSE)),0) | U21: =Q21+R21+S21+T21 | V21: =Q21*PriceEssMonthly*E21+R21*PricePremMonthly*E21+S21*PriceEssAnnual*E21/12+T21*PricePremAnnual*E21/12 | W21: =V21*12 | X21: =Q21*PriceEssMonthly*E21+R21*PricePremMonthly*E21 | Y21: =O21*PriceEssAnnual*E21+P21*PricePremAnnual*E21 | Z21: =O9*POWER(1-(AnnualChurn*VLOOKUP(B21,ChurnSeasonTable,4,FALSE)),1)*PriceEssAnnual*E21+P9*POWER(1-(AnnualChurn*VLOOKUP(B21,ChurnSeasonTable,4,FALSE)),1)*PricePremAnnual*E21 | AA21: =X21+Y21+Z21 | AB21: =SUM(AA10:AA21) | AC21: =OR(AC20,AB21>=VATThreshold) | AD21: =IF(AC21,AA21/(1+VATRate),AA21) | AE21: =AA21-AD21 | AF21: =IF(AC21=0,0,IF(B21=1,SUMPRODUCT(--(($C$5:$C21=$C21-1)*($B$5:$B21>=10)*($B$5:$B21<=12)),$AE$5:$AE21),IF(B21=4,SUMPRODUCT(--(($C$5:$C21=$C21)*($B$5:$B21>=1)*($B$5:$B21<=3)),$AE$5:$AE21),IF(B21=7,SUMPRODUCT(--(($C$5:$C21=$C21)*($B$5:$B21>=4)*($B$5:$B21<=6)),$AE$5:$AE21),IF(B21=10,SUMPRODUCT(--(($C$5:$C21=$C21)*($B$5:$B21>=7)*($B$5:$B21<=9)),$AE$5:$AE21),0))))) | AG21: =AG20+AE21-AF21 | AH21: =IF(ProviderDelay>=1,AD20*ProviderShare,AD21*ProviderShare) | AI21: =AA21*PaymentFee | AJ21: =U21*OpsAI | AK21: =MonthlyFixed | AL21: =I21*ReferralReward | AM21: =G21 | AN21: =AD21-AH21-AI21-AJ21-AK21-AL21-AM21 | AO21: =AO20+AA21-(AH21+AI21+AJ21+AK21+AL21+AM21+AF21) | AP21: =IF(U21>0,V21/U21,0) | AQ21: =IF(U20>0,MAX(0,(U20+J21-U21)/U20),0)
A22: 18 | B22: =MOD(A22-1+LaunchMonth-1,12)+1 | C22: =INT((A22-1+LaunchMonth-1)/12)+1 | D22: =VLOOKUP(B22,SeasonTable,2,FALSE) | E22: =(1+InflationRate)^INT((A22-1)/12) | F22: =MonthlyChurn*VLOOKUP(B22,ChurnSeasonTable,4,FALSE) | G22: =MIN(MAX(MktMin13_18,AA21*MktPct13_18),MAX(0,AO21-CashBuffer)) | H22: =IF(G22>0,MAX(1,ROUND(G22/CAC*D22,0)),0) | I22: =IF(H22>0,ROUND(H22*ReferralMix/(1-ReferralMix),0),0) | J22: =H22+I22 | K22: =ROUND(J22*(1-AnnualMix),0) | L22: =J22-K22 | M22: =ROUND(K22*EssentialMix,0) | N22: =K22-M22 | O22: =ROUND(L22*EssentialMix,0) | P22: =L22-O22 | Q22: =M22+M21+M20+MAX(0,Q21-M21-M20)*(1-F22) | R22: =N22+N21+N20+MAX(0,R21-N21-N20)*(1-F22) | S22: =S21+O22-O10*(AnnualChurn*VLOOKUP(B22,ChurnSeasonTable,4,FALSE))*POWER(1-(AnnualChurn*VLOOKUP(B22,ChurnSeasonTable,4,FALSE)),0) | T22: =T21+P22-P10*(AnnualChurn*VLOOKUP(B22,ChurnSeasonTable,4,FALSE))*POWER(1-(AnnualChurn*VLOOKUP(B22,ChurnSeasonTable,4,FALSE)),0) | U22: =Q22+R22+S22+T22 | V22: =Q22*PriceEssMonthly*E22+R22*PricePremMonthly*E22+S22*PriceEssAnnual*E22/12+T22*PricePremAnnual*E22/12 | W22: =V22*12 | X22: =Q22*PriceEssMonthly*E22+R22*PricePremMonthly*E22 | Y22: =O22*PriceEssAnnual*E22+P22*PricePremAnnual*E22 | Z22: =O10*POWER(1-(AnnualChurn*VLOOKUP(B22,ChurnSeasonTable,4,FALSE)),1)*PriceEssAnnual*E22+P10*POWER(1-(AnnualChurn*VLOOKUP(B22,ChurnSeasonTable,4,FALSE)),1)*PricePremAnnual*E22 | AA22: =X22+Y22+Z22 | AB22: =SUM(AA11:AA22) | AC22: =OR(AC21,AB22>=VATThreshold) | AD22: =IF(AC22,AA22/(1+VATRate),AA22) | AE22: =AA22-AD22 | AF22: =IF(AC22=0,0,IF(B22=1,SUMPRODUCT(--(($C$5:$C22=$C22-1)*($B$5:$B22>=10)*($B$5:$B22<=12)),$AE$5:$AE22),IF(B22=4,SUMPRODUCT(--(($C$5:$C22=$C22)*($B$5:$B22>=1)*($B$5:$B22<=3)),$AE$5:$AE22),IF(B22=7,SUMPRODUCT(--(($C$5:$C22=$C22)*($B$5:$B22>=4)*($B$5:$B22<=6)),$AE$5:$AE22),IF(B22=10,SUMPRODUCT(--(($C$5:$C22=$C22)*($B$5:$B22>=7)*($B$5:$B22<=9)),$AE$5:$AE22),0))))) | AG22: =AG21+AE22-AF22 | AH22: =IF(ProviderDelay>=1,AD21*ProviderShare,AD22*ProviderShare) | AI22: =AA22*PaymentFee | AJ22: =U22*OpsAI | AK22: =MonthlyFixed | AL22: =I22*ReferralReward | AM22: =G22 | AN22: =AD22-AH22-AI22-AJ22-AK22-AL22-AM22 | AO22: =AO21+AA22-(AH22+AI22+AJ22+AK22+AL22+AM22+AF22) | AP22: =IF(U22>0,V22/U22,0) | AQ22: =IF(U21>0,MAX(0,(U21+J22-U22)/U21),0)
A23: 19 | B23: =MOD(A23-1+LaunchMonth-1,12)+1 | C23: =INT((A23-1+LaunchMonth-1)/12)+1 | D23: =VLOOKUP(B23,SeasonTable,2,FALSE) | E23: =(1+InflationRate)^INT((A23-1)/12) | F23: =MonthlyChurn*VLOOKUP(B23,ChurnSeasonTable,4,FALSE) | G23: =MIN(MAX(MktMin19plus,AA22*MktPct19plus),MAX(0,AO22-CashBuffer)) | H23: =IF(G23>0,MAX(1,ROUND(G23/CAC*D23,0)),0) | I23: =IF(H23>0,ROUND(H23*ReferralMix/(1-ReferralMix),0),0) | J23: =H23+I23 | K23: =ROUND(J23*(1-AnnualMix),0) | L23: =J23-K23 | M23: =ROUND(K23*EssentialMix,0) | N23: =K23-M23 | O23: =ROUND(L23*EssentialMix,0) | P23: =L23-O23 | Q23: =M23+M22+M21+MAX(0,Q22-M22-M21)*(1-F23) | R23: =N23+N22+N21+MAX(0,R22-N22-N21)*(1-F23) | S23: =S22+O23-O11*(AnnualChurn*VLOOKUP(B23,ChurnSeasonTable,4,FALSE))*POWER(1-(AnnualChurn*VLOOKUP(B23,ChurnSeasonTable,4,FALSE)),0) | T23: =T22+P23-P11*(AnnualChurn*VLOOKUP(B23,ChurnSeasonTable,4,FALSE))*POWER(1-(AnnualChurn*VLOOKUP(B23,ChurnSeasonTable,4,FALSE)),0) | U23: =Q23+R23+S23+T23 | V23: =Q23*PriceEssMonthly*E23+R23*PricePremMonthly*E23+S23*PriceEssAnnual*E23/12+T23*PricePremAnnual*E23/12 | W23: =V23*12 | X23: =Q23*PriceEssMonthly*E23+R23*PricePremMonthly*E23 | Y23: =O23*PriceEssAnnual*E23+P23*PricePremAnnual*E23 | Z23: =O11*POWER(1-(AnnualChurn*VLOOKUP(B23,ChurnSeasonTable,4,FALSE)),1)*PriceEssAnnual*E23+P11*POWER(1-(AnnualChurn*VLOOKUP(B23,ChurnSeasonTable,4,FALSE)),1)*PricePremAnnual*E23 | AA23: =X23+Y23+Z23 | AB23: =SUM(AA12:AA23) | AC23: =OR(AC22,AB23>=VATThreshold) | AD23: =IF(AC23,AA23/(1+VATRate),AA23) | AE23: =AA23-AD23 | AF23: =IF(AC23=0,0,IF(B23=1,SUMPRODUCT(--(($C$5:$C23=$C23-1)*($B$5:$B23>=10)*($B$5:$B23<=12)),$AE$5:$AE23),IF(B23=4,SUMPRODUCT(--(($C$5:$C23=$C23)*($B$5:$B23>=1)*($B$5:$B23<=3)),$AE$5:$AE23),IF(B23=7,SUMPRODUCT(--(($C$5:$C23=$C23)*($B$5:$B23>=4)*($B$5:$B23<=6)),$AE$5:$AE23),IF(B23=10,SUMPRODUCT(--(($C$5:$C23=$C23)*($B$5:$B23>=7)*($B$5:$B23<=9)),$AE$5:$AE23),0))))) | AG23: =AG22+AE23-AF23 | AH23: =IF(ProviderDelay>=1,AD22*ProviderShare,AD23*ProviderShare) | AI23: =AA23*PaymentFee | AJ23: =U23*OpsAI | AK23: =MonthlyFixed | AL23: =I23*ReferralReward | AM23: =G23 | AN23: =AD23-AH23-AI23-AJ23-AK23-AL23-AM23 | AO23: =AO22+AA23-(AH23+AI23+AJ23+AK23+AL23+AM23+AF23) | AP23: =IF(U23>0,V23/U23,0) | AQ23: =IF(U22>0,MAX(0,(U22+J23-U23)/U22),0)
A24: 20 | B24: =MOD(A24-1+LaunchMonth-1,12)+1 | C24: =INT((A24-1+LaunchMonth-1)/12)+1 | D24: =VLOOKUP(B24,SeasonTable,2,FALSE) | E24: =(1+InflationRate)^INT((A24-1)/12) | F24: =MonthlyChurn*VLOOKUP(B24,ChurnSeasonTable,4,FALSE) | G24: =MIN(MAX(MktMin19plus,AA23*MktPct19plus),MAX(0,AO23-CashBuffer)) | H24: =IF(G24>0,MAX(1,ROUND(G24/CAC*D24,0)),0) | I24: =IF(H24>0,ROUND(H24*ReferralMix/(1-ReferralMix),0),0) | J24: =H24+I24 | K24: =ROUND(J24*(1-AnnualMix),0) | L24: =J24-K24 | M24: =ROUND(K24*EssentialMix,0) | N24: =K24-M24 | O24: =ROUND(L24*EssentialMix,0) | P24: =L24-O24 | Q24: =M24+M23+M22+MAX(0,Q23-M23-M22)*(1-F24) | R24: =N24+N23+N22+MAX(0,R23-N23-N22)*(1-F24) | S24: =S23+O24-O12*(AnnualChurn*VLOOKUP(B24,ChurnSeasonTable,4,FALSE))*POWER(1-(AnnualChurn*VLOOKUP(B24,ChurnSeasonTable,4,FALSE)),0) | T24: =T23+P24-P12*(AnnualChurn*VLOOKUP(B24,ChurnSeasonTable,4,FALSE))*POWER(1-(AnnualChurn*VLOOKUP(B24,ChurnSeasonTable,4,FALSE)),0) | U24: =Q24+R24+S24+T24 | V24: =Q24*PriceEssMonthly*E24+R24*PricePremMonthly*E24+S24*PriceEssAnnual*E24/12+T24*PricePremAnnual*E24/12 | W24: =V24*12 | X24: =Q24*PriceEssMonthly*E24+R24*PricePremMonthly*E24 | Y24: =O24*PriceEssAnnual*E24+P24*PricePremAnnual*E24 | Z24: =O12*POWER(1-(AnnualChurn*VLOOKUP(B24,ChurnSeasonTable,4,FALSE)),1)*PriceEssAnnual*E24+P12*POWER(1-(AnnualChurn*VLOOKUP(B24,ChurnSeasonTable,4,FALSE)),1)*PricePremAnnual*E24 | AA24: =X24+Y24+Z24 | AB24: =SUM(AA13:AA24) | AC24: =OR(AC23,AB24>=VATThreshold) | AD24: =IF(AC24,AA24/(1+VATRate),AA24) | AE24: =AA24-AD24 | AF24: =IF(AC24=0,0,IF(B24=1,SUMPRODUCT(--(($C$5:$C24=$C24-1)*($B$5:$B24>=10)*($B$5:$B24<=12)),$AE$5:$AE24),IF(B24=4,SUMPRODUCT(--(($C$5:$C24=$C24)*($B$5:$B24>=1)*($B$5:$B24<=3)),$AE$5:$AE24),IF(B24=7,SUMPRODUCT(--(($C$5:$C24=$C24)*($B$5:$B24>=4)*($B$5:$B24<=6)),$AE$5:$AE24),IF(B24=10,SUMPRODUCT(--(($C$5:$C24=$C24)*($B$5:$B24>=7)*($B$5:$B24<=9)),$AE$5:$AE24),0))))) | AG24: =AG23+AE24-AF24 | AH24: =IF(ProviderDelay>=1,AD23*ProviderShare,AD24*ProviderShare) | AI24: =AA24*PaymentFee | AJ24: =U24*OpsAI | AK24: =MonthlyFixed | AL24: =I24*ReferralReward | AM24: =G24 | AN24: =AD24-AH24-AI24-AJ24-AK24-AL24-AM24 | AO24: =AO23+AA24-(AH24+AI24+AJ24+AK24+AL24+AM24+AF24) | AP24: =IF(U24>0,V24/U24,0) | AQ24: =IF(U23>0,MAX(0,(U23+J24-U24)/U23),0)
A25: 21 | B25: =MOD(A25-1+LaunchMonth-1,12)+1 | C25: =INT((A25-1+LaunchMonth-1)/12)+1 | D25: =VLOOKUP(B25,SeasonTable,2,FALSE) | E25: =(1+InflationRate)^INT((A25-1)/12) | F25: =MonthlyChurn*VLOOKUP(B25,ChurnSeasonTable,4,FALSE) | G25: =MIN(MAX(MktMin19plus,AA24*MktPct19plus),MAX(0,AO24-CashBuffer)) | H25: =IF(G25>0,MAX(1,ROUND(G25/CAC*D25,0)),0) | I25: =IF(H25>0,ROUND(H25*ReferralMix/(1-ReferralMix),0),0) | J25: =H25+I25 | K25: =ROUND(J25*(1-AnnualMix),0) | L25: =J25-K25 | M25: =ROUND(K25*EssentialMix,0) | N25: =K25-M25 | O25: =ROUND(L25*EssentialMix,0) | P25: =L25-O25 | Q25: =M25+M24+M23+MAX(0,Q24-M24-M23)*(1-F25) | R25: =N25+N24+N23+MAX(0,R24-N24-N23)*(1-F25) | S25: =S24+O25-O13*(AnnualChurn*VLOOKUP(B25,ChurnSeasonTable,4,FALSE))*POWER(1-(AnnualChurn*VLOOKUP(B25,ChurnSeasonTable,4,FALSE)),0) | T25: =T24+P25-P13*(AnnualChurn*VLOOKUP(B25,ChurnSeasonTable,4,FALSE))*POWER(1-(AnnualChurn*VLOOKUP(B25,ChurnSeasonTable,4,FALSE)),0) | U25: =Q25+R25+S25+T25 | V25: =Q25*PriceEssMonthly*E25+R25*PricePremMonthly*E25+S25*PriceEssAnnual*E25/12+T25*PricePremAnnual*E25/12 | W25: =V25*12 | X25: =Q25*PriceEssMonthly*E25+R25*PricePremMonthly*E25 | Y25: =O25*PriceEssAnnual*E25+P25*PricePremAnnual*E25 | Z25: =O13*POWER(1-(AnnualChurn*VLOOKUP(B25,ChurnSeasonTable,4,FALSE)),1)*PriceEssAnnual*E25+P13*POWER(1-(AnnualChurn*VLOOKUP(B25,ChurnSeasonTable,4,FALSE)),1)*PricePremAnnual*E25 | AA25: =X25+Y25+Z25 | AB25: =SUM(AA14:AA25) | AC25: =OR(AC24,AB25>=VATThreshold) | AD25: =IF(AC25,AA25/(1+VATRate),AA25) | AE25: =AA25-AD25 | AF25: =IF(AC25=0,0,IF(B25=1,SUMPRODUCT(--(($C$5:$C25=$C25-1)*($B$5:$B25>=10)*($B$5:$B25<=12)),$AE$5:$AE25),IF(B25=4,SUMPRODUCT(--(($C$5:$C25=$C25)*($B$5:$B25>=1)*($B$5:$B25<=3)),$AE$5:$AE25),IF(B25=7,SUMPRODUCT(--(($C$5:$C25=$C25)*($B$5:$B25>=4)*($B$5:$B25<=6)),$AE$5:$AE25),IF(B25=10,SUMPRODUCT(--(($C$5:$C25=$C25)*($B$5:$B25>=7)*($B$5:$B25<=9)),$AE$5:$AE25),0))))) | AG25: =AG24+AE25-AF25 | AH25: =IF(ProviderDelay>=1,AD24*ProviderShare,AD25*ProviderShare) | AI25: =AA25*PaymentFee | AJ25: =U25*OpsAI | AK25: =MonthlyFixed | AL25: =I25*ReferralReward | AM25: =G25 | AN25: =AD25-AH25-AI25-AJ25-AK25-AL25-AM25 | AO25: =AO24+AA25-(AH25+AI25+AJ25+AK25+AL25+AM25+AF25) | AP25: =IF(U25>0,V25/U25,0) | AQ25: =IF(U24>0,MAX(0,(U24+J25-U25)/U24),0)
A26: 22 | B26: =MOD(A26-1+LaunchMonth-1,12)+1 | C26: =INT((A26-1+LaunchMonth-1)/12)+1 | D26: =VLOOKUP(B26,SeasonTable,2,FALSE) | E26: =(1+InflationRate)^INT((A26-1)/12) | F26: =MonthlyChurn*VLOOKUP(B26,ChurnSeasonTable,4,FALSE) | G26: =MIN(MAX(MktMin19plus,AA25*MktPct19plus),MAX(0,AO25-CashBuffer)) | H26: =IF(G26>0,MAX(1,ROUND(G26/CAC*D26,0)),0) | I26: =IF(H26>0,ROUND(H26*ReferralMix/(1-ReferralMix),0),0) | J26: =H26+I26 | K26: =ROUND(J26*(1-AnnualMix),0) | L26: =J26-K26 | M26: =ROUND(K26*EssentialMix,0) | N26: =K26-M26 | O26: =ROUND(L26*EssentialMix,0) | P26: =L26-O26 | Q26: =M26+M25+M24+MAX(0,Q25-M25-M24)*(1-F26) | R26: =N26+N25+N24+MAX(0,R25-N25-N24)*(1-F26) | S26: =S25+O26-O14*(AnnualChurn*VLOOKUP(B26,ChurnSeasonTable,4,FALSE))*POWER(1-(AnnualChurn*VLOOKUP(B26,ChurnSeasonTable,4,FALSE)),0) | T26: =T25+P26-P14*(AnnualChurn*VLOOKUP(B26,ChurnSeasonTable,4,FALSE))*POWER(1-(AnnualChurn*VLOOKUP(B26,ChurnSeasonTable,4,FALSE)),0) | U26: =Q26+R26+S26+T26 | V26: =Q26*PriceEssMonthly*E26+R26*PricePremMonthly*E26+S26*PriceEssAnnual*E26/12+T26*PricePremAnnual*E26/12 | W26: =V26*12 | X26: =Q26*PriceEssMonthly*E26+R26*PricePremMonthly*E26 | Y26: =O26*PriceEssAnnual*E26+P26*PricePremAnnual*E26 | Z26: =O14*POWER(1-(AnnualChurn*VLOOKUP(B26,ChurnSeasonTable,4,FALSE)),1)*PriceEssAnnual*E26+P14*POWER(1-(AnnualChurn*VLOOKUP(B26,ChurnSeasonTable,4,FALSE)),1)*PricePremAnnual*E26 | AA26: =X26+Y26+Z26 | AB26: =SUM(AA15:AA26) | AC26: =OR(AC25,AB26>=VATThreshold) | AD26: =IF(AC26,AA26/(1+VATRate),AA26) | AE26: =AA26-AD26 | AF26: =IF(AC26=0,0,IF(B26=1,SUMPRODUCT(--(($C$5:$C26=$C26-1)*($B$5:$B26>=10)*($B$5:$B26<=12)),$AE$5:$AE26),IF(B26=4,SUMPRODUCT(--(($C$5:$C26=$C26)*($B$5:$B26>=1)*($B$5:$B26<=3)),$AE$5:$AE26),IF(B26=7,SUMPRODUCT(--(($C$5:$C26=$C26)*($B$5:$B26>=4)*($B$5:$B26<=6)),$AE$5:$AE26),IF(B26=10,SUMPRODUCT(--(($C$5:$C26=$C26)*($B$5:$B26>=7)*($B$5:$B26<=9)),$AE$5:$AE26),0))))) | AG26: =AG25+AE26-AF26 | AH26: =IF(ProviderDelay>=1,AD25*ProviderShare,AD26*ProviderShare) | AI26: =AA26*PaymentFee | AJ26: =U26*OpsAI | AK26: =MonthlyFixed | AL26: =I26*ReferralReward | AM26: =G26 | AN26: =AD26-AH26-AI26-AJ26-AK26-AL26-AM26 | AO26: =AO25+AA26-(AH26+AI26+AJ26+AK26+AL26+AM26+AF26) | AP26: =IF(U26>0,V26/U26,0) | AQ26: =IF(U25>0,MAX(0,(U25+J26-U26)/U25),0)
A27: 23 | B27: =MOD(A27-1+LaunchMonth-1,12)+1 | C27: =INT((A27-1+LaunchMonth-1)/12)+1 | D27: =VLOOKUP(B27,SeasonTable,2,FALSE) | E27: =(1+InflationRate)^INT((A27-1)/12) | F27: =MonthlyChurn*VLOOKUP(B27,ChurnSeasonTable,4,FALSE) | G27: =MIN(MAX(MktMin19plus,AA26*MktPct19plus),MAX(0,AO26-CashBuffer)) | H27: =IF(G27>0,MAX(1,ROUND(G27/CAC*D27,0)),0) | I27: =IF(H27>0,ROUND(H27*ReferralMix/(1-ReferralMix),0),0) | J27: =H27+I27 | K27: =ROUND(J27*(1-AnnualMix),0) | L27: =J27-K27 | M27: =ROUND(K27*EssentialMix,0) | N27: =K27-M27 | O27: =ROUND(L27*EssentialMix,0) | P27: =L27-O27 | Q27: =M27+M26+M25+MAX(0,Q26-M26-M25)*(1-F27) | R27: =N27+N26+N25+MAX(0,R26-N26-N25)*(1-F27) | S27: =S26+O27-O15*(AnnualChurn*VLOOKUP(B27,ChurnSeasonTable,4,FALSE))*POWER(1-(AnnualChurn*VLOOKUP(B27,ChurnSeasonTable,4,FALSE)),0) | T27: =T26+P27-P15*(AnnualChurn*VLOOKUP(B27,ChurnSeasonTable,4,FALSE))*POWER(1-(AnnualChurn*VLOOKUP(B27,ChurnSeasonTable,4,FALSE)),0) | U27: =Q27+R27+S27+T27 | V27: =Q27*PriceEssMonthly*E27+R27*PricePremMonthly*E27+S27*PriceEssAnnual*E27/12+T27*PricePremAnnual*E27/12 | W27: =V27*12 | X27: =Q27*PriceEssMonthly*E27+R27*PricePremMonthly*E27 | Y27: =O27*PriceEssAnnual*E27+P27*PricePremAnnual*E27 | Z27: =O15*POWER(1-(AnnualChurn*VLOOKUP(B27,ChurnSeasonTable,4,FALSE)),1)*PriceEssAnnual*E27+P15*POWER(1-(AnnualChurn*VLOOKUP(B27,ChurnSeasonTable,4,FALSE)),1)*PricePremAnnual*E27 | AA27: =X27+Y27+Z27 | AB27: =SUM(AA16:AA27) | AC27: =OR(AC26,AB27>=VATThreshold) | AD27: =IF(AC27,AA27/(1+VATRate),AA27) | AE27: =AA27-AD27 | AF27: =IF(AC27=0,0,IF(B27=1,SUMPRODUCT(--(($C$5:$C27=$C27-1)*($B$5:$B27>=10)*($B$5:$B27<=12)),$AE$5:$AE27),IF(B27=4,SUMPRODUCT(--(($C$5:$C27=$C27)*($B$5:$B27>=1)*($B$5:$B27<=3)),$AE$5:$AE27),IF(B27=7,SUMPRODUCT(--(($C$5:$C27=$C27)*($B$5:$B27>=4)*($B$5:$B27<=6)),$AE$5:$AE27),IF(B27=10,SUMPRODUCT(--(($C$5:$C27=$C27)*($B$5:$B27>=7)*($B$5:$B27<=9)),$AE$5:$AE27),0))))) | AG27: =AG26+AE27-AF27 | AH27: =IF(ProviderDelay>=1,AD26*ProviderShare,AD27*ProviderShare) | AI27: =AA27*PaymentFee | AJ27: =U27*OpsAI | AK27: =MonthlyFixed | AL27: =I27*ReferralReward | AM27: =G27 | AN27: =AD27-AH27-AI27-AJ27-AK27-AL27-AM27 | AO27: =AO26+AA27-(AH27+AI27+AJ27+AK27+AL27+AM27+AF27) | AP27: =IF(U27>0,V27/U27,0) | AQ27: =IF(U26>0,MAX(0,(U26+J27-U27)/U26),0)
A28: 24 | B28: =MOD(A28-1+LaunchMonth-1,12)+1 | C28: =INT((A28-1+LaunchMonth-1)/12)+1 | D28: =VLOOKUP(B28,SeasonTable,2,FALSE) | E28: =(1+InflationRate)^INT((A28-1)/12) | F28: =MonthlyChurn*VLOOKUP(B28,ChurnSeasonTable,4,FALSE) | G28: =MIN(MAX(MktMin19plus,AA27*MktPct19plus),MAX(0,AO27-CashBuffer)) | H28: =IF(G28>0,MAX(1,ROUND(G28/CAC*D28,0)),0) | I28: =IF(H28>0,ROUND(H28*ReferralMix/(1-ReferralMix),0),0) | J28: =H28+I28 | K28: =ROUND(J28*(1-AnnualMix),0) | L28: =J28-K28 | M28: =ROUND(K28*EssentialMix,0) | N28: =K28-M28 | O28: =ROUND(L28*EssentialMix,0) | P28: =L28-O28 | Q28: =M28+M27+M26+MAX(0,Q27-M27-M26)*(1-F28) | R28: =N28+N27+N26+MAX(0,R27-N27-N26)*(1-F28) | S28: =S27+O28-O16*(AnnualChurn*VLOOKUP(B28,ChurnSeasonTable,4,FALSE))*POWER(1-(AnnualChurn*VLOOKUP(B28,ChurnSeasonTable,4,FALSE)),0) | T28: =T27+P28-P16*(AnnualChurn*VLOOKUP(B28,ChurnSeasonTable,4,FALSE))*POWER(1-(AnnualChurn*VLOOKUP(B28,ChurnSeasonTable,4,FALSE)),0) | U28: =Q28+R28+S28+T28 | V28: =Q28*PriceEssMonthly*E28+R28*PricePremMonthly*E28+S28*PriceEssAnnual*E28/12+T28*PricePremAnnual*E28/12 | W28: =V28*12 | X28: =Q28*PriceEssMonthly*E28+R28*PricePremMonthly*E28 | Y28: =O28*PriceEssAnnual*E28+P28*PricePremAnnual*E28 | Z28: =O16*POWER(1-(AnnualChurn*VLOOKUP(B28,ChurnSeasonTable,4,FALSE)),1)*PriceEssAnnual*E28+P16*POWER(1-(AnnualChurn*VLOOKUP(B28,ChurnSeasonTable,4,FALSE)),1)*PricePremAnnual*E28 | AA28: =X28+Y28+Z28 | AB28: =SUM(AA17:AA28) | AC28: =OR(AC27,AB28>=VATThreshold) | AD28: =IF(AC28,AA28/(1+VATRate),AA28) | AE28: =AA28-AD28 | AF28: =IF(AC28=0,0,IF(B28=1,SUMPRODUCT(--(($C$5:$C28=$C28-1)*($B$5:$B28>=10)*($B$5:$B28<=12)),$AE$5:$AE28),IF(B28=4,SUMPRODUCT(--(($C$5:$C28=$C28)*($B$5:$B28>=1)*($B$5:$B28<=3)),$AE$5:$AE28),IF(B28=7,SUMPRODUCT(--(($C$5:$C28=$C28)*($B$5:$B28>=4)*($B$5:$B28<=6)),$AE$5:$AE28),IF(B28=10,SUMPRODUCT(--(($C$5:$C28=$C28)*($B$5:$B28>=7)*($B$5:$B28<=9)),$AE$5:$AE28),0))))) | AG28: =AG27+AE28-AF28 | AH28: =IF(ProviderDelay>=1,AD27*ProviderShare,AD28*ProviderShare) | AI28: =AA28*PaymentFee | AJ28: =U28*OpsAI | AK28: =MonthlyFixed | AL28: =I28*ReferralReward | AM28: =G28 | AN28: =AD28-AH28-AI28-AJ28-AK28-AL28-AM28 | AO28: =AO27+AA28-(AH28+AI28+AJ28+AK28+AL28+AM28+AF28) | AP28: =IF(U28>0,V28/U28,0) | AQ28: =IF(U27>0,MAX(0,(U27+J28-U28)/U27),0)
A29: 25 | B29: =MOD(A29-1+LaunchMonth-1,12)+1 | C29: =INT((A29-1+LaunchMonth-1)/12)+1 | D29: =VLOOKUP(B29,SeasonTable,2,FALSE) | E29: =(1+InflationRate)^INT((A29-1)/12) | F29: =MonthlyChurn*VLOOKUP(B29,ChurnSeasonTable,4,FALSE) | G29: =MIN(MAX(MktMin19plus,AA28*MktPct19plus),MAX(0,AO28-CashBuffer)) | H29: =IF(G29>0,MAX(1,ROUND(G29/CAC*D29,0)),0) | I29: =IF(H29>0,ROUND(H29*ReferralMix/(1-ReferralMix),0),0) | J29: =H29+I29 | K29: =ROUND(J29*(1-AnnualMix),0) | L29: =J29-K29 | M29: =ROUND(K29*EssentialMix,0) | N29: =K29-M29 | O29: =ROUND(L29*EssentialMix,0) | P29: =L29-O29 | Q29: =M29+M28+M27+MAX(0,Q28-M28-M27)*(1-F29) | R29: =N29+N28+N27+MAX(0,R28-N28-N27)*(1-F29) | S29: =S28+O29-O17*(AnnualChurn*VLOOKUP(B29,ChurnSeasonTable,4,FALSE))*POWER(1-(AnnualChurn*VLOOKUP(B29,ChurnSeasonTable,4,FALSE)),0)+O5*(AnnualChurn*VLOOKUP(B29,ChurnSeasonTable,4,FALSE))*POWER(1-(AnnualChurn*VLOOKUP(B29,ChurnSeasonTable,4,FALSE)),1) | T29: =T28+P29-P17*(AnnualChurn*VLOOKUP(B29,ChurnSeasonTable,4,FALSE))*POWER(1-(AnnualChurn*VLOOKUP(B29,ChurnSeasonTable,4,FALSE)),0)+P5*(AnnualChurn*VLOOKUP(B29,ChurnSeasonTable,4,FALSE))*POWER(1-(AnnualChurn*VLOOKUP(B29,ChurnSeasonTable,4,FALSE)),1) | U29: =Q29+R29+S29+T29 | V29: =Q29*PriceEssMonthly*E29+R29*PricePremMonthly*E29+S29*PriceEssAnnual*E29/12+T29*PricePremAnnual*E29/12 | W29: =V29*12 | X29: =Q29*PriceEssMonthly*E29+R29*PricePremMonthly*E29 | Y29: =O29*PriceEssAnnual*E29+P29*PricePremAnnual*E29 | Z29: =O17*POWER(1-(AnnualChurn*VLOOKUP(B29,ChurnSeasonTable,4,FALSE)),1)*PriceEssAnnual*E29+O5*POWER(1-(AnnualChurn*VLOOKUP(B29,ChurnSeasonTable,4,FALSE)),2)*PriceEssAnnual*E29+P17*POWER(1-(AnnualChurn*VLOOKUP(B29,ChurnSeasonTable,4,FALSE)),1)*PricePremAnnual*E29+P5*POWER(1-(AnnualChurn*VLOOKUP(B29,ChurnSeasonTable,4,FALSE)),2)*PricePremAnnual*E29 | AA29: =X29+Y29+Z29 | AB29: =SUM(AA18:AA29) | AC29: =OR(AC28,AB29>=VATThreshold) | AD29: =IF(AC29,AA29/(1+VATRate),AA29) | AE29: =AA29-AD29 | AF29: =IF(AC29=0,0,IF(B29=1,SUMPRODUCT(--(($C$5:$C29=$C29-1)*($B$5:$B29>=10)*($B$5:$B29<=12)),$AE$5:$AE29),IF(B29=4,SUMPRODUCT(--(($C$5:$C29=$C29)*($B$5:$B29>=1)*($B$5:$B29<=3)),$AE$5:$AE29),IF(B29=7,SUMPRODUCT(--(($C$5:$C29=$C29)*($B$5:$B29>=4)*($B$5:$B29<=6)),$AE$5:$AE29),IF(B29=10,SUMPRODUCT(--(($C$5:$C29=$C29)*($B$5:$B29>=7)*($B$5:$B29<=9)),$AE$5:$AE29),0))))) | AG29: =AG28+AE29-AF29 | AH29: =IF(ProviderDelay>=1,AD28*ProviderShare,AD29*ProviderShare) | AI29: =AA29*PaymentFee | AJ29: =U29*OpsAI | AK29: =MonthlyFixed | AL29: =I29*ReferralReward | AM29: =G29 | AN29: =AD29-AH29-AI29-AJ29-AK29-AL29-AM29 | AO29: =AO28+AA29-(AH29+AI29+AJ29+AK29+AL29+AM29+AF29) | AP29: =IF(U29>0,V29/U29,0) | AQ29: =IF(U28>0,MAX(0,(U28+J29-U29)/U28),0)
A30: 26 | B30: =MOD(A30-1+LaunchMonth-1,12)+1 | C30: =INT((A30-1+LaunchMonth-1)/12)+1 | D30: =VLOOKUP(B30,SeasonTable,2,FALSE) | E30: =(1+InflationRate)^INT((A30-1)/12) | F30: =MonthlyChurn*VLOOKUP(B30,ChurnSeasonTable,4,FALSE) | G30: =MIN(MAX(MktMin19plus,AA29*MktPct19plus),MAX(0,AO29-CashBuffer)) | H30: =IF(G30>0,MAX(1,ROUND(G30/CAC*D30,0)),0) | I30: =IF(H30>0,ROUND(H30*ReferralMix/(1-ReferralMix),0),0) | J30: =H30+I30 | K30: =ROUND(J30*(1-AnnualMix),0) | L30: =J30-K30 | M30: =ROUND(K30*EssentialMix,0) | N30: =K30-M30 | O30: =ROUND(L30*EssentialMix,0) | P30: =L30-O30 | Q30: =M30+M29+M28+MAX(0,Q29-M29-M28)*(1-F30) | R30: =N30+N29+N28+MAX(0,R29-N29-N28)*(1-F30) | S30: =S29+O30-O18*(AnnualChurn*VLOOKUP(B30,ChurnSeasonTable,4,FALSE))*POWER(1-(AnnualChurn*VLOOKUP(B30,ChurnSeasonTable,4,FALSE)),0)+O6*(AnnualChurn*VLOOKUP(B30,ChurnSeasonTable,4,FALSE))*POWER(1-(AnnualChurn*VLOOKUP(B30,ChurnSeasonTable,4,FALSE)),1) | T30: =T29+P30-P18*(AnnualChurn*VLOOKUP(B30,ChurnSeasonTable,4,FALSE))*POWER(1-(AnnualChurn*VLOOKUP(B30,ChurnSeasonTable,4,FALSE)),0)+P6*(AnnualChurn*VLOOKUP(B30,ChurnSeasonTable,4,FALSE))*POWER(1-(AnnualChurn*VLOOKUP(B30,ChurnSeasonTable,4,FALSE)),1) | U30: =Q30+R30+S30+T30 | V30: =Q30*PriceEssMonthly*E30+R30*PricePremMonthly*E30+S30*PriceEssAnnual*E30/12+T30*PricePremAnnual*E30/12 | W30: =V30*12 | X30: =Q30*PriceEssMonthly*E30+R30*PricePremMonthly*E30 | Y30: =O30*PriceEssAnnual*E30+P30*PricePremAnnual*E30 | Z30: =O18*POWER(1-(AnnualChurn*VLOOKUP(B30,ChurnSeasonTable,4,FALSE)),1)*PriceEssAnnual*E30+O6*POWER(1-(AnnualChurn*VLOOKUP(B30,ChurnSeasonTable,4,FALSE)),2)*PriceEssAnnual*E30+P18*POWER(1-(AnnualChurn*VLOOKUP(B30,ChurnSeasonTable,4,FALSE)),1)*PricePremAnnual*E30+P6*POWER(1-(AnnualChurn*VLOOKUP(B30,ChurnSeasonTable,4,FALSE)),2)*PricePremAnnual*E30 | AA30: =X30+Y30+Z30 | AB30: =SUM(AA19:AA30) | AC30: =OR(AC29,AB30>=VATThreshold) | AD30: =IF(AC30,AA30/(1+VATRate),AA30) | AE30: =AA30-AD30 | AF30: =IF(AC30=0,0,IF(B30=1,SUMPRODUCT(--(($C$5:$C30=$C30-1)*($B$5:$B30>=10)*($B$5:$B30<=12)),$AE$5:$AE30),IF(B30=4,SUMPRODUCT(--(($C$5:$C30=$C30)*($B$5:$B30>=1)*($B$5:$B30<=3)),$AE$5:$AE30),IF(B30=7,SUMPRODUCT(--(($C$5:$C30=$C30)*($B$5:$B30>=4)*($B$5:$B30<=6)),$AE$5:$AE30),IF(B30=10,SUMPRODUCT(--(($C$5:$C30=$C30)*($B$5:$B30>=7)*($B$5:$B30<=9)),$AE$5:$AE30),0))))) | AG30: =AG29+AE30-AF30 | AH30: =IF(ProviderDelay>=1,AD29*ProviderShare,AD30*ProviderShare) | AI30: =AA30*PaymentFee | AJ30: =U30*OpsAI | AK30: =MonthlyFixed | AL30: =I30*ReferralReward | AM30: =G30 | AN30: =AD30-AH30-AI30-AJ30-AK30-AL30-AM30 | AO30: =AO29+AA30-(AH30+AI30+AJ30+AK30+AL30+AM30+AF30) | AP30: =IF(U30>0,V30/U30,0) | AQ30: =IF(U29>0,MAX(0,(U29+J30-U30)/U29),0)
A31: 27 | B31: =MOD(A31-1+LaunchMonth-1,12)+1 | C31: =INT((A31-1+LaunchMonth-1)/12)+1 | D31: =VLOOKUP(B31,SeasonTable,2,FALSE) | E31: =(1+InflationRate)^INT((A31-1)/12) | F31: =MonthlyChurn*VLOOKUP(B31,ChurnSeasonTable,4,FALSE) | G31: =MIN(MAX(MktMin19plus,AA30*MktPct19plus),MAX(0,AO30-CashBuffer)) | H31: =IF(G31>0,MAX(1,ROUND(G31/CAC*D31,0)),0) | I31: =IF(H31>0,ROUND(H31*ReferralMix/(1-ReferralMix),0),0) | J31: =H31+I31 | K31: =ROUND(J31*(1-AnnualMix),0) | L31: =J31-K31 | M31: =ROUND(K31*EssentialMix,0) | N31: =K31-M31 | O31: =ROUND(L31*EssentialMix,0) | P31: =L31-O31 | Q31: =M31+M30+M29+MAX(0,Q30-M30-M29)*(1-F31) | R31: =N31+N30+N29+MAX(0,R30-N30-N29)*(1-F31) | S31: =S30+O31-O19*(AnnualChurn*VLOOKUP(B31,ChurnSeasonTable,4,FALSE))*POWER(1-(AnnualChurn*VLOOKUP(B31,ChurnSeasonTable,4,FALSE)),0)+O7*(AnnualChurn*VLOOKUP(B31,ChurnSeasonTable,4,FALSE))*POWER(1-(AnnualChurn*VLOOKUP(B31,ChurnSeasonTable,4,FALSE)),1) | T31: =T30+P31-P19*(AnnualChurn*VLOOKUP(B31,ChurnSeasonTable,4,FALSE))*POWER(1-(AnnualChurn*VLOOKUP(B31,ChurnSeasonTable,4,FALSE)),0)+P7*(AnnualChurn*VLOOKUP(B31,ChurnSeasonTable,4,FALSE))*POWER(1-(AnnualChurn*VLOOKUP(B31,ChurnSeasonTable,4,FALSE)),1) | U31: =Q31+R31+S31+T31 | V31: =Q31*PriceEssMonthly*E31+R31*PricePremMonthly*E31+S31*PriceEssAnnual*E31/12+T31*PricePremAnnual*E31/12 | W31: =V31*12 | X31: =Q31*PriceEssMonthly*E31+R31*PricePremMonthly*E31 | Y31: =O31*PriceEssAnnual*E31+P31*PricePremAnnual*E31 | Z31: =O19*POWER(1-(AnnualChurn*VLOOKUP(B31,ChurnSeasonTable,4,FALSE)),1)*PriceEssAnnual*E31+O7*POWER(1-(AnnualChurn*VLOOKUP(B31,ChurnSeasonTable,4,FALSE)),2)*PriceEssAnnual*E31+P19*POWER(1-(AnnualChurn*VLOOKUP(B31,ChurnSeasonTable,4,FALSE)),1)*PricePremAnnual*E31+P7*POWER(1-(AnnualChurn*VLOOKUP(B31,ChurnSeasonTable,4,FALSE)),2)*PricePremAnnual*E31 | AA31: =X31+Y31+Z31 | AB31: =SUM(AA20:AA31) | AC31: =OR(AC30,AB31>=VATThreshold) | AD31: =IF(AC31,AA31/(1+VATRate),AA31) | AE31: =AA31-AD31 | AF31: =IF(AC31=0,0,IF(B31=1,SUMPRODUCT(--(($C$5:$C31=$C31-1)*($B$5:$B31>=10)*($B$5:$B31<=12)),$AE$5:$AE31),IF(B31=4,SUMPRODUCT(--(($C$5:$C31=$C31)*($B$5:$B31>=1)*($B$5:$B31<=3)),$AE$5:$AE31),IF(B31=7,SUMPRODUCT(--(($C$5:$C31=$C31)*($B$5:$B31>=4)*($B$5:$B31<=6)),$AE$5:$AE31),IF(B31=10,SUMPRODUCT(--(($C$5:$C31=$C31)*($B$5:$B31>=7)*($B$5:$B31<=9)),$AE$5:$AE31),0))))) | AG31: =AG30+AE31-AF31 | AH31: =IF(ProviderDelay>=1,AD30*ProviderShare,AD31*ProviderShare) | AI31: =AA31*PaymentFee | AJ31: =U31*OpsAI | AK31: =MonthlyFixed | AL31: =I31*ReferralReward | AM31: =G31 | AN31: =AD31-AH31-AI31-AJ31-AK31-AL31-AM31 | AO31: =AO30+AA31-(AH31+AI31+AJ31+AK31+AL31+AM31+AF31) | AP31: =IF(U31>0,V31/U31,0) | AQ31: =IF(U30>0,MAX(0,(U30+J31-U31)/U30),0)
A32: 28 | B32: =MOD(A32-1+LaunchMonth-1,12)+1 | C32: =INT((A32-1+LaunchMonth-1)/12)+1 | D32: =VLOOKUP(B32,SeasonTable,2,FALSE) | E32: =(1+InflationRate)^INT((A32-1)/12) | F32: =MonthlyChurn*VLOOKUP(B32,ChurnSeasonTable,4,FALSE) | G32: =MIN(MAX(MktMin19plus,AA31*MktPct19plus),MAX(0,AO31-CashBuffer)) | H32: =IF(G32>0,MAX(1,ROUND(G32/CAC*D32,0)),0) | I32: =IF(H32>0,ROUND(H32*ReferralMix/(1-ReferralMix),0),0) | J32: =H32+I32 | K32: =ROUND(J32*(1-AnnualMix),0) | L32: =J32-K32 | M32: =ROUND(K32*EssentialMix,0) | N32: =K32-M32 | O32: =ROUND(L32*EssentialMix,0) | P32: =L32-O32 | Q32: =M32+M31+M30+MAX(0,Q31-M31-M30)*(1-F32) | R32: =N32+N31+N30+MAX(0,R31-N31-N30)*(1-F32) | S32: =S31+O32-O20*(AnnualChurn*VLOOKUP(B32,ChurnSeasonTable,4,FALSE))*POWER(1-(AnnualChurn*VLOOKUP(B32,ChurnSeasonTable,4,FALSE)),0)+O8*(AnnualChurn*VLOOKUP(B32,ChurnSeasonTable,4,FALSE))*POWER(1-(AnnualChurn*VLOOKUP(B32,ChurnSeasonTable,4,FALSE)),1) | T32: =T31+P32-P20*(AnnualChurn*VLOOKUP(B32,ChurnSeasonTable,4,FALSE))*POWER(1-(AnnualChurn*VLOOKUP(B32,ChurnSeasonTable,4,FALSE)),0)+P8*(AnnualChurn*VLOOKUP(B32,ChurnSeasonTable,4,FALSE))*POWER(1-(AnnualChurn*VLOOKUP(B32,ChurnSeasonTable,4,FALSE)),1) | U32: =Q32+R32+S32+T32 | V32: =Q32*PriceEssMonthly*E32+R32*PricePremMonthly*E32+S32*PriceEssAnnual*E32/12+T32*PricePremAnnual*E32/12 | W32: =V32*12 | X32: =Q32*PriceEssMonthly*E32+R32*PricePremMonthly*E32 | Y32: =O32*PriceEssAnnual*E32+P32*PricePremAnnual*E32 | Z32: =O20*POWER(1-(AnnualChurn*VLOOKUP(B32,ChurnSeasonTable,4,FALSE)),1)*PriceEssAnnual*E32+O8*POWER(1-(AnnualChurn*VLOOKUP(B32,ChurnSeasonTable,4,FALSE)),2)*PriceEssAnnual*E32+P20*POWER(1-(AnnualChurn*VLOOKUP(B32,ChurnSeasonTable,4,FALSE)),1)*PricePremAnnual*E32+P8*POWER(1-(AnnualChurn*VLOOKUP(B32,ChurnSeasonTable,4,FALSE)),2)*PricePremAnnual*E32 | AA32: =X32+Y32+Z32 | AB32: =SUM(AA21:AA32) | AC32: =OR(AC31,AB32>=VATThreshold) | AD32: =IF(AC32,AA32/(1+VATRate),AA32) | AE32: =AA32-AD32 | AF32: =IF(AC32=0,0,IF(B32=1,SUMPRODUCT(--(($C$5:$C32=$C32-1)*($B$5:$B32>=10)*($B$5:$B32<=12)),$AE$5:$AE32),IF(B32=4,SUMPRODUCT(--(($C$5:$C32=$C32)*($B$5:$B32>=1)*($B$5:$B32<=3)),$AE$5:$AE32),IF(B32=7,SUMPRODUCT(--(($C$5:$C32=$C32)*($B$5:$B32>=4)*($B$5:$B32<=6)),$AE$5:$AE32),IF(B32=10,SUMPRODUCT(--(($C$5:$C32=$C32)*($B$5:$B32>=7)*($B$5:$B32<=9)),$AE$5:$AE32),0))))) | AG32: =AG31+AE32-AF32 | AH32: =IF(ProviderDelay>=1,AD31*ProviderShare,AD32*ProviderShare) | AI32: =AA32*PaymentFee | AJ32: =U32*OpsAI | AK32: =MonthlyFixed | AL32: =I32*ReferralReward | AM32: =G32 | AN32: =AD32-AH32-AI32-AJ32-AK32-AL32-AM32 | AO32: =AO31+AA32-(AH32+AI32+AJ32+AK32+AL32+AM32+AF32) | AP32: =IF(U32>0,V32/U32,0) | AQ32: =IF(U31>0,MAX(0,(U31+J32-U32)/U31),0)
A33: 29 | B33: =MOD(A33-1+LaunchMonth-1,12)+1 | C33: =INT((A33-1+LaunchMonth-1)/12)+1 | D33: =VLOOKUP(B33,SeasonTable,2,FALSE) | E33: =(1+InflationRate)^INT((A33-1)/12) | F33: =MonthlyChurn*VLOOKUP(B33,ChurnSeasonTable,4,FALSE) | G33: =MIN(MAX(MktMin19plus,AA32*MktPct19plus),MAX(0,AO32-CashBuffer)) | H33: =IF(G33>0,MAX(1,ROUND(G33/CAC*D33,0)),0) | I33: =IF(H33>0,ROUND(H33*ReferralMix/(1-ReferralMix),0),0) | J33: =H33+I33 | K33: =ROUND(J33*(1-AnnualMix),0) | L33: =J33-K33 | M33: =ROUND(K33*EssentialMix,0) | N33: =K33-M33 | O33: =ROUND(L33*EssentialMix,0) | P33: =L33-O33 | Q33: =M33+M32+M31+MAX(0,Q32-M32-M31)*(1-F33) | R33: =N33+N32+N31+MAX(0,R32-N32-N31)*(1-F33) | S33: =S32+O33-O21*(AnnualChurn*VLOOKUP(B33,ChurnSeasonTable,4,FALSE))*POWER(1-(AnnualChurn*VLOOKUP(B33,ChurnSeasonTable,4,FALSE)),0)+O9*(AnnualChurn*VLOOKUP(B33,ChurnSeasonTable,4,FALSE))*POWER(1-(AnnualChurn*VLOOKUP(B33,ChurnSeasonTable,4,FALSE)),1) | T33: =T32+P33-P21*(AnnualChurn*VLOOKUP(B33,ChurnSeasonTable,4,FALSE))*POWER(1-(AnnualChurn*VLOOKUP(B33,ChurnSeasonTable,4,FALSE)),0)+P9*(AnnualChurn*VLOOKUP(B33,ChurnSeasonTable,4,FALSE))*POWER(1-(AnnualChurn*VLOOKUP(B33,ChurnSeasonTable,4,FALSE)),1) | U33: =Q33+R33+S33+T33 | V33: =Q33*PriceEssMonthly*E33+R33*PricePremMonthly*E33+S33*PriceEssAnnual*E33/12+T33*PricePremAnnual*E33/12 | W33: =V33*12 | X33: =Q33*PriceEssMonthly*E33+R33*PricePremMonthly*E33 | Y33: =O33*PriceEssAnnual*E33+P33*PricePremAnnual*E33 | Z33: =O21*POWER(1-(AnnualChurn*VLOOKUP(B33,ChurnSeasonTable,4,FALSE)),1)*PriceEssAnnual*E33+O9*POWER(1-(AnnualChurn*VLOOKUP(B33,ChurnSeasonTable,4,FALSE)),2)*PriceEssAnnual*E33+P21*POWER(1-(AnnualChurn*VLOOKUP(B33,ChurnSeasonTable,4,FALSE)),1)*PricePremAnnual*E33+P9*POWER(1-(AnnualChurn*VLOOKUP(B33,ChurnSeasonTable,4,FALSE)),2)*PricePremAnnual*E33 | AA33: =X33+Y33+Z33 | AB33: =SUM(AA22:AA33) | AC33: =OR(AC32,AB33>=VATThreshold) | AD33: =IF(AC33,AA33/(1+VATRate),AA33) | AE33: =AA33-AD33 | AF33: =IF(AC33=0,0,IF(B33=1,SUMPRODUCT(--(($C$5:$C33=$C33-1)*($B$5:$B33>=10)*($B$5:$B33<=12)),$AE$5:$AE33),IF(B33=4,SUMPRODUCT(--(($C$5:$C33=$C33)*($B$5:$B33>=1)*($B$5:$B33<=3)),$AE$5:$AE33),IF(B33=7,SUMPRODUCT(--(($C$5:$C33=$C33)*($B$5:$B33>=4)*($B$5:$B33<=6)),$AE$5:$AE33),IF(B33=10,SUMPRODUCT(--(($C$5:$C33=$C33)*($B$5:$B33>=7)*($B$5:$B33<=9)),$AE$5:$AE33),0))))) | AG33: =AG32+AE33-AF33 | AH33: =IF(ProviderDelay>=1,AD32*ProviderShare,AD33*ProviderShare) | AI33: =AA33*PaymentFee | AJ33: =U33*OpsAI | AK33: =MonthlyFixed | AL33: =I33*ReferralReward | AM33: =G33 | AN33: =AD33-AH33-AI33-AJ33-AK33-AL33-AM33 | AO33: =AO32+AA33-(AH33+AI33+AJ33+AK33+AL33+AM33+AF33) | AP33: =IF(U33>0,V33/U33,0) | AQ33: =IF(U32>0,MAX(0,(U32+J33-U33)/U32),0)
A34: 30 | B34: =MOD(A34-1+LaunchMonth-1,12)+1 | C34: =INT((A34-1+LaunchMonth-1)/12)+1 | D34: =VLOOKUP(B34,SeasonTable,2,FALSE) | E34: =(1+InflationRate)^INT((A34-1)/12) | F34: =MonthlyChurn*VLOOKUP(B34,ChurnSeasonTable,4,FALSE) | G34: =MIN(MAX(MktMin19plus,AA33*MktPct19plus),MAX(0,AO33-CashBuffer)) | H34: =IF(G34>0,MAX(1,ROUND(G34/CAC*D34,0)),0) | I34: =IF(H34>0,ROUND(H34*ReferralMix/(1-ReferralMix),0),0) | J34: =H34+I34 | K34: =ROUND(J34*(1-AnnualMix),0) | L34: =J34-K34 | M34: =ROUND(K34*EssentialMix,0) | N34: =K34-M34 | O34: =ROUND(L34*EssentialMix,0) | P34: =L34-O34 | Q34: =M34+M33+M32+MAX(0,Q33-M33-M32)*(1-F34) | R34: =N34+N33+N32+MAX(0,R33-N33-N32)*(1-F34) | S34: =S33+O34-O22*(AnnualChurn*VLOOKUP(B34,ChurnSeasonTable,4,FALSE))*POWER(1-(AnnualChurn*VLOOKUP(B34,ChurnSeasonTable,4,FALSE)),0)+O10*(AnnualChurn*VLOOKUP(B34,ChurnSeasonTable,4,FALSE))*POWER(1-(AnnualChurn*VLOOKUP(B34,ChurnSeasonTable,4,FALSE)),1) | T34: =T33+P34-P22*(AnnualChurn*VLOOKUP(B34,ChurnSeasonTable,4,FALSE))*POWER(1-(AnnualChurn*VLOOKUP(B34,ChurnSeasonTable,4,FALSE)),0)+P10*(AnnualChurn*VLOOKUP(B34,ChurnSeasonTable,4,FALSE))*POWER(1-(AnnualChurn*VLOOKUP(B34,ChurnSeasonTable,4,FALSE)),1) | U34: =Q34+R34+S34+T34 | V34: =Q34*PriceEssMonthly*E34+R34*PricePremMonthly*E34+S34*PriceEssAnnual*E34/12+T34*PricePremAnnual*E34/12 | W34: =V34*12 | X34: =Q34*PriceEssMonthly*E34+R34*PricePremMonthly*E34 | Y34: =O34*PriceEssAnnual*E34+P34*PricePremAnnual*E34 | Z34: =O22*POWER(1-(AnnualChurn*VLOOKUP(B34,ChurnSeasonTable,4,FALSE)),1)*PriceEssAnnual*E34+O10*POWER(1-(AnnualChurn*VLOOKUP(B34,ChurnSeasonTable,4,FALSE)),2)*PriceEssAnnual*E34+P22*POWER(1-(AnnualChurn*VLOOKUP(B34,ChurnSeasonTable,4,FALSE)),1)*PricePremAnnual*E34+P10*POWER(1-(AnnualChurn*VLOOKUP(B34,ChurnSeasonTable,4,FALSE)),2)*PricePremAnnual*E34 | AA34: =X34+Y34+Z34 | AB34: =SUM(AA23:AA34) | AC34: =OR(AC33,AB34>=VATThreshold) | AD34: =IF(AC34,AA34/(1+VATRate),AA34) | AE34: =AA34-AD34 | AF34: =IF(AC34=0,0,IF(B34=1,SUMPRODUCT(--(($C$5:$C34=$C34-1)*($B$5:$B34>=10)*($B$5:$B34<=12)),$AE$5:$AE34),IF(B34=4,SUMPRODUCT(--(($C$5:$C34=$C34)*($B$5:$B34>=1)*($B$5:$B34<=3)),$AE$5:$AE34),IF(B34=7,SUMPRODUCT(--(($C$5:$C34=$C34)*($B$5:$B34>=4)*($B$5:$B34<=6)),$AE$5:$AE34),IF(B34=10,SUMPRODUCT(--(($C$5:$C34=$C34)*($B$5:$B34>=7)*($B$5:$B34<=9)),$AE$5:$AE34),0))))) | AG34: =AG33+AE34-AF34 | AH34: =IF(ProviderDelay>=1,AD33*ProviderShare,AD34*ProviderShare) | AI34: =AA34*PaymentFee | AJ34: =U34*OpsAI | AK34: =MonthlyFixed | AL34: =I34*ReferralReward | AM34: =G34 | AN34: =AD34-AH34-AI34-AJ34-AK34-AL34-AM34 | AO34: =AO33+AA34-(AH34+AI34+AJ34+AK34+AL34+AM34+AF34) | AP34: =IF(U34>0,V34/U34,0) | AQ34: =IF(U33>0,MAX(0,(U33+J34-U34)/U33),0)
A35: 31 | B35: =MOD(A35-1+LaunchMonth-1,12)+1 | C35: =INT((A35-1+LaunchMonth-1)/12)+1 | D35: =VLOOKUP(B35,SeasonTable,2,FALSE) | E35: =(1+InflationRate)^INT((A35-1)/12) | F35: =MonthlyChurn*VLOOKUP(B35,ChurnSeasonTable,4,FALSE) | G35: =MIN(MAX(MktMin19plus,AA34*MktPct19plus),MAX(0,AO34-CashBuffer)) | H35: =IF(G35>0,MAX(1,ROUND(G35/CAC*D35,0)),0) | I35: =IF(H35>0,ROUND(H35*ReferralMix/(1-ReferralMix),0),0) | J35: =H35+I35 | K35: =ROUND(J35*(1-AnnualMix),0) | L35: =J35-K35 | M35: =ROUND(K35*EssentialMix,0) | N35: =K35-M35 | O35: =ROUND(L35*EssentialMix,0) | P35: =L35-O35 | Q35: =M35+M34+M33+MAX(0,Q34-M34-M33)*(1-F35) | R35: =N35+N34+N33+MAX(0,R34-N34-N33)*(1-F35) | S35: =S34+O35-O23*(AnnualChurn*VLOOKUP(B35,ChurnSeasonTable,4,FALSE))*POWER(1-(AnnualChurn*VLOOKUP(B35,ChurnSeasonTable,4,FALSE)),0)+O11*(AnnualChurn*VLOOKUP(B35,ChurnSeasonTable,4,FALSE))*POWER(1-(AnnualChurn*VLOOKUP(B35,ChurnSeasonTable,4,FALSE)),1) | T35: =T34+P35-P23*(AnnualChurn*VLOOKUP(B35,ChurnSeasonTable,4,FALSE))*POWER(1-(AnnualChurn*VLOOKUP(B35,ChurnSeasonTable,4,FALSE)),0)+P11*(AnnualChurn*VLOOKUP(B35,ChurnSeasonTable,4,FALSE))*POWER(1-(AnnualChurn*VLOOKUP(B35,ChurnSeasonTable,4,FALSE)),1) | U35: =Q35+R35+S35+T35 | V35: =Q35*PriceEssMonthly*E35+R35*PricePremMonthly*E35+S35*PriceEssAnnual*E35/12+T35*PricePremAnnual*E35/12 | W35: =V35*12 | X35: =Q35*PriceEssMonthly*E35+R35*PricePremMonthly*E35 | Y35: =O35*PriceEssAnnual*E35+P35*PricePremAnnual*E35 | Z35: =O23*POWER(1-(AnnualChurn*VLOOKUP(B35,ChurnSeasonTable,4,FALSE)),1)*PriceEssAnnual*E35+O11*POWER(1-(AnnualChurn*VLOOKUP(B35,ChurnSeasonTable,4,FALSE)),2)*PriceEssAnnual*E35+P23*POWER(1-(AnnualChurn*VLOOKUP(B35,ChurnSeasonTable,4,FALSE)),1)*PricePremAnnual*E35+P11*POWER(1-(AnnualChurn*VLOOKUP(B35,ChurnSeasonTable,4,FALSE)),2)*PricePremAnnual*E35 | AA35: =X35+Y35+Z35 | AB35: =SUM(AA24:AA35) | AC35: =OR(AC34,AB35>=VATThreshold) | AD35: =IF(AC35,AA35/(1+VATRate),AA35) | AE35: =AA35-AD35 | AF35: =IF(AC35=0,0,IF(B35=1,SUMPRODUCT(--(($C$5:$C35=$C35-1)*($B$5:$B35>=10)*($B$5:$B35<=12)),$AE$5:$AE35),IF(B35=4,SUMPRODUCT(--(($C$5:$C35=$C35)*($B$5:$B35>=1)*($B$5:$B35<=3)),$AE$5:$AE35),IF(B35=7,SUMPRODUCT(--(($C$5:$C35=$C35)*($B$5:$B35>=4)*($B$5:$B35<=6)),$AE$5:$AE35),IF(B35=10,SUMPRODUCT(--(($C$5:$C35=$C35)*($B$5:$B35>=7)*($B$5:$B35<=9)),$AE$5:$AE35),0))))) | AG35: =AG34+AE35-AF35 | AH35: =IF(ProviderDelay>=1,AD34*ProviderShare,AD35*ProviderShare) | AI35: =AA35*PaymentFee | AJ35: =U35*OpsAI | AK35: =MonthlyFixed | AL35: =I35*ReferralReward | AM35: =G35 | AN35: =AD35-AH35-AI35-AJ35-AK35-AL35-AM35 | AO35: =AO34+AA35-(AH35+AI35+AJ35+AK35+AL35+AM35+AF35) | AP35: =IF(U35>0,V35/U35,0) | AQ35: =IF(U34>0,MAX(0,(U34+J35-U35)/U34),0)
A36: 32 | B36: =MOD(A36-1+LaunchMonth-1,12)+1 | C36: =INT((A36-1+LaunchMonth-1)/12)+1 | D36: =VLOOKUP(B36,SeasonTable,2,FALSE) | E36: =(1+InflationRate)^INT((A36-1)/12) | F36: =MonthlyChurn*VLOOKUP(B36,ChurnSeasonTable,4,FALSE) | G36: =MIN(MAX(MktMin19plus,AA35*MktPct19plus),MAX(0,AO35-CashBuffer)) | H36: =IF(G36>0,MAX(1,ROUND(G36/CAC*D36,0)),0) | I36: =IF(H36>0,ROUND(H36*ReferralMix/(1-ReferralMix),0),0) | J36: =H36+I36 | K36: =ROUND(J36*(1-AnnualMix),0) | L36: =J36-K36 | M36: =ROUND(K36*EssentialMix,0) | N36: =K36-M36 | O36: =ROUND(L36*EssentialMix,0) | P36: =L36-O36 | Q36: =M36+M35+M34+MAX(0,Q35-M35-M34)*(1-F36) | R36: =N36+N35+N34+MAX(0,R35-N35-N34)*(1-F36) | S36: =S35+O36-O24*(AnnualChurn*VLOOKUP(B36,ChurnSeasonTable,4,FALSE))*POWER(1-(AnnualChurn*VLOOKUP(B36,ChurnSeasonTable,4,FALSE)),0)+O12*(AnnualChurn*VLOOKUP(B36,ChurnSeasonTable,4,FALSE))*POWER(1-(AnnualChurn*VLOOKUP(B36,ChurnSeasonTable,4,FALSE)),1) | T36: =T35+P36-P24*(AnnualChurn*VLOOKUP(B36,ChurnSeasonTable,4,FALSE))*POWER(1-(AnnualChurn*VLOOKUP(B36,ChurnSeasonTable,4,FALSE)),0)+P12*(AnnualChurn*VLOOKUP(B36,ChurnSeasonTable,4,FALSE))*POWER(1-(AnnualChurn*VLOOKUP(B36,ChurnSeasonTable,4,FALSE)),1) | U36: =Q36+R36+S36+T36 | V36: =Q36*PriceEssMonthly*E36+R36*PricePremMonthly*E36+S36*PriceEssAnnual*E36/12+T36*PricePremAnnual*E36/12 | W36: =V36*12 | X36: =Q36*PriceEssMonthly*E36+R36*PricePremMonthly*E36 | Y36: =O36*PriceEssAnnual*E36+P36*PricePremAnnual*E36 | Z36: =O24*POWER(1-(AnnualChurn*VLOOKUP(B36,ChurnSeasonTable,4,FALSE)),1)*PriceEssAnnual*E36+O12*POWER(1-(AnnualChurn*VLOOKUP(B36,ChurnSeasonTable,4,FALSE)),2)*PriceEssAnnual*E36+P24*POWER(1-(AnnualChurn*VLOOKUP(B36,ChurnSeasonTable,4,FALSE)),1)*PricePremAnnual*E36+P12*POWER(1-(AnnualChurn*VLOOKUP(B36,ChurnSeasonTable,4,FALSE)),2)*PricePremAnnual*E36 | AA36: =X36+Y36+Z36 | AB36: =SUM(AA25:AA36) | AC36: =OR(AC35,AB36>=VATThreshold) | AD36: =IF(AC36,AA36/(1+VATRate),AA36) | AE36: =AA36-AD36 | AF36: =IF(AC36=0,0,IF(B36=1,SUMPRODUCT(--(($C$5:$C36=$C36-1)*($B$5:$B36>=10)*($B$5:$B36<=12)),$AE$5:$AE36),IF(B36=4,SUMPRODUCT(--(($C$5:$C36=$C36)*($B$5:$B36>=1)*($B$5:$B36<=3)),$AE$5:$AE36),IF(B36=7,SUMPRODUCT(--(($C$5:$C36=$C36)*($B$5:$B36>=4)*($B$5:$B36<=6)),$AE$5:$AE36),IF(B36=10,SUMPRODUCT(--(($C$5:$C36=$C36)*($B$5:$B36>=7)*($B$5:$B36<=9)),$AE$5:$AE36),0))))) | AG36: =AG35+AE36-AF36 | AH36: =IF(ProviderDelay>=1,AD35*ProviderShare,AD36*ProviderShare) | AI36: =AA36*PaymentFee | AJ36: =U36*OpsAI | AK36: =MonthlyFixed | AL36: =I36*ReferralReward | AM36: =G36 | AN36: =AD36-AH36-AI36-AJ36-AK36-AL36-AM36 | AO36: =AO35+AA36-(AH36+AI36+AJ36+AK36+AL36+AM36+AF36) | AP36: =IF(U36>0,V36/U36,0) | AQ36: =IF(U35>0,MAX(0,(U35+J36-U36)/U35),0)
A37: 33 | B37: =MOD(A37-1+LaunchMonth-1,12)+1 | C37: =INT((A37-1+LaunchMonth-1)/12)+1 | D37: =VLOOKUP(B37,SeasonTable,2,FALSE) | E37: =(1+InflationRate)^INT((A37-1)/12) | F37: =MonthlyChurn*VLOOKUP(B37,ChurnSeasonTable,4,FALSE) | G37: =MIN(MAX(MktMin19plus,AA36*MktPct19plus),MAX(0,AO36-CashBuffer)) | H37: =IF(G37>0,MAX(1,ROUND(G37/CAC*D37,0)),0) | I37: =IF(H37>0,ROUND(H37*ReferralMix/(1-ReferralMix),0),0) | J37: =H37+I37 | K37: =ROUND(J37*(1-AnnualMix),0) | L37: =J37-K37 | M37: =ROUND(K37*EssentialMix,0) | N37: =K37-M37 | O37: =ROUND(L37*EssentialMix,0) | P37: =L37-O37 | Q37: =M37+M36+M35+MAX(0,Q36-M36-M35)*(1-F37) | R37: =N37+N36+N35+MAX(0,R36-N36-N35)*(1-F37) | S37: =S36+O37-O25*(AnnualChurn*VLOOKUP(B37,ChurnSeasonTable,4,FALSE))*POWER(1-(AnnualChurn*VLOOKUP(B37,ChurnSeasonTable,4,FALSE)),0)+O13*(AnnualChurn*VLOOKUP(B37,ChurnSeasonTable,4,FALSE))*POWER(1-(AnnualChurn*VLOOKUP(B37,ChurnSeasonTable,4,FALSE)),1) | T37: =T36+P37-P25*(AnnualChurn*VLOOKUP(B37,ChurnSeasonTable,4,FALSE))*POWER(1-(AnnualChurn*VLOOKUP(B37,ChurnSeasonTable,4,FALSE)),0)+P13*(AnnualChurn*VLOOKUP(B37,ChurnSeasonTable,4,FALSE))*POWER(1-(AnnualChurn*VLOOKUP(B37,ChurnSeasonTable,4,FALSE)),1) | U37: =Q37+R37+S37+T37 | V37: =Q37*PriceEssMonthly*E37+R37*PricePremMonthly*E37+S37*PriceEssAnnual*E37/12+T37*PricePremAnnual*E37/12 | W37: =V37*12 | X37: =Q37*PriceEssMonthly*E37+R37*PricePremMonthly*E37 | Y37: =O37*PriceEssAnnual*E37+P37*PricePremAnnual*E37 | Z37: =O25*POWER(1-(AnnualChurn*VLOOKUP(B37,ChurnSeasonTable,4,FALSE)),1)*PriceEssAnnual*E37+O13*POWER(1-(AnnualChurn*VLOOKUP(B37,ChurnSeasonTable,4,FALSE)),2)*PriceEssAnnual*E37+P25*POWER(1-(AnnualChurn*VLOOKUP(B37,ChurnSeasonTable,4,FALSE)),1)*PricePremAnnual*E37+P13*POWER(1-(AnnualChurn*VLOOKUP(B37,ChurnSeasonTable,4,FALSE)),2)*PricePremAnnual*E37 | AA37: =X37+Y37+Z37 | AB37: =SUM(AA26:AA37) | AC37: =OR(AC36,AB37>=VATThreshold) | AD37: =IF(AC37,AA37/(1+VATRate),AA37) | AE37: =AA37-AD37 | AF37: =IF(AC37=0,0,IF(B37=1,SUMPRODUCT(--(($C$5:$C37=$C37-1)*($B$5:$B37>=10)*($B$5:$B37<=12)),$AE$5:$AE37),IF(B37=4,SUMPRODUCT(--(($C$5:$C37=$C37)*($B$5:$B37>=1)*($B$5:$B37<=3)),$AE$5:$AE37),IF(B37=7,SUMPRODUCT(--(($C$5:$C37=$C37)*($B$5:$B37>=4)*($B$5:$B37<=6)),$AE$5:$AE37),IF(B37=10,SUMPRODUCT(--(($C$5:$C37=$C37)*($B$5:$B37>=7)*($B$5:$B37<=9)),$AE$5:$AE37),0))))) | AG37: =AG36+AE37-AF37 | AH37: =IF(ProviderDelay>=1,AD36*ProviderShare,AD37*ProviderShare) | AI37: =AA37*PaymentFee | AJ37: =U37*OpsAI | AK37: =MonthlyFixed | AL37: =I37*ReferralReward | AM37: =G37 | AN37: =AD37-AH37-AI37-AJ37-AK37-AL37-AM37 | AO37: =AO36+AA37-(AH37+AI37+AJ37+AK37+AL37+AM37+AF37) | AP37: =IF(U37>0,V37/U37,0) | AQ37: =IF(U36>0,MAX(0,(U36+J37-U37)/U36),0)
A38: 34 | B38: =MOD(A38-1+LaunchMonth-1,12)+1 | C38: =INT((A38-1+LaunchMonth-1)/12)+1 | D38: =VLOOKUP(B38,SeasonTable,2,FALSE) | E38: =(1+InflationRate)^INT((A38-1)/12) | F38: =MonthlyChurn*VLOOKUP(B38,ChurnSeasonTable,4,FALSE) | G38: =MIN(MAX(MktMin19plus,AA37*MktPct19plus),MAX(0,AO37-CashBuffer)) | H38: =IF(G38>0,MAX(1,ROUND(G38/CAC*D38,0)),0) | I38: =IF(H38>0,ROUND(H38*ReferralMix/(1-ReferralMix),0),0) | J38: =H38+I38 | K38: =ROUND(J38*(1-AnnualMix),0) | L38: =J38-K38 | M38: =ROUND(K38*EssentialMix,0) | N38: =K38-M38 | O38: =ROUND(L38*EssentialMix,0) | P38: =L38-O38 | Q38: =M38+M37+M36+MAX(0,Q37-M37-M36)*(1-F38) | R38: =N38+N37+N36+MAX(0,R37-N37-N36)*(1-F38) | S38: =S37+O38-O26*(AnnualChurn*VLOOKUP(B38,ChurnSeasonTable,4,FALSE))*POWER(1-(AnnualChurn*VLOOKUP(B38,ChurnSeasonTable,4,FALSE)),0)+O14*(AnnualChurn*VLOOKUP(B38,ChurnSeasonTable,4,FALSE))*POWER(1-(AnnualChurn*VLOOKUP(B38,ChurnSeasonTable,4,FALSE)),1) | T38: =T37+P38-P26*(AnnualChurn*VLOOKUP(B38,ChurnSeasonTable,4,FALSE))*POWER(1-(AnnualChurn*VLOOKUP(B38,ChurnSeasonTable,4,FALSE)),0)+P14*(AnnualChurn*VLOOKUP(B38,ChurnSeasonTable,4,FALSE))*POWER(1-(AnnualChurn*VLOOKUP(B38,ChurnSeasonTable,4,FALSE)),1) | U38: =Q38+R38+S38+T38 | V38: =Q38*PriceEssMonthly*E38+R38*PricePremMonthly*E38+S38*PriceEssAnnual*E38/12+T38*PricePremAnnual*E38/12 | W38: =V38*12 | X38: =Q38*PriceEssMonthly*E38+R38*PricePremMonthly*E38 | Y38: =O38*PriceEssAnnual*E38+P38*PricePremAnnual*E38 | Z38: =O26*POWER(1-(AnnualChurn*VLOOKUP(B38,ChurnSeasonTable,4,FALSE)),1)*PriceEssAnnual*E38+O14*POWER(1-(AnnualChurn*VLOOKUP(B38,ChurnSeasonTable,4,FALSE)),2)*PriceEssAnnual*E38+P26*POWER(1-(AnnualChurn*VLOOKUP(B38,ChurnSeasonTable,4,FALSE)),1)*PricePremAnnual*E38+P14*POWER(1-(AnnualChurn*VLOOKUP(B38,ChurnSeasonTable,4,FALSE)),2)*PricePremAnnual*E38 | AA38: =X38+Y38+Z38 | AB38: =SUM(AA27:AA38) | AC38: =OR(AC37,AB38>=VATThreshold) | AD38: =IF(AC38,AA38/(1+VATRate),AA38) | AE38: =AA38-AD38 | AF38: =IF(AC38=0,0,IF(B38=1,SUMPRODUCT(--(($C$5:$C38=$C38-1)*($B$5:$B38>=10)*($B$5:$B38<=12)),$AE$5:$AE38),IF(B38=4,SUMPRODUCT(--(($C$5:$C38=$C38)*($B$5:$B38>=1)*($B$5:$B38<=3)),$AE$5:$AE38),IF(B38=7,SUMPRODUCT(--(($C$5:$C38=$C38)*($B$5:$B38>=4)*($B$5:$B38<=6)),$AE$5:$AE38),IF(B38=10,SUMPRODUCT(--(($C$5:$C38=$C38)*($B$5:$B38>=7)*($B$5:$B38<=9)),$AE$5:$AE38),0))))) | AG38: =AG37+AE38-AF38 | AH38: =IF(ProviderDelay>=1,AD37*ProviderShare,AD38*ProviderShare) | AI38: =AA38*PaymentFee | AJ38: =U38*OpsAI | AK38: =MonthlyFixed | AL38: =I38*ReferralReward | AM38: =G38 | AN38: =AD38-AH38-AI38-AJ38-AK38-AL38-AM38 | AO38: =AO37+AA38-(AH38+AI38+AJ38+AK38+AL38+AM38+AF38) | AP38: =IF(U38>0,V38/U38,0) | AQ38: =IF(U37>0,MAX(0,(U37+J38-U38)/U37),0)
A39: 35 | B39: =MOD(A39-1+LaunchMonth-1,12)+1 | C39: =INT((A39-1+LaunchMonth-1)/12)+1 | D39: =VLOOKUP(B39,SeasonTable,2,FALSE) | E39: =(1+InflationRate)^INT((A39-1)/12) | F39: =MonthlyChurn*VLOOKUP(B39,ChurnSeasonTable,4,FALSE) | G39: =MIN(MAX(MktMin19plus,AA38*MktPct19plus),MAX(0,AO38-CashBuffer)) | H39: =IF(G39>0,MAX(1,ROUND(G39/CAC*D39,0)),0) | I39: =IF(H39>0,ROUND(H39*ReferralMix/(1-ReferralMix),0),0) | J39: =H39+I39 | K39: =ROUND(J39*(1-AnnualMix),0) | L39: =J39-K39 | M39: =ROUND(K39*EssentialMix,0) | N39: =K39-M39 | O39: =ROUND(L39*EssentialMix,0) | P39: =L39-O39 | Q39: =M39+M38+M37+MAX(0,Q38-M38-M37)*(1-F39) | R39: =N39+N38+N37+MAX(0,R38-N38-N37)*(1-F39) | S39: =S38+O39-O27*(AnnualChurn*VLOOKUP(B39,ChurnSeasonTable,4,FALSE))*POWER(1-(AnnualChurn*VLOOKUP(B39,ChurnSeasonTable,4,FALSE)),0)+O15*(AnnualChurn*VLOOKUP(B39,ChurnSeasonTable,4,FALSE))*POWER(1-(AnnualChurn*VLOOKUP(B39,ChurnSeasonTable,4,FALSE)),1) | T39: =T38+P39-P27*(AnnualChurn*VLOOKUP(B39,ChurnSeasonTable,4,FALSE))*POWER(1-(AnnualChurn*VLOOKUP(B39,ChurnSeasonTable,4,FALSE)),0)+P15*(AnnualChurn*VLOOKUP(B39,ChurnSeasonTable,4,FALSE))*POWER(1-(AnnualChurn*VLOOKUP(B39,ChurnSeasonTable,4,FALSE)),1) | U39: =Q39+R39+S39+T39 | V39: =Q39*PriceEssMonthly*E39+R39*PricePremMonthly*E39+S39*PriceEssAnnual*E39/12+T39*PricePremAnnual*E39/12 | W39: =V39*12 | X39: =Q39*PriceEssMonthly*E39+R39*PricePremMonthly*E39 | Y39: =O39*PriceEssAnnual*E39+P39*PricePremAnnual*E39 | Z39: =O27*POWER(1-(AnnualChurn*VLOOKUP(B39,ChurnSeasonTable,4,FALSE)),1)*PriceEssAnnual*E39+O15*POWER(1-(AnnualChurn*VLOOKUP(B39,ChurnSeasonTable,4,FALSE)),2)*PriceEssAnnual*E39+P27*POWER(1-(AnnualChurn*VLOOKUP(B39,ChurnSeasonTable,4,FALSE)),1)*PricePremAnnual*E39+P15*POWER(1-(AnnualChurn*VLOOKUP(B39,ChurnSeasonTable,4,FALSE)),2)*PricePremAnnual*E39 | AA39: =X39+Y39+Z39 | AB39: =SUM(AA28:AA39) | AC39: =OR(AC38,AB39>=VATThreshold) | AD39: =IF(AC39,AA39/(1+VATRate),AA39) | AE39: =AA39-AD39 | AF39: =IF(AC39=0,0,IF(B39=1,SUMPRODUCT(--(($C$5:$C39=$C39-1)*($B$5:$B39>=10)*($B$5:$B39<=12)),$AE$5:$AE39),IF(B39=4,SUMPRODUCT(--(($C$5:$C39=$C39)*($B$5:$B39>=1)*($B$5:$B39<=3)),$AE$5:$AE39),IF(B39=7,SUMPRODUCT(--(($C$5:$C39=$C39)*($B$5:$B39>=4)*($B$5:$B39<=6)),$AE$5:$AE39),IF(B39=10,SUMPRODUCT(--(($C$5:$C39=$C39)*($B$5:$B39>=7)*($B$5:$B39<=9)),$AE$5:$AE39),0))))) | AG39: =AG38+AE39-AF39 | AH39: =IF(ProviderDelay>=1,AD38*ProviderShare,AD39*ProviderShare) | AI39: =AA39*PaymentFee | AJ39: =U39*OpsAI | AK39: =MonthlyFixed | AL39: =I39*ReferralReward | AM39: =G39 | AN39: =AD39-AH39-AI39-AJ39-AK39-AL39-AM39 | AO39: =AO38+AA39-(AH39+AI39+AJ39+AK39+AL39+AM39+AF39) | AP39: =IF(U39>0,V39/U39,0) | AQ39: =IF(U38>0,MAX(0,(U38+J39-U39)/U38),0)
A40: 36 | B40: =MOD(A40-1+LaunchMonth-1,12)+1 | C40: =INT((A40-1+LaunchMonth-1)/12)+1 | D40: =VLOOKUP(B40,SeasonTable,2,FALSE) | E40: =(1+InflationRate)^INT((A40-1)/12) | F40: =MonthlyChurn*VLOOKUP(B40,ChurnSeasonTable,4,FALSE) | G40: =MIN(MAX(MktMin19plus,AA39*MktPct19plus),MAX(0,AO39-CashBuffer)) | H40: =IF(G40>0,MAX(1,ROUND(G40/CAC*D40,0)),0) | I40: =IF(H40>0,ROUND(H40*ReferralMix/(1-ReferralMix),0),0) | J40: =H40+I40 | K40: =ROUND(J40*(1-AnnualMix),0) | L40: =J40-K40 | M40: =ROUND(K40*EssentialMix,0) | N40: =K40-M40 | O40: =ROUND(L40*EssentialMix,0) | P40: =L40-O40 | Q40: =M40+M39+M38+MAX(0,Q39-M39-M38)*(1-F40) | R40: =N40+N39+N38+MAX(0,R39-N39-N38)*(1-F40) | S40: =S39+O40-O28*(AnnualChurn*VLOOKUP(B40,ChurnSeasonTable,4,FALSE))*POWER(1-(AnnualChurn*VLOOKUP(B40,ChurnSeasonTable,4,FALSE)),0)+O16*(AnnualChurn*VLOOKUP(B40,ChurnSeasonTable,4,FALSE))*POWER(1-(AnnualChurn*VLOOKUP(B40,ChurnSeasonTable,4,FALSE)),1) | T40: =T39+P40-P28*(AnnualChurn*VLOOKUP(B40,ChurnSeasonTable,4,FALSE))*POWER(1-(AnnualChurn*VLOOKUP(B40,ChurnSeasonTable,4,FALSE)),0)+P16*(AnnualChurn*VLOOKUP(B40,ChurnSeasonTable,4,FALSE))*POWER(1-(AnnualChurn*VLOOKUP(B40,ChurnSeasonTable,4,FALSE)),1) | U40: =Q40+R40+S40+T40 | V40: =Q40*PriceEssMonthly*E40+R40*PricePremMonthly*E40+S40*PriceEssAnnual*E40/12+T40*PricePremAnnual*E40/12 | W40: =V40*12 | X40: =Q40*PriceEssMonthly*E40+R40*PricePremMonthly*E40 | Y40: =O40*PriceEssAnnual*E40+P40*PricePremAnnual*E40 | Z40: =O28*POWER(1-(AnnualChurn*VLOOKUP(B40,ChurnSeasonTable,4,FALSE)),1)*PriceEssAnnual*E40+O16*POWER(1-(AnnualChurn*VLOOKUP(B40,ChurnSeasonTable,4,FALSE)),2)*PriceEssAnnual*E40+P28*POWER(1-(AnnualChurn*VLOOKUP(B40,ChurnSeasonTable,4,FALSE)),1)*PricePremAnnual*E40+P16*POWER(1-(AnnualChurn*VLOOKUP(B40,ChurnSeasonTable,4,FALSE)),2)*PricePremAnnual*E40 | AA40: =X40+Y40+Z40 | AB40: =SUM(AA29:AA40) | AC40: =OR(AC39,AB40>=VATThreshold) | AD40: =IF(AC40,AA40/(1+VATRate),AA40) | AE40: =AA40-AD40 | AF40: =IF(AC40=0,0,IF(B40=1,SUMPRODUCT(--(($C$5:$C40=$C40-1)*($B$5:$B40>=10)*($B$5:$B40<=12)),$AE$5:$AE40),IF(B40=4,SUMPRODUCT(--(($C$5:$C40=$C40)*($B$5:$B40>=1)*($B$5:$B40<=3)),$AE$5:$AE40),IF(B40=7,SUMPRODUCT(--(($C$5:$C40=$C40)*($B$5:$B40>=4)*($B$5:$B40<=6)),$AE$5:$AE40),IF(B40=10,SUMPRODUCT(--(($C$5:$C40=$C40)*($B$5:$B40>=7)*($B$5:$B40<=9)),$AE$5:$AE40),0))))) | AG40: =AG39+AE40-AF40 | AH40: =IF(ProviderDelay>=1,AD39*ProviderShare,AD40*ProviderShare) | AI40: =AA40*PaymentFee | AJ40: =U40*OpsAI | AK40: =MonthlyFixed | AL40: =I40*ReferralReward | AM40: =G40 | AN40: =AD40-AH40-AI40-AJ40-AK40-AL40-AM40 | AO40: =AO39+AA40-(AH40+AI40+AJ40+AK40+AL40+AM40+AF40) | AP40: =IF(U40>0,V40/U40,0) | AQ40: =IF(U39>0,MAX(0,(U39+J40-U40)/U39),0)
A41: 37 | B41: =MOD(A41-1+LaunchMonth-1,12)+1 | C41: =INT((A41-1+LaunchMonth-1)/12)+1 | D41: =VLOOKUP(B41,SeasonTable,2,FALSE) | E41: =(1+InflationRate)^INT((A41-1)/12) | F41: =MonthlyChurn*VLOOKUP(B41,ChurnSeasonTable,4,FALSE) | G41: =MIN(MAX(MktMin19plus,AA40*MktPct19plus),MAX(0,AO40-CashBuffer)) | H41: =IF(G41>0,MAX(1,ROUND(G41/CAC*D41,0)),0) | I41: =IF(H41>0,ROUND(H41*ReferralMix/(1-ReferralMix),0),0) | J41: =H41+I41 | K41: =ROUND(J41*(1-AnnualMix),0) | L41: =J41-K41 | M41: =ROUND(K41*EssentialMix,0) | N41: =K41-M41 | O41: =ROUND(L41*EssentialMix,0) | P41: =L41-O41 | Q41: =M41+M40+M39+MAX(0,Q40-M40-M39)*(1-F41) | R41: =N41+N40+N39+MAX(0,R40-N40-N39)*(1-F41) | S41: =S40+O41-O29*(AnnualChurn*VLOOKUP(B41,ChurnSeasonTable,4,FALSE))*POWER(1-(AnnualChurn*VLOOKUP(B41,ChurnSeasonTable,4,FALSE)),0)+O17*(AnnualChurn*VLOOKUP(B41,ChurnSeasonTable,4,FALSE))*POWER(1-(AnnualChurn*VLOOKUP(B41,ChurnSeasonTable,4,FALSE)),1)+O5*(AnnualChurn*VLOOKUP(B41,ChurnSeasonTable,4,FALSE))*POWER(1-(AnnualChurn*VLOOKUP(B41,ChurnSeasonTable,4,FALSE)),2) | T41: =T40+P41-P29*(AnnualChurn*VLOOKUP(B41,ChurnSeasonTable,4,FALSE))*POWER(1-(AnnualChurn*VLOOKUP(B41,ChurnSeasonTable,4,FALSE)),0)+P17*(AnnualChurn*VLOOKUP(B41,ChurnSeasonTable,4,FALSE))*POWER(1-(AnnualChurn*VLOOKUP(B41,ChurnSeasonTable,4,FALSE)),1)+P5*(AnnualChurn*VLOOKUP(B41,ChurnSeasonTable,4,FALSE))*POWER(1-(AnnualChurn*VLOOKUP(B41,ChurnSeasonTable,4,FALSE)),2) | U41: =Q41+R41+S41+T41 | V41: =Q41*PriceEssMonthly*E41+R41*PricePremMonthly*E41+S41*PriceEssAnnual*E41/12+T41*PricePremAnnual*E41/12 | W41: =V41*12 | X41: =Q41*PriceEssMonthly*E41+R41*PricePremMonthly*E41 | Y41: =O41*PriceEssAnnual*E41+P41*PricePremAnnual*E41 | Z41: =O29*POWER(1-(AnnualChurn*VLOOKUP(B41,ChurnSeasonTable,4,FALSE)),1)*PriceEssAnnual*E41+O17*POWER(1-(AnnualChurn*VLOOKUP(B41,ChurnSeasonTable,4,FALSE)),2)*PriceEssAnnual*E41+O5*POWER(1-(AnnualChurn*VLOOKUP(B41,ChurnSeasonTable,4,FALSE)),3)*PriceEssAnnual*E41+P29*POWER(1-(AnnualChurn*VLOOKUP(B41,ChurnSeasonTable,4,FALSE)),1)*PricePremAnnual*E41+P17*POWER(1-(AnnualChurn*VLOOKUP(B41,ChurnSeasonTable,4,FALSE)),2)*PricePremAnnual*E41+P5*POWER(1-(AnnualChurn*VLOOKUP(B41,ChurnSeasonTable,4,FALSE)),3)*PricePremAnnual*E41 | AA41: =X41+Y41+Z41 | AB41: =SUM(AA30:AA41) | AC41: =OR(AC40,AB41>=VATThreshold) | AD41: =IF(AC41,AA41/(1+VATRate),AA41) | AE41: =AA41-AD41 | AF41: =IF(AC41=0,0,IF(B41=1,SUMPRODUCT(--(($C$5:$C41=$C41-1)*($B$5:$B41>=10)*($B$5:$B41<=12)),$AE$5:$AE41),IF(B41=4,SUMPRODUCT(--(($C$5:$C41=$C41)*($B$5:$B41>=1)*($B$5:$B41<=3)),$AE$5:$AE41),IF(B41=7,SUMPRODUCT(--(($C$5:$C41=$C41)*($B$5:$B41>=4)*($B$5:$B41<=6)),$AE$5:$AE41),IF(B41=10,SUMPRODUCT(--(($C$5:$C41=$C41)*($B$5:$B41>=7)*($B$5:$B41<=9)),$AE$5:$AE41),0))))) | AG41: =AG40+AE41-AF41 | AH41: =IF(ProviderDelay>=1,AD40*ProviderShare,AD41*ProviderShare) | AI41: =AA41*PaymentFee | AJ41: =U41*OpsAI | AK41: =MonthlyFixed | AL41: =I41*ReferralReward | AM41: =G41 | AN41: =AD41-AH41-AI41-AJ41-AK41-AL41-AM41 | AO41: =AO40+AA41-(AH41+AI41+AJ41+AK41+AL41+AM41+AF41) | AP41: =IF(U41>0,V41/U41,0) | AQ41: =IF(U40>0,MAX(0,(U40+J41-U41)/U40),0)
A42: 38 | B42: =MOD(A42-1+LaunchMonth-1,12)+1 | C42: =INT((A42-1+LaunchMonth-1)/12)+1 | D42: =VLOOKUP(B42,SeasonTable,2,FALSE) | E42: =(1+InflationRate)^INT((A42-1)/12) | F42: =MonthlyChurn*VLOOKUP(B42,ChurnSeasonTable,4,FALSE) | G42: =MIN(MAX(MktMin19plus,AA41*MktPct19plus),MAX(0,AO41-CashBuffer)) | H42: =IF(G42>0,MAX(1,ROUND(G42/CAC*D42,0)),0) | I42: =IF(H42>0,ROUND(H42*ReferralMix/(1-ReferralMix),0),0) | J42: =H42+I42 | K42: =ROUND(J42*(1-AnnualMix),0) | L42: =J42-K42 | M42: =ROUND(K42*EssentialMix,0) | N42: =K42-M42 | O42: =ROUND(L42*EssentialMix,0) | P42: =L42-O42 | Q42: =M42+M41+M40+MAX(0,Q41-M41-M40)*(1-F42) | R42: =N42+N41+N40+MAX(0,R41-N41-N40)*(1-F42) | S42: =S41+O42-O30*(AnnualChurn*VLOOKUP(B42,ChurnSeasonTable,4,FALSE))*POWER(1-(AnnualChurn*VLOOKUP(B42,ChurnSeasonTable,4,FALSE)),0)+O18*(AnnualChurn*VLOOKUP(B42,ChurnSeasonTable,4,FALSE))*POWER(1-(AnnualChurn*VLOOKUP(B42,ChurnSeasonTable,4,FALSE)),1)+O6*(AnnualChurn*VLOOKUP(B42,ChurnSeasonTable,4,FALSE))*POWER(1-(AnnualChurn*VLOOKUP(B42,ChurnSeasonTable,4,FALSE)),2) | T42: =T41+P42-P30*(AnnualChurn*VLOOKUP(B42,ChurnSeasonTable,4,FALSE))*POWER(1-(AnnualChurn*VLOOKUP(B42,ChurnSeasonTable,4,FALSE)),0)+P18*(AnnualChurn*VLOOKUP(B42,ChurnSeasonTable,4,FALSE))*POWER(1-(AnnualChurn*VLOOKUP(B42,ChurnSeasonTable,4,FALSE)),1)+P6*(AnnualChurn*VLOOKUP(B42,ChurnSeasonTable,4,FALSE))*POWER(1-(AnnualChurn*VLOOKUP(B42,ChurnSeasonTable,4,FALSE)),2) | U42: =Q42+R42+S42+T42 | V42: =Q42*PriceEssMonthly*E42+R42*PricePremMonthly*E42+S42*PriceEssAnnual*E42/12+T42*PricePremAnnual*E42/12 | W42: =V42*12 | X42: =Q42*PriceEssMonthly*E42+R42*PricePremMonthly*E42 | Y42: =O42*PriceEssAnnual*E42+P42*PricePremAnnual*E42 | Z42: =O30*POWER(1-(AnnualChurn*VLOOKUP(B42,ChurnSeasonTable,4,FALSE)),1)*PriceEssAnnual*E42+O18*POWER(1-(AnnualChurn*VLOOKUP(B42,ChurnSeasonTable,4,FALSE)),2)*PriceEssAnnual*E42+O6*POWER(1-(AnnualChurn*VLOOKUP(B42,ChurnSeasonTable,4,FALSE)),3)*PriceEssAnnual*E42+P30*POWER(1-(AnnualChurn*VLOOKUP(B42,ChurnSeasonTable,4,FALSE)),1)*PricePremAnnual*E42+P18*POWER(1-(AnnualChurn*VLOOKUP(B42,ChurnSeasonTable,4,FALSE)),2)*PricePremAnnual*E42+P6*POWER(1-(AnnualChurn*VLOOKUP(B42,ChurnSeasonTable,4,FALSE)),3)*PricePremAnnual*E42 | AA42: =X42+Y42+Z42 | AB42: =SUM(AA31:AA42) | AC42: =OR(AC41,AB42>=VATThreshold) | AD42: =IF(AC42,AA42/(1+VATRate),AA42) | AE42: =AA42-AD42 | AF42: =IF(AC42=0,0,IF(B42=1,SUMPRODUCT(--(($C$5:$C42=$C42-1)*($B$5:$B42>=10)*($B$5:$B42<=12)),$AE$5:$AE42),IF(B42=4,SUMPRODUCT(--(($C$5:$C42=$C42)*($B$5:$B42>=1)*($B$5:$B42<=3)),$AE$5:$AE42),IF(B42=7,SUMPRODUCT(--(($C$5:$C42=$C42)*($B$5:$B42>=4)*($B$5:$B42<=6)),$AE$5:$AE42),IF(B42=10,SUMPRODUCT(--(($C$5:$C42=$C42)*($B$5:$B42>=7)*($B$5:$B42<=9)),$AE$5:$AE42),0))))) | AG42: =AG41+AE42-AF42 | AH42: =IF(ProviderDelay>=1,AD41*ProviderShare,AD42*ProviderShare) | AI42: =AA42*PaymentFee | AJ42: =U42*OpsAI | AK42: =MonthlyFixed | AL42: =I42*ReferralReward | AM42: =G42 | AN42: =AD42-AH42-AI42-AJ42-AK42-AL42-AM42 | AO42: =AO41+AA42-(AH42+AI42+AJ42+AK42+AL42+AM42+AF42) | AP42: =IF(U42>0,V42/U42,0) | AQ42: =IF(U41>0,MAX(0,(U41+J42-U42)/U41),0)
A43: 39 | B43: =MOD(A43-1+LaunchMonth-1,12)+1 | C43: =INT((A43-1+LaunchMonth-1)/12)+1 | D43: =VLOOKUP(B43,SeasonTable,2,FALSE) | E43: =(1+InflationRate)^INT((A43-1)/12) | F43: =MonthlyChurn*VLOOKUP(B43,ChurnSeasonTable,4,FALSE) | G43: =MIN(MAX(MktMin19plus,AA42*MktPct19plus),MAX(0,AO42-CashBuffer)) | H43: =IF(G43>0,MAX(1,ROUND(G43/CAC*D43,0)),0) | I43: =IF(H43>0,ROUND(H43*ReferralMix/(1-ReferralMix),0),0) | J43: =H43+I43 | K43: =ROUND(J43*(1-AnnualMix),0) | L43: =J43-K43 | M43: =ROUND(K43*EssentialMix,0) | N43: =K43-M43 | O43: =ROUND(L43*EssentialMix,0) | P43: =L43-O43 | Q43: =M43+M42+M41+MAX(0,Q42-M42-M41)*(1-F43) | R43: =N43+N42+N41+MAX(0,R42-N42-N41)*(1-F43) | S43: =S42+O43-O31*(AnnualChurn*VLOOKUP(B43,ChurnSeasonTable,4,FALSE))*POWER(1-(AnnualChurn*VLOOKUP(B43,ChurnSeasonTable,4,FALSE)),0)+O19*(AnnualChurn*VLOOKUP(B43,ChurnSeasonTable,4,FALSE))*POWER(1-(AnnualChurn*VLOOKUP(B43,ChurnSeasonTable,4,FALSE)),1)+O7*(AnnualChurn*VLOOKUP(B43,ChurnSeasonTable,4,FALSE))*POWER(1-(AnnualChurn*VLOOKUP(B43,ChurnSeasonTable,4,FALSE)),2) | T43: =T42+P43-P31*(AnnualChurn*VLOOKUP(B43,ChurnSeasonTable,4,FALSE))*POWER(1-(AnnualChurn*VLOOKUP(B43,ChurnSeasonTable,4,FALSE)),0)+P19*(AnnualChurn*VLOOKUP(B43,ChurnSeasonTable,4,FALSE))*POWER(1-(AnnualChurn*VLOOKUP(B43,ChurnSeasonTable,4,FALSE)),1)+P7*(AnnualChurn*VLOOKUP(B43,ChurnSeasonTable,4,FALSE))*POWER(1-(AnnualChurn*VLOOKUP(B43,ChurnSeasonTable,4,FALSE)),2) | U43: =Q43+R43+S43+T43 | V43: =Q43*PriceEssMonthly*E43+R43*PricePremMonthly*E43+S43*PriceEssAnnual*E43/12+T43*PricePremAnnual*E43/12 | W43: =V43*12 | X43: =Q43*PriceEssMonthly*E43+R43*PricePremMonthly*E43 | Y43: =O43*PriceEssAnnual*E43+P43*PricePremAnnual*E43 | Z43: =O31*POWER(1-(AnnualChurn*VLOOKUP(B43,ChurnSeasonTable,4,FALSE)),1)*PriceEssAnnual*E43+O19*POWER(1-(AnnualChurn*VLOOKUP(B43,ChurnSeasonTable,4,FALSE)),2)*PriceEssAnnual*E43+O7*POWER(1-(AnnualChurn*VLOOKUP(B43,ChurnSeasonTable,4,FALSE)),3)*PriceEssAnnual*E43+P31*POWER(1-(AnnualChurn*VLOOKUP(B43,ChurnSeasonTable,4,FALSE)),1)*PricePremAnnual*E43+P19*POWER(1-(AnnualChurn*VLOOKUP(B43,ChurnSeasonTable,4,FALSE)),2)*PricePremAnnual*E43+P7*POWER(1-(AnnualChurn*VLOOKUP(B43,ChurnSeasonTable,4,FALSE)),3)*PricePremAnnual*E43 | AA43: =X43+Y43+Z43 | AB43: =SUM(AA32:AA43) | AC43: =OR(AC42,AB43>=VATThreshold) | AD43: =IF(AC43,AA43/(1+VATRate),AA43) | AE43: =AA43-AD43 | AF43: =IF(AC43=0,0,IF(B43=1,SUMPRODUCT(--(($C$5:$C43=$C43-1)*($B$5:$B43>=10)*($B$5:$B43<=12)),$AE$5:$AE43),IF(B43=4,SUMPRODUCT(--(($C$5:$C43=$C43)*($B$5:$B43>=1)*($B$5:$B43<=3)),$AE$5:$AE43),IF(B43=7,SUMPRODUCT(--(($C$5:$C43=$C43)*($B$5:$B43>=4)*($B$5:$B43<=6)),$AE$5:$AE43),IF(B43=10,SUMPRODUCT(--(($C$5:$C43=$C43)*($B$5:$B43>=7)*($B$5:$B43<=9)),$AE$5:$AE43),0))))) | AG43: =AG42+AE43-AF43 | AH43: =IF(ProviderDelay>=1,AD42*ProviderShare,AD43*ProviderShare) | AI43: =AA43*PaymentFee | AJ43: =U43*OpsAI | AK43: =MonthlyFixed | AL43: =I43*ReferralReward | AM43: =G43 | AN43: =AD43-AH43-AI43-AJ43-AK43-AL43-AM43 | AO43: =AO42+AA43-(AH43+AI43+AJ43+AK43+AL43+AM43+AF43) | AP43: =IF(U43>0,V43/U43,0) | AQ43: =IF(U42>0,MAX(0,(U42+J43-U43)/U42),0)
A44: 40 | B44: =MOD(A44-1+LaunchMonth-1,12)+1 | C44: =INT((A44-1+LaunchMonth-1)/12)+1 | D44: =VLOOKUP(B44,SeasonTable,2,FALSE) | E44: =(1+InflationRate)^INT((A44-1)/12) | F44: =MonthlyChurn*VLOOKUP(B44,ChurnSeasonTable,4,FALSE) | G44: =MIN(MAX(MktMin19plus,AA43*MktPct19plus),MAX(0,AO43-CashBuffer)) | H44: =IF(G44>0,MAX(1,ROUND(G44/CAC*D44,0)),0) | I44: =IF(H44>0,ROUND(H44*ReferralMix/(1-ReferralMix),0),0) | J44: =H44+I44 | K44: =ROUND(J44*(1-AnnualMix),0) | L44: =J44-K44 | M44: =ROUND(K44*EssentialMix,0) | N44: =K44-M44 | O44: =ROUND(L44*EssentialMix,0) | P44: =L44-O44 | Q44: =M44+M43+M42+MAX(0,Q43-M43-M42)*(1-F44) | R44: =N44+N43+N42+MAX(0,R43-N43-N42)*(1-F44) | S44: =S43+O44-O32*(AnnualChurn*VLOOKUP(B44,ChurnSeasonTable,4,FALSE))*POWER(1-(AnnualChurn*VLOOKUP(B44,ChurnSeasonTable,4,FALSE)),0)+O20*(AnnualChurn*VLOOKUP(B44,ChurnSeasonTable,4,FALSE))*POWER(1-(AnnualChurn*VLOOKUP(B44,ChurnSeasonTable,4,FALSE)),1)+O8*(AnnualChurn*VLOOKUP(B44,ChurnSeasonTable,4,FALSE))*POWER(1-(AnnualChurn*VLOOKUP(B44,ChurnSeasonTable,4,FALSE)),2) | T44: =T43+P44-P32*(AnnualChurn*VLOOKUP(B44,ChurnSeasonTable,4,FALSE))*POWER(1-(AnnualChurn*VLOOKUP(B44,ChurnSeasonTable,4,FALSE)),0)+P20*(AnnualChurn*VLOOKUP(B44,ChurnSeasonTable,4,FALSE))*POWER(1-(AnnualChurn*VLOOKUP(B44,ChurnSeasonTable,4,FALSE)),1)+P8*(AnnualChurn*VLOOKUP(B44,ChurnSeasonTable,4,FALSE))*POWER(1-(AnnualChurn*VLOOKUP(B44,ChurnSeasonTable,4,FALSE)),2) | U44: =Q44+R44+S44+T44 | V44: =Q44*PriceEssMonthly*E44+R44*PricePremMonthly*E44+S44*PriceEssAnnual*E44/12+T44*PricePremAnnual*E44/12 | W44: =V44*12 | X44: =Q44*PriceEssMonthly*E44+R44*PricePremMonthly*E44 | Y44: =O44*PriceEssAnnual*E44+P44*PricePremAnnual*E44 | Z44: =O32*POWER(1-(AnnualChurn*VLOOKUP(B44,ChurnSeasonTable,4,FALSE)),1)*PriceEssAnnual*E44+O20*POWER(1-(AnnualChurn*VLOOKUP(B44,ChurnSeasonTable,4,FALSE)),2)*PriceEssAnnual*E44+O8*POWER(1-(AnnualChurn*VLOOKUP(B44,ChurnSeasonTable,4,FALSE)),3)*PriceEssAnnual*E44+P32*POWER(1-(AnnualChurn*VLOOKUP(B44,ChurnSeasonTable,4,FALSE)),1)*PricePremAnnual*E44+P20*POWER(1-(AnnualChurn*VLOOKUP(B44,ChurnSeasonTable,4,FALSE)),2)*PricePremAnnual*E44+P8*POWER(1-(AnnualChurn*VLOOKUP(B44,ChurnSeasonTable,4,FALSE)),3)*PricePremAnnual*E44 | AA44: =X44+Y44+Z44 | AB44: =SUM(AA33:AA44) | AC44: =OR(AC43,AB44>=VATThreshold) | AD44: =IF(AC44,AA44/(1+VATRate),AA44) | AE44: =AA44-AD44 | AF44: =IF(AC44=0,0,IF(B44=1,SUMPRODUCT(--(($C$5:$C44=$C44-1)*($B$5:$B44>=10)*($B$5:$B44<=12)),$AE$5:$AE44),IF(B44=4,SUMPRODUCT(--(($C$5:$C44=$C44)*($B$5:$B44>=1)*($B$5:$B44<=3)),$AE$5:$AE44),IF(B44=7,SUMPRODUCT(--(($C$5:$C44=$C44)*($B$5:$B44>=4)*($B$5:$B44<=6)),$AE$5:$AE44),IF(B44=10,SUMPRODUCT(--(($C$5:$C44=$C44)*($B$5:$B44>=7)*($B$5:$B44<=9)),$AE$5:$AE44),0))))) | AG44: =AG43+AE44-AF44 | AH44: =IF(ProviderDelay>=1,AD43*ProviderShare,AD44*ProviderShare) | AI44: =AA44*PaymentFee | AJ44: =U44*OpsAI | AK44: =MonthlyFixed | AL44: =I44*ReferralReward | AM44: =G44 | AN44: =AD44-AH44-AI44-AJ44-AK44-AL44-AM44 | AO44: =AO43+AA44-(AH44+AI44+AJ44+AK44+AL44+AM44+AF44) | AP44: =IF(U44>0,V44/U44,0) | AQ44: =IF(U43>0,MAX(0,(U43+J44-U44)/U43),0)
A45: 41 | B45: =MOD(A45-1+LaunchMonth-1,12)+1 | C45: =INT((A45-1+LaunchMonth-1)/12)+1 | D45: =VLOOKUP(B45,SeasonTable,2,FALSE) | E45: =(1+InflationRate)^INT((A45-1)/12) | F45: =MonthlyChurn*VLOOKUP(B45,ChurnSeasonTable,4,FALSE) | G45: =MIN(MAX(MktMin19plus,AA44*MktPct19plus),MAX(0,AO44-CashBuffer)) | H45: =IF(G45>0,MAX(1,ROUND(G45/CAC*D45,0)),0) | I45: =IF(H45>0,ROUND(H45*ReferralMix/(1-ReferralMix),0),0) | J45: =H45+I45 | K45: =ROUND(J45*(1-AnnualMix),0) | L45: =J45-K45 | M45: =ROUND(K45*EssentialMix,0) | N45: =K45-M45 | O45: =ROUND(L45*EssentialMix,0) | P45: =L45-O45 | Q45: =M45+M44+M43+MAX(0,Q44-M44-M43)*(1-F45) | R45: =N45+N44+N43+MAX(0,R44-N44-N43)*(1-F45) | S45: =S44+O45-O33*(AnnualChurn*VLOOKUP(B45,ChurnSeasonTable,4,FALSE))*POWER(1-(AnnualChurn*VLOOKUP(B45,ChurnSeasonTable,4,FALSE)),0)+O21*(AnnualChurn*VLOOKUP(B45,ChurnSeasonTable,4,FALSE))*POWER(1-(AnnualChurn*VLOOKUP(B45,ChurnSeasonTable,4,FALSE)),1)+O9*(AnnualChurn*VLOOKUP(B45,ChurnSeasonTable,4,FALSE))*POWER(1-(AnnualChurn*VLOOKUP(B45,ChurnSeasonTable,4,FALSE)),2) | T45: =T44+P45-P33*(AnnualChurn*VLOOKUP(B45,ChurnSeasonTable,4,FALSE))*POWER(1-(AnnualChurn*VLOOKUP(B45,ChurnSeasonTable,4,FALSE)),0)+P21*(AnnualChurn*VLOOKUP(B45,ChurnSeasonTable,4,FALSE))*POWER(1-(AnnualChurn*VLOOKUP(B45,ChurnSeasonTable,4,FALSE)),1)+P9*(AnnualChurn*VLOOKUP(B45,ChurnSeasonTable,4,FALSE))*POWER(1-(AnnualChurn*VLOOKUP(B45,ChurnSeasonTable,4,FALSE)),2) | U45: =Q45+R45+S45+T45 | V45: =Q45*PriceEssMonthly*E45+R45*PricePremMonthly*E45+S45*PriceEssAnnual*E45/12+T45*PricePremAnnual*E45/12 | W45: =V45*12 | X45: =Q45*PriceEssMonthly*E45+R45*PricePremMonthly*E45 | Y45: =O45*PriceEssAnnual*E45+P45*PricePremAnnual*E45 | Z45: =O33*POWER(1-(AnnualChurn*VLOOKUP(B45,ChurnSeasonTable,4,FALSE)),1)*PriceEssAnnual*E45+O21*POWER(1-(AnnualChurn*VLOOKUP(B45,ChurnSeasonTable,4,FALSE)),2)*PriceEssAnnual*E45+O9*POWER(1-(AnnualChurn*VLOOKUP(B45,ChurnSeasonTable,4,FALSE)),3)*PriceEssAnnual*E45+P33*POWER(1-(AnnualChurn*VLOOKUP(B45,ChurnSeasonTable,4,FALSE)),1)*PricePremAnnual*E45+P21*POWER(1-(AnnualChurn*VLOOKUP(B45,ChurnSeasonTable,4,FALSE)),2)*PricePremAnnual*E45+P9*POWER(1-(AnnualChurn*VLOOKUP(B45,ChurnSeasonTable,4,FALSE)),3)*PricePremAnnual*E45 | AA45: =X45+Y45+Z45 | AB45: =SUM(AA34:AA45) | AC45: =OR(AC44,AB45>=VATThreshold) | AD45: =IF(AC45,AA45/(1+VATRate),AA45) | AE45: =AA45-AD45 | AF45: =IF(AC45=0,0,IF(B45=1,SUMPRODUCT(--(($C$5:$C45=$C45-1)*($B$5:$B45>=10)*($B$5:$B45<=12)),$AE$5:$AE45),IF(B45=4,SUMPRODUCT(--(($C$5:$C45=$C45)*($B$5:$B45>=1)*($B$5:$B45<=3)),$AE$5:$AE45),IF(B45=7,SUMPRODUCT(--(($C$5:$C45=$C45)*($B$5:$B45>=4)*($B$5:$B45<=6)),$AE$5:$AE45),IF(B45=10,SUMPRODUCT(--(($C$5:$C45=$C45)*($B$5:$B45>=7)*($B$5:$B45<=9)),$AE$5:$AE45),0))))) | AG45: =AG44+AE45-AF45 | AH45: =IF(ProviderDelay>=1,AD44*ProviderShare,AD45*ProviderShare) | AI45: =AA45*PaymentFee | AJ45: =U45*OpsAI | AK45: =MonthlyFixed | AL45: =I45*ReferralReward | AM45: =G45 | AN45: =AD45-AH45-AI45-AJ45-AK45-AL45-AM45 | AO45: =AO44+AA45-(AH45+AI45+AJ45+AK45+AL45+AM45+AF45) | AP45: =IF(U45>0,V45/U45,0) | AQ45: =IF(U44>0,MAX(0,(U44+J45-U45)/U44),0)
A46: 42 | B46: =MOD(A46-1+LaunchMonth-1,12)+1 | C46: =INT((A46-1+LaunchMonth-1)/12)+1 | D46: =VLOOKUP(B46,SeasonTable,2,FALSE) | E46: =(1+InflationRate)^INT((A46-1)/12) | F46: =MonthlyChurn*VLOOKUP(B46,ChurnSeasonTable,4,FALSE) | G46: =MIN(MAX(MktMin19plus,AA45*MktPct19plus),MAX(0,AO45-CashBuffer)) | H46: =IF(G46>0,MAX(1,ROUND(G46/CAC*D46,0)),0) | I46: =IF(H46>0,ROUND(H46*ReferralMix/(1-ReferralMix),0),0) | J46: =H46+I46 | K46: =ROUND(J46*(1-AnnualMix),0) | L46: =J46-K46 | M46: =ROUND(K46*EssentialMix,0) | N46: =K46-M46 | O46: =ROUND(L46*EssentialMix,0) | P46: =L46-O46 | Q46: =M46+M45+M44+MAX(0,Q45-M45-M44)*(1-F46) | R46: =N46+N45+N44+MAX(0,R45-N45-N44)*(1-F46) | S46: =S45+O46-O34*(AnnualChurn*VLOOKUP(B46,ChurnSeasonTable,4,FALSE))*POWER(1-(AnnualChurn*VLOOKUP(B46,ChurnSeasonTable,4,FALSE)),0)+O22*(AnnualChurn*VLOOKUP(B46,ChurnSeasonTable,4,FALSE))*POWER(1-(AnnualChurn*VLOOKUP(B46,ChurnSeasonTable,4,FALSE)),1)+O10*(AnnualChurn*VLOOKUP(B46,ChurnSeasonTable,4,FALSE))*POWER(1-(AnnualChurn*VLOOKUP(B46,ChurnSeasonTable,4,FALSE)),2) | T46: =T45+P46-P34*(AnnualChurn*VLOOKUP(B46,ChurnSeasonTable,4,FALSE))*POWER(1-(AnnualChurn*VLOOKUP(B46,ChurnSeasonTable,4,FALSE)),0)+P22*(AnnualChurn*VLOOKUP(B46,ChurnSeasonTable,4,FALSE))*POWER(1-(AnnualChurn*VLOOKUP(B46,ChurnSeasonTable,4,FALSE)),1)+P10*(AnnualChurn*VLOOKUP(B46,ChurnSeasonTable,4,FALSE))*POWER(1-(AnnualChurn*VLOOKUP(B46,ChurnSeasonTable,4,FALSE)),2) | U46: =Q46+R46+S46+T46 | V46: =Q46*PriceEssMonthly*E46+R46*PricePremMonthly*E46+S46*PriceEssAnnual*E46/12+T46*PricePremAnnual*E46/12 | W46: =V46*12 | X46: =Q46*PriceEssMonthly*E46+R46*PricePremMonthly*E46 | Y46: =O46*PriceEssAnnual*E46+P46*PricePremAnnual*E46 | Z46: =O34*POWER(1-(AnnualChurn*VLOOKUP(B46,ChurnSeasonTable,4,FALSE)),1)*PriceEssAnnual*E46+O22*POWER(1-(AnnualChurn*VLOOKUP(B46,ChurnSeasonTable,4,FALSE)),2)*PriceEssAnnual*E46+O10*POWER(1-(AnnualChurn*VLOOKUP(B46,ChurnSeasonTable,4,FALSE)),3)*PriceEssAnnual*E46+P34*POWER(1-(AnnualChurn*VLOOKUP(B46,ChurnSeasonTable,4,FALSE)),1)*PricePremAnnual*E46+P22*POWER(1-(AnnualChurn*VLOOKUP(B46,ChurnSeasonTable,4,FALSE)),2)*PricePremAnnual*E46+P10*POWER(1-(AnnualChurn*VLOOKUP(B46,ChurnSeasonTable,4,FALSE)),3)*PricePremAnnual*E46 | AA46: =X46+Y46+Z46 | AB46: =SUM(AA35:AA46) | AC46: =OR(AC45,AB46>=VATThreshold) | AD46: =IF(AC46,AA46/(1+VATRate),AA46) | AE46: =AA46-AD46 | AF46: =IF(AC46=0,0,IF(B46=1,SUMPRODUCT(--(($C$5:$C46=$C46-1)*($B$5:$B46>=10)*($B$5:$B46<=12)),$AE$5:$AE46),IF(B46=4,SUMPRODUCT(--(($C$5:$C46=$C46)*($B$5:$B46>=1)*($B$5:$B46<=3)),$AE$5:$AE46),IF(B46=7,SUMPRODUCT(--(($C$5:$C46=$C46)*($B$5:$B46>=4)*($B$5:$B46<=6)),$AE$5:$AE46),IF(B46=10,SUMPRODUCT(--(($C$5:$C46=$C46)*($B$5:$B46>=7)*($B$5:$B46<=9)),$AE$5:$AE46),0))))) | AG46: =AG45+AE46-AF46 | AH46: =IF(ProviderDelay>=1,AD45*ProviderShare,AD46*ProviderShare) | AI46: =AA46*PaymentFee | AJ46: =U46*OpsAI | AK46: =MonthlyFixed | AL46: =I46*ReferralReward | AM46: =G46 | AN46: =AD46-AH46-AI46-AJ46-AK46-AL46-AM46 | AO46: =AO45+AA46-(AH46+AI46+AJ46+AK46+AL46+AM46+AF46) | AP46: =IF(U46>0,V46/U46,0) | AQ46: =IF(U45>0,MAX(0,(U45+J46-U46)/U45),0)
A47: 43 | B47: =MOD(A47-1+LaunchMonth-1,12)+1 | C47: =INT((A47-1+LaunchMonth-1)/12)+1 | D47: =VLOOKUP(B47,SeasonTable,2,FALSE) | E47: =(1+InflationRate)^INT((A47-1)/12) | F47: =MonthlyChurn*VLOOKUP(B47,ChurnSeasonTable,4,FALSE) | G47: =MIN(MAX(MktMin19plus,AA46*MktPct19plus),MAX(0,AO46-CashBuffer)) | H47: =IF(G47>0,MAX(1,ROUND(G47/CAC*D47,0)),0) | I47: =IF(H47>0,ROUND(H47*ReferralMix/(1-ReferralMix),0),0) | J47: =H47+I47 | K47: =ROUND(J47*(1-AnnualMix),0) | L47: =J47-K47 | M47: =ROUND(K47*EssentialMix,0) | N47: =K47-M47 | O47: =ROUND(L47*EssentialMix,0) | P47: =L47-O47 | Q47: =M47+M46+M45+MAX(0,Q46-M46-M45)*(1-F47) | R47: =N47+N46+N45+MAX(0,R46-N46-N45)*(1-F47) | S47: =S46+O47-O35*(AnnualChurn*VLOOKUP(B47,ChurnSeasonTable,4,FALSE))*POWER(1-(AnnualChurn*VLOOKUP(B47,ChurnSeasonTable,4,FALSE)),0)+O23*(AnnualChurn*VLOOKUP(B47,ChurnSeasonTable,4,FALSE))*POWER(1-(AnnualChurn*VLOOKUP(B47,ChurnSeasonTable,4,FALSE)),1)+O11*(AnnualChurn*VLOOKUP(B47,ChurnSeasonTable,4,FALSE))*POWER(1-(AnnualChurn*VLOOKUP(B47,ChurnSeasonTable,4,FALSE)),2) | T47: =T46+P47-P35*(AnnualChurn*VLOOKUP(B47,ChurnSeasonTable,4,FALSE))*POWER(1-(AnnualChurn*VLOOKUP(B47,ChurnSeasonTable,4,FALSE)),0)+P23*(AnnualChurn*VLOOKUP(B47,ChurnSeasonTable,4,FALSE))*POWER(1-(AnnualChurn*VLOOKUP(B47,ChurnSeasonTable,4,FALSE)),1)+P11*(AnnualChurn*VLOOKUP(B47,ChurnSeasonTable,4,FALSE))*POWER(1-(AnnualChurn*VLOOKUP(B47,ChurnSeasonTable,4,FALSE)),2) | U47: =Q47+R47+S47+T47 | V47: =Q47*PriceEssMonthly*E47+R47*PricePremMonthly*E47+S47*PriceEssAnnual*E47/12+T47*PricePremAnnual*E47/12 | W47: =V47*12 | X47: =Q47*PriceEssMonthly*E47+R47*PricePremMonthly*E47 | Y47: =O47*PriceEssAnnual*E47+P47*PricePremAnnual*E47 | Z47: =O35*POWER(1-(AnnualChurn*VLOOKUP(B47,ChurnSeasonTable,4,FALSE)),1)*PriceEssAnnual*E47+O23*POWER(1-(AnnualChurn*VLOOKUP(B47,ChurnSeasonTable,4,FALSE)),2)*PriceEssAnnual*E47+O11*POWER(1-(AnnualChurn*VLOOKUP(B47,ChurnSeasonTable,4,FALSE)),3)*PriceEssAnnual*E47+P35*POWER(1-(AnnualChurn*VLOOKUP(B47,ChurnSeasonTable,4,FALSE)),1)*PricePremAnnual*E47+P23*POWER(1-(AnnualChurn*VLOOKUP(B47,ChurnSeasonTable,4,FALSE)),2)*PricePremAnnual*E47+P11*POWER(1-(AnnualChurn*VLOOKUP(B47,ChurnSeasonTable,4,FALSE)),3)*PricePremAnnual*E47 | AA47: =X47+Y47+Z47 | AB47: =SUM(AA36:AA47) | AC47: =OR(AC46,AB47>=VATThreshold) | AD47: =IF(AC47,AA47/(1+VATRate),AA47) | AE47: =AA47-AD47 | AF47: =IF(AC47=0,0,IF(B47=1,SUMPRODUCT(--(($C$5:$C47=$C47-1)*($B$5:$B47>=10)*($B$5:$B47<=12)),$AE$5:$AE47),IF(B47=4,SUMPRODUCT(--(($C$5:$C47=$C47)*($B$5:$B47>=1)*($B$5:$B47<=3)),$AE$5:$AE47),IF(B47=7,SUMPRODUCT(--(($C$5:$C47=$C47)*($B$5:$B47>=4)*($B$5:$B47<=6)),$AE$5:$AE47),IF(B47=10,SUMPRODUCT(--(($C$5:$C47=$C47)*($B$5:$B47>=7)*($B$5:$B47<=9)),$AE$5:$AE47),0))))) | AG47: =AG46+AE47-AF47 | AH47: =IF(ProviderDelay>=1,AD46*ProviderShare,AD47*ProviderShare) | AI47: =AA47*PaymentFee | AJ47: =U47*OpsAI | AK47: =MonthlyFixed | AL47: =I47*ReferralReward | AM47: =G47 | AN47: =AD47-AH47-AI47-AJ47-AK47-AL47-AM47 | AO47: =AO46+AA47-(AH47+AI47+AJ47+AK47+AL47+AM47+AF47) | AP47: =IF(U47>0,V47/U47,0) | AQ47: =IF(U46>0,MAX(0,(U46+J47-U47)/U46),0)
A48: 44 | B48: =MOD(A48-1+LaunchMonth-1,12)+1 | C48: =INT((A48-1+LaunchMonth-1)/12)+1 | D48: =VLOOKUP(B48,SeasonTable,2,FALSE) | E48: =(1+InflationRate)^INT((A48-1)/12) | F48: =MonthlyChurn*VLOOKUP(B48,ChurnSeasonTable,4,FALSE) | G48: =MIN(MAX(MktMin19plus,AA47*MktPct19plus),MAX(0,AO47-CashBuffer)) | H48: =IF(G48>0,MAX(1,ROUND(G48/CAC*D48,0)),0) | I48: =IF(H48>0,ROUND(H48*ReferralMix/(1-ReferralMix),0),0) | J48: =H48+I48 | K48: =ROUND(J48*(1-AnnualMix),0) | L48: =J48-K48 | M48: =ROUND(K48*EssentialMix,0) | N48: =K48-M48 | O48: =ROUND(L48*EssentialMix,0) | P48: =L48-O48 | Q48: =M48+M47+M46+MAX(0,Q47-M47-M46)*(1-F48) | R48: =N48+N47+N46+MAX(0,R47-N47-N46)*(1-F48) | S48: =S47+O48-O36*(AnnualChurn*VLOOKUP(B48,ChurnSeasonTable,4,FALSE))*POWER(1-(AnnualChurn*VLOOKUP(B48,ChurnSeasonTable,4,FALSE)),0)+O24*(AnnualChurn*VLOOKUP(B48,ChurnSeasonTable,4,FALSE))*POWER(1-(AnnualChurn*VLOOKUP(B48,ChurnSeasonTable,4,FALSE)),1)+O12*(AnnualChurn*VLOOKUP(B48,ChurnSeasonTable,4,FALSE))*POWER(1-(AnnualChurn*VLOOKUP(B48,ChurnSeasonTable,4,FALSE)),2) | T48: =T47+P48-P36*(AnnualChurn*VLOOKUP(B48,ChurnSeasonTable,4,FALSE))*POWER(1-(AnnualChurn*VLOOKUP(B48,ChurnSeasonTable,4,FALSE)),0)+P24*(AnnualChurn*VLOOKUP(B48,ChurnSeasonTable,4,FALSE))*POWER(1-(AnnualChurn*VLOOKUP(B48,ChurnSeasonTable,4,FALSE)),1)+P12*(AnnualChurn*VLOOKUP(B48,ChurnSeasonTable,4,FALSE))*POWER(1-(AnnualChurn*VLOOKUP(B48,ChurnSeasonTable,4,FALSE)),2) | U48: =Q48+R48+S48+T48 | V48: =Q48*PriceEssMonthly*E48+R48*PricePremMonthly*E48+S48*PriceEssAnnual*E48/12+T48*PricePremAnnual*E48/12 | W48: =V48*12 | X48: =Q48*PriceEssMonthly*E48+R48*PricePremMonthly*E48 | Y48: =O48*PriceEssAnnual*E48+P48*PricePremAnnual*E48 | Z48: =O36*POWER(1-(AnnualChurn*VLOOKUP(B48,ChurnSeasonTable,4,FALSE)),1)*PriceEssAnnual*E48+O24*POWER(1-(AnnualChurn*VLOOKUP(B48,ChurnSeasonTable,4,FALSE)),2)*PriceEssAnnual*E48+O12*POWER(1-(AnnualChurn*VLOOKUP(B48,ChurnSeasonTable,4,FALSE)),3)*PriceEssAnnual*E48+P36*POWER(1-(AnnualChurn*VLOOKUP(B48,ChurnSeasonTable,4,FALSE)),1)*PricePremAnnual*E48+P24*POWER(1-(AnnualChurn*VLOOKUP(B48,ChurnSeasonTable,4,FALSE)),2)*PricePremAnnual*E48+P12*POWER(1-(AnnualChurn*VLOOKUP(B48,ChurnSeasonTable,4,FALSE)),3)*PricePremAnnual*E48 | AA48: =X48+Y48+Z48 | AB48: =SUM(AA37:AA48) | AC48: =OR(AC47,AB48>=VATThreshold) | AD48: =IF(AC48,AA48/(1+VATRate),AA48) | AE48: =AA48-AD48 | AF48: =IF(AC48=0,0,IF(B48=1,SUMPRODUCT(--(($C$5:$C48=$C48-1)*($B$5:$B48>=10)*($B$5:$B48<=12)),$AE$5:$AE48),IF(B48=4,SUMPRODUCT(--(($C$5:$C48=$C48)*($B$5:$B48>=1)*($B$5:$B48<=3)),$AE$5:$AE48),IF(B48=7,SUMPRODUCT(--(($C$5:$C48=$C48)*($B$5:$B48>=4)*($B$5:$B48<=6)),$AE$5:$AE48),IF(B48=10,SUMPRODUCT(--(($C$5:$C48=$C48)*($B$5:$B48>=7)*($B$5:$B48<=9)),$AE$5:$AE48),0))))) | AG48: =AG47+AE48-AF48 | AH48: =IF(ProviderDelay>=1,AD47*ProviderShare,AD48*ProviderShare) | AI48: =AA48*PaymentFee | AJ48: =U48*OpsAI | AK48: =MonthlyFixed | AL48: =I48*ReferralReward | AM48: =G48 | AN48: =AD48-AH48-AI48-AJ48-AK48-AL48-AM48 | AO48: =AO47+AA48-(AH48+AI48+AJ48+AK48+AL48+AM48+AF48) | AP48: =IF(U48>0,V48/U48,0) | AQ48: =IF(U47>0,MAX(0,(U47+J48-U48)/U47),0)
A49: 45 | B49: =MOD(A49-1+LaunchMonth-1,12)+1 | C49: =INT((A49-1+LaunchMonth-1)/12)+1 | D49: =VLOOKUP(B49,SeasonTable,2,FALSE) | E49: =(1+InflationRate)^INT((A49-1)/12) | F49: =MonthlyChurn*VLOOKUP(B49,ChurnSeasonTable,4,FALSE) | G49: =MIN(MAX(MktMin19plus,AA48*MktPct19plus),MAX(0,AO48-CashBuffer)) | H49: =IF(G49>0,MAX(1,ROUND(G49/CAC*D49,0)),0) | I49: =IF(H49>0,ROUND(H49*ReferralMix/(1-ReferralMix),0),0) | J49: =H49+I49 | K49: =ROUND(J49*(1-AnnualMix),0) | L49: =J49-K49 | M49: =ROUND(K49*EssentialMix,0) | N49: =K49-M49 | O49: =ROUND(L49*EssentialMix,0) | P49: =L49-O49 | Q49: =M49+M48+M47+MAX(0,Q48-M48-M47)*(1-F49) | R49: =N49+N48+N47+MAX(0,R48-N48-N47)*(1-F49) | S49: =S48+O49-O37*(AnnualChurn*VLOOKUP(B49,ChurnSeasonTable,4,FALSE))*POWER(1-(AnnualChurn*VLOOKUP(B49,ChurnSeasonTable,4,FALSE)),0)+O25*(AnnualChurn*VLOOKUP(B49,ChurnSeasonTable,4,FALSE))*POWER(1-(AnnualChurn*VLOOKUP(B49,ChurnSeasonTable,4,FALSE)),1)+O13*(AnnualChurn*VLOOKUP(B49,ChurnSeasonTable,4,FALSE))*POWER(1-(AnnualChurn*VLOOKUP(B49,ChurnSeasonTable,4,FALSE)),2) | T49: =T48+P49-P37*(AnnualChurn*VLOOKUP(B49,ChurnSeasonTable,4,FALSE))*POWER(1-(AnnualChurn*VLOOKUP(B49,ChurnSeasonTable,4,FALSE)),0)+P25*(AnnualChurn*VLOOKUP(B49,ChurnSeasonTable,4,FALSE))*POWER(1-(AnnualChurn*VLOOKUP(B49,ChurnSeasonTable,4,FALSE)),1)+P13*(AnnualChurn*VLOOKUP(B49,ChurnSeasonTable,4,FALSE))*POWER(1-(AnnualChurn*VLOOKUP(B49,ChurnSeasonTable,4,FALSE)),2) | U49: =Q49+R49+S49+T49 | V49: =Q49*PriceEssMonthly*E49+R49*PricePremMonthly*E49+S49*PriceEssAnnual*E49/12+T49*PricePremAnnual*E49/12 | W49: =V49*12 | X49: =Q49*PriceEssMonthly*E49+R49*PricePremMonthly*E49 | Y49: =O49*PriceEssAnnual*E49+P49*PricePremAnnual*E49 | Z49: =O37*POWER(1-(AnnualChurn*VLOOKUP(B49,ChurnSeasonTable,4,FALSE)),1)*PriceEssAnnual*E49+O25*POWER(1-(AnnualChurn*VLOOKUP(B49,ChurnSeasonTable,4,FALSE)),2)*PriceEssAnnual*E49+O13*POWER(1-(AnnualChurn*VLOOKUP(B49,ChurnSeasonTable,4,FALSE)),3)*PriceEssAnnual*E49+P37*POWER(1-(AnnualChurn*VLOOKUP(B49,ChurnSeasonTable,4,FALSE)),1)*PricePremAnnual*E49+P25*POWER(1-(AnnualChurn*VLOOKUP(B49,ChurnSeasonTable,4,FALSE)),2)*PricePremAnnual*E49+P13*POWER(1-(AnnualChurn*VLOOKUP(B49,ChurnSeasonTable,4,FALSE)),3)*PricePremAnnual*E49 | AA49: =X49+Y49+Z49 | AB49: =SUM(AA38:AA49) | AC49: =OR(AC48,AB49>=VATThreshold) | AD49: =IF(AC49,AA49/(1+VATRate),AA49) | AE49: =AA49-AD49 | AF49: =IF(AC49=0,0,IF(B49=1,SUMPRODUCT(--(($C$5:$C49=$C49-1)*($B$5:$B49>=10)*($B$5:$B49<=12)),$AE$5:$AE49),IF(B49=4,SUMPRODUCT(--(($C$5:$C49=$C49)*($B$5:$B49>=1)*($B$5:$B49<=3)),$AE$5:$AE49),IF(B49=7,SUMPRODUCT(--(($C$5:$C49=$C49)*($B$5:$B49>=4)*($B$5:$B49<=6)),$AE$5:$AE49),IF(B49=10,SUMPRODUCT(--(($C$5:$C49=$C49)*($B$5:$B49>=7)*($B$5:$B49<=9)),$AE$5:$AE49),0))))) | AG49: =AG48+AE49-AF49 | AH49: =IF(ProviderDelay>=1,AD48*ProviderShare,AD49*ProviderShare) | AI49: =AA49*PaymentFee | AJ49: =U49*OpsAI | AK49: =MonthlyFixed | AL49: =I49*ReferralReward | AM49: =G49 | AN49: =AD49-AH49-AI49-AJ49-AK49-AL49-AM49 | AO49: =AO48+AA49-(AH49+AI49+AJ49+AK49+AL49+AM49+AF49) | AP49: =IF(U49>0,V49/U49,0) | AQ49: =IF(U48>0,MAX(0,(U48+J49-U49)/U48),0)
A50: 46 | B50: =MOD(A50-1+LaunchMonth-1,12)+1 | C50: =INT((A50-1+LaunchMonth-1)/12)+1 | D50: =VLOOKUP(B50,SeasonTable,2,FALSE) | E50: =(1+InflationRate)^INT((A50-1)/12) | F50: =MonthlyChurn*VLOOKUP(B50,ChurnSeasonTable,4,FALSE) | G50: =MIN(MAX(MktMin19plus,AA49*MktPct19plus),MAX(0,AO49-CashBuffer)) | H50: =IF(G50>0,MAX(1,ROUND(G50/CAC*D50,0)),0) | I50: =IF(H50>0,ROUND(H50*ReferralMix/(1-ReferralMix),0),0) | J50: =H50+I50 | K50: =ROUND(J50*(1-AnnualMix),0) | L50: =J50-K50 | M50: =ROUND(K50*EssentialMix,0) | N50: =K50-M50 | O50: =ROUND(L50*EssentialMix,0) | P50: =L50-O50 | Q50: =M50+M49+M48+MAX(0,Q49-M49-M48)*(1-F50) | R50: =N50+N49+N48+MAX(0,R49-N49-N48)*(1-F50) | S50: =S49+O50-O38*(AnnualChurn*VLOOKUP(B50,ChurnSeasonTable,4,FALSE))*POWER(1-(AnnualChurn*VLOOKUP(B50,ChurnSeasonTable,4,FALSE)),0)+O26*(AnnualChurn*VLOOKUP(B50,ChurnSeasonTable,4,FALSE))*POWER(1-(AnnualChurn*VLOOKUP(B50,ChurnSeasonTable,4,FALSE)),1)+O14*(AnnualChurn*VLOOKUP(B50,ChurnSeasonTable,4,FALSE))*POWER(1-(AnnualChurn*VLOOKUP(B50,ChurnSeasonTable,4,FALSE)),2) | T50: =T49+P50-P38*(AnnualChurn*VLOOKUP(B50,ChurnSeasonTable,4,FALSE))*POWER(1-(AnnualChurn*VLOOKUP(B50,ChurnSeasonTable,4,FALSE)),0)+P26*(AnnualChurn*VLOOKUP(B50,ChurnSeasonTable,4,FALSE))*POWER(1-(AnnualChurn*VLOOKUP(B50,ChurnSeasonTable,4,FALSE)),1)+P14*(AnnualChurn*VLOOKUP(B50,ChurnSeasonTable,4,FALSE))*POWER(1-(AnnualChurn*VLOOKUP(B50,ChurnSeasonTable,4,FALSE)),2) | U50: =Q50+R50+S50+T50 | V50: =Q50*PriceEssMonthly*E50+R50*PricePremMonthly*E50+S50*PriceEssAnnual*E50/12+T50*PricePremAnnual*E50/12 | W50: =V50*12 | X50: =Q50*PriceEssMonthly*E50+R50*PricePremMonthly*E50 | Y50: =O50*PriceEssAnnual*E50+P50*PricePremAnnual*E50 | Z50: =O38*POWER(1-(AnnualChurn*VLOOKUP(B50,ChurnSeasonTable,4,FALSE)),1)*PriceEssAnnual*E50+O26*POWER(1-(AnnualChurn*VLOOKUP(B50,ChurnSeasonTable,4,FALSE)),2)*PriceEssAnnual*E50+O14*POWER(1-(AnnualChurn*VLOOKUP(B50,ChurnSeasonTable,4,FALSE)),3)*PriceEssAnnual*E50+P38*POWER(1-(AnnualChurn*VLOOKUP(B50,ChurnSeasonTable,4,FALSE)),1)*PricePremAnnual*E50+P26*POWER(1-(AnnualChurn*VLOOKUP(B50,ChurnSeasonTable,4,FALSE)),2)*PricePremAnnual*E50+P14*POWER(1-(AnnualChurn*VLOOKUP(B50,ChurnSeasonTable,4,FALSE)),3)*PricePremAnnual*E50 | AA50: =X50+Y50+Z50 | AB50: =SUM(AA39:AA50) | AC50: =OR(AC49,AB50>=VATThreshold) | AD50: =IF(AC50,AA50/(1+VATRate),AA50) | AE50: =AA50-AD50 | AF50: =IF(AC50=0,0,IF(B50=1,SUMPRODUCT(--(($C$5:$C50=$C50-1)*($B$5:$B50>=10)*($B$5:$B50<=12)),$AE$5:$AE50),IF(B50=4,SUMPRODUCT(--(($C$5:$C50=$C50)*($B$5:$B50>=1)*($B$5:$B50<=3)),$AE$5:$AE50),IF(B50=7,SUMPRODUCT(--(($C$5:$C50=$C50)*($B$5:$B50>=4)*($B$5:$B50<=6)),$AE$5:$AE50),IF(B50=10,SUMPRODUCT(--(($C$5:$C50=$C50)*($B$5:$B50>=7)*($B$5:$B50<=9)),$AE$5:$AE50),0))))) | AG50: =AG49+AE50-AF50 | AH50: =IF(ProviderDelay>=1,AD49*ProviderShare,AD50*ProviderShare) | AI50: =AA50*PaymentFee | AJ50: =U50*OpsAI | AK50: =MonthlyFixed | AL50: =I50*ReferralReward | AM50: =G50 | AN50: =AD50-AH50-AI50-AJ50-AK50-AL50-AM50 | AO50: =AO49+AA50-(AH50+AI50+AJ50+AK50+AL50+AM50+AF50) | AP50: =IF(U50>0,V50/U50,0) | AQ50: =IF(U49>0,MAX(0,(U49+J50-U50)/U49),0)
A51: 47 | B51: =MOD(A51-1+LaunchMonth-1,12)+1 | C51: =INT((A51-1+LaunchMonth-1)/12)+1 | D51: =VLOOKUP(B51,SeasonTable,2,FALSE) | E51: =(1+InflationRate)^INT((A51-1)/12) | F51: =MonthlyChurn*VLOOKUP(B51,ChurnSeasonTable,4,FALSE) | G51: =MIN(MAX(MktMin19plus,AA50*MktPct19plus),MAX(0,AO50-CashBuffer)) | H51: =IF(G51>0,MAX(1,ROUND(G51/CAC*D51,0)),0) | I51: =IF(H51>0,ROUND(H51*ReferralMix/(1-ReferralMix),0),0) | J51: =H51+I51 | K51: =ROUND(J51*(1-AnnualMix),0) | L51: =J51-K51 | M51: =ROUND(K51*EssentialMix,0) | N51: =K51-M51 | O51: =ROUND(L51*EssentialMix,0) | P51: =L51-O51 | Q51: =M51+M50+M49+MAX(0,Q50-M50-M49)*(1-F51) | R51: =N51+N50+N49+MAX(0,R50-N50-N49)*(1-F51) | S51: =S50+O51-O39*(AnnualChurn*VLOOKUP(B51,ChurnSeasonTable,4,FALSE))*POWER(1-(AnnualChurn*VLOOKUP(B51,ChurnSeasonTable,4,FALSE)),0)+O27*(AnnualChurn*VLOOKUP(B51,ChurnSeasonTable,4,FALSE))*POWER(1-(AnnualChurn*VLOOKUP(B51,ChurnSeasonTable,4,FALSE)),1)+O15*(AnnualChurn*VLOOKUP(B51,ChurnSeasonTable,4,FALSE))*POWER(1-(AnnualChurn*VLOOKUP(B51,ChurnSeasonTable,4,FALSE)),2) | T51: =T50+P51-P39*(AnnualChurn*VLOOKUP(B51,ChurnSeasonTable,4,FALSE))*POWER(1-(AnnualChurn*VLOOKUP(B51,ChurnSeasonTable,4,FALSE)),0)+P27*(AnnualChurn*VLOOKUP(B51,ChurnSeasonTable,4,FALSE))*POWER(1-(AnnualChurn*VLOOKUP(B51,ChurnSeasonTable,4,FALSE)),1)+P15*(AnnualChurn*VLOOKUP(B51,ChurnSeasonTable,4,FALSE))*POWER(1-(AnnualChurn*VLOOKUP(B51,ChurnSeasonTable,4,FALSE)),2) | U51: =Q51+R51+S51+T51 | V51: =Q51*PriceEssMonthly*E51+R51*PricePremMonthly*E51+S51*PriceEssAnnual*E51/12+T51*PricePremAnnual*E51/12 | W51: =V51*12 | X51: =Q51*PriceEssMonthly*E51+R51*PricePremMonthly*E51 | Y51: =O51*PriceEssAnnual*E51+P51*PricePremAnnual*E51 | Z51: =O39*POWER(1-(AnnualChurn*VLOOKUP(B51,ChurnSeasonTable,4,FALSE)),1)*PriceEssAnnual*E51+O27*POWER(1-(AnnualChurn*VLOOKUP(B51,ChurnSeasonTable,4,FALSE)),2)*PriceEssAnnual*E51+O15*POWER(1-(AnnualChurn*VLOOKUP(B51,ChurnSeasonTable,4,FALSE)),3)*PriceEssAnnual*E51+P39*POWER(1-(AnnualChurn*VLOOKUP(B51,ChurnSeasonTable,4,FALSE)),1)*PricePremAnnual*E51+P27*POWER(1-(AnnualChurn*VLOOKUP(B51,ChurnSeasonTable,4,FALSE)),2)*PricePremAnnual*E51+P15*POWER(1-(AnnualChurn*VLOOKUP(B51,ChurnSeasonTable,4,FALSE)),3)*PricePremAnnual*E51 | AA51: =X51+Y51+Z51 | AB51: =SUM(AA40:AA51) | AC51: =OR(AC50,AB51>=VATThreshold) | AD51: =IF(AC51,AA51/(1+VATRate),AA51) | AE51: =AA51-AD51 | AF51: =IF(AC51=0,0,IF(B51=1,SUMPRODUCT(--(($C$5:$C51=$C51-1)*($B$5:$B51>=10)*($B$5:$B51<=12)),$AE$5:$AE51),IF(B51=4,SUMPRODUCT(--(($C$5:$C51=$C51)*($B$5:$B51>=1)*($B$5:$B51<=3)),$AE$5:$AE51),IF(B51=7,SUMPRODUCT(--(($C$5:$C51=$C51)*($B$5:$B51>=4)*($B$5:$B51<=6)),$AE$5:$AE51),IF(B51=10,SUMPRODUCT(--(($C$5:$C51=$C51)*($B$5:$B51>=7)*($B$5:$B51<=9)),$AE$5:$AE51),0))))) | AG51: =AG50+AE51-AF51 | AH51: =IF(ProviderDelay>=1,AD50*ProviderShare,AD51*ProviderShare) | AI51: =AA51*PaymentFee | AJ51: =U51*OpsAI | AK51: =MonthlyFixed | AL51: =I51*ReferralReward | AM51: =G51 | AN51: =AD51-AH51-AI51-AJ51-AK51-AL51-AM51 | AO51: =AO50+AA51-(AH51+AI51+AJ51+AK51+AL51+AM51+AF51) | AP51: =IF(U51>0,V51/U51,0) | AQ51: =IF(U50>0,MAX(0,(U50+J51-U51)/U50),0)
A52: 48 | B52: =MOD(A52-1+LaunchMonth-1,12)+1 | C52: =INT((A52-1+LaunchMonth-1)/12)+1 | D52: =VLOOKUP(B52,SeasonTable,2,FALSE) | E52: =(1+InflationRate)^INT((A52-1)/12) | F52: =MonthlyChurn*VLOOKUP(B52,ChurnSeasonTable,4,FALSE) | G52: =MIN(MAX(MktMin19plus,AA51*MktPct19plus),MAX(0,AO51-CashBuffer)) | H52: =IF(G52>0,MAX(1,ROUND(G52/CAC*D52,0)),0) | I52: =IF(H52>0,ROUND(H52*ReferralMix/(1-ReferralMix),0),0) | J52: =H52+I52 | K52: =ROUND(J52*(1-AnnualMix),0) | L52: =J52-K52 | M52: =ROUND(K52*EssentialMix,0) | N52: =K52-M52 | O52: =ROUND(L52*EssentialMix,0) | P52: =L52-O52 | Q52: =M52+M51+M50+MAX(0,Q51-M51-M50)*(1-F52) | R52: =N52+N51+N50+MAX(0,R51-N51-N50)*(1-F52) | S52: =S51+O52-O40*(AnnualChurn*VLOOKUP(B52,ChurnSeasonTable,4,FALSE))*POWER(1-(AnnualChurn*VLOOKUP(B52,ChurnSeasonTable,4,FALSE)),0)+O28*(AnnualChurn*VLOOKUP(B52,ChurnSeasonTable,4,FALSE))*POWER(1-(AnnualChurn*VLOOKUP(B52,ChurnSeasonTable,4,FALSE)),1)+O16*(AnnualChurn*VLOOKUP(B52,ChurnSeasonTable,4,FALSE))*POWER(1-(AnnualChurn*VLOOKUP(B52,ChurnSeasonTable,4,FALSE)),2) | T52: =T51+P52-P40*(AnnualChurn*VLOOKUP(B52,ChurnSeasonTable,4,FALSE))*POWER(1-(AnnualChurn*VLOOKUP(B52,ChurnSeasonTable,4,FALSE)),0)+P28*(AnnualChurn*VLOOKUP(B52,ChurnSeasonTable,4,FALSE))*POWER(1-(AnnualChurn*VLOOKUP(B52,ChurnSeasonTable,4,FALSE)),1)+P16*(AnnualChurn*VLOOKUP(B52,ChurnSeasonTable,4,FALSE))*POWER(1-(AnnualChurn*VLOOKUP(B52,ChurnSeasonTable,4,FALSE)),2) | U52: =Q52+R52+S52+T52 | V52: =Q52*PriceEssMonthly*E52+R52*PricePremMonthly*E52+S52*PriceEssAnnual*E52/12+T52*PricePremAnnual*E52/12 | W52: =V52*12 | X52: =Q52*PriceEssMonthly*E52+R52*PricePremMonthly*E52 | Y52: =O52*PriceEssAnnual*E52+P52*PricePremAnnual*E52 | Z52: =O40*POWER(1-(AnnualChurn*VLOOKUP(B52,ChurnSeasonTable,4,FALSE)),1)*PriceEssAnnual*E52+O28*POWER(1-(AnnualChurn*VLOOKUP(B52,ChurnSeasonTable,4,FALSE)),2)*PriceEssAnnual*E52+O16*POWER(1-(AnnualChurn*VLOOKUP(B52,ChurnSeasonTable,4,FALSE)),3)*PriceEssAnnual*E52+P40*POWER(1-(AnnualChurn*VLOOKUP(B52,ChurnSeasonTable,4,FALSE)),1)*PricePremAnnual*E52+P28*POWER(1-(AnnualChurn*VLOOKUP(B52,ChurnSeasonTable,4,FALSE)),2)*PricePremAnnual*E52+P16*POWER(1-(AnnualChurn*VLOOKUP(B52,ChurnSeasonTable,4,FALSE)),3)*PricePremAnnual*E52 | AA52: =X52+Y52+Z52 | AB52: =SUM(AA41:AA52) | AC52: =OR(AC51,AB52>=VATThreshold) | AD52: =IF(AC52,AA52/(1+VATRate),AA52) | AE52: =AA52-AD52 | AF52: =IF(AC52=0,0,IF(B52=1,SUMPRODUCT(--(($C$5:$C52=$C52-1)*($B$5:$B52>=10)*($B$5:$B52<=12)),$AE$5:$AE52),IF(B52=4,SUMPRODUCT(--(($C$5:$C52=$C52)*($B$5:$B52>=1)*($B$5:$B52<=3)),$AE$5:$AE52),IF(B52=7,SUMPRODUCT(--(($C$5:$C52=$C52)*($B$5:$B52>=4)*($B$5:$B52<=6)),$AE$5:$AE52),IF(B52=10,SUMPRODUCT(--(($C$5:$C52=$C52)*($B$5:$B52>=7)*($B$5:$B52<=9)),$AE$5:$AE52),0))))) | AG52: =AG51+AE52-AF52 | AH52: =IF(ProviderDelay>=1,AD51*ProviderShare,AD52*ProviderShare) | AI52: =AA52*PaymentFee | AJ52: =U52*OpsAI | AK52: =MonthlyFixed | AL52: =I52*ReferralReward | AM52: =G52 | AN52: =AD52-AH52-AI52-AJ52-AK52-AL52-AM52 | AO52: =AO51+AA52-(AH52+AI52+AJ52+AK52+AL52+AM52+AF52) | AP52: =IF(U52>0,V52/U52,0) | AQ52: =IF(U51>0,MAX(0,(U51+J52-U52)/U51),0)
A53: 49 | B53: =MOD(A53-1+LaunchMonth-1,12)+1 | C53: =INT((A53-1+LaunchMonth-1)/12)+1 | D53: =VLOOKUP(B53,SeasonTable,2,FALSE) | E53: =(1+InflationRate)^INT((A53-1)/12) | F53: =MonthlyChurn*VLOOKUP(B53,ChurnSeasonTable,4,FALSE) | G53: =MIN(MAX(MktMin19plus,AA52*MktPct19plus),MAX(0,AO52-CashBuffer)) | H53: =IF(G53>0,MAX(1,ROUND(G53/CAC*D53,0)),0) | I53: =IF(H53>0,ROUND(H53*ReferralMix/(1-ReferralMix),0),0) | J53: =H53+I53 | K53: =ROUND(J53*(1-AnnualMix),0) | L53: =J53-K53 | M53: =ROUND(K53*EssentialMix,0) | N53: =K53-M53 | O53: =ROUND(L53*EssentialMix,0) | P53: =L53-O53 | Q53: =M53+M52+M51+MAX(0,Q52-M52-M51)*(1-F53) | R53: =N53+N52+N51+MAX(0,R52-N52-N51)*(1-F53) | S53: =S52+O53-O41*(AnnualChurn*VLOOKUP(B53,ChurnSeasonTable,4,FALSE))*POWER(1-(AnnualChurn*VLOOKUP(B53,ChurnSeasonTable,4,FALSE)),0)+O29*(AnnualChurn*VLOOKUP(B53,ChurnSeasonTable,4,FALSE))*POWER(1-(AnnualChurn*VLOOKUP(B53,ChurnSeasonTable,4,FALSE)),1)+O17*(AnnualChurn*VLOOKUP(B53,ChurnSeasonTable,4,FALSE))*POWER(1-(AnnualChurn*VLOOKUP(B53,ChurnSeasonTable,4,FALSE)),2)+O5*(AnnualChurn*VLOOKUP(B53,ChurnSeasonTable,4,FALSE))*POWER(1-(AnnualChurn*VLOOKUP(B53,ChurnSeasonTable,4,FALSE)),3) | T53: =T52+P53-P41*(AnnualChurn*VLOOKUP(B53,ChurnSeasonTable,4,FALSE))*POWER(1-(AnnualChurn*VLOOKUP(B53,ChurnSeasonTable,4,FALSE)),0)+P29*(AnnualChurn*VLOOKUP(B53,ChurnSeasonTable,4,FALSE))*POWER(1-(AnnualChurn*VLOOKUP(B53,ChurnSeasonTable,4,FALSE)),1)+P17*(AnnualChurn*VLOOKUP(B53,ChurnSeasonTable,4,FALSE))*POWER(1-(AnnualChurn*VLOOKUP(B53,ChurnSeasonTable,4,FALSE)),2)+P5*(AnnualChurn*VLOOKUP(B53,ChurnSeasonTable,4,FALSE))*POWER(1-(AnnualChurn*VLOOKUP(B53,ChurnSeasonTable,4,FALSE)),3) | U53: =Q53+R53+S53+T53 | V53: =Q53*PriceEssMonthly*E53+R53*PricePremMonthly*E53+S53*PriceEssAnnual*E53/12+T53*PricePremAnnual*E53/12 | W53: =V53*12 | X53: =Q53*PriceEssMonthly*E53+R53*PricePremMonthly*E53 | Y53: =O53*PriceEssAnnual*E53+P53*PricePremAnnual*E53 | Z53: =O41*POWER(1-(AnnualChurn*VLOOKUP(B53,ChurnSeasonTable,4,FALSE)),1)*PriceEssAnnual*E53+O29*POWER(1-(AnnualChurn*VLOOKUP(B53,ChurnSeasonTable,4,FALSE)),2)*PriceEssAnnual*E53+O17*POWER(1-(AnnualChurn*VLOOKUP(B53,ChurnSeasonTable,4,FALSE)),3)*PriceEssAnnual*E53+O5*POWER(1-(AnnualChurn*VLOOKUP(B53,ChurnSeasonTable,4,FALSE)),4)*PriceEssAnnual*E53+P41*POWER(1-(AnnualChurn*VLOOKUP(B53,ChurnSeasonTable,4,FALSE)),1)*PricePremAnnual*E53+P29*POWER(1-(AnnualChurn*VLOOKUP(B53,ChurnSeasonTable,4,FALSE)),2)*PricePremAnnual*E53+P17*POWER(1-(AnnualChurn*VLOOKUP(B53,ChurnSeasonTable,4,FALSE)),3)*PricePremAnnual*E53+P5*POWER(1-(AnnualChurn*VLOOKUP(B53,ChurnSeasonTable,4,FALSE)),4)*PricePremAnnual*E53 | AA53: =X53+Y53+Z53 | AB53: =SUM(AA42:AA53) | AC53: =OR(AC52,AB53>=VATThreshold) | AD53: =IF(AC53,AA53/(1+VATRate),AA53) | AE53: =AA53-AD53 | AF53: =IF(AC53=0,0,IF(B53=1,SUMPRODUCT(--(($C$5:$C53=$C53-1)*($B$5:$B53>=10)*($B$5:$B53<=12)),$AE$5:$AE53),IF(B53=4,SUMPRODUCT(--(($C$5:$C53=$C53)*($B$5:$B53>=1)*($B$5:$B53<=3)),$AE$5:$AE53),IF(B53=7,SUMPRODUCT(--(($C$5:$C53=$C53)*($B$5:$B53>=4)*($B$5:$B53<=6)),$AE$5:$AE53),IF(B53=10,SUMPRODUCT(--(($C$5:$C53=$C53)*($B$5:$B53>=7)*($B$5:$B53<=9)),$AE$5:$AE53),0))))) | AG53: =AG52+AE53-AF53 | AH53: =IF(ProviderDelay>=1,AD52*ProviderShare,AD53*ProviderShare) | AI53: =AA53*PaymentFee | AJ53: =U53*OpsAI | AK53: =MonthlyFixed | AL53: =I53*ReferralReward | AM53: =G53 | AN53: =AD53-AH53-AI53-AJ53-AK53-AL53-AM53 | AO53: =AO52+AA53-(AH53+AI53+AJ53+AK53+AL53+AM53+AF53) | AP53: =IF(U53>0,V53/U53,0) | AQ53: =IF(U52>0,MAX(0,(U52+J53-U53)/U52),0)
A54: 50 | B54: =MOD(A54-1+LaunchMonth-1,12)+1 | C54: =INT((A54-1+LaunchMonth-1)/12)+1 | D54: =VLOOKUP(B54,SeasonTable,2,FALSE) | E54: =(1+InflationRate)^INT((A54-1)/12) | F54: =MonthlyChurn*VLOOKUP(B54,ChurnSeasonTable,4,FALSE) | G54: =MIN(MAX(MktMin19plus,AA53*MktPct19plus),MAX(0,AO53-CashBuffer)) | H54: =IF(G54>0,MAX(1,ROUND(G54/CAC*D54,0)),0) | I54: =IF(H54>0,ROUND(H54*ReferralMix/(1-ReferralMix),0),0) | J54: =H54+I54 | K54: =ROUND(J54*(1-AnnualMix),0) | L54: =J54-K54 | M54: =ROUND(K54*EssentialMix,0) | N54: =K54-M54 | O54: =ROUND(L54*EssentialMix,0) | P54: =L54-O54 | Q54: =M54+M53+M52+MAX(0,Q53-M53-M52)*(1-F54) | R54: =N54+N53+N52+MAX(0,R53-N53-N52)*(1-F54) | S54: =S53+O54-O42*(AnnualChurn*VLOOKUP(B54,ChurnSeasonTable,4,FALSE))*POWER(1-(AnnualChurn*VLOOKUP(B54,ChurnSeasonTable,4,FALSE)),0)+O30*(AnnualChurn*VLOOKUP(B54,ChurnSeasonTable,4,FALSE))*POWER(1-(AnnualChurn*VLOOKUP(B54,ChurnSeasonTable,4,FALSE)),1)+O18*(AnnualChurn*VLOOKUP(B54,ChurnSeasonTable,4,FALSE))*POWER(1-(AnnualChurn*VLOOKUP(B54,ChurnSeasonTable,4,FALSE)),2)+O6*(AnnualChurn*VLOOKUP(B54,ChurnSeasonTable,4,FALSE))*POWER(1-(AnnualChurn*VLOOKUP(B54,ChurnSeasonTable,4,FALSE)),3) | T54: =T53+P54-P42*(AnnualChurn*VLOOKUP(B54,ChurnSeasonTable,4,FALSE))*POWER(1-(AnnualChurn*VLOOKUP(B54,ChurnSeasonTable,4,FALSE)),0)+P30*(AnnualChurn*VLOOKUP(B54,ChurnSeasonTable,4,FALSE))*POWER(1-(AnnualChurn*VLOOKUP(B54,ChurnSeasonTable,4,FALSE)),1)+P18*(AnnualChurn*VLOOKUP(B54,ChurnSeasonTable,4,FALSE))*POWER(1-(AnnualChurn*VLOOKUP(B54,ChurnSeasonTable,4,FALSE)),2)+P6*(AnnualChurn*VLOOKUP(B54,ChurnSeasonTable,4,FALSE))*POWER(1-(AnnualChurn*VLOOKUP(B54,ChurnSeasonTable,4,FALSE)),3) | U54: =Q54+R54+S54+T54 | V54: =Q54*PriceEssMonthly*E54+R54*PricePremMonthly*E54+S54*PriceEssAnnual*E54/12+T54*PricePremAnnual*E54/12 | W54: =V54*12 | X54: =Q54*PriceEssMonthly*E54+R54*PricePremMonthly*E54 | Y54: =O54*PriceEssAnnual*E54+P54*PricePremAnnual*E54 | Z54: =O42*POWER(1-(AnnualChurn*VLOOKUP(B54,ChurnSeasonTable,4,FALSE)),1)*PriceEssAnnual*E54+O30*POWER(1-(AnnualChurn*VLOOKUP(B54,ChurnSeasonTable,4,FALSE)),2)*PriceEssAnnual*E54+O18*POWER(1-(AnnualChurn*VLOOKUP(B54,ChurnSeasonTable,4,FALSE)),3)*PriceEssAnnual*E54+O6*POWER(1-(AnnualChurn*VLOOKUP(B54,ChurnSeasonTable,4,FALSE)),4)*PriceEssAnnual*E54+P42*POWER(1-(AnnualChurn*VLOOKUP(B54,ChurnSeasonTable,4,FALSE)),1)*PricePremAnnual*E54+P30*POWER(1-(AnnualChurn*VLOOKUP(B54,ChurnSeasonTable,4,FALSE)),2)*PricePremAnnual*E54+P18*POWER(1-(AnnualChurn*VLOOKUP(B54,ChurnSeasonTable,4,FALSE)),3)*PricePremAnnual*E54+P6*POWER(1-(AnnualChurn*VLOOKUP(B54,ChurnSeasonTable,4,FALSE)),4)*PricePremAnnual*E54 | AA54: =X54+Y54+Z54 | AB54: =SUM(AA43:AA54) | AC54: =OR(AC53,AB54>=VATThreshold) | AD54: =IF(AC54,AA54/(1+VATRate),AA54) | AE54: =AA54-AD54 | AF54: =IF(AC54=0,0,IF(B54=1,SUMPRODUCT(--(($C$5:$C54=$C54-1)*($B$5:$B54>=10)*($B$5:$B54<=12)),$AE$5:$AE54),IF(B54=4,SUMPRODUCT(--(($C$5:$C54=$C54)*($B$5:$B54>=1)*($B$5:$B54<=3)),$AE$5:$AE54),IF(B54=7,SUMPRODUCT(--(($C$5:$C54=$C54)*($B$5:$B54>=4)*($B$5:$B54<=6)),$AE$5:$AE54),IF(B54=10,SUMPRODUCT(--(($C$5:$C54=$C54)*($B$5:$B54>=7)*($B$5:$B54<=9)),$AE$5:$AE54),0))))) | AG54: =AG53+AE54-AF54 | AH54: =IF(ProviderDelay>=1,AD53*ProviderShare,AD54*ProviderShare) | AI54: =AA54*PaymentFee | AJ54: =U54*OpsAI | AK54: =MonthlyFixed | AL54: =I54*ReferralReward | AM54: =G54 | AN54: =AD54-AH54-AI54-AJ54-AK54-AL54-AM54 | AO54: =AO53+AA54-(AH54+AI54+AJ54+AK54+AL54+AM54+AF54) | AP54: =IF(U54>0,V54/U54,0) | AQ54: =IF(U53>0,MAX(0,(U53+J54-U54)/U53),0)
A55: 51 | B55: =MOD(A55-1+LaunchMonth-1,12)+1 | C55: =INT((A55-1+LaunchMonth-1)/12)+1 | D55: =VLOOKUP(B55,SeasonTable,2,FALSE) | E55: =(1+InflationRate)^INT((A55-1)/12) | F55: =MonthlyChurn*VLOOKUP(B55,ChurnSeasonTable,4,FALSE) | G55: =MIN(MAX(MktMin19plus,AA54*MktPct19plus),MAX(0,AO54-CashBuffer)) | H55: =IF(G55>0,MAX(1,ROUND(G55/CAC*D55,0)),0) | I55: =IF(H55>0,ROUND(H55*ReferralMix/(1-ReferralMix),0),0) | J55: =H55+I55 | K55: =ROUND(J55*(1-AnnualMix),0) | L55: =J55-K55 | M55: =ROUND(K55*EssentialMix,0) | N55: =K55-M55 | O55: =ROUND(L55*EssentialMix,0) | P55: =L55-O55 | Q55: =M55+M54+M53+MAX(0,Q54-M54-M53)*(1-F55) | R55: =N55+N54+N53+MAX(0,R54-N54-N53)*(1-F55) | S55: =S54+O55-O43*(AnnualChurn*VLOOKUP(B55,ChurnSeasonTable,4,FALSE))*POWER(1-(AnnualChurn*VLOOKUP(B55,ChurnSeasonTable,4,FALSE)),0)+O31*(AnnualChurn*VLOOKUP(B55,ChurnSeasonTable,4,FALSE))*POWER(1-(AnnualChurn*VLOOKUP(B55,ChurnSeasonTable,4,FALSE)),1)+O19*(AnnualChurn*VLOOKUP(B55,ChurnSeasonTable,4,FALSE))*POWER(1-(AnnualChurn*VLOOKUP(B55,ChurnSeasonTable,4,FALSE)),2)+O7*(AnnualChurn*VLOOKUP(B55,ChurnSeasonTable,4,FALSE))*POWER(1-(AnnualChurn*VLOOKUP(B55,ChurnSeasonTable,4,FALSE)),3) | T55: =T54+P55-P43*(AnnualChurn*VLOOKUP(B55,ChurnSeasonTable,4,FALSE))*POWER(1-(AnnualChurn*VLOOKUP(B55,ChurnSeasonTable,4,FALSE)),0)+P31*(AnnualChurn*VLOOKUP(B55,ChurnSeasonTable,4,FALSE))*POWER(1-(AnnualChurn*VLOOKUP(B55,ChurnSeasonTable,4,FALSE)),1)+P19*(AnnualChurn*VLOOKUP(B55,ChurnSeasonTable,4,FALSE))*POWER(1-(AnnualChurn*VLOOKUP(B55,ChurnSeasonTable,4,FALSE)),2)+P7*(AnnualChurn*VLOOKUP(B55,ChurnSeasonTable,4,FALSE))*POWER(1-(AnnualChurn*VLOOKUP(B55,ChurnSeasonTable,4,FALSE)),3) | U55: =Q55+R55+S55+T55 | V55: =Q55*PriceEssMonthly*E55+R55*PricePremMonthly*E55+S55*PriceEssAnnual*E55/12+T55*PricePremAnnual*E55/12 | W55: =V55*12 | X55: =Q55*PriceEssMonthly*E55+R55*PricePremMonthly*E55 | Y55: =O55*PriceEssAnnual*E55+P55*PricePremAnnual*E55 | Z55: =O43*POWER(1-(AnnualChurn*VLOOKUP(B55,ChurnSeasonTable,4,FALSE)),1)*PriceEssAnnual*E55+O31*POWER(1-(AnnualChurn*VLOOKUP(B55,ChurnSeasonTable,4,FALSE)),2)*PriceEssAnnual*E55+O19*POWER(1-(AnnualChurn*VLOOKUP(B55,ChurnSeasonTable,4,FALSE)),3)*PriceEssAnnual*E55+O7*POWER(1-(AnnualChurn*VLOOKUP(B55,ChurnSeasonTable,4,FALSE)),4)*PriceEssAnnual*E55+P43*POWER(1-(AnnualChurn*VLOOKUP(B55,ChurnSeasonTable,4,FALSE)),1)*PricePremAnnual*E55+P31*POWER(1-(AnnualChurn*VLOOKUP(B55,ChurnSeasonTable,4,FALSE)),2)*PricePremAnnual*E55+P19*POWER(1-(AnnualChurn*VLOOKUP(B55,ChurnSeasonTable,4,FALSE)),3)*PricePremAnnual*E55+P7*POWER(1-(AnnualChurn*VLOOKUP(B55,ChurnSeasonTable,4,FALSE)),4)*PricePremAnnual*E55 | AA55: =X55+Y55+Z55 | AB55: =SUM(AA44:AA55) | AC55: =OR(AC54,AB55>=VATThreshold) | AD55: =IF(AC55,AA55/(1+VATRate),AA55) | AE55: =AA55-AD55 | AF55: =IF(AC55=0,0,IF(B55=1,SUMPRODUCT(--(($C$5:$C55=$C55-1)*($B$5:$B55>=10)*($B$5:$B55<=12)),$AE$5:$AE55),IF(B55=4,SUMPRODUCT(--(($C$5:$C55=$C55)*($B$5:$B55>=1)*($B$5:$B55<=3)),$AE$5:$AE55),IF(B55=7,SUMPRODUCT(--(($C$5:$C55=$C55)*($B$5:$B55>=4)*($B$5:$B55<=6)),$AE$5:$AE55),IF(B55=10,SUMPRODUCT(--(($C$5:$C55=$C55)*($B$5:$B55>=7)*($B$5:$B55<=9)),$AE$5:$AE55),0))))) | AG55: =AG54+AE55-AF55 | AH55: =IF(ProviderDelay>=1,AD54*ProviderShare,AD55*ProviderShare) | AI55: =AA55*PaymentFee | AJ55: =U55*OpsAI | AK55: =MonthlyFixed | AL55: =I55*ReferralReward | AM55: =G55 | AN55: =AD55-AH55-AI55-AJ55-AK55-AL55-AM55 | AO55: =AO54+AA55-(AH55+AI55+AJ55+AK55+AL55+AM55+AF55) | AP55: =IF(U55>0,V55/U55,0) | AQ55: =IF(U54>0,MAX(0,(U54+J55-U55)/U54),0)
A56: 52 | B56: =MOD(A56-1+LaunchMonth-1,12)+1 | C56: =INT((A56-1+LaunchMonth-1)/12)+1 | D56: =VLOOKUP(B56,SeasonTable,2,FALSE) | E56: =(1+InflationRate)^INT((A56-1)/12) | F56: =MonthlyChurn*VLOOKUP(B56,ChurnSeasonTable,4,FALSE) | G56: =MIN(MAX(MktMin19plus,AA55*MktPct19plus),MAX(0,AO55-CashBuffer)) | H56: =IF(G56>0,MAX(1,ROUND(G56/CAC*D56,0)),0) | I56: =IF(H56>0,ROUND(H56*ReferralMix/(1-ReferralMix),0),0) | J56: =H56+I56 | K56: =ROUND(J56*(1-AnnualMix),0) | L56: =J56-K56 | M56: =ROUND(K56*EssentialMix,0) | N56: =K56-M56 | O56: =ROUND(L56*EssentialMix,0) | P56: =L56-O56 | Q56: =M56+M55+M54+MAX(0,Q55-M55-M54)*(1-F56) | R56: =N56+N55+N54+MAX(0,R55-N55-N54)*(1-F56) | S56: =S55+O56-O44*(AnnualChurn*VLOOKUP(B56,ChurnSeasonTable,4,FALSE))*POWER(1-(AnnualChurn*VLOOKUP(B56,ChurnSeasonTable,4,FALSE)),0)+O32*(AnnualChurn*VLOOKUP(B56,ChurnSeasonTable,4,FALSE))*POWER(1-(AnnualChurn*VLOOKUP(B56,ChurnSeasonTable,4,FALSE)),1)+O20*(AnnualChurn*VLOOKUP(B56,ChurnSeasonTable,4,FALSE))*POWER(1-(AnnualChurn*VLOOKUP(B56,ChurnSeasonTable,4,FALSE)),2)+O8*(AnnualChurn*VLOOKUP(B56,ChurnSeasonTable,4,FALSE))*POWER(1-(AnnualChurn*VLOOKUP(B56,ChurnSeasonTable,4,FALSE)),3) | T56: =T55+P56-P44*(AnnualChurn*VLOOKUP(B56,ChurnSeasonTable,4,FALSE))*POWER(1-(AnnualChurn*VLOOKUP(B56,ChurnSeasonTable,4,FALSE)),0)+P32*(AnnualChurn*VLOOKUP(B56,ChurnSeasonTable,4,FALSE))*POWER(1-(AnnualChurn*VLOOKUP(B56,ChurnSeasonTable,4,FALSE)),1)+P20*(AnnualChurn*VLOOKUP(B56,ChurnSeasonTable,4,FALSE))*POWER(1-(AnnualChurn*VLOOKUP(B56,ChurnSeasonTable,4,FALSE)),2)+P8*(AnnualChurn*VLOOKUP(B56,ChurnSeasonTable,4,FALSE))*POWER(1-(AnnualChurn*VLOOKUP(B56,ChurnSeasonTable,4,FALSE)),3) | U56: =Q56+R56+S56+T56 | V56: =Q56*PriceEssMonthly*E56+R56*PricePremMonthly*E56+S56*PriceEssAnnual*E56/12+T56*PricePremAnnual*E56/12 | W56: =V56*12 | X56: =Q56*PriceEssMonthly*E56+R56*PricePremMonthly*E56 | Y56: =O56*PriceEssAnnual*E56+P56*PricePremAnnual*E56 | Z56: =O44*POWER(1-(AnnualChurn*VLOOKUP(B56,ChurnSeasonTable,4,FALSE)),1)*PriceEssAnnual*E56+O32*POWER(1-(AnnualChurn*VLOOKUP(B56,ChurnSeasonTable,4,FALSE)),2)*PriceEssAnnual*E56+O20*POWER(1-(AnnualChurn*VLOOKUP(B56,ChurnSeasonTable,4,FALSE)),3)*PriceEssAnnual*E56+O8*POWER(1-(AnnualChurn*VLOOKUP(B56,ChurnSeasonTable,4,FALSE)),4)*PriceEssAnnual*E56+P44*POWER(1-(AnnualChurn*VLOOKUP(B56,ChurnSeasonTable,4,FALSE)),1)*PricePremAnnual*E56+P32*POWER(1-(AnnualChurn*VLOOKUP(B56,ChurnSeasonTable,4,FALSE)),2)*PricePremAnnual*E56+P20*POWER(1-(AnnualChurn*VLOOKUP(B56,ChurnSeasonTable,4,FALSE)),3)*PricePremAnnual*E56+P8*POWER(1-(AnnualChurn*VLOOKUP(B56,ChurnSeasonTable,4,FALSE)),4)*PricePremAnnual*E56 | AA56: =X56+Y56+Z56 | AB56: =SUM(AA45:AA56) | AC56: =OR(AC55,AB56>=VATThreshold) | AD56: =IF(AC56,AA56/(1+VATRate),AA56) | AE56: =AA56-AD56 | AF56: =IF(AC56=0,0,IF(B56=1,SUMPRODUCT(--(($C$5:$C56=$C56-1)*($B$5:$B56>=10)*($B$5:$B56<=12)),$AE$5:$AE56),IF(B56=4,SUMPRODUCT(--(($C$5:$C56=$C56)*($B$5:$B56>=1)*($B$5:$B56<=3)),$AE$5:$AE56),IF(B56=7,SUMPRODUCT(--(($C$5:$C56=$C56)*($B$5:$B56>=4)*($B$5:$B56<=6)),$AE$5:$AE56),IF(B56=10,SUMPRODUCT(--(($C$5:$C56=$C56)*($B$5:$B56>=7)*($B$5:$B56<=9)),$AE$5:$AE56),0))))) | AG56: =AG55+AE56-AF56 | AH56: =IF(ProviderDelay>=1,AD55*ProviderShare,AD56*ProviderShare) | AI56: =AA56*PaymentFee | AJ56: =U56*OpsAI | AK56: =MonthlyFixed | AL56: =I56*ReferralReward | AM56: =G56 | AN56: =AD56-AH56-AI56-AJ56-AK56-AL56-AM56 | AO56: =AO55+AA56-(AH56+AI56+AJ56+AK56+AL56+AM56+AF56) | AP56: =IF(U56>0,V56/U56,0) | AQ56: =IF(U55>0,MAX(0,(U55+J56-U56)/U55),0)
A57: 53 | B57: =MOD(A57-1+LaunchMonth-1,12)+1 | C57: =INT((A57-1+LaunchMonth-1)/12)+1 | D57: =VLOOKUP(B57,SeasonTable,2,FALSE) | E57: =(1+InflationRate)^INT((A57-1)/12) | F57: =MonthlyChurn*VLOOKUP(B57,ChurnSeasonTable,4,FALSE) | G57: =MIN(MAX(MktMin19plus,AA56*MktPct19plus),MAX(0,AO56-CashBuffer)) | H57: =IF(G57>0,MAX(1,ROUND(G57/CAC*D57,0)),0) | I57: =IF(H57>0,ROUND(H57*ReferralMix/(1-ReferralMix),0),0) | J57: =H57+I57 | K57: =ROUND(J57*(1-AnnualMix),0) | L57: =J57-K57 | M57: =ROUND(K57*EssentialMix,0) | N57: =K57-M57 | O57: =ROUND(L57*EssentialMix,0) | P57: =L57-O57 | Q57: =M57+M56+M55+MAX(0,Q56-M56-M55)*(1-F57) | R57: =N57+N56+N55+MAX(0,R56-N56-N55)*(1-F57) | S57: =S56+O57-O45*(AnnualChurn*VLOOKUP(B57,ChurnSeasonTable,4,FALSE))*POWER(1-(AnnualChurn*VLOOKUP(B57,ChurnSeasonTable,4,FALSE)),0)+O33*(AnnualChurn*VLOOKUP(B57,ChurnSeasonTable,4,FALSE))*POWER(1-(AnnualChurn*VLOOKUP(B57,ChurnSeasonTable,4,FALSE)),1)+O21*(AnnualChurn*VLOOKUP(B57,ChurnSeasonTable,4,FALSE))*POWER(1-(AnnualChurn*VLOOKUP(B57,ChurnSeasonTable,4,FALSE)),2)+O9*(AnnualChurn*VLOOKUP(B57,ChurnSeasonTable,4,FALSE))*POWER(1-(AnnualChurn*VLOOKUP(B57,ChurnSeasonTable,4,FALSE)),3) | T57: =T56+P57-P45*(AnnualChurn*VLOOKUP(B57,ChurnSeasonTable,4,FALSE))*POWER(1-(AnnualChurn*VLOOKUP(B57,ChurnSeasonTable,4,FALSE)),0)+P33*(AnnualChurn*VLOOKUP(B57,ChurnSeasonTable,4,FALSE))*POWER(1-(AnnualChurn*VLOOKUP(B57,ChurnSeasonTable,4,FALSE)),1)+P21*(AnnualChurn*VLOOKUP(B57,ChurnSeasonTable,4,FALSE))*POWER(1-(AnnualChurn*VLOOKUP(B57,ChurnSeasonTable,4,FALSE)),2)+P9*(AnnualChurn*VLOOKUP(B57,ChurnSeasonTable,4,FALSE))*POWER(1-(AnnualChurn*VLOOKUP(B57,ChurnSeasonTable,4,FALSE)),3) | U57: =Q57+R57+S57+T57 | V57: =Q57*PriceEssMonthly*E57+R57*PricePremMonthly*E57+S57*PriceEssAnnual*E57/12+T57*PricePremAnnual*E57/12 | W57: =V57*12 | X57: =Q57*PriceEssMonthly*E57+R57*PricePremMonthly*E57 | Y57: =O57*PriceEssAnnual*E57+P57*PricePremAnnual*E57 | Z57: =O45*POWER(1-(AnnualChurn*VLOOKUP(B57,ChurnSeasonTable,4,FALSE)),1)*PriceEssAnnual*E57+O33*POWER(1-(AnnualChurn*VLOOKUP(B57,ChurnSeasonTable,4,FALSE)),2)*PriceEssAnnual*E57+O21*POWER(1-(AnnualChurn*VLOOKUP(B57,ChurnSeasonTable,4,FALSE)),3)*PriceEssAnnual*E57+O9*POWER(1-(AnnualChurn*VLOOKUP(B57,ChurnSeasonTable,4,FALSE)),4)*PriceEssAnnual*E57+P45*POWER(1-(AnnualChurn*VLOOKUP(B57,ChurnSeasonTable,4,FALSE)),1)*PricePremAnnual*E57+P33*POWER(1-(AnnualChurn*VLOOKUP(B57,ChurnSeasonTable,4,FALSE)),2)*PricePremAnnual*E57+P21*POWER(1-(AnnualChurn*VLOOKUP(B57,ChurnSeasonTable,4,FALSE)),3)*PricePremAnnual*E57+P9*POWER(1-(AnnualChurn*VLOOKUP(B57,ChurnSeasonTable,4,FALSE)),4)*PricePremAnnual*E57 | AA57: =X57+Y57+Z57 | AB57: =SUM(AA46:AA57) | AC57: =OR(AC56,AB57>=VATThreshold) | AD57: =IF(AC57,AA57/(1+VATRate),AA57) | AE57: =AA57-AD57 | AF57: =IF(AC57=0,0,IF(B57=1,SUMPRODUCT(--(($C$5:$C57=$C57-1)*($B$5:$B57>=10)*($B$5:$B57<=12)),$AE$5:$AE57),IF(B57=4,SUMPRODUCT(--(($C$5:$C57=$C57)*($B$5:$B57>=1)*($B$5:$B57<=3)),$AE$5:$AE57),IF(B57=7,SUMPRODUCT(--(($C$5:$C57=$C57)*($B$5:$B57>=4)*($B$5:$B57<=6)),$AE$5:$AE57),IF(B57=10,SUMPRODUCT(--(($C$5:$C57=$C57)*($B$5:$B57>=7)*($B$5:$B57<=9)),$AE$5:$AE57),0))))) | AG57: =AG56+AE57-AF57 | AH57: =IF(ProviderDelay>=1,AD56*ProviderShare,AD57*ProviderShare) | AI57: =AA57*PaymentFee | AJ57: =U57*OpsAI | AK57: =MonthlyFixed | AL57: =I57*ReferralReward | AM57: =G57 | AN57: =AD57-AH57-AI57-AJ57-AK57-AL57-AM57 | AO57: =AO56+AA57-(AH57+AI57+AJ57+AK57+AL57+AM57+AF57) | AP57: =IF(U57>0,V57/U57,0) | AQ57: =IF(U56>0,MAX(0,(U56+J57-U57)/U56),0)
A58: 54 | B58: =MOD(A58-1+LaunchMonth-1,12)+1 | C58: =INT((A58-1+LaunchMonth-1)/12)+1 | D58: =VLOOKUP(B58,SeasonTable,2,FALSE) | E58: =(1+InflationRate)^INT((A58-1)/12) | F58: =MonthlyChurn*VLOOKUP(B58,ChurnSeasonTable,4,FALSE) | G58: =MIN(MAX(MktMin19plus,AA57*MktPct19plus),MAX(0,AO57-CashBuffer)) | H58: =IF(G58>0,MAX(1,ROUND(G58/CAC*D58,0)),0) | I58: =IF(H58>0,ROUND(H58*ReferralMix/(1-ReferralMix),0),0) | J58: =H58+I58 | K58: =ROUND(J58*(1-AnnualMix),0) | L58: =J58-K58 | M58: =ROUND(K58*EssentialMix,0) | N58: =K58-M58 | O58: =ROUND(L58*EssentialMix,0) | P58: =L58-O58 | Q58: =M58+M57+M56+MAX(0,Q57-M57-M56)*(1-F58) | R58: =N58+N57+N56+MAX(0,R57-N57-N56)*(1-F58) | S58: =S57+O58-O46*(AnnualChurn*VLOOKUP(B58,ChurnSeasonTable,4,FALSE))*POWER(1-(AnnualChurn*VLOOKUP(B58,ChurnSeasonTable,4,FALSE)),0)+O34*(AnnualChurn*VLOOKUP(B58,ChurnSeasonTable,4,FALSE))*POWER(1-(AnnualChurn*VLOOKUP(B58,ChurnSeasonTable,4,FALSE)),1)+O22*(AnnualChurn*VLOOKUP(B58,ChurnSeasonTable,4,FALSE))*POWER(1-(AnnualChurn*VLOOKUP(B58,ChurnSeasonTable,4,FALSE)),2)+O10*(AnnualChurn*VLOOKUP(B58,ChurnSeasonTable,4,FALSE))*POWER(1-(AnnualChurn*VLOOKUP(B58,ChurnSeasonTable,4,FALSE)),3) | T58: =T57+P58-P46*(AnnualChurn*VLOOKUP(B58,ChurnSeasonTable,4,FALSE))*POWER(1-(AnnualChurn*VLOOKUP(B58,ChurnSeasonTable,4,FALSE)),0)+P34*(AnnualChurn*VLOOKUP(B58,ChurnSeasonTable,4,FALSE))*POWER(1-(AnnualChurn*VLOOKUP(B58,ChurnSeasonTable,4,FALSE)),1)+P22*(AnnualChurn*VLOOKUP(B58,ChurnSeasonTable,4,FALSE))*POWER(1-(AnnualChurn*VLOOKUP(B58,ChurnSeasonTable,4,FALSE)),2)+P10*(AnnualChurn*VLOOKUP(B58,ChurnSeasonTable,4,FALSE))*POWER(1-(AnnualChurn*VLOOKUP(B58,ChurnSeasonTable,4,FALSE)),3) | U58: =Q58+R58+S58+T58 | V58: =Q58*PriceEssMonthly*E58+R58*PricePremMonthly*E58+S58*PriceEssAnnual*E58/12+T58*PricePremAnnual*E58/12 | W58: =V58*12 | X58: =Q58*PriceEssMonthly*E58+R58*PricePremMonthly*E58 | Y58: =O58*PriceEssAnnual*E58+P58*PricePremAnnual*E58 | Z58: =O46*POWER(1-(AnnualChurn*VLOOKUP(B58,ChurnSeasonTable,4,FALSE)),1)*PriceEssAnnual*E58+O34*POWER(1-(AnnualChurn*VLOOKUP(B58,ChurnSeasonTable,4,FALSE)),2)*PriceEssAnnual*E58+O22*POWER(1-(AnnualChurn*VLOOKUP(B58,ChurnSeasonTable,4,FALSE)),3)*PriceEssAnnual*E58+O10*POWER(1-(AnnualChurn*VLOOKUP(B58,ChurnSeasonTable,4,FALSE)),4)*PriceEssAnnual*E58+P46*POWER(1-(AnnualChurn*VLOOKUP(B58,ChurnSeasonTable,4,FALSE)),1)*PricePremAnnual*E58+P34*POWER(1-(AnnualChurn*VLOOKUP(B58,ChurnSeasonTable,4,FALSE)),2)*PricePremAnnual*E58+P22*POWER(1-(AnnualChurn*VLOOKUP(B58,ChurnSeasonTable,4,FALSE)),3)*PricePremAnnual*E58+P10*POWER(1-(AnnualChurn*VLOOKUP(B58,ChurnSeasonTable,4,FALSE)),4)*PricePremAnnual*E58 | AA58: =X58+Y58+Z58 | AB58: =SUM(AA47:AA58) | AC58: =OR(AC57,AB58>=VATThreshold) | AD58: =IF(AC58,AA58/(1+VATRate),AA58) | AE58: =AA58-AD58 | AF58: =IF(AC58=0,0,IF(B58=1,SUMPRODUCT(--(($C$5:$C58=$C58-1)*($B$5:$B58>=10)*($B$5:$B58<=12)),$AE$5:$AE58),IF(B58=4,SUMPRODUCT(--(($C$5:$C58=$C58)*($B$5:$B58>=1)*($B$5:$B58<=3)),$AE$5:$AE58),IF(B58=7,SUMPRODUCT(--(($C$5:$C58=$C58)*($B$5:$B58>=4)*($B$5:$B58<=6)),$AE$5:$AE58),IF(B58=10,SUMPRODUCT(--(($C$5:$C58=$C58)*($B$5:$B58>=7)*($B$5:$B58<=9)),$AE$5:$AE58),0))))) | AG58: =AG57+AE58-AF58 | AH58: =IF(ProviderDelay>=1,AD57*ProviderShare,AD58*ProviderShare) | AI58: =AA58*PaymentFee | AJ58: =U58*OpsAI | AK58: =MonthlyFixed | AL58: =I58*ReferralReward | AM58: =G58 | AN58: =AD58-AH58-AI58-AJ58-AK58-AL58-AM58 | AO58: =AO57+AA58-(AH58+AI58+AJ58+AK58+AL58+AM58+AF58) | AP58: =IF(U58>0,V58/U58,0) | AQ58: =IF(U57>0,MAX(0,(U57+J58-U58)/U57),0)
A59: 55 | B59: =MOD(A59-1+LaunchMonth-1,12)+1 | C59: =INT((A59-1+LaunchMonth-1)/12)+1 | D59: =VLOOKUP(B59,SeasonTable,2,FALSE) | E59: =(1+InflationRate)^INT((A59-1)/12) | F59: =MonthlyChurn*VLOOKUP(B59,ChurnSeasonTable,4,FALSE) | G59: =MIN(MAX(MktMin19plus,AA58*MktPct19plus),MAX(0,AO58-CashBuffer)) | H59: =IF(G59>0,MAX(1,ROUND(G59/CAC*D59,0)),0) | I59: =IF(H59>0,ROUND(H59*ReferralMix/(1-ReferralMix),0),0) | J59: =H59+I59 | K59: =ROUND(J59*(1-AnnualMix),0) | L59: =J59-K59 | M59: =ROUND(K59*EssentialMix,0) | N59: =K59-M59 | O59: =ROUND(L59*EssentialMix,0) | P59: =L59-O59 | Q59: =M59+M58+M57+MAX(0,Q58-M58-M57)*(1-F59) | R59: =N59+N58+N57+MAX(0,R58-N58-N57)*(1-F59) | S59: =S58+O59-O47*(AnnualChurn*VLOOKUP(B59,ChurnSeasonTable,4,FALSE))*POWER(1-(AnnualChurn*VLOOKUP(B59,ChurnSeasonTable,4,FALSE)),0)+O35*(AnnualChurn*VLOOKUP(B59,ChurnSeasonTable,4,FALSE))*POWER(1-(AnnualChurn*VLOOKUP(B59,ChurnSeasonTable,4,FALSE)),1)+O23*(AnnualChurn*VLOOKUP(B59,ChurnSeasonTable,4,FALSE))*POWER(1-(AnnualChurn*VLOOKUP(B59,ChurnSeasonTable,4,FALSE)),2)+O11*(AnnualChurn*VLOOKUP(B59,ChurnSeasonTable,4,FALSE))*POWER(1-(AnnualChurn*VLOOKUP(B59,ChurnSeasonTable,4,FALSE)),3) | T59: =T58+P59-P47*(AnnualChurn*VLOOKUP(B59,ChurnSeasonTable,4,FALSE))*POWER(1-(AnnualChurn*VLOOKUP(B59,ChurnSeasonTable,4,FALSE)),0)+P35*(AnnualChurn*VLOOKUP(B59,ChurnSeasonTable,4,FALSE))*POWER(1-(AnnualChurn*VLOOKUP(B59,ChurnSeasonTable,4,FALSE)),1)+P23*(AnnualChurn*VLOOKUP(B59,ChurnSeasonTable,4,FALSE))*POWER(1-(AnnualChurn*VLOOKUP(B59,ChurnSeasonTable,4,FALSE)),2)+P11*(AnnualChurn*VLOOKUP(B59,ChurnSeasonTable,4,FALSE))*POWER(1-(AnnualChurn*VLOOKUP(B59,ChurnSeasonTable,4,FALSE)),3) | U59: =Q59+R59+S59+T59 | V59: =Q59*PriceEssMonthly*E59+R59*PricePremMonthly*E59+S59*PriceEssAnnual*E59/12+T59*PricePremAnnual*E59/12 | W59: =V59*12 | X59: =Q59*PriceEssMonthly*E59+R59*PricePremMonthly*E59 | Y59: =O59*PriceEssAnnual*E59+P59*PricePremAnnual*E59 | Z59: =O47*POWER(1-(AnnualChurn*VLOOKUP(B59,ChurnSeasonTable,4,FALSE)),1)*PriceEssAnnual*E59+O35*POWER(1-(AnnualChurn*VLOOKUP(B59,ChurnSeasonTable,4,FALSE)),2)*PriceEssAnnual*E59+O23*POWER(1-(AnnualChurn*VLOOKUP(B59,ChurnSeasonTable,4,FALSE)),3)*PriceEssAnnual*E59+O11*POWER(1-(AnnualChurn*VLOOKUP(B59,ChurnSeasonTable,4,FALSE)),4)*PriceEssAnnual*E59+P47*POWER(1-(AnnualChurn*VLOOKUP(B59,ChurnSeasonTable,4,FALSE)),1)*PricePremAnnual*E59+P35*POWER(1-(AnnualChurn*VLOOKUP(B59,ChurnSeasonTable,4,FALSE)),2)*PricePremAnnual*E59+P23*POWER(1-(AnnualChurn*VLOOKUP(B59,ChurnSeasonTable,4,FALSE)),3)*PricePremAnnual*E59+P11*POWER(1-(AnnualChurn*VLOOKUP(B59,ChurnSeasonTable,4,FALSE)),4)*PricePremAnnual*E59 | AA59: =X59+Y59+Z59 | AB59: =SUM(AA48:AA59) | AC59: =OR(AC58,AB59>=VATThreshold) | AD59: =IF(AC59,AA59/(1+VATRate),AA59) | AE59: =AA59-AD59 | AF59: =IF(AC59=0,0,IF(B59=1,SUMPRODUCT(--(($C$5:$C59=$C59-1)*($B$5:$B59>=10)*($B$5:$B59<=12)),$AE$5:$AE59),IF(B59=4,SUMPRODUCT(--(($C$5:$C59=$C59)*($B$5:$B59>=1)*($B$5:$B59<=3)),$AE$5:$AE59),IF(B59=7,SUMPRODUCT(--(($C$5:$C59=$C59)*($B$5:$B59>=4)*($B$5:$B59<=6)),$AE$5:$AE59),IF(B59=10,SUMPRODUCT(--(($C$5:$C59=$C59)*($B$5:$B59>=7)*($B$5:$B59<=9)),$AE$5:$AE59),0))))) | AG59: =AG58+AE59-AF59 | AH59: =IF(ProviderDelay>=1,AD58*ProviderShare,AD59*ProviderShare) | AI59: =AA59*PaymentFee | AJ59: =U59*OpsAI | AK59: =MonthlyFixed | AL59: =I59*ReferralReward | AM59: =G59 | AN59: =AD59-AH59-AI59-AJ59-AK59-AL59-AM59 | AO59: =AO58+AA59-(AH59+AI59+AJ59+AK59+AL59+AM59+AF59) | AP59: =IF(U59>0,V59/U59,0) | AQ59: =IF(U58>0,MAX(0,(U58+J59-U59)/U58),0)
A60: 56 | B60: =MOD(A60-1+LaunchMonth-1,12)+1 | C60: =INT((A60-1+LaunchMonth-1)/12)+1 | D60: =VLOOKUP(B60,SeasonTable,2,FALSE) | E60: =(1+InflationRate)^INT((A60-1)/12) | F60: =MonthlyChurn*VLOOKUP(B60,ChurnSeasonTable,4,FALSE) | G60: =MIN(MAX(MktMin19plus,AA59*MktPct19plus),MAX(0,AO59-CashBuffer)) | H60: =IF(G60>0,MAX(1,ROUND(G60/CAC*D60,0)),0) | I60: =IF(H60>0,ROUND(H60*ReferralMix/(1-ReferralMix),0),0) | J60: =H60+I60 | K60: =ROUND(J60*(1-AnnualMix),0) | L60: =J60-K60 | M60: =ROUND(K60*EssentialMix,0) | N60: =K60-M60 | O60: =ROUND(L60*EssentialMix,0) | P60: =L60-O60 | Q60: =M60+M59+M58+MAX(0,Q59-M59-M58)*(1-F60) | R60: =N60+N59+N58+MAX(0,R59-N59-N58)*(1-F60) | S60: =S59+O60-O48*(AnnualChurn*VLOOKUP(B60,ChurnSeasonTable,4,FALSE))*POWER(1-(AnnualChurn*VLOOKUP(B60,ChurnSeasonTable,4,FALSE)),0)+O36*(AnnualChurn*VLOOKUP(B60,ChurnSeasonTable,4,FALSE))*POWER(1-(AnnualChurn*VLOOKUP(B60,ChurnSeasonTable,4,FALSE)),1)+O24*(AnnualChurn*VLOOKUP(B60,ChurnSeasonTable,4,FALSE))*POWER(1-(AnnualChurn*VLOOKUP(B60,ChurnSeasonTable,4,FALSE)),2)+O12*(AnnualChurn*VLOOKUP(B60,ChurnSeasonTable,4,FALSE))*POWER(1-(AnnualChurn*VLOOKUP(B60,ChurnSeasonTable,4,FALSE)),3) | T60: =T59+P60-P48*(AnnualChurn*VLOOKUP(B60,ChurnSeasonTable,4,FALSE))*POWER(1-(AnnualChurn*VLOOKUP(B60,ChurnSeasonTable,4,FALSE)),0)+P36*(AnnualChurn*VLOOKUP(B60,ChurnSeasonTable,4,FALSE))*POWER(1-(AnnualChurn*VLOOKUP(B60,ChurnSeasonTable,4,FALSE)),1)+P24*(AnnualChurn*VLOOKUP(B60,ChurnSeasonTable,4,FALSE))*POWER(1-(AnnualChurn*VLOOKUP(B60,ChurnSeasonTable,4,FALSE)),2)+P12*(AnnualChurn*VLOOKUP(B60,ChurnSeasonTable,4,FALSE))*POWER(1-(AnnualChurn*VLOOKUP(B60,ChurnSeasonTable,4,FALSE)),3) | U60: =Q60+R60+S60+T60 | V60: =Q60*PriceEssMonthly*E60+R60*PricePremMonthly*E60+S60*PriceEssAnnual*E60/12+T60*PricePremAnnual*E60/12 | W60: =V60*12 | X60: =Q60*PriceEssMonthly*E60+R60*PricePremMonthly*E60 | Y60: =O60*PriceEssAnnual*E60+P60*PricePremAnnual*E60 | Z60: =O48*POWER(1-(AnnualChurn*VLOOKUP(B60,ChurnSeasonTable,4,FALSE)),1)*PriceEssAnnual*E60+O36*POWER(1-(AnnualChurn*VLOOKUP(B60,ChurnSeasonTable,4,FALSE)),2)*PriceEssAnnual*E60+O24*POWER(1-(AnnualChurn*VLOOKUP(B60,ChurnSeasonTable,4,FALSE)),3)*PriceEssAnnual*E60+O12*POWER(1-(AnnualChurn*VLOOKUP(B60,ChurnSeasonTable,4,FALSE)),4)*PriceEssAnnual*E60+P48*POWER(1-(AnnualChurn*VLOOKUP(B60,ChurnSeasonTable,4,FALSE)),1)*PricePremAnnual*E60+P36*POWER(1-(AnnualChurn*VLOOKUP(B60,ChurnSeasonTable,4,FALSE)),2)*PricePremAnnual*E60+P24*POWER(1-(AnnualChurn*VLOOKUP(B60,ChurnSeasonTable,4,FALSE)),3)*PricePremAnnual*E60+P12*POWER(1-(AnnualChurn*VLOOKUP(B60,ChurnSeasonTable,4,FALSE)),4)*PricePremAnnual*E60 | AA60: =X60+Y60+Z60 | AB60: =SUM(AA49:AA60) | AC60: =OR(AC59,AB60>=VATThreshold) | AD60: =IF(AC60,AA60/(1+VATRate),AA60) | AE60: =AA60-AD60 | AF60: =IF(AC60=0,0,IF(B60=1,SUMPRODUCT(--(($C$5:$C60=$C60-1)*($B$5:$B60>=10)*($B$5:$B60<=12)),$AE$5:$AE60),IF(B60=4,SUMPRODUCT(--(($C$5:$C60=$C60)*($B$5:$B60>=1)*($B$5:$B60<=3)),$AE$5:$AE60),IF(B60=7,SUMPRODUCT(--(($C$5:$C60=$C60)*($B$5:$B60>=4)*($B$5:$B60<=6)),$AE$5:$AE60),IF(B60=10,SUMPRODUCT(--(($C$5:$C60=$C60)*($B$5:$B60>=7)*($B$5:$B60<=9)),$AE$5:$AE60),0))))) | AG60: =AG59+AE60-AF60 | AH60: =IF(ProviderDelay>=1,AD59*ProviderShare,AD60*ProviderShare) | AI60: =AA60*PaymentFee | AJ60: =U60*OpsAI | AK60: =MonthlyFixed | AL60: =I60*ReferralReward | AM60: =G60 | AN60: =AD60-AH60-AI60-AJ60-AK60-AL60-AM60 | AO60: =AO59+AA60-(AH60+AI60+AJ60+AK60+AL60+AM60+AF60) | AP60: =IF(U60>0,V60/U60,0) | AQ60: =IF(U59>0,MAX(0,(U59+J60-U60)/U59),0)
A61: 57 | B61: =MOD(A61-1+LaunchMonth-1,12)+1 | C61: =INT((A61-1+LaunchMonth-1)/12)+1 | D61: =VLOOKUP(B61,SeasonTable,2,FALSE) | E61: =(1+InflationRate)^INT((A61-1)/12) | F61: =MonthlyChurn*VLOOKUP(B61,ChurnSeasonTable,4,FALSE) | G61: =MIN(MAX(MktMin19plus,AA60*MktPct19plus),MAX(0,AO60-CashBuffer)) | H61: =IF(G61>0,MAX(1,ROUND(G61/CAC*D61,0)),0) | I61: =IF(H61>0,ROUND(H61*ReferralMix/(1-ReferralMix),0),0) | J61: =H61+I61 | K61: =ROUND(J61*(1-AnnualMix),0) | L61: =J61-K61 | M61: =ROUND(K61*EssentialMix,0) | N61: =K61-M61 | O61: =ROUND(L61*EssentialMix,0) | P61: =L61-O61 | Q61: =M61+M60+M59+MAX(0,Q60-M60-M59)*(1-F61) | R61: =N61+N60+N59+MAX(0,R60-N60-N59)*(1-F61) | S61: =S60+O61-O49*(AnnualChurn*VLOOKUP(B61,ChurnSeasonTable,4,FALSE))*POWER(1-(AnnualChurn*VLOOKUP(B61,ChurnSeasonTable,4,FALSE)),0)+O37*(AnnualChurn*VLOOKUP(B61,ChurnSeasonTable,4,FALSE))*POWER(1-(AnnualChurn*VLOOKUP(B61,ChurnSeasonTable,4,FALSE)),1)+O25*(AnnualChurn*VLOOKUP(B61,ChurnSeasonTable,4,FALSE))*POWER(1-(AnnualChurn*VLOOKUP(B61,ChurnSeasonTable,4,FALSE)),2)+O13*(AnnualChurn*VLOOKUP(B61,ChurnSeasonTable,4,FALSE))*POWER(1-(AnnualChurn*VLOOKUP(B61,ChurnSeasonTable,4,FALSE)),3) | T61: =T60+P61-P49*(AnnualChurn*VLOOKUP(B61,ChurnSeasonTable,4,FALSE))*POWER(1-(AnnualChurn*VLOOKUP(B61,ChurnSeasonTable,4,FALSE)),0)+P37*(AnnualChurn*VLOOKUP(B61,ChurnSeasonTable,4,FALSE))*POWER(1-(AnnualChurn*VLOOKUP(B61,ChurnSeasonTable,4,FALSE)),1)+P25*(AnnualChurn*VLOOKUP(B61,ChurnSeasonTable,4,FALSE))*POWER(1-(AnnualChurn*VLOOKUP(B61,ChurnSeasonTable,4,FALSE)),2)+P13*(AnnualChurn*VLOOKUP(B61,ChurnSeasonTable,4,FALSE))*POWER(1-(AnnualChurn*VLOOKUP(B61,ChurnSeasonTable,4,FALSE)),3) | U61: =Q61+R61+S61+T61 | V61: =Q61*PriceEssMonthly*E61+R61*PricePremMonthly*E61+S61*PriceEssAnnual*E61/12+T61*PricePremAnnual*E61/12 | W61: =V61*12 | X61: =Q61*PriceEssMonthly*E61+R61*PricePremMonthly*E61 | Y61: =O61*PriceEssAnnual*E61+P61*PricePremAnnual*E61 | Z61: =O49*POWER(1-(AnnualChurn*VLOOKUP(B61,ChurnSeasonTable,4,FALSE)),1)*PriceEssAnnual*E61+O37*POWER(1-(AnnualChurn*VLOOKUP(B61,ChurnSeasonTable,4,FALSE)),2)*PriceEssAnnual*E61+O25*POWER(1-(AnnualChurn*VLOOKUP(B61,ChurnSeasonTable,4,FALSE)),3)*PriceEssAnnual*E61+O13*POWER(1-(AnnualChurn*VLOOKUP(B61,ChurnSeasonTable,4,FALSE)),4)*PriceEssAnnual*E61+P49*POWER(1-(AnnualChurn*VLOOKUP(B61,ChurnSeasonTable,4,FALSE)),1)*PricePremAnnual*E61+P37*POWER(1-(AnnualChurn*VLOOKUP(B61,ChurnSeasonTable,4,FALSE)),2)*PricePremAnnual*E61+P25*POWER(1-(AnnualChurn*VLOOKUP(B61,ChurnSeasonTable,4,FALSE)),3)*PricePremAnnual*E61+P13*POWER(1-(AnnualChurn*VLOOKUP(B61,ChurnSeasonTable,4,FALSE)),4)*PricePremAnnual*E61 | AA61: =X61+Y61+Z61 | AB61: =SUM(AA50:AA61) | AC61: =OR(AC60,AB61>=VATThreshold) | AD61: =IF(AC61,AA61/(1+VATRate),AA61) | AE61: =AA61-AD61 | AF61: =IF(AC61=0,0,IF(B61=1,SUMPRODUCT(--(($C$5:$C61=$C61-1)*($B$5:$B61>=10)*($B$5:$B61<=12)),$AE$5:$AE61),IF(B61=4,SUMPRODUCT(--(($C$5:$C61=$C61)*($B$5:$B61>=1)*($B$5:$B61<=3)),$AE$5:$AE61),IF(B61=7,SUMPRODUCT(--(($C$5:$C61=$C61)*($B$5:$B61>=4)*($B$5:$B61<=6)),$AE$5:$AE61),IF(B61=10,SUMPRODUCT(--(($C$5:$C61=$C61)*($B$5:$B61>=7)*($B$5:$B61<=9)),$AE$5:$AE61),0))))) | AG61: =AG60+AE61-AF61 | AH61: =IF(ProviderDelay>=1,AD60*ProviderShare,AD61*ProviderShare) | AI61: =AA61*PaymentFee | AJ61: =U61*OpsAI | AK61: =MonthlyFixed | AL61: =I61*ReferralReward | AM61: =G61 | AN61: =AD61-AH61-AI61-AJ61-AK61-AL61-AM61 | AO61: =AO60+AA61-(AH61+AI61+AJ61+AK61+AL61+AM61+AF61) | AP61: =IF(U61>0,V61/U61,0) | AQ61: =IF(U60>0,MAX(0,(U60+J61-U61)/U60),0)
A62: 58 | B62: =MOD(A62-1+LaunchMonth-1,12)+1 | C62: =INT((A62-1+LaunchMonth-1)/12)+1 | D62: =VLOOKUP(B62,SeasonTable,2,FALSE) | E62: =(1+InflationRate)^INT((A62-1)/12) | F62: =MonthlyChurn*VLOOKUP(B62,ChurnSeasonTable,4,FALSE) | G62: =MIN(MAX(MktMin19plus,AA61*MktPct19plus),MAX(0,AO61-CashBuffer)) | H62: =IF(G62>0,MAX(1,ROUND(G62/CAC*D62,0)),0) | I62: =IF(H62>0,ROUND(H62*ReferralMix/(1-ReferralMix),0),0) | J62: =H62+I62 | K62: =ROUND(J62*(1-AnnualMix),0) | L62: =J62-K62 | M62: =ROUND(K62*EssentialMix,0) | N62: =K62-M62 | O62: =ROUND(L62*EssentialMix,0) | P62: =L62-O62 | Q62: =M62+M61+M60+MAX(0,Q61-M61-M60)*(1-F62) | R62: =N62+N61+N60+MAX(0,R61-N61-N60)*(1-F62) | S62: =S61+O62-O50*(AnnualChurn*VLOOKUP(B62,ChurnSeasonTable,4,FALSE))*POWER(1-(AnnualChurn*VLOOKUP(B62,ChurnSeasonTable,4,FALSE)),0)+O38*(AnnualChurn*VLOOKUP(B62,ChurnSeasonTable,4,FALSE))*POWER(1-(AnnualChurn*VLOOKUP(B62,ChurnSeasonTable,4,FALSE)),1)+O26*(AnnualChurn*VLOOKUP(B62,ChurnSeasonTable,4,FALSE))*POWER(1-(AnnualChurn*VLOOKUP(B62,ChurnSeasonTable,4,FALSE)),2)+O14*(AnnualChurn*VLOOKUP(B62,ChurnSeasonTable,4,FALSE))*POWER(1-(AnnualChurn*VLOOKUP(B62,ChurnSeasonTable,4,FALSE)),3) | T62: =T61+P62-P50*(AnnualChurn*VLOOKUP(B62,ChurnSeasonTable,4,FALSE))*POWER(1-(AnnualChurn*VLOOKUP(B62,ChurnSeasonTable,4,FALSE)),0)+P38*(AnnualChurn*VLOOKUP(B62,ChurnSeasonTable,4,FALSE))*POWER(1-(AnnualChurn*VLOOKUP(B62,ChurnSeasonTable,4,FALSE)),1)+P26*(AnnualChurn*VLOOKUP(B62,ChurnSeasonTable,4,FALSE))*POWER(1-(AnnualChurn*VLOOKUP(B62,ChurnSeasonTable,4,FALSE)),2)+P14*(AnnualChurn*VLOOKUP(B62,ChurnSeasonTable,4,FALSE))*POWER(1-(AnnualChurn*VLOOKUP(B62,ChurnSeasonTable,4,FALSE)),3) | U62: =Q62+R62+S62+T62 | V62: =Q62*PriceEssMonthly*E62+R62*PricePremMonthly*E62+S62*PriceEssAnnual*E62/12+T62*PricePremAnnual*E62/12 | W62: =V62*12 | X62: =Q62*PriceEssMonthly*E62+R62*PricePremMonthly*E62 | Y62: =O62*PriceEssAnnual*E62+P62*PricePremAnnual*E62 | Z62: =O50*POWER(1-(AnnualChurn*VLOOKUP(B62,ChurnSeasonTable,4,FALSE)),1)*PriceEssAnnual*E62+O38*POWER(1-(AnnualChurn*VLOOKUP(B62,ChurnSeasonTable,4,FALSE)),2)*PriceEssAnnual*E62+O26*POWER(1-(AnnualChurn*VLOOKUP(B62,ChurnSeasonTable,4,FALSE)),3)*PriceEssAnnual*E62+O14*POWER(1-(AnnualChurn*VLOOKUP(B62,ChurnSeasonTable,4,FALSE)),4)*PriceEssAnnual*E62+P50*POWER(1-(AnnualChurn*VLOOKUP(B62,ChurnSeasonTable,4,FALSE)),1)*PricePremAnnual*E62+P38*POWER(1-(AnnualChurn*VLOOKUP(B62,ChurnSeasonTable,4,FALSE)),2)*PricePremAnnual*E62+P26*POWER(1-(AnnualChurn*VLOOKUP(B62,ChurnSeasonTable,4,FALSE)),3)*PricePremAnnual*E62+P14*POWER(1-(AnnualChurn*VLOOKUP(B62,ChurnSeasonTable,4,FALSE)),4)*PricePremAnnual*E62 | AA62: =X62+Y62+Z62 | AB62: =SUM(AA51:AA62) | AC62: =OR(AC61,AB62>=VATThreshold) | AD62: =IF(AC62,AA62/(1+VATRate),AA62) | AE62: =AA62-AD62 | AF62: =IF(AC62=0,0,IF(B62=1,SUMPRODUCT(--(($C$5:$C62=$C62-1)*($B$5:$B62>=10)*($B$5:$B62<=12)),$AE$5:$AE62),IF(B62=4,SUMPRODUCT(--(($C$5:$C62=$C62)*($B$5:$B62>=1)*($B$5:$B62<=3)),$AE$5:$AE62),IF(B62=7,SUMPRODUCT(--(($C$5:$C62=$C62)*($B$5:$B62>=4)*($B$5:$B62<=6)),$AE$5:$AE62),IF(B62=10,SUMPRODUCT(--(($C$5:$C62=$C62)*($B$5:$B62>=7)*($B$5:$B62<=9)),$AE$5:$AE62),0))))) | AG62: =AG61+AE62-AF62 | AH62: =IF(ProviderDelay>=1,AD61*ProviderShare,AD62*ProviderShare) | AI62: =AA62*PaymentFee | AJ62: =U62*OpsAI | AK62: =MonthlyFixed | AL62: =I62*ReferralReward | AM62: =G62 | AN62: =AD62-AH62-AI62-AJ62-AK62-AL62-AM62 | AO62: =AO61+AA62-(AH62+AI62+AJ62+AK62+AL62+AM62+AF62) | AP62: =IF(U62>0,V62/U62,0) | AQ62: =IF(U61>0,MAX(0,(U61+J62-U62)/U61),0)
A63: 59 | B63: =MOD(A63-1+LaunchMonth-1,12)+1 | C63: =INT((A63-1+LaunchMonth-1)/12)+1 | D63: =VLOOKUP(B63,SeasonTable,2,FALSE) | E63: =(1+InflationRate)^INT((A63-1)/12) | F63: =MonthlyChurn*VLOOKUP(B63,ChurnSeasonTable,4,FALSE) | G63: =MIN(MAX(MktMin19plus,AA62*MktPct19plus),MAX(0,AO62-CashBuffer)) | H63: =IF(G63>0,MAX(1,ROUND(G63/CAC*D63,0)),0) | I63: =IF(H63>0,ROUND(H63*ReferralMix/(1-ReferralMix),0),0) | J63: =H63+I63 | K63: =ROUND(J63*(1-AnnualMix),0) | L63: =J63-K63 | M63: =ROUND(K63*EssentialMix,0) | N63: =K63-M63 | O63: =ROUND(L63*EssentialMix,0) | P63: =L63-O63 | Q63: =M63+M62+M61+MAX(0,Q62-M62-M61)*(1-F63) | R63: =N63+N62+N61+MAX(0,R62-N62-N61)*(1-F63) | S63: =S62+O63-O51*(AnnualChurn*VLOOKUP(B63,ChurnSeasonTable,4,FALSE))*POWER(1-(AnnualChurn*VLOOKUP(B63,ChurnSeasonTable,4,FALSE)),0)+O39*(AnnualChurn*VLOOKUP(B63,ChurnSeasonTable,4,FALSE))*POWER(1-(AnnualChurn*VLOOKUP(B63,ChurnSeasonTable,4,FALSE)),1)+O27*(AnnualChurn*VLOOKUP(B63,ChurnSeasonTable,4,FALSE))*POWER(1-(AnnualChurn*VLOOKUP(B63,ChurnSeasonTable,4,FALSE)),2)+O15*(AnnualChurn*VLOOKUP(B63,ChurnSeasonTable,4,FALSE))*POWER(1-(AnnualChurn*VLOOKUP(B63,ChurnSeasonTable,4,FALSE)),3) | T63: =T62+P63-P51*(AnnualChurn*VLOOKUP(B63,ChurnSeasonTable,4,FALSE))*POWER(1-(AnnualChurn*VLOOKUP(B63,ChurnSeasonTable,4,FALSE)),0)+P39*(AnnualChurn*VLOOKUP(B63,ChurnSeasonTable,4,FALSE))*POWER(1-(AnnualChurn*VLOOKUP(B63,ChurnSeasonTable,4,FALSE)),1)+P27*(AnnualChurn*VLOOKUP(B63,ChurnSeasonTable,4,FALSE))*POWER(1-(AnnualChurn*VLOOKUP(B63,ChurnSeasonTable,4,FALSE)),2)+P15*(AnnualChurn*VLOOKUP(B63,ChurnSeasonTable,4,FALSE))*POWER(1-(AnnualChurn*VLOOKUP(B63,ChurnSeasonTable,4,FALSE)),3) | U63: =Q63+R63+S63+T63 | V63: =Q63*PriceEssMonthly*E63+R63*PricePremMonthly*E63+S63*PriceEssAnnual*E63/12+T63*PricePremAnnual*E63/12 | W63: =V63*12 | X63: =Q63*PriceEssMonthly*E63+R63*PricePremMonthly*E63 | Y63: =O63*PriceEssAnnual*E63+P63*PricePremAnnual*E63 | Z63: =O51*POWER(1-(AnnualChurn*VLOOKUP(B63,ChurnSeasonTable,4,FALSE)),1)*PriceEssAnnual*E63+O39*POWER(1-(AnnualChurn*VLOOKUP(B63,ChurnSeasonTable,4,FALSE)),2)*PriceEssAnnual*E63+O27*POWER(1-(AnnualChurn*VLOOKUP(B63,ChurnSeasonTable,4,FALSE)),3)*PriceEssAnnual*E63+O15*POWER(1-(AnnualChurn*VLOOKUP(B63,ChurnSeasonTable,4,FALSE)),4)*PriceEssAnnual*E63+P51*POWER(1-(AnnualChurn*VLOOKUP(B63,ChurnSeasonTable,4,FALSE)),1)*PricePremAnnual*E63+P39*POWER(1-(AnnualChurn*VLOOKUP(B63,ChurnSeasonTable,4,FALSE)),2)*PricePremAnnual*E63+P27*POWER(1-(AnnualChurn*VLOOKUP(B63,ChurnSeasonTable,4,FALSE)),3)*PricePremAnnual*E63+P15*POWER(1-(AnnualChurn*VLOOKUP(B63,ChurnSeasonTable,4,FALSE)),4)*PricePremAnnual*E63 | AA63: =X63+Y63+Z63 | AB63: =SUM(AA52:AA63) | AC63: =OR(AC62,AB63>=VATThreshold) | AD63: =IF(AC63,AA63/(1+VATRate),AA63) | AE63: =AA63-AD63 | AF63: =IF(AC63=0,0,IF(B63=1,SUMPRODUCT(--(($C$5:$C63=$C63-1)*($B$5:$B63>=10)*($B$5:$B63<=12)),$AE$5:$AE63),IF(B63=4,SUMPRODUCT(--(($C$5:$C63=$C63)*($B$5:$B63>=1)*($B$5:$B63<=3)),$AE$5:$AE63),IF(B63=7,SUMPRODUCT(--(($C$5:$C63=$C63)*($B$5:$B63>=4)*($B$5:$B63<=6)),$AE$5:$AE63),IF(B63=10,SUMPRODUCT(--(($C$5:$C63=$C63)*($B$5:$B63>=7)*($B$5:$B63<=9)),$AE$5:$AE63),0))))) | AG63: =AG62+AE63-AF63 | AH63: =IF(ProviderDelay>=1,AD62*ProviderShare,AD63*ProviderShare) | AI63: =AA63*PaymentFee | AJ63: =U63*OpsAI | AK63: =MonthlyFixed | AL63: =I63*ReferralReward | AM63: =G63 | AN63: =AD63-AH63-AI63-AJ63-AK63-AL63-AM63 | AO63: =AO62+AA63-(AH63+AI63+AJ63+AK63+AL63+AM63+AF63) | AP63: =IF(U63>0,V63/U63,0) | AQ63: =IF(U62>0,MAX(0,(U62+J63-U63)/U62),0)
A64: 60 | B64: =MOD(A64-1+LaunchMonth-1,12)+1 | C64: =INT((A64-1+LaunchMonth-1)/12)+1 | D64: =VLOOKUP(B64,SeasonTable,2,FALSE) | E64: =(1+InflationRate)^INT((A64-1)/12) | F64: =MonthlyChurn*VLOOKUP(B64,ChurnSeasonTable,4,FALSE) | G64: =MIN(MAX(MktMin19plus,AA63*MktPct19plus),MAX(0,AO63-CashBuffer)) | H64: =IF(G64>0,MAX(1,ROUND(G64/CAC*D64,0)),0) | I64: =IF(H64>0,ROUND(H64*ReferralMix/(1-ReferralMix),0),0) | J64: =H64+I64 | K64: =ROUND(J64*(1-AnnualMix),0) | L64: =J64-K64 | M64: =ROUND(K64*EssentialMix,0) | N64: =K64-M64 | O64: =ROUND(L64*EssentialMix,0) | P64: =L64-O64 | Q64: =M64+M63+M62+MAX(0,Q63-M63-M62)*(1-F64) | R64: =N64+N63+N62+MAX(0,R63-N63-N62)*(1-F64) | S64: =S63+O64-O52*(AnnualChurn*VLOOKUP(B64,ChurnSeasonTable,4,FALSE))*POWER(1-(AnnualChurn*VLOOKUP(B64,ChurnSeasonTable,4,FALSE)),0)+O40*(AnnualChurn*VLOOKUP(B64,ChurnSeasonTable,4,FALSE))*POWER(1-(AnnualChurn*VLOOKUP(B64,ChurnSeasonTable,4,FALSE)),1)+O28*(AnnualChurn*VLOOKUP(B64,ChurnSeasonTable,4,FALSE))*POWER(1-(AnnualChurn*VLOOKUP(B64,ChurnSeasonTable,4,FALSE)),2)+O16*(AnnualChurn*VLOOKUP(B64,ChurnSeasonTable,4,FALSE))*POWER(1-(AnnualChurn*VLOOKUP(B64,ChurnSeasonTable,4,FALSE)),3) | T64: =T63+P64-P52*(AnnualChurn*VLOOKUP(B64,ChurnSeasonTable,4,FALSE))*POWER(1-(AnnualChurn*VLOOKUP(B64,ChurnSeasonTable,4,FALSE)),0)+P40*(AnnualChurn*VLOOKUP(B64,ChurnSeasonTable,4,FALSE))*POWER(1-(AnnualChurn*VLOOKUP(B64,ChurnSeasonTable,4,FALSE)),1)+P28*(AnnualChurn*VLOOKUP(B64,ChurnSeasonTable,4,FALSE))*POWER(1-(AnnualChurn*VLOOKUP(B64,ChurnSeasonTable,4,FALSE)),2)+P16*(AnnualChurn*VLOOKUP(B64,ChurnSeasonTable,4,FALSE))*POWER(1-(AnnualChurn*VLOOKUP(B64,ChurnSeasonTable,4,FALSE)),3) | U64: =Q64+R64+S64+T64 | V64: =Q64*PriceEssMonthly*E64+R64*PricePremMonthly*E64+S64*PriceEssAnnual*E64/12+T64*PricePremAnnual*E64/12 | W64: =V64*12 | X64: =Q64*PriceEssMonthly*E64+R64*PricePremMonthly*E64 | Y64: =O64*PriceEssAnnual*E64+P64*PricePremAnnual*E64 | Z64: =O52*POWER(1-(AnnualChurn*VLOOKUP(B64,ChurnSeasonTable,4,FALSE)),1)*PriceEssAnnual*E64+O40*POWER(1-(AnnualChurn*VLOOKUP(B64,ChurnSeasonTable,4,FALSE)),2)*PriceEssAnnual*E64+O28*POWER(1-(AnnualChurn*VLOOKUP(B64,ChurnSeasonTable,4,FALSE)),3)*PriceEssAnnual*E64+O16*POWER(1-(AnnualChurn*VLOOKUP(B64,ChurnSeasonTable,4,FALSE)),4)*PriceEssAnnual*E64+P52*POWER(1-(AnnualChurn*VLOOKUP(B64,ChurnSeasonTable,4,FALSE)),1)*PricePremAnnual*E64+P40*POWER(1-(AnnualChurn*VLOOKUP(B64,ChurnSeasonTable,4,FALSE)),2)*PricePremAnnual*E64+P28*POWER(1-(AnnualChurn*VLOOKUP(B64,ChurnSeasonTable,4,FALSE)),3)*PricePremAnnual*E64+P16*POWER(1-(AnnualChurn*VLOOKUP(B64,ChurnSeasonTable,4,FALSE)),4)*PricePremAnnual*E64 | AA64: =X64+Y64+Z64 | AB64: =SUM(AA53:AA64) | AC64: =OR(AC63,AB64>=VATThreshold) | AD64: =IF(AC64,AA64/(1+VATRate),AA64) | AE64: =AA64-AD64 | AF64: =IF(AC64=0,0,IF(B64=1,SUMPRODUCT(--(($C$5:$C64=$C64-1)*($B$5:$B64>=10)*($B$5:$B64<=12)),$AE$5:$AE64),IF(B64=4,SUMPRODUCT(--(($C$5:$C64=$C64)*($B$5:$B64>=1)*($B$5:$B64<=3)),$AE$5:$AE64),IF(B64=7,SUMPRODUCT(--(($C$5:$C64=$C64)*($B$5:$B64>=4)*($B$5:$B64<=6)),$AE$5:$AE64),IF(B64=10,SUMPRODUCT(--(($C$5:$C64=$C64)*($B$5:$B64>=7)*($B$5:$B64<=9)),$AE$5:$AE64),0))))) | AG64: =AG63+AE64-AF64 | AH64: =IF(ProviderDelay>=1,AD63*ProviderShare,AD64*ProviderShare) | AI64: =AA64*PaymentFee | AJ64: =U64*OpsAI | AK64: =MonthlyFixed | AL64: =I64*ReferralReward | AM64: =G64 | AN64: =AD64-AH64-AI64-AJ64-AK64-AL64-AM64 | AO64: =AO63+AA64-(AH64+AI64+AJ64+AK64+AL64+AM64+AF64) | AP64: =IF(U64>0,V64/U64,0) | AQ64: =IF(U63>0,MAX(0,(U63+J64-U64)/U63),0)

Sheet Scenario Engine
A2: Conservative | AS2: Base | CK2: Aggressive | EC2: Ch0 | FU2: Ch1 | HM2: Ch2 | JE2: Ch3 | KW2: Ch4 | MO2: Ch5 | OG2: Ch6 | PY2: Ch7 | RQ2: Ch8 | TI2: Mx0 | VA2: Mx1 | WS2: Mx2 | YK2: Mx3 | AAC2: Mx4 | ABU2: Mx5 | ADM2: Mx6 | AFE2: Cac0 | AGW2: Cac1 | AIO2: Cac2 | AKG2: Cac3 | ALY2: Cac4 | ANQ2: Cac5 | API2: Cac6 | ARA2: Winter Pivot
